Workbook

Sheet Exhibiciones 
C1: Formato para el registro de las exhibiciones de pasillos calzado | V1: Código: MS-AUE/02-03
V2: Versión: 001
C3: Periodo de evaluación: | O3: Del 29 al 03 de Julio del 2026 | V3: Vigencia a partir : Mayo 2022
A4: ECATEPEC | C4: Nave | D4: Catalogo | E4: Pasillo | F4: Modelos por Pasillo | G4: Calzado no exhibido | H4: Calzado sin elastico y/o suelto y/o mal amrrado | I4: Calzado blanco o claro, sin playo, playo roto | J4: Calzado no exhibido correctamente | K4: Calzado sucio | L4: Calzado maltratado / dañado | M4: Calzado mal agujetado | N4: Pie izquierdo | O4: Sin relleno autorizado | P4: Sin talla autorizada | Q4: Calzado sin rotacion | R4: Pasillo alineado | S4: Total de areas de oportunidad | T4: Total de areas de oportunidad RECUPERADAS | U4: Nomina | V4: Nombre | W4: % de eficiencia | X4: % de RECUPERACION | Y4: NO MODIFICAR ESTA COLUMNA NI OCULTAR | AD4: ESTAS COLUMNAS NO SE DEBEN MODIFICAR SOLO OCULTAR
A5: SEMANA 26 | B5: Lunes | C5: A | D5: Botas | E5: 15 | F5: 48 | G5: 0 | H5: 0 | I5: 0 | J5: 0 | K5: 0 | L5: 0 | M5: 0 | N5: 0 | O5: 0 | P5: 0 | Q5: 0 | R5: SI | S5: =IF(F5="-","",SUM(G5:Q5)) -> 0 | T5: 0 | U5: 144695 | V5: =IFERROR(VLOOKUP(U5,'Plantilla y Concentrado'!$B$4:$C$811,2,0),"") -> Alvarez Becerra Emiliano | W5: =IF(S5=0,1,IF(S5>AD5,(1-AE5),IF(S5<AD5,1))) -> 1 | X5: =IF(OR(S5=0,S5=""),"-",T5/S5) -> - | Y5: =IF(T5>S5,"SI") -> 0 | Z5: Solo colocar los pasillos evaluados, si algun pasillo se encuentra en cuadraje o movimiento no colocar | AD5: =IF(F5="-","",F5*0.021) -> 1.008 | AE5: =IF(S5=0,"-",IF(S5<AD5,(S5/100),((S5-AD5)/100))) -> - | AF5: =G5 -> 0 | AG5: =SUM(H5:Q5) -> 0
C6: A | D6: Botas | E6: 16 | F6: 33 | G6: 0 | H6: 0 | I6: 0 | J6: 0 | K6: 0 | L6: 0 | M6: 0 | N6: 0 | O6: 0 | P6: 0 | Q6: 0 | R6: SI | S6: =IF(F6="-","",SUM(G6:Q6)) -> 0 | T6: 0 | U6: 144695 | V6: =IFERROR(VLOOKUP(U6,'Plantilla y Concentrado'!$B$4:$C$811,2,0),"") -> Alvarez Becerra Emiliano | W6: =IF(S6=0,1,IF(S6>AD6,(1-AE6),IF(S6<AD6,1))) -> 1 | X6: =IF(OR(S6=0,S6=""),"-",T6/S6) -> - | Y6: =IF(T6>S6,"SI") -> 0 | AD6: =IF(F6="-","",F6*0.021) -> 0.693 | AE6: =IF(S6=0,"-",IF(S6<AD6,(S6/100),((S6-AD6)/100))) -> - | AF6: =G6 -> 0 | AG6: =SUM(H6:Q6) -> 0
C7: A | D7: Botas | E7: 17 | F7: 43 | G7: 0 | H7: 0 | I7: 0 | J7: 0 | K7: 0 | L7: 0 | M7: 0 | N7: 0 | O7: 0 | P7: 0 | Q7: 0 | R7: SI | S7: =IF(F7="-","",SUM(G7:Q7)) -> 0 | T7: 0 | U7: 144695 | V7: =IFERROR(VLOOKUP(U7,'Plantilla y Concentrado'!$B$4:$C$811,2,0),"") -> Alvarez Becerra Emiliano | W7: =IF(S7=0,1,IF(S7>AD7,(1-AE7),IF(S7<AD7,1))) -> 1 | X7: =IF(OR(S7=0,S7=""),"-",T7/S7) -> - | Y7: =IF(T7>S7,"SI") -> 0 | AD7: =IF(F7="-","",F7*0.021) -> 0.903 | AE7: =IF(S7=0,"-",IF(S7<AD7,(S7/100),((S7-AD7)/100))) -> - | AF7: =G7 -> 0 | AG7: =SUM(H7:Q7) -> 0
C8: A | D8: Botas | E8: 18 | F8: 41 | G8: 0 | H8: 0 | I8: 0 | J8: 0 | K8: 0 | L8: 0 | M8: 0 | N8: 0 | O8: 0 | P8: 0 | Q8: 0 | R8: SI | S8: =IF(F8="-","",SUM(G8:Q8)) -> 0 | T8: 0 | U8: 144695 | V8: =IFERROR(VLOOKUP(U8,'Plantilla y Concentrado'!$B$4:$C$811,2,0),"") -> Alvarez Becerra Emiliano | W8: =IF(S8=0,1,IF(S8>AD8,(1-AE8),IF(S8<AD8,1))) -> 1 | X8: =IF(OR(S8=0,S8=""),"-",T8/S8) -> - | Y8: =IF(T8>S8,"SI") -> 0 | AD8: =IF(F8="-","",F8*0.021) -> 0.861 | AE8: =IF(S8=0,"-",IF(S8<AD8,(S8/100),((S8-AD8)/100))) -> - | AF8: =G8 -> 0 | AG8: =SUM(H8:Q8) -> 0
C9: A | D9: Botas | E9: 19 | F9: 55 | G9: 0 | H9: 0 | I9: 0 | J9: 0 | K9: 0 | L9: 0 | M9: 0 | N9: 0 | O9: 0 | P9: 0 | Q9: 0 | R9: SI | S9: =IF(F9="-","",SUM(G9:Q9)) -> 0 | T9: 0 | U9: 144695 | V9: =IFERROR(VLOOKUP(U9,'Plantilla y Concentrado'!$B$4:$C$811,2,0),"") -> Alvarez Becerra Emiliano | W9: =IF(S9=0,1,IF(S9>AD9,(1-AE9),IF(S9<AD9,1))) -> 1 | X9: =IF(OR(S9=0,S9=""),"-",T9/S9) -> - | Y9: =IF(T9>S9,"SI") -> 0 | AD9: =IF(F9="-","",F9*0.021) -> 1.155 | AE9: =IF(S9=0,"-",IF(S9<AD9,(S9/100),((S9-AD9)/100))) -> - | AF9: =G9 -> 0 | AG9: =SUM(H9:Q9) -> 0
C10: A | D10: Botas | E10: 20 | F10: 43 | G10: 0 | H10: 0 | I10: 0 | J10: 0 | K10: 0 | L10: 0 | M10: 0 | N10: 0 | O10: 0 | P10: 0 | Q10: 0 | R10: SI | S10: =IF(F10="-","",SUM(G10:Q10)) -> 0 | T10: 0 | U10: 144695 | V10: =IFERROR(VLOOKUP(U10,'Plantilla y Concentrado'!$B$4:$C$811,2,0),"") -> Alvarez Becerra Emiliano | W10: =IF(S10=0,1,IF(S10>AD10,(1-AE10),IF(S10<AD10,1))) -> 1 | X10: =IF(OR(S10=0,S10=""),"-",T10/S10) -> - | Y10: =IF(T10>S10,"SI") -> 0 | AD10: =IF(F10="-","",F10*0.021) -> 0.903 | AE10: =IF(S10=0,"-",IF(S10<AD10,(S10/100),((S10-AD10)/100))) -> - | AF10: =G10 -> 0 | AG10: =SUM(H10:Q10) -> 0
C11: A | D11: Botas | E11: 21 | F11: 33 | G11: 0 | H11: 0 | I11: 0 | J11: 0 | K11: 0 | L11: 0 | M11: 0 | N11: 0 | O11: 0 | P11: 0 | Q11: 0 | R11: SI | S11: =IF(F11="-","",SUM(G11:Q11)) -> 0 | T11: 0 | U11: 136867 | V11: =IFERROR(VLOOKUP(U11,'Plantilla y Concentrado'!$B$4:$C$811,2,0),"") -> Barba Ramirez Jatziri Lizeth | W11: =IF(S11=0,1,IF(S11>AD11,(1-AE11),IF(S11<AD11,1))) -> 1 | X11: =IF(OR(S11=0,S11=""),"-",T11/S11) -> - | Y11: =IF(T11>S11,"SI") -> 0 | AD11: =IF(F11="-","",F11*0.021) -> 0.693 | AE11: =IF(S11=0,"-",IF(S11<AD11,(S11/100),((S11-AD11)/100))) -> - | AF11: =G11 -> 0 | AG11: =SUM(H11:Q11) -> 0
C12: A | D12: Botas | E12: 22 | F12: 50 | G12: 0 | H12: 0 | I12: 0 | J12: 0 | K12: 0 | L12: 0 | M12: 0 | N12: 0 | O12: 0 | P12: 0 | Q12: 0 | R12: - | S12: =IF(F12="-","",SUM(G12:Q12)) -> 0 | T12: 0 | U12: 136867 | V12: =IFERROR(VLOOKUP(U12,'Plantilla y Concentrado'!$B$4:$C$811,2,0),"") -> Barba Ramirez Jatziri Lizeth | W12: =IF(S12=0,1,IF(S12>AD12,(1-AE12),IF(S12<AD12,1))) -> 1 | X12: =IF(OR(S12=0,S12=""),"-",T12/S12) -> - | Y12: =IF(T12>S12,"SI") -> 0 | AD12: =IF(F12="-","",F12*0.021) -> 1.05 | AE12: =IF(S12=0,"-",IF(S12<AD12,(S12/100),((S12-AD12)/100))) -> - | AF12: =G12 -> 0 | AG12: =SUM(H12:Q12) -> 0
C13: A | D13: Botas | E13: 23 | F13: 46 | G13: 0 | H13: 0 | I13: 0 | J13: 0 | K13: 0 | L13: 0 | M13: 0 | N13: 0 | O13: 0 | P13: 0 | Q13: 0 | R13: - | S13: =IF(F13="-","",SUM(G13:Q13)) -> 0 | T13: 0 | U13: 136867 | V13: =IFERROR(VLOOKUP(U13,'Plantilla y Concentrado'!$B$4:$C$811,2,0),"") -> Barba Ramirez Jatziri Lizeth | W13: =IF(S13=0,1,IF(S13>AD13,(1-AE13),IF(S13<AD13,1))) -> 1 | X13: =IF(OR(S13=0,S13=""),"-",T13/S13) -> - | Y13: =IF(T13>S13,"SI") -> 0 | AD13: =IF(F13="-","",F13*0.021) -> 0.966 | AE13: =IF(S13=0,"-",IF(S13<AD13,(S13/100),((S13-AD13)/100))) -> - | AF13: =G13 -> 0 | AG13: =SUM(H13:Q13) -> 0
C14: A | D14: Botas | E14: 24 | F14: 34 | G14: 0 | H14: 0 | I14: 0 | J14: 0 | K14: 0 | L14: 0 | M14: 0 | N14: 0 | O14: 0 | P14: 0 | Q14: 0 | R14: - | S14: =IF(F14="-","",SUM(G14:Q14)) -> 0 | T14: 0 | U14: 136867 | V14: =IFERROR(VLOOKUP(U14,'Plantilla y Concentrado'!$B$4:$C$811,2,0),"") -> Barba Ramirez Jatziri Lizeth | W14: =IF(S14=0,1,IF(S14>AD14,(1-AE14),IF(S14<AD14,1))) -> 1 | X14: =IF(OR(S14=0,S14=""),"-",T14/S14) -> - | Y14: =IF(T14>S14,"SI") -> 0 | AD14: =IF(F14="-","",F14*0.021) -> 0.714 | AE14: =IF(S14=0,"-",IF(S14<AD14,(S14/100),((S14-AD14)/100))) -> - | AF14: =G14 -> 0 | AG14: =SUM(H14:Q14) -> 0
C15: A | D15: Botas | E15: 25 | F15: 37 | G15: 0 | H15: 0 | I15: 0 | J15: 0 | K15: 0 | L15: 0 | M15: 0 | N15: 0 | O15: 0 | P15: 0 | Q15: 0 | R15: - | S15: =IF(F15="-","",SUM(G15:Q15)) -> 0 | T15: 0 | U15: 158001 | V15: =IFERROR(VLOOKUP(U15,'Plantilla y Concentrado'!$B$4:$C$811,2,0),"") -> Nuñez Garcia Clarissa Naomi | W15: =IF(S15=0,1,IF(S15>AD15,(1-AE15),IF(S15<AD15,1))) -> 1 | X15: =IF(OR(S15=0,S15=""),"-",T15/S15) -> - | Y15: =IF(T15>S15,"SI") -> 0 | AD15: =IF(F15="-","",F15*0.021) -> 0.777 | AE15: =IF(S15=0,"-",IF(S15<AD15,(S15/100),((S15-AD15)/100))) -> - | AF15: =G15 -> 0 | AG15: =SUM(H15:Q15) -> 0
C16: A | D16: Botas | E16: 26 | F16: 43 | G16: 0 | H16: 0 | I16: 0 | J16: 0 | K16: 0 | L16: 0 | M16: 0 | N16: 0 | O16: 0 | P16: 0 | Q16: 0 | R16: - | S16: =IF(F16="-","",SUM(G16:Q16)) -> 0 | T16: 0 | U16: 151630 | V16: =IFERROR(VLOOKUP(U16,'Plantilla y Concentrado'!$B$4:$C$811,2,0),"") -> Muñoz Lara Karla Paola | W16: =IF(S16=0,1,IF(S16>AD16,(1-AE16),IF(S16<AD16,1))) -> 1 | X16: =IF(OR(S16=0,S16=""),"-",T16/S16) -> - | Y16: =IF(T16>S16,"SI") -> 0 | AD16: =IF(F16="-","",F16*0.021) -> 0.903 | AE16: =IF(S16=0,"-",IF(S16<AD16,(S16/100),((S16-AD16)/100))) -> - | AF16: =G16 -> 0 | AG16: =SUM(H16:Q16) -> 0
C17: A | D17: Botas | E17: 27 | F17: 48 | G17: 0 | H17: 0 | I17: 0 | J17: 0 | K17: 0 | L17: 0 | M17: 0 | N17: 0 | O17: 0 | P17: 0 | Q17: 0 | R17: - | S17: =IF(F17="-","",SUM(G17:Q17)) -> 0 | T17: 0 | U17: 151630 | V17: =IFERROR(VLOOKUP(U17,'Plantilla y Concentrado'!$B$4:$C$811,2,0),"") -> Muñoz Lara Karla Paola | W17: =IF(S17=0,1,IF(S17>AD17,(1-AE17),IF(S17<AD17,1))) -> 1 | X17: =IF(OR(S17=0,S17=""),"-",T17/S17) -> - | Y17: =IF(T17>S17,"SI") -> 0 | AD17: =IF(F17="-","",F17*0.021) -> 1.008 | AE17: =IF(S17=0,"-",IF(S17<AD17,(S17/100),((S17-AD17)/100))) -> - | AF17: =G17 -> 0 | AG17: =SUM(H17:Q17) -> 0
... C22: A | D22: Botas | E22: 3 | F22: 32 | G22: 0 | H22: 0 | I22: 0 | J22: 0 | K22: 0 | L22: 0 | M22: 0 | N22: 0 | O22: 0 | P22: 0 | Q22: 0 | R22: - | S22: =IF(F22="-","",SUM(G22:Q22)) -> 0 | T22: 0 | U22: 151630 | V22: =IFERROR(VLOOKUP(U22,'Plantilla y Concentrado'!$B$4:$C$811,2,0),"") -> Muñoz Lara Karla Paola | W22: =IF(S22=0,1,IF(S22>AD22,(1-AE22),IF(S22<AD22,1))) -> 1 | X22: =IF(OR(S22=0,S22=""),"-",T22/S22) -> - | Y22: =IF(T22>S22,"SI") -> 0 | AD22: =IF(F22="-","",F22*0.021) -> 0.672 | AE22: =IF(S22=0,"-",IF(S22<AD22,(S22/100),((S22-AD22)/100))) -> - | AF22: =G22 -> 0 | AG22: =SUM(H22:Q22) -> 0
C23: A | D23: Botas | F23: - | G23: 0 | H23: 0 | I23: 0 | J23: 0 | K23: 0 | L23: 0 | M23: 0 | N23: 0 | O23: 0 | P23: 0 | Q23: 0 | R23: - | S23: =IF(F23="-","",SUM(G23:Q23)) | T23: 0 | V23: =IFERROR(VLOOKUP(U23,'Plantilla y Concentrado'!$B$4:$C$811,2,0),"") | W23: =IF(S23=0,1,IF(S23>AD23,(1-AE23),IF(S23<AD23,1))) -> 0 | X23: =IF(OR(S23=0,S23=""),"-",T23/S23) -> - | Y23: =IF(T23>S23,"SI") -> 0 | AD23: =IF(F23="-","",F23*0.021) | AE23: =IF(S23=0,"-",IF(S23<AD23,(S23/100),((S23-AD23)/100))) -> #VALUE! | AF23: =G23 -> 0 | AG23: =SUM(H23:Q23) -> 0
C24: A | D24: Botas | F24: - | G24: 0 | H24: 0 | I24: 0 | J24: 0 | K24: 0 | L24: 0 | M24: 0 | N24: 0 | O24: 0 | P24: 0 | Q24: 0 | R24: - | S24: =IF(F24="-","",SUM(G24:Q24)) | T24: 0 | V24: =IFERROR(VLOOKUP(U24,'Plantilla y Concentrado'!$B$4:$C$811,2,0),"") | W24: =IF(S24=0,1,IF(S24>AD24,(1-AE24),IF(S24<AD24,1))) -> 0 | X24: =IF(OR(S24=0,S24=""),"-",T24/S24) -> - | Y24: =IF(T24>S24,"SI") -> 0 | AD24: =IF(F24="-","",F24*0.021) | AE24: =IF(S24=0,"-",IF(S24<AD24,(S24/100),((S24-AD24)/100))) -> #VALUE! | AF24: =G24 -> 0 | AG24: =SUM(H24:Q24) -> 0
C25: A | D25: Botas | F25: - | G25: 0 | H25: 0 | I25: 0 | J25: 0 | K25: 0 | L25: 0 | M25: 0 | N25: 0 | O25: 0 | P25: 0 | Q25: 0 | R25: - | S25: =IF(F25="-","",SUM(G25:Q25)) | T25: 0 | V25: =IFERROR(VLOOKUP(U25,'Plantilla y Concentrado'!$B$4:$C$811,2,0),"") | W25: =IF(S25=0,1,IF(S25>AD25,(1-AE25),IF(S25<AD25,1))) -> 0 | X25: =IF(OR(S25=0,S25=""),"-",T25/S25) -> - | Y25: =IF(T25>S25,"SI") -> 0 | AD25: =IF(F25="-","",F25*0.021) | AE25: =IF(S25=0,"-",IF(S25<AD25,(S25/100),((S25-AD25)/100))) -> #VALUE! | AF25: =G25 -> 0 | AG25: =SUM(H25:Q25) -> 0
C26: A | D26: Botas | F26: - | G26: 0 | H26: 0 | I26: 0 | J26: 0 | K26: 0 | L26: 0 | M26: 0 | N26: 0 | O26: 0 | P26: 0 | Q26: 0 | R26: - | S26: =IF(F26="-","",SUM(G26:Q26)) | T26: 0 | V26: =IFERROR(VLOOKUP(U26,'Plantilla y Concentrado'!$B$4:$C$811,2,0),"") | W26: =IF(S26=0,1,IF(S26>AD26,(1-AE26),IF(S26<AD26,1))) -> 0 | X26: =IF(OR(S26=0,S26=""),"-",T26/S26) -> - | Y26: =IF(T26>S26,"SI") -> 0 | AD26: =IF(F26="-","",F26*0.021) | AE26: =IF(S26=0,"-",IF(S26<AD26,(S26/100),((S26-AD26)/100))) -> #VALUE! | AF26: =G26 -> 0 | AG26: =SUM(H26:Q26) -> 0
C27: A | D27: Botas | F27: - | G27: 0 | H27: 0 | I27: 0 | J27: 0 | K27: 0 | L27: 0 | M27: 0 | N27: 0 | O27: 0 | P27: 0 | Q27: 0 | R27: - | S27: =IF(F27="-","",SUM(G27:Q27)) | T27: 0 | V27: =IFERROR(VLOOKUP(U27,'Plantilla y Concentrado'!$B$4:$C$811,2,0),"") | W27: =IF(S27=0,1,IF(S27>AD27,(1-AE27),IF(S27<AD27,1))) -> 0 | X27: =IF(OR(S27=0,S27=""),"-",T27/S27) -> - | Y27: =IF(T27>S27,"SI") -> 0 | AD27: =IF(F27="-","",F27*0.021) | AE27: =IF(S27=0,"-",IF(S27<AD27,(S27/100),((S27-AD27)/100))) -> #VALUE! | AF27: =G27 -> 0 | AG27: =SUM(H27:Q27) -> 0
C28: A | D28: Botas | F28: - | G28: 0 | H28: 0 | I28: 0 | J28: 0 | K28: 0 | L28: 0 | M28: 0 | N28: 0 | O28: 0 | P28: 0 | Q28: 0 | R28: - | S28: =IF(F28="-","",SUM(G28:Q28)) | T28: 0 | V28: =IFERROR(VLOOKUP(U28,'Plantilla y Concentrado'!$B$4:$C$811,2,0),"") | W28: =IF(S28=0,1,IF(S28>AD28,(1-AE28),IF(S28<AD28,1))) -> 0 | X28: =IF(OR(S28=0,S28=""),"-",T28/S28) -> - | Y28: =IF(T28>S28,"SI") -> 0 | AD28: =IF(F28="-","",F28*0.021) | AE28: =IF(S28=0,"-",IF(S28<AD28,(S28/100),((S28-AD28)/100))) -> #VALUE! | AF28: =G28 -> 0 | AG28: =SUM(H28:Q28) -> 0
C29: A | D29: Botas | F29: - | G29: 0 | H29: 0 | I29: 0 | J29: 0 | K29: 0 | L29: 0 | M29: 0 | N29: 0 | O29: 0 | P29: 0 | Q29: 0 | R29: - | S29: =IF(F29="-","",SUM(G29:Q29)) | T29: 0 | V29: =IFERROR(VLOOKUP(U29,'Plantilla y Concentrado'!$B$4:$C$811,2,0),"") | W29: =IF(S29=0,1,IF(S29>AD29,(1-AE29),IF(S29<AD29,1))) -> 0 | X29: =IF(OR(S29=0,S29=""),"-",T29/S29) -> - | Y29: =IF(T29>S29,"SI") -> 0 | AD29: =IF(F29="-","",F29*0.021) | AE29: =IF(S29=0,"-",IF(S29<AD29,(S29/100),((S29-AD29)/100))) -> #VALUE! | AF29: =G29 -> 0 | AG29: =SUM(H29:Q29) -> 0
C30: A | D30: Botas | F30: - | G30: 0 | H30: 0 | I30: 0 | J30: 0 | K30: 0 | L30: 0 | M30: 0 | N30: 0 | O30: 0 | P30: 0 | Q30: 0 | R30: - | S30: =IF(F30="-","",SUM(G30:Q30)) | T30: 0 | V30: =IFERROR(VLOOKUP(U30,'Plantilla y Concentrado'!$B$4:$C$811,2,0),"") | W30: =IF(S30=0,1,IF(S30>AD30,(1-AE30),IF(S30<AD30,1))) -> 0 | X30: =IF(OR(S30=0,S30=""),"-",T30/S30) -> - | Y30: =IF(T30>S30,"SI") -> 0 | AD30: =IF(F30="-","",F30*0.021) | AE30: =IF(S30=0,"-",IF(S30<AD30,(S30/100),((S30-AD30)/100))) -> #VALUE! | AF30: =G30 -> 0 | AG30: =SUM(H30:Q30) -> 0
C31: A | D31: Botas | F31: - | G31: 0 | H31: 0 | I31: 0 | J31: 0 | K31: 0 | L31: 0 | M31: 0 | N31: 0 | O31: 0 | P31: 0 | Q31: 0 | R31: - | S31: =IF(F31="-","",SUM(G31:Q31)) | T31: 0 | V31: =IFERROR(VLOOKUP(U31,'Plantilla y Concentrado'!$B$4:$C$811,2,0),"") | W31: =IF(S31=0,1,IF(S31>AD31,(1-AE31),IF(S31<AD31,1))) -> 0 | X31: =IF(OR(S31=0,S31=""),"-",T31/S31) -> - | Y31: =IF(T31>S31,"SI") -> 0 | AD31: =IF(F31="-","",F31*0.021) | AE31: =IF(S31=0,"-",IF(S31<AD31,(S31/100),((S31-AD31)/100))) -> #VALUE! | AF31: =G31 -> 0 | AG31: =SUM(H31:Q31) -> 0
C32: A | D32: Botas | F32: - | G32: 0 | H32: 0 | I32: 0 | J32: 0 | K32: 0 | L32: 0 | M32: 0 | N32: 0 | O32: 0 | P32: 0 | Q32: 0 | R32: - | S32: =IF(F32="-","",SUM(G32:Q32)) | T32: 0 | V32: =IFERROR(VLOOKUP(U32,'Plantilla y Concentrado'!$B$4:$C$811,2,0),"") | W32: =IF(S32=0,1,IF(S32>AD32,(1-AE32),IF(S32<AD32,1))) -> 0 | X32: =IF(OR(S32=0,S32=""),"-",T32/S32) -> - | Y32: =IF(T32>S32,"SI") -> 0 | AD32: =IF(F32="-","",F32*0.021) | AE32: =IF(S32=0,"-",IF(S32<AD32,(S32/100),((S32-AD32)/100))) -> #VALUE! | AF32: =G32 -> 0 | AG32: =SUM(H32:Q32) -> 0
C33: A | D33: Botas | F33: - | G33: 0 | H33: 0 | I33: 0 | J33: 0 | K33: 0 | L33: 0 | M33: 0 | N33: 0 | O33: 0 | P33: 0 | Q33: 0 | R33: - | S33: =IF(F33="-","",SUM(G33:Q33)) | T33: 0 | V33: =IFERROR(VLOOKUP(U33,'Plantilla y Concentrado'!$B$4:$C$811,2,0),"") | W33: =IF(S33=0,1,IF(S33>AD33,(1-AE33),IF(S33<AD33,1))) -> 0 | X33: =IF(OR(S33=0,S33=""),"-",T33/S33) -> - | Y33: =IF(T33>S33,"SI") -> 0 | AD33: =IF(F33="-","",F33*0.021) | AE33: =IF(S33=0,"-",IF(S33<AD33,(S33/100),((S33-AD33)/100))) -> #VALUE! | AF33: =G33 -> 0 | AG33: =SUM(H33:Q33) -> 0
C34: A | D34: Botas | F34: - | G34: 0 | H34: 0 | I34: 0 | J34: 0 | K34: 0 | L34: 0 | M34: 0 | N34: 0 | O34: 0 | P34: 0 | Q34: 0 | R34: - | S34: =IF(F34="-","",SUM(G34:Q34)) | T34: 0 | V34: =IFERROR(VLOOKUP(U34,'Plantilla y Concentrado'!$B$4:$C$811,2,0),"") | W34: =IF(S34=0,1,IF(S34>AD34,(1-AE34),IF(S34<AD34,1))) -> 0 | X34: =IF(OR(S34=0,S34=""),"-",T34/S34) -> - | Y34: =IF(T34>S34,"SI") -> 0 | AD34: =IF(F34="-","",F34*0.021) | AE34: =IF(S34=0,"-",IF(S34<AD34,(S34/100),((S34-AD34)/100))) -> #VALUE! | AF34: =G34 -> 0 | AG34: =SUM(H34:Q34) -> 0
C35: TOTAL BOTAS | F35: =SUM(F5:F34) -> 844 | G35: =SUM(G5:G34) -> 0 | H35: =SUM(H5:H34) -> 0 | I35: =SUM(I5:I34) -> 0 | J35: =SUM(J5:J34) -> 0 | K35: =SUM(K5:K34) -> 0 | L35: =SUM(L5:L34) -> 0 | M35: =SUM(M5:M34) -> 0 | ... Q35: =SUM(Q5:Q34) -> 0 | R35: =COUNTIF((R5:R34),"Si") -> 7 | S35: =IF(F35="-","",SUM(G35:Q35)) -> 0 | T35: =SUM(T5:T34) -> 0 | V35: =IFERROR(VLOOKUP(U35,'Plantilla y Concentrado'!$B$4:$C$811,2,0),"") | W35: =AVERAGE(W5:W34) -> 0.6 | X35: =IF(OR(S35=0,S35=""),"-",T35/S35) -> - | Y35: =IF(T35>S35,"SI") -> 0 | AD35: =IF(F35="-","",F35*0.021) -> 17.724 | AE35: =IF(S35=0,"-",IF(S35<AD35,(S35/100),((S35-AD35)/100))) -> - | AF35: =G35 -> 0 | AG35: =SUM(H35:Q35) -> 0
C36: B | D36: Caballeros | E36: 48 | F36: 66 | G36: 0 | H36: 0 | I36: 0 | J36: 0 | K36: 0 | L36: 0 | M36: 0 | N36: 0 | O36: 0 | P36: 0 | Q36: 0 | R36: SI | S36: =IF(F36="-","",SUM(G36:Q36)) -> 0 | T36: 0 | U36: 139272 | V36: =IFERROR(VLOOKUP(U36,'Plantilla y Concentrado'!$B$4:$C$811,2,0),"") -> Guzman Navarrete Arlen Esmeralda | W36: =IF(S36=0,1,IF(S36>AD36,(1-AE36),IF(S36<AD36,1))) -> 1 | X36: =IF(OR(S36=0,S36=""),"-",T36/S36) -> - | Y36: =IF(T36>S36,"SI") -> 0 | AD36: =IF(F36="-","",F36*0.021) -> 1.386 | AE36: =IF(S36=0,"-",IF(S36<AD36,(S36/100),((S36-AD36)/100))) -> - | AF36: =G36 -> 0 | AG36: =SUM(H36:Q36) -> 0
C37: B | D37: Caballeros | E37: 49 | F37: 62 | G37: 0 | H37: 0 | I37: 0 | J37: 0 | K37: 0 | L37: 0 | M37: 0 | N37: 0 | O37: 0 | P37: 0 | Q37: 0 | R37: SI | S37: =IF(F37="-","",SUM(G37:Q37)) -> 0 | T37: 0 | U37: 139272 | V37: =IFERROR(VLOOKUP(U37,'Plantilla y Concentrado'!$B$4:$C$811,2,0),"") -> Guzman Navarrete Arlen Esmeralda | W37: =IF(S37=0,1,IF(S37>AD37,(1-AE37),IF(S37<AD37,1))) -> 1 | X37: =IF(OR(S37=0,S37=""),"-",T37/S37) -> - | Y37: =IF(T37>S37,"SI") -> 0 | AD37: =IF(F37="-","",F37*0.021) -> 1.302 | AE37: =IF(S37=0,"-",IF(S37<AD37,(S37/100),((S37-AD37)/100))) -> - | AF37: =G37 -> 0 | AG37: =SUM(H37:Q37) -> 0
C38: B | D38: Caballeros | E38: 50 | F38: 74 | G38: 0 | H38: 0 | I38: 0 | J38: 0 | K38: 0 | L38: 0 | M38: 0 | N38: 0 | O38: 0 | P38: 0 | Q38: 0 | R38: SI | S38: =IF(F38="-","",SUM(G38:Q38)) -> 0 | T38: 0 | U38: 145279 | V38: =IFERROR(VLOOKUP(U38,'Plantilla y Concentrado'!$B$4:$C$811,2,0),"") -> Ferrusca Solis Karla Marcela | W38: =IF(S38=0,1,IF(S38>AD38,(1-AE38),IF(S38<AD38,1))) -> 1 | X38: =IF(OR(S38=0,S38=""),"-",T38/S38) -> - | Y38: =IF(T38>S38,"SI") -> 0 | AD38: =IF(F38="-","",F38*0.021) -> 1.554 | AE38: =IF(S38=0,"-",IF(S38<AD38,(S38/100),((S38-AD38)/100))) -> - | AF38: =G38 -> 0 | AG38: =SUM(H38:Q38) -> 0
C39: B | D39: Caballeros | E39: 51 | F39: 85 | G39: 0 | H39: 0 | I39: 0 | J39: 0 | K39: 0 | L39: 0 | M39: 0 | N39: 0 | O39: 0 | P39: 0 | Q39: 0 | R39: SI | S39: =IF(F39="-","",SUM(G39:Q39)) -> 0 | T39: 0 | U39: 145279 | V39: =IFERROR(VLOOKUP(U39,'Plantilla y Concentrado'!$B$4:$C$811,2,0),"") -> Ferrusca Solis Karla Marcela | W39: =IF(S39=0,1,IF(S39>AD39,(1-AE39),IF(S39<AD39,1))) -> 1 | X39: =IF(OR(S39=0,S39=""),"-",T39/S39) -> - | Y39: =IF(T39>S39,"SI") -> 0 | AD39: =IF(F39="-","",F39*0.021) -> 1.785 | AE39: =IF(S39=0,"-",IF(S39<AD39,(S39/100),((S39-AD39)/100))) -> - | AF39: =G39 -> 0 | AG39: =SUM(H39:Q39) -> 0
C40: B | D40: Caballeros | E40: 52 | F40: 51 | G40: 0 | H40: 0 | I40: 0 | J40: 0 | K40: 0 | L40: 0 | M40: 0 | N40: 0 | O40: 0 | P40: 0 | Q40: 0 | R40: SI | S40: =IF(F40="-","",SUM(G40:Q40)) -> 0 | T40: 0 | U40: 145279 | V40: =IFERROR(VLOOKUP(U40,'Plantilla y Concentrado'!$B$4:$C$811,2,0),"") -> Ferrusca Solis Karla Marcela | W40: =IF(S40=0,1,IF(S40>AD40,(1-AE40),IF(S40<AD40,1))) -> 1 | X40: =IF(OR(S40=0,S40=""),"-",T40/S40) -> - | Y40: =IF(T40>S40,"SI") -> 0 | AD40: =IF(F40="-","",F40*0.021) -> 1.071 | AE40: =IF(S40=0,"-",IF(S40<AD40,(S40/100),((S40-AD40)/100))) -> - | AF40: =G40 -> 0 | AG40: =SUM(H40:Q40) -> 0
C41: B | D41: Caballeros | E41: 53A | F41: 75 | G41: 0 | H41: 0 | I41: 0 | J41: 0 | K41: 0 | L41: 0 | M41: 0 | N41: 0 | O41: 0 | P41: 1 | Q41: 0 | R41: SI | S41: =IF(F41="-","",SUM(G41:Q41)) -> 1 | T41: 1 | U41: 145279 | V41: =IFERROR(VLOOKUP(U41,'Plantilla y Concentrado'!$B$4:$C$811,2,0),"") -> Ferrusca Solis Karla Marcela | W41: =IF(S41=0,1,IF(S41>AD41,(1-AE41),IF(S41<AD41,1))) -> 1 | X41: =IF(OR(S41=0,S41=""),"-",T41/S41) -> 1 | Y41: =IF(T41>S41,"SI") -> 0 | AD41: =IF(F41="-","",F41*0.021) -> 1.575 | AE41: =IF(S41=0,"-",IF(S41<AD41,(S41/100),((S41-AD41)/100))) -> 0.01 | AF41: =G41 -> 0 | AG41: =SUM(H41:Q41) -> 1
C42: B | D42: Caballeros | E42: 56 | F42: 60 | G42: 0 | H42: 0 | I42: 0 | J42: 0 | K42: 0 | L42: 0 | M42: 0 | N42: 0 | O42: 0 | P42: 1 | Q42: 0 | R42: SI | S42: =IF(F42="-","",SUM(G42:Q42)) -> 1 | T42: 1 | U42: 145279 | V42: =IFERROR(VLOOKUP(U42,'Plantilla y Concentrado'!$B$4:$C$811,2,0),"") -> Ferrusca Solis Karla Marcela | W42: =IF(S42=0,1,IF(S42>AD42,(1-AE42),IF(S42<AD42,1))) -> 1 | X42: =IF(OR(S42=0,S42=""),"-",T42/S42) -> 1 | Y42: =IF(T42>S42,"SI") -> 0 | AD42: =IF(F42="-","",F42*0.021) -> 1.26 | AE42: =IF(S42=0,"-",IF(S42<AD42,(S42/100),((S42-AD42)/100))) -> 0.01 | AF42: =G42 -> 0 | AG42: =SUM(H42:Q42) -> 1
C43: B | D43: Caballeros | E43: 57 | F43: 81 | G43: 0 | H43: 0 | I43: 0 | J43: 0 | K43: 0 | L43: 0 | M43: 0 | N43: 1 | O43: 0 | P43: 0 | Q43: 0 | R43: SI | S43: =IF(F43="-","",SUM(G43:Q43)) -> 1 | T43: 1 | U43: 139272 | V43: =IFERROR(VLOOKUP(U43,'Plantilla y Concentrado'!$B$4:$C$811,2,0),"") -> Guzman Navarrete Arlen Esmeralda | W43: =IF(S43=0,1,IF(S43>AD43,(1-AE43),IF(S43<AD43,1))) -> 1 | X43: =IF(OR(S43=0,S43=""),"-",T43/S43) -> 1 | Y43: =IF(T43>S43,"SI") -> 0 | AD43: =IF(F43="-","",F43*0.021) -> 1.701 | AE43: =IF(S43=0,"-",IF(S43<AD43,(S43/100),((S43-AD43)/100))) -> 0.01 | AF43: =G43 -> 0 | AG43: =SUM(H43:Q43) -> 1
C44: B | D44: Caballeros | E44: 58 | F44: 57 | G44: 0 | H44: 0 | I44: 0 | J44: 0 | K44: 0 | L44: 0 | M44: 0 | N44: 0 | O44: 0 | P44: 0 | Q44: 0 | R44: SI | S44: =IF(F44="-","",SUM(G44:Q44)) -> 0 | T44: 0 | U44: 139272 | V44: =IFERROR(VLOOKUP(U44,'Plantilla y Concentrado'!$B$4:$C$811,2,0),"") -> Guzman Navarrete Arlen Esmeralda | W44: =IF(S44=0,1,IF(S44>AD44,(1-AE44),IF(S44<AD44,1))) -> 1 | X44: =IF(OR(S44=0,S44=""),"-",T44/S44) -> - | Y44: =IF(T44>S44,"SI") -> 0 | AD44: =IF(F44="-","",F44*0.021) -> 1.197 | AE44: =IF(S44=0,"-",IF(S44<AD44,(S44/100),((S44-AD44)/100))) -> - | AF44: =G44 -> 0 | AG44: =SUM(H44:Q44) -> 0
C45: C | D45: Caballeros | F45: - | G45: 0 | H45: 0 | I45: 0 | J45: 0 | K45: 0 | L45: 0 | M45: 0 | N45: 0 | O45: 0 | P45: 0 | Q45: 0 | R45: - | S45: =IF(F45="-","",SUM(G45:Q45)) | T45: 0 | V45: =IFERROR(VLOOKUP(U45,'Plantilla y Concentrado'!$B$4:$C$811,2,0),"") | W45: =IF(S45=0,1,IF(S45>AD45,(1-AE45),IF(S45<AD45,1))) -> 0 | X45: =IF(OR(S45=0,S45=""),"-",T45/S45) -> - | Y45: =IF(T45>S45,"SI") -> 0 | AD45: =IF(F45="-","",F45*0.021) | AE45: =IF(S45=0,"-",IF(S45<AD45,(S45/100),((S45-AD45)/100))) -> #VALUE! | AF45: =G45 -> 0 | AG45: =SUM(H45:Q45) -> 0
C46: B | D46: Caballeros | F46: - | G46: 0 | H46: 0 | I46: 0 | J46: 0 | K46: 0 | L46: 0 | M46: 0 | N46: 0 | O46: 0 | P46: 0 | Q46: 0 | R46: - | S46: =IF(F46="-","",SUM(G46:Q46)) | T46: 0 | V46: =IFERROR(VLOOKUP(U46,'Plantilla y Concentrado'!$B$4:$C$811,2,0),"") | W46: =IF(S46=0,1,IF(S46>AD46,(1-AE46),IF(S46<AD46,1))) -> 0 | X46: =IF(OR(S46=0,S46=""),"-",T46/S46) -> - | Y46: =IF(T46>S46,"SI") -> 0 | AD46: =IF(F46="-","",F46*0.021) | AE46: =IF(S46=0,"-",IF(S46<AD46,(S46/100),((S46-AD46)/100))) -> #VALUE! | AF46: =G46 -> 0 | AG46: =SUM(H46:Q46) -> 0
C47: B | D47: Caballeros | F47: - | G47: 0 | H47: 0 | I47: 0 | J47: 0 | K47: 0 | L47: 0 | M47: 0 | N47: 0 | O47: 0 | P47: 0 | Q47: 0 | R47: - | S47: =IF(F47="-","",SUM(G47:Q47)) | T47: 0 | V47: =IFERROR(VLOOKUP(U47,'Plantilla y Concentrado'!$B$4:$C$811,2,0),"") | W47: =IF(S47=0,1,IF(S47>AD47,(1-AE47),IF(S47<AD47,1))) -> 0 | X47: =IF(OR(S47=0,S47=""),"-",T47/S47) -> - | Y47: =IF(T47>S47,"SI") -> 0 | AD47: =IF(F47="-","",F47*0.021) | AE47: =IF(S47=0,"-",IF(S47<AD47,(S47/100),((S47-AD47)/100))) -> #VALUE! | AF47: =G47 -> 0 | AG47: =SUM(H47:Q47) -> 0
C48: B | D48: Caballeros | F48: - | G48: 0 | H48: 0 | I48: 0 | J48: 0 | K48: 0 | L48: 0 | M48: 0 | N48: 0 | O48: 0 | P48: 0 | Q48: 0 | R48: - | S48: =IF(F48="-","",SUM(G48:Q48)) | T48: 0 | V48: =IFERROR(VLOOKUP(U48,'Plantilla y Concentrado'!$B$4:$C$811,2,0),"") | W48: =IF(S48=0,1,IF(S48>AD48,(1-AE48),IF(S48<AD48,1))) -> 0 | X48: =IF(OR(S48=0,S48=""),"-",T48/S48) -> - | Y48: =IF(T48>S48,"SI") -> 0 | AD48: =IF(F48="-","",F48*0.021) | AE48: =IF(S48=0,"-",IF(S48<AD48,(S48/100),((S48-AD48)/100))) -> #VALUE! | AF48: =G48 -> 0 | AG48: =SUM(H48:Q48) -> 0
C49: B | D49: Caballeros | F49: - | G49: 0 | H49: 0 | I49: 0 | J49: 0 | K49: 0 | L49: 0 | M49: 0 | N49: 0 | O49: 0 | P49: 0 | Q49: 0 | R49: - | S49: =IF(F49="-","",SUM(G49:Q49)) | T49: 0 | V49: =IFERROR(VLOOKUP(U49,'Plantilla y Concentrado'!$B$4:$C$811,2,0),"") | W49: =IF(S49=0,1,IF(S49>AD49,(1-AE49),IF(S49<AD49,1))) -> 0 | X49: =IF(OR(S49=0,S49=""),"-",T49/S49) -> - | Y49: =IF(T49>S49,"SI") -> 0 | AD49: =IF(F49="-","",F49*0.021) | AE49: =IF(S49=0,"-",IF(S49<AD49,(S49/100),((S49-AD49)/100))) -> #VALUE! | AF49: =G49 -> 0 | AG49: =SUM(H49:Q49) -> 0
C50: B | D50: Caballeros | F50: - | G50: 0 | H50: 0 | I50: 0 | J50: 0 | K50: 0 | L50: 0 | M50: 0 | N50: 0 | O50: 0 | P50: 0 | Q50: 0 | R50: - | S50: =IF(F50="-","",SUM(G50:Q50)) | T50: 0 | V50: =IFERROR(VLOOKUP(U50,'Plantilla y Concentrado'!$B$4:$C$811,2,0),"") | W50: =IF(S50=0,1,IF(S50>AD50,(1-AE50),IF(S50<AD50,1))) -> 0 | X50: =IF(OR(S50=0,S50=""),"-",T50/S50) -> - | Y50: =IF(T50>S50,"SI") -> 0 | AD50: =IF(F50="-","",F50*0.021) | AE50: =IF(S50=0,"-",IF(S50<AD50,(S50/100),((S50-AD50)/100))) -> #VALUE! | AF50: =G50 -> 0 | AG50: =SUM(H50:Q50) -> 0
C51: B | D51: Caballeros | F51: - | G51: 0 | H51: 0 | I51: 0 | J51: 0 | K51: 0 | L51: 0 | M51: 0 | N51: 0 | O51: 0 | P51: 0 | Q51: 0 | R51: - | S51: =IF(F51="-","",SUM(G51:Q51)) | T51: 0 | V51: =IFERROR(VLOOKUP(U51,'Plantilla y Concentrado'!$B$4:$C$811,2,0),"") | W51: =IF(S51=0,1,IF(S51>AD51,(1-AE51),IF(S51<AD51,1))) -> 0 | X51: =IF(OR(S51=0,S51=""),"-",T51/S51) -> - | Y51: =IF(T51>S51,"SI") -> 0 | AD51: =IF(F51="-","",F51*0.021) | AE51: =IF(S51=0,"-",IF(S51<AD51,(S51/100),((S51-AD51)/100))) -> #VALUE! | AF51: =G51 -> 0 | AG51: =SUM(H51:Q51) -> 0
C52: B | D52: Caballeros | F52: - | G52: 0 | H52: 0 | I52: 0 | J52: 0 | K52: 0 | L52: 0 | M52: 0 | N52: 0 | O52: 0 | P52: 0 | Q52: 0 | R52: - | S52: =IF(F52="-","",SUM(G52:Q52)) | T52: 0 | V52: =IFERROR(VLOOKUP(U52,'Plantilla y Concentrado'!$B$4:$C$811,2,0),"") | W52: =IF(S52=0,1,IF(S52>AD52,(1-AE52),IF(S52<AD52,1))) -> 0 | X52: =IF(OR(S52=0,S52=""),"-",T52/S52) -> - | Y52: =IF(T52>S52,"SI") -> 0 | AD52: =IF(F52="-","",F52*0.021) | AE52: =IF(S52=0,"-",IF(S52<AD52,(S52/100),((S52-AD52)/100))) -> #VALUE! | AF52: =G52 -> 0 | AG52: =SUM(H52:Q52) -> 0
C53: B | D53: Caballeros | F53: - | G53: 0 | H53: 0 | I53: 0 | J53: 0 | K53: 0 | L53: 0 | M53: 0 | N53: 0 | O53: 0 | P53: 0 | Q53: 0 | R53: - | S53: =IF(F53="-","",SUM(G53:Q53)) | T53: 0 | V53: =IFERROR(VLOOKUP(U53,'Plantilla y Concentrado'!$B$4:$C$811,2,0),"") | W53: =IF(S53=0,1,IF(S53>AD53,(1-AE53),IF(S53<AD53,1))) -> 0 | X53: =IF(OR(S53=0,S53=""),"-",T53/S53) -> - | Y53: =IF(T53>S53,"SI") -> 0 | AD53: =IF(F53="-","",F53*0.021) | AE53: =IF(S53=0,"-",IF(S53<AD53,(S53/100),((S53-AD53)/100))) -> #VALUE! | AF53: =G53 -> 0 | AG53: =SUM(H53:Q53) -> 0
C54: B | D54: Caballeros | F54: - | G54: 0 | H54: 0 | I54: 0 | J54: 0 | K54: 0 | L54: 0 | M54: 0 | N54: 0 | O54: 0 | P54: 0 | Q54: 0 | R54: - | S54: =IF(F54="-","",SUM(G54:Q54)) | T54: 0 | V54: =IFERROR(VLOOKUP(U54,'Plantilla y Concentrado'!$B$4:$C$811,2,0),"") | W54: =IF(S54=0,1,IF(S54>AD54,(1-AE54),IF(S54<AD54,1))) -> 0 | X54: =IF(OR(S54=0,S54=""),"-",T54/S54) -> - | Y54: =IF(T54>S54,"SI") -> 0 | AD54: =IF(F54="-","",F54*0.021) | AE54: =IF(S54=0,"-",IF(S54<AD54,(S54/100),((S54-AD54)/100))) -> #VALUE! | AF54: =G54 -> 0 | AG54: =SUM(H54:Q54) -> 0
C55: B | D55: Caballeros | F55: - | G55: 0 | H55: 0 | I55: 0 | J55: 0 | K55: 0 | L55: 0 | M55: 0 | N55: 0 | O55: 0 | P55: 0 | Q55: 0 | R55: - | S55: =IF(F55="-","",SUM(G55:Q55)) | T55: 0 | V55: =IFERROR(VLOOKUP(U55,'Plantilla y Concentrado'!$B$4:$C$811,2,0),"") | W55: =IF(S55=0,1,IF(S55>AD55,(1-AE55),IF(S55<AD55,1))) -> 0 | X55: =IF(OR(S55=0,S55=""),"-",T55/S55) -> - | Y55: =IF(T55>S55,"SI") -> 0 | AD55: =IF(F55="-","",F55*0.021) | AE55: =IF(S55=0,"-",IF(S55<AD55,(S55/100),((S55-AD55)/100))) -> #VALUE! | AF55: =G55 -> 0 | AG55: =SUM(H55:Q55) -> 0
C56: TOTAL CABALLEROS | F56: =SUM(F36:F55) -> 611 | G56: =SUM(G36:G55) -> 0 | H56: =SUM(H36:H55) -> 0 | I56: =SUM(I36:I55) -> 0 | J56: =SUM(J36:J55) -> 0 | K56: =SUM(K36:K55) -> 0 | L56: =SUM(L36:L55) -> 0 | M56: =SUM(M36:M55) -> 0 | ... Q56: =SUM(Q36:Q55) -> 0 | R56: =COUNTIF((R36:R55),"Si") -> 9 | S56: =IF(F56="-","",SUM(G56:Q56)) -> 3 | T56: =SUM(T36:T55) -> 3 | V56: =IFERROR(VLOOKUP(U56,'Plantilla y Concentrado'!$B$4:$C$811,2,0),"") | W56: =AVERAGE(W36:W55) -> 0.45 | X56: =IF(OR(S56=0,S56=""),"-",T56/S56) -> 1 | Y56: =IF(T56>S56,"SI") -> 0 | AD56: =IF(F56="-","",F56*0.021) -> 12.831 | AE56: =IF(S56=0,"-",IF(S56<AD56,(S56/100),((S56-AD56)/100))) -> 0.03 | AF56: =G56 -> 0 | AG56: =SUM(H56:Q56) -> 3
C57: B | D57: Confort | E57: 32B | F57: 18 | G57: 0 | H57: 0 | I57: 0 | J57: 0 | K57: 0 | L57: 0 | M57: 0 | N57: 0 | O57: 0 | P57: 0 | Q57: 0 | R57: SI | S57: =IF(F57="-","",SUM(G57:Q57)) -> 0 | T57: 0 | U57: 136675 | V57: =IFERROR(VLOOKUP(U57,'Plantilla y Concentrado'!$B$4:$C$811,2,0),"") -> Montiel Ramirez Cintya Elizabeth | W57: =IF(S57=0,1,IF(S57>AD57,(1-AE57),IF(S57<AD57,1))) -> 1 | X57: =IF(OR(S57=0,S57=""),"-",T57/S57) -> - | Y57: =IF(T57>S57,"SI") -> 0 | AD57: =IF(F57="-","",F57*0.021) -> 0.378 | AE57: =IF(S57=0,"-",IF(S57<AD57,(S57/100),((S57-AD57)/100))) -> - | AF57: =G57 -> 0 | AG57: =SUM(H57:Q57) -> 0
C58: B | D58: Confort | E58: 33 | F58: 59 | G58: 0 | H58: 0 | I58: 0 | J58: 0 | K58: 0 | L58: 0 | M58: 0 | N58: 0 | O58: 0 | P58: 0 | Q58: 0 | R58: SI | S58: =IF(F58="-","",SUM(G58:Q58)) -> 0 | T58: 0 | U58: 136675 | V58: =IFERROR(VLOOKUP(U58,'Plantilla y Concentrado'!$B$4:$C$811,2,0),"") -> Montiel Ramirez Cintya Elizabeth | W58: =IF(S58=0,1,IF(S58>AD58,(1-AE58),IF(S58<AD58,1))) -> 1 | X58: =IF(OR(S58=0,S58=""),"-",T58/S58) -> - | Y58: =IF(T58>S58,"SI") -> 0 | AD58: =IF(F58="-","",F58*0.021) -> 1.239 | AE58: =IF(S58=0,"-",IF(S58<AD58,(S58/100),((S58-AD58)/100))) -> - | AF58: =G58 -> 0 | AG58: =SUM(H58:Q58) -> 0
C59: B | D59: Confort | E59: 34 | F59: 58 | G59: 0 | H59: 0 | I59: 0 | J59: 0 | K59: 0 | L59: 0 | M59: 0 | N59: 0 | O59: 0 | P59: 0 | Q59: 0 | R59: SI | S59: =IF(F59="-","",SUM(G59:Q59)) -> 0 | T59: 0 | U59: 136675 | V59: =IFERROR(VLOOKUP(U59,'Plantilla y Concentrado'!$B$4:$C$811,2,0),"") -> Montiel Ramirez Cintya Elizabeth | W59: =IF(S59=0,1,IF(S59>AD59,(1-AE59),IF(S59<AD59,1))) -> 1 | X59: =IF(OR(S59=0,S59=""),"-",T59/S59) -> - | Y59: =IF(T59>S59,"SI") -> 0 | AD59: =IF(F59="-","",F59*0.021) -> 1.218 | AE59: =IF(S59=0,"-",IF(S59<AD59,(S59/100),((S59-AD59)/100))) -> - | AF59: =G59 -> 0 | AG59: =SUM(H59:Q59) -> 0
C60: B | D60: Confort | E60: 35 | F60: 56 | G60: 0 | H60: 0 | I60: 0 | J60: 0 | K60: 0 | L60: 0 | M60: 0 | N60: 0 | O60: 0 | P60: 0 | Q60: 0 | R60: SI | S60: =IF(F60="-","",SUM(G60:Q60)) -> 0 | T60: 0 | U60: 136675 | V60: =IFERROR(VLOOKUP(U60,'Plantilla y Concentrado'!$B$4:$C$811,2,0),"") -> Montiel Ramirez Cintya Elizabeth | W60: =IF(S60=0,1,IF(S60>AD60,(1-AE60),IF(S60<AD60,1))) -> 1 | X60: =IF(OR(S60=0,S60=""),"-",T60/S60) -> - | Y60: =IF(T60>S60,"SI") -> 0 | AD60: =IF(F60="-","",F60*0.021) -> 1.176 | AE60: =IF(S60=0,"-",IF(S60<AD60,(S60/100),((S60-AD60)/100))) -> - | AF60: =G60 -> 0 | AG60: =SUM(H60:Q60) -> 0
C61: B | D61: Confort | E61: 36 | F61: 50 | G61: 0 | H61: 0 | I61: 0 | J61: 0 | K61: 0 | L61: 0 | M61: 0 | N61: 1 | O61: 0 | P61: 0 | Q61: 1 | R61: SI | S61: =IF(F61="-","",SUM(G61:Q61)) -> 2 | T61: 2 | U61: 136675 | V61: =IFERROR(VLOOKUP(U61,'Plantilla y Concentrado'!$B$4:$C$811,2,0),"") -> Montiel Ramirez Cintya Elizabeth | W61: =IF(S61=0,1,IF(S61>AD61,(1-AE61),IF(S61<AD61,1))) -> 0.9905 | X61: =IF(OR(S61=0,S61=""),"-",T61/S61) -> 1 | Y61: =IF(T61>S61,"SI") -> 0 | AD61: =IF(F61="-","",F61*0.021) -> 1.05 | AE61: =IF(S61=0,"-",IF(S61<AD61,(S61/100),((S61-AD61)/100))) -> 0.0095 | AF61: =G61 -> 0 | AG61: =SUM(H61:Q61) -> 2
C62: B | D62: Confort | E62: 37A | F62: 34 | G62: 0 | H62: 0 | I62: 0 | J62: 0 | K62: 0 | L62: 0 | M62: 0 | N62: 0 | O62: 0 | P62: 0 | Q62: 0 | R62: SI | S62: =IF(F62="-","",SUM(G62:Q62)) -> 0 | T62: 0 | U62: 136675 | V62: =IFERROR(VLOOKUP(U62,'Plantilla y Concentrado'!$B$4:$C$811,2,0),"") -> Montiel Ramirez Cintya Elizabeth | W62: =IF(S62=0,1,IF(S62>AD62,(1-AE62),IF(S62<AD62,1))) -> 1 | X62: =IF(OR(S62=0,S62=""),"-",T62/S62) -> - | Y62: =IF(T62>S62,"SI") -> 0 | AD62: =IF(F62="-","",F62*0.021) -> 0.714 | AE62: =IF(S62=0,"-",IF(S62<AD62,(S62/100),((S62-AD62)/100))) -> - | AF62: =G62 -> 0 | AG62: =SUM(H62:Q62) -> 0
C63: B | D63: Confort | F63: - | G63: 0 | H63: 0 | I63: 0 | J63: 0 | K63: 0 | L63: 0 | M63: 0 | N63: 0 | O63: 0 | P63: 0 | Q63: 0 | R63: - | S63: =IF(F63="-","",SUM(G63:Q63)) | T63: 0 | V63: =IFERROR(VLOOKUP(U63,'Plantilla y Concentrado'!$B$4:$C$811,2,0),"") | W63: =IF(S63=0,1,IF(S63>AD63,(1-AE63),IF(S63<AD63,1))) -> 0 | X63: =IF(OR(S63=0,S63=""),"-",T63/S63) -> - | Y63: =IF(T63>S63,"SI") -> 0 | AD63: =IF(F63="-","",F63*0.021) | AE63: =IF(S63=0,"-",IF(S63<AD63,(S63/100),((S63-AD63)/100))) -> #VALUE! | AF63: =G63 -> 0 | AG63: =SUM(H63:Q63) -> 0
C64: B | D64: Confort | F64: - | G64: 0 | H64: 0 | I64: 0 | J64: 0 | K64: 0 | L64: 0 | M64: 0 | N64: 0 | O64: 0 | P64: 0 | Q64: 0 | R64: - | S64: =IF(F64="-","",SUM(G64:Q64)) | T64: 0 | V64: =IFERROR(VLOOKUP(U64,'Plantilla y Concentrado'!$B$4:$C$811,2,0),"") | W64: =IF(S64=0,1,IF(S64>AD64,(1-AE64),IF(S64<AD64,1))) -> 0 | X64: =IF(OR(S64=0,S64=""),"-",T64/S64) -> - | Y64: =IF(T64>S64,"SI") -> 0 | AD64: =IF(F64="-","",F64*0.021) | AE64: =IF(S64=0,"-",IF(S64<AD64,(S64/100),((S64-AD64)/100))) -> #VALUE! | AF64: =G64 -> 0 | AG64: =SUM(H64:Q64) -> 0
C65: B | D65: Confort | F65: - | G65: 0 | H65: 0 | I65: 0 | J65: 0 | K65: 0 | L65: 0 | M65: 0 | N65: 0 | O65: 0 | P65: 0 | Q65: 0 | R65: - | S65: =IF(F65="-","",SUM(G65:Q65)) | T65: 0 | V65: =IFERROR(VLOOKUP(U65,'Plantilla y Concentrado'!$B$4:$C$811,2,0),"") | W65: =IF(S65=0,1,IF(S65>AD65,(1-AE65),IF(S65<AD65,1))) -> 0 | X65: =IF(OR(S65=0,S65=""),"-",T65/S65) -> - | Y65: =IF(T65>S65,"SI") -> 0 | AD65: =IF(F65="-","",F65*0.021) | AE65: =IF(S65=0,"-",IF(S65<AD65,(S65/100),((S65-AD65)/100))) -> #VALUE! | AF65: =G65 -> 0 | AG65: =SUM(H65:Q65) -> 0
C66: B | D66: Confort | F66: - | G66: 0 | H66: 0 | I66: 0 | J66: 0 | K66: 0 | L66: 0 | M66: 0 | N66: 0 | O66: 0 | P66: 0 | Q66: 0 | R66: - | S66: =IF(F66="-","",SUM(G66:Q66)) | T66: 0 | V66: =IFERROR(VLOOKUP(U66,'Plantilla y Concentrado'!$B$4:$C$811,2,0),"") | W66: =IF(S66=0,1,IF(S66>AD66,(1-AE66),IF(S66<AD66,1))) -> 0 | X66: =IF(OR(S66=0,S66=""),"-",T66/S66) -> - | Y66: =IF(T66>S66,"SI") -> 0 | AD66: =IF(F66="-","",F66*0.021) | AE66: =IF(S66=0,"-",IF(S66<AD66,(S66/100),((S66-AD66)/100))) -> #VALUE! | AF66: =G66 -> 0 | AG66: =SUM(H66:Q66) -> 0
C67: B | D67: Confort | F67: - | G67: 0 | H67: 0 | I67: 0 | J67: 0 | K67: 0 | L67: 0 | M67: 0 | N67: 0 | O67: 0 | P67: 0 | Q67: 0 | R67: - | S67: =IF(F67="-","",SUM(G67:Q67)) | T67: 0 | V67: =IFERROR(VLOOKUP(U67,'Plantilla y Concentrado'!$B$4:$C$811,2,0),"") | W67: =IF(S67=0,1,IF(S67>AD67,(1-AE67),IF(S67<AD67,1))) -> 0 | X67: =IF(OR(S67=0,S67=""),"-",T67/S67) -> - | Y67: =IF(T67>S67,"SI") -> 0 | AD67: =IF(F67="-","",F67*0.021) | AE67: =IF(S67=0,"-",IF(S67<AD67,(S67/100),((S67-AD67)/100))) -> #VALUE! | AF67: =G67 -> 0 | AG67: =SUM(H67:Q67) -> 0
C68: B | D68: Confort | F68: - | G68: 0 | H68: 0 | I68: 0 | J68: 0 | K68: 0 | L68: 0 | M68: 0 | N68: 0 | O68: 0 | P68: 0 | Q68: 0 | R68: - | S68: =IF(F68="-","",SUM(G68:Q68)) | T68: 0 | V68: =IFERROR(VLOOKUP(U68,'Plantilla y Concentrado'!$B$4:$C$811,2,0),"") | W68: =IF(S68=0,1,IF(S68>AD68,(1-AE68),IF(S68<AD68,1))) -> 0 | X68: =IF(OR(S68=0,S68=""),"-",T68/S68) -> - | Y68: =IF(T68>S68,"SI") -> 0 | AD68: =IF(F68="-","",F68*0.021) | AE68: =IF(S68=0,"-",IF(S68<AD68,(S68/100),((S68-AD68)/100))) -> #VALUE! | AF68: =G68 -> 0 | AG68: =SUM(H68:Q68) -> 0
C69: B | D69: Confort | F69: - | G69: 0 | H69: 0 | I69: 0 | J69: 0 | K69: 0 | L69: 0 | M69: 0 | N69: 0 | O69: 0 | P69: 0 | Q69: 0 | R69: - | S69: =IF(F69="-","",SUM(G69:Q69)) | T69: 0 | V69: =IFERROR(VLOOKUP(U69,'Plantilla y Concentrado'!$B$4:$C$811,2,0),"") | W69: =IF(S69=0,1,IF(S69>AD69,(1-AE69),IF(S69<AD69,1))) -> 0 | X69: =IF(OR(S69=0,S69=""),"-",T69/S69) -> - | Y69: =IF(T69>S69,"SI") -> 0 | AD69: =IF(F69="-","",F69*0.021) | AE69: =IF(S69=0,"-",IF(S69<AD69,(S69/100),((S69-AD69)/100))) -> #VALUE! | AF69: =G69 -> 0 | AG69: =SUM(H69:Q69) -> 0
C70: B | D70: Confort | F70: - | G70: 0 | H70: 0 | I70: 0 | J70: 0 | K70: 0 | L70: 0 | M70: 0 | N70: 0 | O70: 0 | P70: 0 | Q70: 0 | R70: - | S70: =IF(F70="-","",SUM(G70:Q70)) | T70: 0 | V70: =IFERROR(VLOOKUP(U70,'Plantilla y Concentrado'!$B$4:$C$811,2,0),"") | W70: =IF(S70=0,1,IF(S70>AD70,(1-AE70),IF(S70<AD70,1))) -> 0 | X70: =IF(OR(S70=0,S70=""),"-",T70/S70) -> - | Y70: =IF(T70>S70,"SI") -> 0 | AD70: =IF(F70="-","",F70*0.021) | AE70: =IF(S70=0,"-",IF(S70<AD70,(S70/100),((S70-AD70)/100))) -> #VALUE! | AF70: =G70 -> 0 | AG70: =SUM(H70:Q70) -> 0
C71: B | D71: Confort | F71: - | G71: 0 | H71: 0 | I71: 0 | J71: 0 | K71: 0 | L71: 0 | M71: 0 | N71: 0 | O71: 0 | P71: 0 | Q71: 0 | R71: - | S71: =IF(F71="-","",SUM(G71:Q71)) | T71: 0 | V71: =IFERROR(VLOOKUP(U71,'Plantilla y Concentrado'!$B$4:$C$811,2,0),"") | W71: =IF(S71=0,1,IF(S71>AD71,(1-AE71),IF(S71<AD71,1))) -> 0 | X71: =IF(OR(S71=0,S71=""),"-",T71/S71) -> - | Y71: =IF(T71>S71,"SI") -> 0 | AD71: =IF(F71="-","",F71*0.021) | AE71: =IF(S71=0,"-",IF(S71<AD71,(S71/100),((S71-AD71)/100))) -> #VALUE! | AF71: =G71 -> 0 | AG71: =SUM(H71:Q71) -> 0
C72: TOTAL CONFORT | F72: =SUM(F57:F71) -> 275 | G72: =SUM(G57:G71) -> 0 | H72: =SUM(H57:H71) -> 0 | I72: =SUM(I57:I71) -> 0 | J72: =SUM(J57:J71) -> 0 | K72: =SUM(K57:K71) -> 0 | L72: =SUM(L57:L71) -> 0 | M72: =SUM(M57:M71) -> 0 | ... Q72: =SUM(Q57:Q71) -> 1 | R72: =COUNTIF((R57:R71),"Si") -> 6 | S72: =IF(F72="-","",SUM(G72:Q72)) -> 2 | T72: =SUM(T57:T71) -> 2 | V72: =IFERROR(VLOOKUP(U72,'Plantilla y Concentrado'!$B$4:$C$811,2,0),"") | W72: =AVERAGE(W57:W71) -> 0.39936667 | X72: =IF(OR(S72=0,S72=""),"-",T72/S72) -> 1 | Y72: =IF(T72>S72,"SI") -> 0 | AD72: =IF(F72="-","",F72*0.021) -> 5.775 | AE72: =IF(S72=0,"-",IF(S72<AD72,(S72/100),((S72-AD72)/100))) -> 0.02 | AF72: =G72 -> 0 | AG72: =SUM(H72:Q72) -> 2
C73: B | D73: Escolar | E73: 41A | F73: 29 | G73: 0 | H73: 0 | I73: 0 | J73: 0 | K73: 0 | L73: 0 | M73: 0 | N73: 0 | O73: 0 | P73: 0 | Q73: 0 | R73: SI | S73: =IF(F73="-","",SUM(G73:Q73)) -> 0 | T73: 0 | U73: 155938 | V73: =IFERROR(VLOOKUP(U73,'Plantilla y Concentrado'!$B$4:$C$811,2,0),"") -> Aguilar Flores Erika Jazmin | W73: =IF(S73=0,1,IF(S73>AD73,(1-AE73),IF(S73<AD73,1))) -> 1 | X73: =IF(OR(S73=0,S73=""),"-",T73/S73) -> - | Y73: =IF(T73>S73,"SI") -> 0 | AD73: =IF(F73="-","",F73*0.021) -> 0.609 | AE73: =IF(S73=0,"-",IF(S73<AD73,(S73/100),((S73-AD73)/100))) -> - | AF73: =G73 -> 0 | AG73: =SUM(H73:Q73) -> 0
C74: B | D74: Escolar | E74: 42 | F74: 68 | G74: 0 | H74: 0 | I74: 0 | J74: 0 | K74: 0 | L74: 0 | M74: 0 | N74: 0 | O74: 0 | P74: 2 | Q74: 0 | R74: SI | S74: =IF(F74="-","",SUM(G74:Q74)) -> 2 | T74: 2 | U74: 155938 | V74: =IFERROR(VLOOKUP(U74,'Plantilla y Concentrado'!$B$4:$C$811,2,0),"") -> Aguilar Flores Erika Jazmin | W74: =IF(S74=0,1,IF(S74>AD74,(1-AE74),IF(S74<AD74,1))) -> 0.99428 | X74: =IF(OR(S74=0,S74=""),"-",T74/S74) -> 1 | Y74: =IF(T74>S74,"SI") -> 0 | AD74: =IF(F74="-","",F74*0.021) -> 1.428 | AE74: =IF(S74=0,"-",IF(S74<AD74,(S74/100),((S74-AD74)/100))) -> 0.00572 | AF74: =G74 -> 0 | AG74: =SUM(H74:Q74) -> 2
C75: B | D75: Escolar | E75: 43 | F75: 43 | G75: 0 | H75: 0 | I75: 0 | J75: 0 | K75: 0 | L75: 0 | M75: 0 | N75: 0 | O75: 0 | P75: 0 | Q75: 1 | R75: SI | S75: =IF(F75="-","",SUM(G75:Q75)) -> 1 | T75: 1 | U75: 155938 | V75: =IFERROR(VLOOKUP(U75,'Plantilla y Concentrado'!$B$4:$C$811,2,0),"") -> Aguilar Flores Erika Jazmin | W75: =IF(S75=0,1,IF(S75>AD75,(1-AE75),IF(S75<AD75,1))) -> 0.99903 | X75: =IF(OR(S75=0,S75=""),"-",T75/S75) -> 1 | Y75: =IF(T75>S75,"SI") -> 0 | AD75: =IF(F75="-","",F75*0.021) -> 0.903 | AE75: =IF(S75=0,"-",IF(S75<AD75,(S75/100),((S75-AD75)/100))) -> 0.00097 | AF75: =G75 -> 0 | AG75: =SUM(H75:Q75) -> 1
C76: B | D76: Escolar | E76: 44 | F76: 33 | G76: 0 | H76: 0 | I76: 0 | J76: 0 | K76: 0 | L76: 0 | M76: 0 | N76: 0 | O76: 0 | P76: 0 | Q76: 0 | R76: Si | S76: =IF(F76="-","",SUM(G76:Q76)) -> 0 | T76: 0 | U76: 141072 | V76: =IFERROR(VLOOKUP(U76,'Plantilla y Concentrado'!$B$4:$C$811,2,0),"") -> Ramirez Vazquez Lizeth Mariel | W76: =IF(S76=0,1,IF(S76>AD76,(1-AE76),IF(S76<AD76,1))) -> 1 | X76: =IF(OR(S76=0,S76=""),"-",T76/S76) -> - | Y76: =IF(T76>S76,"SI") -> 0 | AD76: =IF(F76="-","",F76*0.021) -> 0.693 | AE76: =IF(S76=0,"-",IF(S76<AD76,(S76/100),((S76-AD76)/100))) -> - | AF76: =G76 -> 0 | AG76: =SUM(H76:Q76) -> 0
C77: B | D77: Escolar | E77: 45 | F77: 51 | G77: 0 | H77: 0 | I77: 0 | J77: 0 | K77: 0 | L77: 0 | M77: 0 | N77: 0 | O77: 0 | P77: 0 | Q77: 0 | R77: Si | S77: =IF(F77="-","",SUM(G77:Q77)) -> 0 | T77: 0 | U77: 141072 | V77: =IFERROR(VLOOKUP(U77,'Plantilla y Concentrado'!$B$4:$C$811,2,0),"") -> Ramirez Vazquez Lizeth Mariel | W77: =IF(S77=0,1,IF(S77>AD77,(1-AE77),IF(S77<AD77,1))) -> 1 | X77: =IF(OR(S77=0,S77=""),"-",T77/S77) -> - | Y77: =IF(T77>S77,"SI") -> 0 | AD77: =IF(F77="-","",F77*0.021) -> 1.071 | AE77: =IF(S77=0,"-",IF(S77<AD77,(S77/100),((S77-AD77)/100))) -> - | AF77: =G77 -> 0 | AG77: =SUM(H77:Q77) -> 0
C78: B | D78: Escolar | E78: 46 | F78: 59 | G78: 0 | H78: 0 | I78: 0 | J78: 0 | K78: 0 | L78: 0 | M78: 0 | N78: 0 | O78: 0 | P78: 0 | Q78: 0 | R78: Si | S78: =IF(F78="-","",SUM(G78:Q78)) -> 0 | T78: 0 | U78: 141072 | V78: =IFERROR(VLOOKUP(U78,'Plantilla y Concentrado'!$B$4:$C$811,2,0),"") -> Ramirez Vazquez Lizeth Mariel | W78: =IF(S78=0,1,IF(S78>AD78,(1-AE78),IF(S78<AD78,1))) -> 1 | X78: =IF(OR(S78=0,S78=""),"-",T78/S78) -> - | Y78: =IF(T78>S78,"SI") -> 0 | AD78: =IF(F78="-","",F78*0.021) -> 1.239 | AE78: =IF(S78=0,"-",IF(S78<AD78,(S78/100),((S78-AD78)/100))) -> - | AF78: =G78 -> 0 | AG78: =SUM(H78:Q78) -> 0
C79: B | D79: Escolar | E79: 47B | F79: 47 | G79: 0 | H79: 0 | I79: 0 | J79: 0 | K79: 0 | L79: 0 | M79: 0 | N79: 0 | O79: 0 | P79: 0 | Q79: 0 | R79: Si | S79: =IF(F79="-","",SUM(G79:Q79)) -> 0 | T79: 0 | U79: 141072 | V79: =IFERROR(VLOOKUP(U79,'Plantilla y Concentrado'!$B$4:$C$811,2,0),"") -> Ramirez Vazquez Lizeth Mariel | W79: =IF(S79=0,1,IF(S79>AD79,(1-AE79),IF(S79<AD79,1))) -> 1 | X79: =IF(OR(S79=0,S79=""),"-",T79/S79) -> - | Y79: =IF(T79>S79,"SI") -> 0 | AD79: =IF(F79="-","",F79*0.021) -> 0.987 | AE79: =IF(S79=0,"-",IF(S79<AD79,(S79/100),((S79-AD79)/100))) -> - | AF79: =G79 -> 0 | AG79: =SUM(H79:Q79) -> 0
C80: B | D80: Escolar | F80: - | G80: 0 | H80: 0 | I80: 0 | J80: 0 | K80: 0 | L80: 0 | M80: 0 | N80: 0 | O80: 0 | P80: 0 | Q80: 0 | R80: - | S80: =IF(F80="-","",SUM(G80:Q80)) | T80: 0 | V80: =IFERROR(VLOOKUP(U80,'Plantilla y Concentrado'!$B$4:$C$811,2,0),"") | W80: =IF(S80=0,1,IF(S80>AD80,(1-AE80),IF(S80<AD80,1))) -> 0 | X80: =IF(OR(S80=0,S80=""),"-",T80/S80) -> - | Y80: =IF(T80>S80,"SI") -> 0 | AD80: =IF(F80="-","",F80*0.021) | AE80: =IF(S80=0,"-",IF(S80<AD80,(S80/100),((S80-AD80)/100))) -> #VALUE! | AF80: =G80 -> 0 | AG80: =SUM(H80:Q80) -> 0
C81: B | D81: Escolar | F81: - | G81: 0 | H81: 0 | I81: 0 | J81: 0 | K81: 0 | L81: 0 | M81: 0 | N81: 0 | O81: 0 | P81: 0 | Q81: 0 | R81: - | S81: =IF(F81="-","",SUM(G81:Q81)) | T81: 0 | V81: =IFERROR(VLOOKUP(U81,'Plantilla y Concentrado'!$B$4:$C$811,2,0),"") | W81: =IF(S81=0,1,IF(S81>AD81,(1-AE81),IF(S81<AD81,1))) -> 0 | X81: =IF(OR(S81=0,S81=""),"-",T81/S81) -> - | Y81: =IF(T81>S81,"SI") -> 0 | AD81: =IF(F81="-","",F81*0.021) | AE81: =IF(S81=0,"-",IF(S81<AD81,(S81/100),((S81-AD81)/100))) -> #VALUE! | AF81: =G81 -> 0 | AG81: =SUM(H81:Q81) -> 0
C82: B | D82: Escolar | F82: - | G82: 0 | H82: 0 | I82: 0 | J82: 0 | K82: 0 | L82: 0 | M82: 0 | N82: 0 | O82: 0 | P82: 0 | Q82: 0 | R82: - | S82: =IF(F82="-","",SUM(G82:Q82)) | T82: 0 | V82: =IFERROR(VLOOKUP(U82,'Plantilla y Concentrado'!$B$4:$C$811,2,0),"") | W82: =IF(S82=0,1,IF(S82>AD82,(1-AE82),IF(S82<AD82,1))) -> 0 | X82: =IF(OR(S82=0,S82=""),"-",T82/S82) -> - | Y82: =IF(T82>S82,"SI") -> 0 | AD82: =IF(F82="-","",F82*0.021) | AE82: =IF(S82=0,"-",IF(S82<AD82,(S82/100),((S82-AD82)/100))) -> #VALUE! | AF82: =G82 -> 0 | AG82: =SUM(H82:Q82) -> 0
C83: B | D83: Escolar | F83: - | G83: 0 | H83: 0 | I83: 0 | J83: 0 | K83: 0 | L83: 0 | M83: 0 | N83: 0 | O83: 0 | P83: 0 | Q83: 0 | R83: - | S83: =IF(F83="-","",SUM(G83:Q83)) | T83: 0 | V83: =IFERROR(VLOOKUP(U83,'Plantilla y Concentrado'!$B$4:$C$811,2,0),"") | W83: =IF(S83=0,1,IF(S83>AD83,(1-AE83),IF(S83<AD83,1))) -> 0 | X83: =IF(OR(S83=0,S83=""),"-",T83/S83) -> - | Y83: =IF(T83>S83,"SI") -> 0 | AD83: =IF(F83="-","",F83*0.021) | AE83: =IF(S83=0,"-",IF(S83<AD83,(S83/100),((S83-AD83)/100))) -> #VALUE! | AF83: =G83 -> 0 | AG83: =SUM(H83:Q83) -> 0
C84: B | D84: Escolar | F84: - | G84: 0 | H84: 0 | I84: 0 | J84: 0 | K84: 0 | L84: 0 | M84: 0 | N84: 0 | O84: 0 | P84: 0 | Q84: 0 | R84: - | S84: =IF(F84="-","",SUM(G84:Q84)) | T84: 0 | V84: =IFERROR(VLOOKUP(U84,'Plantilla y Concentrado'!$B$4:$C$811,2,0),"") | W84: =IF(S84=0,1,IF(S84>AD84,(1-AE84),IF(S84<AD84,1))) -> 0 | X84: =IF(OR(S84=0,S84=""),"-",T84/S84) -> - | Y84: =IF(T84>S84,"SI") -> 0 | AD84: =IF(F84="-","",F84*0.021) | AE84: =IF(S84=0,"-",IF(S84<AD84,(S84/100),((S84-AD84)/100))) -> #VALUE! | AF84: =G84 -> 0 | AG84: =SUM(H84:Q84) -> 0
C85: B | D85: Escolar | F85: - | G85: 0 | H85: 0 | I85: 0 | J85: 0 | K85: 0 | L85: 0 | M85: 0 | N85: 0 | O85: 0 | P85: 0 | Q85: 0 | R85: - | S85: =IF(F85="-","",SUM(G85:Q85)) | T85: 0 | V85: =IFERROR(VLOOKUP(U85,'Plantilla y Concentrado'!$B$4:$C$811,2,0),"") | W85: =IF(S85=0,1,IF(S85>AD85,(1-AE85),IF(S85<AD85,1))) -> 0 | X85: =IF(OR(S85=0,S85=""),"-",T85/S85) -> - | Y85: =IF(T85>S85,"SI") -> 0 | AD85: =IF(F85="-","",F85*0.021) | AE85: =IF(S85=0,"-",IF(S85<AD85,(S85/100),((S85-AD85)/100))) -> #VALUE! | AF85: =G85 -> 0 | AG85: =SUM(H85:Q85) -> 0
C86: B | D86: Escolar | F86: - | G86: 0 | H86: 0 | I86: 0 | J86: 0 | K86: 0 | L86: 0 | M86: 0 | N86: 0 | O86: 0 | P86: 0 | Q86: 0 | R86: - | S86: =IF(F86="-","",SUM(G86:Q86)) | T86: 0 | V86: =IFERROR(VLOOKUP(U86,'Plantilla y Concentrado'!$B$4:$C$811,2,0),"") | W86: =IF(S86=0,1,IF(S86>AD86,(1-AE86),IF(S86<AD86,1))) -> 0 | X86: =IF(OR(S86=0,S86=""),"-",T86/S86) -> - | Y86: =IF(T86>S86,"SI") -> 0 | AD86: =IF(F86="-","",F86*0.021) | AE86: =IF(S86=0,"-",IF(S86<AD86,(S86/100),((S86-AD86)/100))) -> #VALUE! | AF86: =G86 -> 0 | AG86: =SUM(H86:Q86) -> 0
C87: B | D87: Escolar | F87: - | G87: 0 | H87: 0 | I87: 0 | J87: 0 | K87: 0 | L87: 0 | M87: 0 | N87: 0 | O87: 0 | P87: 0 | Q87: 0 | R87: - | S87: =IF(F87="-","",SUM(G87:Q87)) | T87: 0 | V87: =IFERROR(VLOOKUP(U87,'Plantilla y Concentrado'!$B$4:$C$811,2,0),"") | W87: =IF(S87=0,1,IF(S87>AD87,(1-AE87),IF(S87<AD87,1))) -> 0 | X87: =IF(OR(S87=0,S87=""),"-",T87/S87) -> - | Y87: =IF(T87>S87,"SI") -> 0 | AD87: =IF(F87="-","",F87*0.021) | AE87: =IF(S87=0,"-",IF(S87<AD87,(S87/100),((S87-AD87)/100))) -> #VALUE! | AF87: =G87 -> 0 | AG87: =SUM(H87:Q87) -> 0
C88: B | D88: Escolar | F88: - | G88: 0 | H88: 0 | I88: 0 | J88: 0 | K88: 0 | L88: 0 | M88: 0 | N88: 0 | O88: 0 | P88: 0 | Q88: 0 | R88: - | S88: =IF(F88="-","",SUM(G88:Q88)) | T88: 0 | V88: =IFERROR(VLOOKUP(U88,'Plantilla y Concentrado'!$B$4:$C$811,2,0),"") | W88: =IF(S88=0,1,IF(S88>AD88,(1-AE88),IF(S88<AD88,1))) -> 0 | X88: =IF(OR(S88=0,S88=""),"-",T88/S88) -> - | Y88: =IF(T88>S88,"SI") -> 0 | AD88: =IF(F88="-","",F88*0.021) | AE88: =IF(S88=0,"-",IF(S88<AD88,(S88/100),((S88-AD88)/100))) -> #VALUE! | AF88: =G88 -> 0 | AG88: =SUM(H88:Q88) -> 0
C89: B | D89: Escolar | F89: - | G89: 0 | H89: 0 | I89: 0 | J89: 0 | K89: 0 | L89: 0 | M89: 0 | N89: 0 | O89: 0 | P89: 0 | Q89: 0 | R89: - | S89: =IF(F89="-","",SUM(G89:Q89)) | T89: 0 | V89: =IFERROR(VLOOKUP(U89,'Plantilla y Concentrado'!$B$4:$C$811,2,0),"") | W89: =IF(S89=0,1,IF(S89>AD89,(1-AE89),IF(S89<AD89,1))) -> 0 | X89: =IF(OR(S89=0,S89=""),"-",T89/S89) -> - | Y89: =IF(T89>S89,"SI") -> 0 | AD89: =IF(F89="-","",F89*0.021) | AE89: =IF(S89=0,"-",IF(S89<AD89,(S89/100),((S89-AD89)/100))) -> #VALUE! | AF89: =G89 -> 0 | AG89: =SUM(H89:Q89) -> 0
C90: B | D90: Escolar | F90: - | G90: 0 | H90: 0 | I90: 0 | J90: 0 | K90: 0 | L90: 0 | M90: 0 | N90: 0 | O90: 0 | P90: 0 | Q90: 0 | R90: - | S90: =IF(F90="-","",SUM(G90:Q90)) | T90: 0 | V90: =IFERROR(VLOOKUP(U90,'Plantilla y Concentrado'!$B$4:$C$811,2,0),"") | W90: =IF(S90=0,1,IF(S90>AD90,(1-AE90),IF(S90<AD90,1))) -> 0 | X90: =IF(OR(S90=0,S90=""),"-",T90/S90) -> - | Y90: =IF(T90>S90,"SI") -> 0 | AD90: =IF(F90="-","",F90*0.021) | AE90: =IF(S90=0,"-",IF(S90<AD90,(S90/100),((S90-AD90)/100))) -> #VALUE! | AF90: =G90 -> 0 | AG90: =SUM(H90:Q90) -> 0
C91: B | D91: Escolar | F91: - | G91: 0 | H91: 0 | I91: 0 | J91: 0 | K91: 0 | L91: 0 | M91: 0 | N91: 0 | O91: 0 | P91: 0 | Q91: 0 | R91: - | S91: =IF(F91="-","",SUM(G91:Q91)) | T91: 0 | V91: =IFERROR(VLOOKUP(U91,'Plantilla y Concentrado'!$B$4:$C$811,2,0),"") | W91: =IF(S91=0,1,IF(S91>AD91,(1-AE91),IF(S91<AD91,1))) -> 0 | X91: =IF(OR(S91=0,S91=""),"-",T91/S91) -> - | Y91: =IF(T91>S91,"SI") -> 0 | AD91: =IF(F91="-","",F91*0.021) | AE91: =IF(S91=0,"-",IF(S91<AD91,(S91/100),((S91-AD91)/100))) -> #VALUE! | AF91: =G91 -> 0 | AG91: =SUM(H91:Q91) -> 0
... C94: B | D94: Escolar | F94: - | G94: 0 | H94: 0 | I94: 0 | J94: 0 | K94: 0 | L94: 0 | M94: 0 | N94: 0 | O94: 0 | P94: 0 | Q94: 0 | R94: - | S94: =IF(F94="-","",SUM(G94:Q94)) | T94: 0 | V94: =IFERROR(VLOOKUP(U94,'Plantilla y Concentrado'!$B$4:$C$811,2,0),"") | W94: =IF(S94=0,1,IF(S94>AD94,(1-AE94),IF(S94<AD94,1))) -> 0 | X94: =IF(OR(S94=0,S94=""),"-",T94/S94) -> - | Y94: =IF(T94>S94,"SI") -> 0 | AD94: =IF(F94="-","",F94*0.021) | AE94: =IF(S94=0,"-",IF(S94<AD94,(S94/100),((S94-AD94)/100))) -> #VALUE! | AF94: =G94 -> 0 | AG94: =SUM(H94:Q94) -> 0
C95: TOTAL ESCOLAR | F95: =SUM(F73:F94) -> 330 | G95: =SUM(G73:G94) -> 0 | H95: =SUM(H73:H94) -> 0 | I95: =SUM(I73:I94) -> 0 | J95: =SUM(J73:J94) -> 0 | K95: =SUM(K73:K94) -> 0 | L95: =SUM(L73:L94) -> 0 | M95: =SUM(M73:M94) -> 0 | ... Q95: =SUM(Q73:Q94) -> 1 | R95: =COUNTIF((R73:R94),"Si") -> 7 | S95: =IF(F95="-","",SUM(G95:Q95)) -> 3 | T95: =SUM(T73:T94) -> 3 | V95: =IFERROR(VLOOKUP(U95,'Plantilla y Concentrado'!$B$4:$C$811,2,0),"") | W95: =AVERAGE(W73:W94) -> 0.31787773 | X95: =IF(OR(S95=0,S95=""),"-",T95/S95) -> 1 | Y95: =IF(T95>S95,"SI") -> 0 | AD95: =IF(F95="-","",F95*0.021) -> 6.93 | AE95: =IF(S95=0,"-",IF(S95<AD95,(S95/100),((S95-AD95)/100))) -> 0.03 | AF95: =G95 -> 0 | AG95: =SUM(H95:Q95) -> 3
C96: B | D96: Infantiles | E96: 10B | F96: 81 | G96: 0 | H96: 0 | I96: 0 | J96: 0 | K96: 0 | L96: 0 | M96: 0 | N96: 0 | O96: 0 | P96: 0 | Q96: 0 | R96: SI | S96: =IF(F96="-","",SUM(G96:Q96)) -> 0 | T96: 0 | U96: 154648 | V96: =IFERROR(VLOOKUP(U96,'Plantilla y Concentrado'!$B$4:$C$811,2,0),"") -> Sanchez Vazquez Anayareli | W96: =IF(S96=0,1,IF(S96>AD96,(1-AE96),IF(S96<AD96,1))) -> 1 | X96: =IF(OR(S96=0,S96=""),"-",T96/S96) -> - | Y96: =IF(T96>S96,"SI") -> 0 | AD96: =IF(F96="-","",F96*0.021) -> 1.701 | AE96: =IF(S96=0,"-",IF(S96<AD96,(S96/100),((S96-AD96)/100))) -> - | AF96: =G96 -> 0 | AG96: =SUM(H96:Q96) -> 0
C97: B | D97: Infantiles | E97: 11 | F97: 82 | G97: 0 | H97: 0 | I97: 0 | J97: 0 | K97: 0 | L97: 0 | M97: 0 | N97: 0 | O97: 0 | P97: 0 | Q97: 0 | R97: SI | S97: =IF(F97="-","",SUM(G97:Q97)) -> 0 | T97: 0 | U97: 154648 | V97: =IFERROR(VLOOKUP(U97,'Plantilla y Concentrado'!$B$4:$C$811,2,0),"") -> Sanchez Vazquez Anayareli | W97: =IF(S97=0,1,IF(S97>AD97,(1-AE97),IF(S97<AD97,1))) -> 1 | X97: =IF(OR(S97=0,S97=""),"-",T97/S97) -> - | Y97: =IF(T97>S97,"SI") -> 0 | AD97: =IF(F97="-","",F97*0.021) -> 1.722 | AE97: =IF(S97=0,"-",IF(S97<AD97,(S97/100),((S97-AD97)/100))) -> - | AF97: =G97 -> 0 | AG97: =SUM(H97:Q97) -> 0
C98: B | D98: Infantiles | E98: 12 | F98: 63 | G98: 0 | H98: 0 | I98: 0 | J98: 0 | K98: 0 | L98: 0 | M98: 0 | N98: 0 | O98: 0 | P98: 0 | Q98: 0 | R98: SI | S98: =IF(F98="-","",SUM(G98:Q98)) -> 0 | T98: 0 | U98: 154648 | V98: =IFERROR(VLOOKUP(U98,'Plantilla y Concentrado'!$B$4:$C$811,2,0),"") -> Sanchez Vazquez Anayareli | W98: =IF(S98=0,1,IF(S98>AD98,(1-AE98),IF(S98<AD98,1))) -> 1 | X98: =IF(OR(S98=0,S98=""),"-",T98/S98) -> - | Y98: =IF(T98>S98,"SI") -> 0 | AD98: =IF(F98="-","",F98*0.021) -> 1.323 | AE98: =IF(S98=0,"-",IF(S98<AD98,(S98/100),((S98-AD98)/100))) -> - | AF98: =G98 -> 0 | AG98: =SUM(H98:Q98) -> 0
C99: B | D99: Infantiles | E99: 13 | F99: 65 | G99: 0 | H99: 1 | I99: 0 | J99: 0 | K99: 0 | L99: 0 | M99: 0 | N99: 0 | O99: 0 | P99: 0 | Q99: 0 | R99: SI | S99: =IF(F99="-","",SUM(G99:Q99)) -> 1 | T99: 1 | U99: 154648 | V99: =IFERROR(VLOOKUP(U99,'Plantilla y Concentrado'!$B$4:$C$811,2,0),"") -> Sanchez Vazquez Anayareli | W99: =IF(S99=0,1,IF(S99>AD99,(1-AE99),IF(S99<AD99,1))) -> 1 | X99: =IF(OR(S99=0,S99=""),"-",T99/S99) -> 1 | Y99: =IF(T99>S99,"SI") -> 0 | AD99: =IF(F99="-","",F99*0.021) -> 1.365 | AE99: =IF(S99=0,"-",IF(S99<AD99,(S99/100),((S99-AD99)/100))) -> 0.01 | AF99: =G99 -> 0 | AG99: =SUM(H99:Q99) -> 1
C100: B | D100: Infantiles | E100: 14A | F100: 25 | G100: 0 | H100: 0 | I100: 0 | J100: 0 | K100: 0 | L100: 0 | M100: 0 | N100: 0 | O100: 0 | P100: 0 | Q100: 0 | R100: - | S100: =IF(F100="-","",SUM(G100:Q100)) -> 0 | T100: 0 | U100: 154648 | V100: =IFERROR(VLOOKUP(U100,'Plantilla y Concentrado'!$B$4:$C$811,2,0),"") -> Sanchez Vazquez Anayareli | W100: =IF(S100=0,1,IF(S100>AD100,(1-AE100),IF(S100<AD100,1))) -> 1 | X100: =IF(OR(S100=0,S100=""),"-",T100/S100) -> - | Y100: =IF(T100>S100,"SI") -> 0 | AD100: =IF(F100="-","",F100*0.021) -> 0.525 | AE100: =IF(S100=0,"-",IF(S100<AD100,(S100/100),((S100-AD100)/100))) -> - | AF100: =G100 -> 0 | AG100: =SUM(H100:Q100) -> 0
C101: B | D101: Infantiles | F101: - | G101: 0 | H101: 0 | I101: 0 | J101: 0 | K101: 0 | L101: 0 | M101: 0 | N101: 0 | O101: 0 | P101: 0 | Q101: 0 | R101: - | S101: =IF(F101="-","",SUM(G101:Q101)) | T101: 0 | V101: =IFERROR(VLOOKUP(U101,'Plantilla y Concentrado'!$B$4:$C$811,2,0),"") | W101: =IF(S101=0,1,IF(S101>AD101,(1-AE101),IF(S101<AD101,1))) -> 0 | X101: =IF(OR(S101=0,S101=""),"-",T101/S101) -> - | Y101: =IF(T101>S101,"SI") -> 0 | AD101: =IF(F101="-","",F101*0.021) | AE101: =IF(S101=0,"-",IF(S101<AD101,(S101/100),((S101-AD101)/100))) -> #VALUE! | AF101: =G101 -> 0 | AG101: =SUM(H101:Q101) -> 0
C102: B | D102: Infantiles | F102: - | G102: 0 | H102: 0 | I102: 0 | J102: 0 | K102: 0 | L102: 0 | M102: 0 | N102: 0 | O102: 0 | P102: 0 | Q102: 0 | R102: - | S102: =IF(F102="-","",SUM(G102:Q102)) | T102: 0 | V102: =IFERROR(VLOOKUP(U102,'Plantilla y Concentrado'!$B$4:$C$811,2,0),"") | W102: =IF(S102=0,1,IF(S102>AD102,(1-AE102),IF(S102<AD102,1))) -> 0 | X102: =IF(OR(S102=0,S102=""),"-",T102/S102) -> - | Y102: =IF(T102>S102,"SI") -> 0 | AD102: =IF(F102="-","",F102*0.021) | AE102: =IF(S102=0,"-",IF(S102<AD102,(S102/100),((S102-AD102)/100))) -> #VALUE! | AF102: =G102 -> 0 | AG102: =SUM(H102:Q102) -> 0
C103: B | D103: Infantiles | F103: - | G103: 0 | H103: 0 | I103: 0 | J103: 0 | K103: 0 | L103: 0 | M103: 0 | N103: 0 | O103: 0 | P103: 0 | Q103: 0 | R103: - | S103: =IF(F103="-","",SUM(G103:Q103)) | T103: 0 | V103: =IFERROR(VLOOKUP(U103,'Plantilla y Concentrado'!$B$4:$C$811,2,0),"") | W103: =IF(S103=0,1,IF(S103>AD103,(1-AE103),IF(S103<AD103,1))) -> 0 | X103: =IF(OR(S103=0,S103=""),"-",T103/S103) -> - | Y103: =IF(T103>S103,"SI") -> 0 | AD103: =IF(F103="-","",F103*0.021) | AE103: =IF(S103=0,"-",IF(S103<AD103,(S103/100),((S103-AD103)/100))) -> #VALUE! | AF103: =G103 -> 0 | AG103: =SUM(H103:Q103) -> 0
C104: B | D104: Infantiles | F104: - | G104: 0 | H104: 0 | I104: 0 | J104: 0 | K104: 0 | L104: 0 | M104: 0 | N104: 0 | O104: 0 | P104: 0 | Q104: 0 | R104: - | S104: =IF(F104="-","",SUM(G104:Q104)) | T104: 0 | V104: =IFERROR(VLOOKUP(U104,'Plantilla y Concentrado'!$B$4:$C$811,2,0),"") | W104: =IF(S104=0,1,IF(S104>AD104,(1-AE104),IF(S104<AD104,1))) -> 0 | X104: =IF(OR(S104=0,S104=""),"-",T104/S104) -> - | Y104: =IF(T104>S104,"SI") -> 0 | AD104: =IF(F104="-","",F104*0.021) | AE104: =IF(S104=0,"-",IF(S104<AD104,(S104/100),((S104-AD104)/100))) -> #VALUE! | AF104: =G104 -> 0 | AG104: =SUM(H104:Q104) -> 0
C105: B | D105: Infantiles | F105: - | G105: 0 | H105: 0 | I105: 0 | J105: 0 | K105: 0 | L105: 0 | M105: 0 | N105: 0 | O105: 0 | P105: 0 | Q105: 0 | R105: - | S105: =IF(F105="-","",SUM(G105:Q105)) | T105: 0 | V105: =IFERROR(VLOOKUP(U105,'Plantilla y Concentrado'!$B$4:$C$811,2,0),"") | W105: =IF(S105=0,1,IF(S105>AD105,(1-AE105),IF(S105<AD105,1))) -> 0 | X105: =IF(OR(S105=0,S105=""),"-",T105/S105) -> - | Y105: =IF(T105>S105,"SI") -> 0 | AD105: =IF(F105="-","",F105*0.021) | AE105: =IF(S105=0,"-",IF(S105<AD105,(S105/100),((S105-AD105)/100))) -> #VALUE! | AF105: =G105 -> 0 | AG105: =SUM(H105:Q105) -> 0
C106: B | D106: Infantiles | F106: - | G106: 0 | H106: 0 | I106: 0 | J106: 0 | K106: 0 | L106: 0 | M106: 0 | N106: 0 | O106: 0 | P106: 0 | Q106: 0 | R106: - | S106: =IF(F106="-","",SUM(G106:Q106)) | T106: 0 | V106: =IFERROR(VLOOKUP(U106,'Plantilla y Concentrado'!$B$4:$C$811,2,0),"") | W106: =IF(S106=0,1,IF(S106>AD106,(1-AE106),IF(S106<AD106,1))) -> 0 | X106: =IF(OR(S106=0,S106=""),"-",T106/S106) -> - | Y106: =IF(T106>S106,"SI") -> 0 | AD106: =IF(F106="-","",F106*0.021) | AE106: =IF(S106=0,"-",IF(S106<AD106,(S106/100),((S106-AD106)/100))) -> #VALUE! | AF106: =G106 -> 0 | AG106: =SUM(H106:Q106) -> 0
...

Sheet Incidencias Colaborador
A1: Incidencias colaborador Calzado | N1: Incidencias colaborador Ropa
A2: Tienda | B2: Catalogo | C2: Nomina | D2: Nombre | F2: INCIDENCIAS OPERATIVAS | N2: Tienda | O2: Catalogo | P2: Nomina | Q2: Nombre | T2: INCIDENCIAS OPERATIVAS
E3: Pasillo | F3: Frenteos | G3: Negados por exhibición | H3: Falta de exhibición | I3: Exhibiciones fuera de politica | J3: # de piezas revueltas | K3: Modelos mal entallados | L3: Total de incidencias | R3: Pasillo | S3: Negados de bodega venta | T3: Negados por exhibición | U3: # de piezas revueltas | V3: Modelos mal entallados | W3: Modelo ordenado y/o acondicionado | X3: Total de incidencias
A4: ='Exhibiciones '!$A$4 -> ECATEPEC | B4: =DBot!$D$4 -> BOTAS | C4: =DBot!AG9 -> 127209 | D4: =IFERROR(VLOOKUP(C4,'Plantilla y Concentrado'!$B$4:$C$677,2,0),"") -> Castillo Ramirez Tania Mayeli | E4: =DBot!A9 -> 1 | F4: =DBot!D9 -> 0 | G4: =DBot!M9 -> 0 | J4: =DBot!U9 -> 0 | K4: =DBot!V9 -> 0 | L4: =SUM(F4:K4) -> 0 | M4: 1 | N4: ='Exhibiciones '!$A$4 -> ECATEPEC | O4: =DMes1!$E$4 -> Ropa Doblada | P4: =DMes1!AC10 -> 144847 | Q4: =DMes1!AD10 -> Islas Magaña Janai | R4: =DMes1!B10 -> Mesa 1 | S4: - | T4: =DMes1!G10 -> 0 | U4: =DMes1!T10 -> 0 | V4: =DMes1!R10 -> 0 | W4: =DMes1!S10 -> 0 | X4: =SUM(S4:W4) -> 0
A5: ='Exhibiciones '!$A$4 -> ECATEPEC | B5: =DBot!$D$4 -> BOTAS | C5: =DBot!AG10 -> 144695 | D5: =IFERROR(VLOOKUP(C5,'Plantilla y Concentrado'!$B$4:$C$677,2,0),"") -> Alvarez Becerra Emiliano | E5: =DBot!A10 -> 2 | F5: =DBot!D10 -> 0 | G5: =DBot!M10 -> 0 | J5: =DBot!U10 -> 0 | K5: =DBot!V10 -> 0 | L5: =SUM(F5:K5) -> 0 | M5: 1 | N5: ='Exhibiciones '!$A$4 -> ECATEPEC | O5: =DMes1!$E$4 -> Ropa Doblada | P5: =DMes1!AC11 -> 144847 | Q5: =DMes1!AD11 -> Islas Magaña Janai | R5: =DMes1!B11 -> Mesa 2 | S5: - | T5: =DMes1!G11 -> 0 | U5: =DMes1!T11 -> 0 | V5: =DMes1!R11 -> 0 | W5: =DMes1!S11 -> 0 | X5: =SUM(S5:W5) -> 0 | Y5: 1
A6: ='Exhibiciones '!$A$4 -> ECATEPEC | B6: =DBot!$D$4 -> BOTAS | C6: =DBot!AG11 -> 144695 | D6: =IFERROR(VLOOKUP(C6,'Plantilla y Concentrado'!$B$4:$C$677,2,0),"") -> Alvarez Becerra Emiliano | E6: =DBot!A11 -> 3 | F6: =DBot!D11 -> 0 | G6: =DBot!M11 -> 0 | J6: =DBot!U11 -> 0 | K6: =DBot!V11 -> 0 | L6: =SUM(F6:K6) -> 0 | M6: 1 | N6: ='Exhibiciones '!$A$4 -> ECATEPEC | O6: =DMes1!$E$4 -> Ropa Doblada | P6: =DMes1!AC12 -> 144847 | Q6: =DMes1!AD12 -> Islas Magaña Janai | R6: =DMes1!B12 -> Mesa 3 | S6: - | T6: =DMes1!G12 -> 0 | U6: =DMes1!T12 -> 0 | V6: =DMes1!R12 -> 0 | W6: =DMes1!S12 -> 0 | X6: =SUM(S6:W6) -> 0 | Y6: 1
A7: ='Exhibiciones '!$A$4 -> ECATEPEC | B7: =DBot!$D$4 -> BOTAS | C7: =DBot!AG12 -> 155938 | D7: =IFERROR(VLOOKUP(C7,'Plantilla y Concentrado'!$B$4:$C$677,2,0),"") -> Aguilar Flores Erika Jazmin | E7: =DBot!A12 -> 15 | F7: =DBot!D12 -> 0 | G7: =DBot!M12 -> 0 | J7: =DBot!U12 -> 0 | K7: =DBot!V12 -> 0 | L7: =SUM(F7:K7) -> 0 | M7: 1 | N7: ='Exhibiciones '!$A$4 -> ECATEPEC | O7: =DMes1!$E$4 -> Ropa Doblada | P7: =DMes1!AC13 -> 147547 | Q7: =DMes1!AD13 -> Rojas Diaz Maria Irene | R7: =DMes1!B13 -> Mesa 4 | S7: - | T7: =DMes1!G13 -> 0 | U7: =DMes1!T13 -> 0 | V7: =DMes1!R13 -> 0 | W7: =DMes1!S13 -> 0 | X7: =SUM(S7:W7) -> 0 | Y7: 1
A8: ='Exhibiciones '!$A$4 -> ECATEPEC | B8: =DBot!$D$4 -> BOTAS | C8: =DBot!AG13 -> 158001 | D8: =IFERROR(VLOOKUP(C8,'Plantilla y Concentrado'!$B$4:$C$677,2,0),"") -> Nuñez Garcia Clarissa Naomi | E8: =DBot!A13 -> 16 | F8: =DBot!D13 -> 0 | G8: =DBot!M13 -> 0 | J8: =DBot!U13 -> 0 | K8: =DBot!V13 -> 0 | L8: =SUM(F8:K8) -> 0 | M8: 1 | N8: ='Exhibiciones '!$A$4 -> ECATEPEC | O8: =DMes1!$E$4 -> Ropa Doblada | P8: =DMes1!AC14 -> 147547 | Q8: =DMes1!AD14 -> Rojas Diaz Maria Irene | R8: =DMes1!B14 -> Mesa 5 | S8: - | T8: =DMes1!G14 -> 0 | U8: =DMes1!T14 -> 0 | V8: =DMes1!R14 -> 0 | W8: =DMes1!S14 -> 0 | X8: =SUM(S8:W8) -> 0 | Y8: 1
A9: ='Exhibiciones '!$A$4 -> ECATEPEC | B9: =DBot!$D$4 -> BOTAS | C9: =DBot!AG14 -> 154648 | D9: =IFERROR(VLOOKUP(C9,'Plantilla y Concentrado'!$B$4:$C$677,2,0),"") -> Sanchez Vazquez Anayareli | E9: =DBot!A14 -> 17 | F9: =DBot!D14 -> 0 | G9: =DBot!M14 -> 0 | J9: =DBot!U14 -> 0 | K9: =DBot!V14 -> 0 | L9: =SUM(F9:K9) -> 0 | M9: 1 | N9: ='Exhibiciones '!$A$4 -> ECATEPEC | O9: =DMes1!$E$4 -> Ropa Doblada | P9: =DMes1!AC15 -> 147547 | Q9: =DMes1!AD15 -> Rojas Diaz Maria Irene | R9: =DMes1!B15 -> Mesa 6 | S9: - | T9: =DMes1!G15 -> 0 | U9: =DMes1!T15 -> 0 | V9: =DMes1!R15 -> 0 | W9: =DMes1!S15 -> 0 | X9: =SUM(S9:W9) -> 0 | Y9: 1
A10: ='Exhibiciones '!$A$4 -> ECATEPEC | B10: =DBot!$D$4 -> BOTAS | C10: =DBot!AG15 -> 144695 | D10: =IFERROR(VLOOKUP(C10,'Plantilla y Concentrado'!$B$4:$C$677,2,0),"") -> Alvarez Becerra Emiliano | E10: =DBot!A15 -> 18 | F10: =DBot!D15 -> 0 | G10: =DBot!M15 -> 0 | J10: =DBot!U15 -> 0 | K10: =DBot!V15 -> 0 | L10: =SUM(F10:K10) -> 0 | M10: 1 | N10: ='Exhibiciones '!$A$4 -> ECATEPEC | O10: =DMes1!$E$4 -> Ropa Doblada | P10: =DMes1!AC16 -> 147547 | Q10: =DMes1!AD16 -> Rojas Diaz Maria Irene | R10: =DMes1!B16 -> Mesa 7 | S10: - | T10: =DMes1!G16 -> 0 | U10: =DMes1!T16 -> 0 | V10: =DMes1!R16 -> 0 | W10: =DMes1!S16 -> 0 | X10: =SUM(S10:W10) -> 0 | Y10: 1
A11: ='Exhibiciones '!$A$4 -> ECATEPEC | B11: =DBot!$D$4 -> BOTAS | C11: =DBot!AG16 -> 136867 | D11: =IFERROR(VLOOKUP(C11,'Plantilla y Concentrado'!$B$4:$C$677,2,0),"") -> Barba Ramirez Jatziri Lizeth | E11: =DBot!A16 -> 19 | F11: =DBot!D16 -> 0 | G11: =DBot!M16 -> 0 | J11: =DBot!U16 -> 0 | K11: =DBot!V16 -> 0 | L11: =SUM(F11:K11) -> 0 | M11: 1 | N11: ='Exhibiciones '!$A$4 -> ECATEPEC | O11: =DMes1!$E$4 -> Ropa Doblada | P11: =DMes1!AC17 -> 158054 | Q11: =DMes1!AD17 -> Hernandez Hernandez Lissete | R11: =DMes1!B17 -> Mesa 8 | S11: - | T11: =DMes1!G17 -> 0 | U11: =DMes1!T17 -> 0 | V11: =DMes1!R17 -> 0 | W11: =DMes1!S17 -> 0 | X11: =SUM(S11:W11) -> 0 | Y11: 1
A12: ='Exhibiciones '!$A$4 -> ECATEPEC | B12: =DBot!$D$4 -> BOTAS | C12: =DBot!AG17 -> 155938 | D12: =IFERROR(VLOOKUP(C12,'Plantilla y Concentrado'!$B$4:$C$677,2,0),"") -> Aguilar Flores Erika Jazmin | E12: =DBot!A17 -> 20 | F12: =DBot!D17 -> 1 | G12: =DBot!M17 -> 0 | J12: =DBot!U17 -> 0 | K12: =DBot!V17 -> 3 | L12: =SUM(F12:K12) -> 4 | M12: 1 | N12: ='Exhibiciones '!$A$4 -> ECATEPEC | O12: =DMes1!$E$4 -> Ropa Doblada | P12: =DMes1!AC18 -> 158054 | Q12: =DMes1!AD18 -> Hernandez Hernandez Lissete | R12: =DMes1!B18 -> Mesa 9 | S12: - | T12: =DMes1!G18 -> 2 | U12: =DMes1!T18 -> 0 | V12: =DMes1!R18 -> 0 | W12: =DMes1!S18 -> 0 | X12: =SUM(S12:W12) -> 2 | Y12: 1
A13: ='Exhibiciones '!$A$4 -> ECATEPEC | B13: =DBot!$D$4 -> BOTAS | C13: =DBot!AG18 -> 154648 | D13: =IFERROR(VLOOKUP(C13,'Plantilla y Concentrado'!$B$4:$C$677,2,0),"") -> Sanchez Vazquez Anayareli | E13: =DBot!A18 -> 21 | F13: =DBot!D18 -> 0 | G13: =DBot!M18 -> 0 | J13: =DBot!U18 -> 0 | K13: =DBot!V18 -> 0 | L13: =SUM(F13:K13) -> 0 | M13: 1 | N13: ='Exhibiciones '!$A$4 -> ECATEPEC | O13: =DMes1!$E$4 -> Ropa Doblada | P13: =DMes1!AC19 -> 158054 | Q13: =DMes1!AD19 -> Hernandez Hernandez Lissete | R13: =DMes1!B19 -> Mesa 10 | S13: - | T13: =DMes1!G19 -> 0 | U13: =DMes1!T19 -> 0 | V13: =DMes1!R19 -> 0 | W13: =DMes1!S19 -> 0 | X13: =SUM(S13:W13) -> 0 | Y13: 1
A14: ='Exhibiciones '!$A$4 -> ECATEPEC | B14: =DBot!$D$4 -> BOTAS | C14: =DBot!AG19 -> 158001 | D14: =IFERROR(VLOOKUP(C14,'Plantilla y Concentrado'!$B$4:$C$677,2,0),"") -> Nuñez Garcia Clarissa Naomi | E14: =DBot!A19 -> 22 | F14: =DBot!D19 -> 0 | G14: =DBot!M19 -> 0 | J14: =DBot!U19 -> 1 | K14: =DBot!V19 -> 0 | L14: =SUM(F14:K14) -> 1 | M14: 1 | N14: ='Exhibiciones '!$A$4 -> ECATEPEC | O14: =DMes1!$E$4 -> Ropa Doblada | P14: =DMes1!AC20 -> 118030 | Q14: =DMes1!AD20 -> Aguilar Bello Martha Maria | R14: =DMes1!B20 -> Mesa 11 | S14: - | T14: =DMes1!G20 -> 0 | U14: =DMes1!T20 -> 0 | V14: =DMes1!R20 -> 0 | W14: =DMes1!S20 -> 0 | X14: =SUM(S14:W14) -> 0 | Y14: 1
A15: ='Exhibiciones '!$A$4 -> ECATEPEC | B15: =DBot!$D$4 -> BOTAS | C15: =DBot!AG20 -> 155938 | D15: =IFERROR(VLOOKUP(C15,'Plantilla y Concentrado'!$B$4:$C$677,2,0),"") -> Aguilar Flores Erika Jazmin | E15: =DBot!A20 -> 23 | F15: =DBot!D20 -> 0 | G15: =DBot!M20 -> 0 | J15: =DBot!U20 -> 0 | K15: =DBot!V20 -> 0 | L15: =SUM(F15:K15) -> 0 | M15: 1 | N15: ='Exhibiciones '!$A$4 -> ECATEPEC | O15: =DMes1!$E$4 -> Ropa Doblada | P15: =DMes1!AC21 -> 118030 | Q15: =DMes1!AD21 -> Aguilar Bello Martha Maria | R15: =DMes1!B21 -> Mesa 12 | S15: - | T15: =DMes1!G21 -> 0 | U15: =DMes1!T21 -> 0 | V15: =DMes1!R21 -> 0 | W15: =DMes1!S21 -> 0 | X15: =SUM(S15:W15) -> 0 | Y15: 1
A16: ='Exhibiciones '!$A$4 -> ECATEPEC | B16: =DBot!$D$4 -> BOTAS | C16: =DBot!AG21 -> 136867 | D16: =IFERROR(VLOOKUP(C16,'Plantilla y Concentrado'!$B$4:$C$677,2,0),"") -> Barba Ramirez Jatziri Lizeth | E16: =DBot!A21 -> 24 | F16: =DBot!D21 -> 0 | G16: =DBot!M21 -> 0 | J16: =DBot!U21 -> 0 | K16: =DBot!V21 -> 0 | L16: =SUM(F16:K16) -> 0 | M16: 1 | N16: ='Exhibiciones '!$A$4 -> ECATEPEC | O16: =DMes1!$E$4 -> Ropa Doblada | P16: =DMes1!AC22 -> 118030 | Q16: =DMes1!AD22 -> Aguilar Bello Martha Maria | R16: =DMes1!B22 -> Mesa 13 | S16: - | T16: =DMes1!G22 -> 0 | U16: =DMes1!T22 -> 0 | V16: =DMes1!R22 -> 0 | W16: =DMes1!S22 -> 0 | X16: =SUM(S16:W16) -> 0 | Y16: 1
... A30: ='Exhibiciones '!$A$4 -> ECATEPEC | B30: =DBot!$D$4 -> BOTAS | C30: =DBot!AG35 -> 0 | D30: =IFERROR(VLOOKUP(C30,'Plantilla y Concentrado'!$B$4:$C$677,2,0),"") | E30: =DBot!A35 -> 0 | F30: =DBot!D35 -> 0 | G30: =DBot!M35 -> 0 | J30: =DBot!U35 -> 0 | K30: =DBot!V35 -> 0 | L30: =SUM(F30:K30) -> 0 | M30: 1 | N30: ='Exhibiciones '!$A$4 -> ECATEPEC | O30: =DMes1!$E$4 -> Ropa Doblada | P30: =DMes1!AC36 -> 149039 | Q30: =DMes1!AD36 -> Californias Almaraz Berenice | R30: =DMes1!B36 -> Mesa 39 | S30: - | T30: =DMes1!G36 -> 0 | U30: =DMes1!T36 -> 0 | V30: =DMes1!R36 -> 0 | W30: =DMes1!S36 -> 0 | X30: =SUM(S30:W30) -> 0 | Y30: 1
A31: ='Exhibiciones '!$A$4 -> ECATEPEC | B31: =DUrb!$E$15 -> 0 | C31: =DUrb!AH20 -> Rosas Paniagua Elizabeth | D31: =IFERROR(VLOOKUP(C31,'Plantilla y Concentrado'!$B$4:$C$677,2,0),"") | E31: =DUrb!B20 -> 800 | F31: =DUrb!E21 -> 0 | G31: =DUrb!N20 -> 0 | J31: =DUrb!V20 -> 5 | K31: =DUrb!W20 -> 0 | L31: =SUM(F31:K31) -> 5 | M31: 1 | N31: ='Exhibiciones '!$A$4 -> ECATEPEC | O31: =DMes1!$E$4 -> Ropa Doblada | P31: =DMes1!AC37 -> 149039 | Q31: =DMes1!AD37 -> Californias Almaraz Berenice | R31: =DMes1!B37 -> Mesa 40 | S31: - | T31: =DMes1!G37 -> 0 | U31: =DMes1!T37 -> 0 | V31: =DMes1!R37 -> 0 | W31: =DMes1!S37 -> 0 | X31: =SUM(S31:W31) -> 0 | Y31: 1
A32: ='Exhibiciones '!$A$4 -> ECATEPEC | B32: =DUrb!$E$15 -> 0 | C32: =DUrb!AH21 -> Lopez Sebastian Karen Jazmin | D32: =IFERROR(VLOOKUP(C32,'Plantilla y Concentrado'!$B$4:$C$677,2,0),"") | E32: =DUrb!B21 -> 367 | F32: =DUrb!E21 -> 0 | G32: =DUrb!N21 -> 0 | J32: =DUrb!V21 -> 0 | K32: =DUrb!W21 -> 0 | L32: =SUM(F32:K32) -> 0 | M32: 1 | N32: ='Exhibiciones '!$A$4 -> ECATEPEC | O32: =DMes1!$E$4 -> Ropa Doblada | P32: =DMes1!AC38 -> 149039 | Q32: =DMes1!AD38 -> Californias Almaraz Berenice | R32: =DMes1!B38 -> Mesa 41 | S32: - | T32: =DMes1!G38 -> 0 | U32: =DMes1!T38 -> 0 | V32: =DMes1!R38 -> 0 | W32: =DMes1!S38 -> 0 | X32: =SUM(S32:W32) -> 0 | Y32: 1
A33: ='Exhibiciones '!$A$4 -> ECATEPEC | B33: =DUrb!$E$15 -> 0 | C33: =DUrb!AH22 | D33: =IFERROR(VLOOKUP(C33,'Plantilla y Concentrado'!$B$4:$C$677,2,0),"") | E33: =DUrb!B22 -> 0 | F33: =DUrb!E22 -> 0 | G33: =DUrb!N22 -> 0 | J33: =DUrb!V22 -> 0 | K33: =DUrb!W22 -> 0 | L33: =SUM(F33:K33) -> 0 | M33: 1 | N33: ='Exhibiciones '!$A$4 -> ECATEPEC | O33: =DMes1!$E$4 -> Ropa Doblada | P33: =DMes1!AC39 -> 149039 | Q33: =DMes1!AD39 -> Californias Almaraz Berenice | R33: =DMes1!B39 -> Mesa 42 | S33: - | T33: =DMes1!G39 -> 0 | U33: =DMes1!T39 -> 0 | V33: =DMes1!R39 -> 0 | W33: =DMes1!S39 -> 0 | X33: =SUM(S33:W33) -> 0 | Y33: 1
A34: ='Exhibiciones '!$A$4 -> ECATEPEC | B34: =DUrb!$E$15 -> 0 | C34: =DUrb!AH23 | D34: =IFERROR(VLOOKUP(C34,'Plantilla y Concentrado'!$B$4:$C$677,2,0),"") | E34: =DUrb!B23 -> 0 | F34: =DUrb!E23 -> 0 | G34: =DUrb!N23 -> 0 | J34: =DUrb!V23 -> 0 | K34: =DUrb!W23 -> 0 | L34: =SUM(F34:K34) -> 0 | M34: 1 | N34: ='Exhibiciones '!$A$4 -> ECATEPEC | O34: =DMes1!$E$4 -> Ropa Doblada | P34: =DMes1!AC40 -> 149039 | Q34: =DMes1!AD40 -> Californias Almaraz Berenice | R34: =DMes1!B40 -> Mesa 43 | S34: - | T34: =DMes1!G40 -> 0 | U34: =DMes1!T40 -> 0 | V34: =DMes1!R40 -> 0 | W34: =DMes1!S40 -> 0 | X34: =SUM(S34:W34) -> 0 | Y34: 1
A35: ='Exhibiciones '!$A$4 -> ECATEPEC | B35: =DUrb!$E$15 -> 0 | C35: =DUrb!AH24 | D35: =IFERROR(VLOOKUP(C35,'Plantilla y Concentrado'!$B$4:$C$677,2,0),"") | E35: =DUrb!B24 -> 0 | F35: =DUrb!E24 -> 0 | G35: =DUrb!N24 -> 0 | J35: =DUrb!V24 -> 0 | K35: =DUrb!W24 -> 0 | L35: =SUM(F35:K35) -> 0 | M35: 1 | N35: ='Exhibiciones '!$A$4 -> ECATEPEC | O35: =DMes1!$E$4 -> Ropa Doblada | P35: =DMes1!AC41 -> 34379 | Q35: =DMes1!AD41 -> Gamboa Soto Concepcion del Carmen | R35: =DMes1!B41 -> Mesa 44 | S35: - | T35: =DMes1!G41 -> 1 | U35: =DMes1!T41 -> 0 | V35: =DMes1!R41 -> 0 | W35: =DMes1!S41 -> 0 | X35: =SUM(S35:W35) -> 1 | Y35: 1
A36: ='Exhibiciones '!$A$4 -> ECATEPEC | B36: =DUrb!$E$15 -> 0 | C36: =DUrb!AH25 | D36: =IFERROR(VLOOKUP(C36,'Plantilla y Concentrado'!$B$4:$C$677,2,0),"") | E36: =DUrb!B25 -> 0 | F36: =DUrb!E25 -> 0 | G36: =DUrb!N25 -> 0 | J36: =DUrb!V25 -> 0 | K36: =DUrb!W25 -> 0 | L36: =SUM(F36:K36) -> 0 | M36: 1 | N36: ='Exhibiciones '!$A$4 -> ECATEPEC | O36: =DMes1!$E$4 -> Ropa Doblada | P36: =DMes1!AC42 -> 34379 | Q36: =DMes1!AD42 -> Gamboa Soto Concepcion del Carmen | R36: =DMes1!B42 -> Mesa 45 | S36: - | T36: =DMes1!G42 -> 0 | U36: =DMes1!T42 -> 0 | V36: =DMes1!R42 -> 0 | W36: =DMes1!S42 -> 0 | X36: =SUM(S36:W36) -> 0 | Y36: 1
A37: ='Exhibiciones '!$A$4 -> ECATEPEC | B37: =DUrb!$E$15 -> 0 | C37: =DUrb!AH26 | D37: =IFERROR(VLOOKUP(C37,'Plantilla y Concentrado'!$B$4:$C$677,2,0),"") | E37: =DUrb!B26 -> 0 | F37: =DUrb!E26 -> 0 | G37: =DUrb!N26 -> 0 | J37: =DUrb!V26 -> 0 | K37: =DUrb!W26 -> 0 | L37: =SUM(F37:K37) -> 0 | M37: 1 | N37: ='Exhibiciones '!$A$4 -> ECATEPEC | O37: =DMes1!$E$4 -> Ropa Doblada | P37: =DMes1!AC43 -> 34379 | Q37: =DMes1!AD43 -> Gamboa Soto Concepcion del Carmen | R37: =DMes1!B43 -> Mesa 46 | S37: - | T37: =DMes1!G43 -> 0 | U37: =DMes1!T43 -> 0 | V37: =DMes1!R43 -> 0 | W37: =DMes1!S43 -> 0 | X37: =SUM(S37:W37) -> 0 | Y37: 1
A38: ='Exhibiciones '!$A$4 -> ECATEPEC | B38: =DUrb!$E$15 -> 0 | C38: =DUrb!AH27 | D38: =IFERROR(VLOOKUP(C38,'Plantilla y Concentrado'!$B$4:$C$677,2,0),"") | E38: =DUrb!B27 -> 0 | F38: =DUrb!E27 -> 0 | G38: =DUrb!N27 -> 0 | J38: =DUrb!V27 -> 0 | K38: =DUrb!W27 -> 0 | L38: =SUM(F38:K38) -> 0 | M38: 1 | N38: ='Exhibiciones '!$A$4 -> ECATEPEC | O38: =DMes1!$E$4 -> Ropa Doblada | P38: =DMes1!AC44 -> 34379 | Q38: =DMes1!AD44 -> Gamboa Soto Concepcion del Carmen | R38: =DMes1!B44 -> Mesa 47 | S38: - | T38: =DMes1!G44 -> 0 | U38: =DMes1!T44 -> 0 | V38: =DMes1!R44 -> 0 | W38: =DMes1!S44 -> 0 | X38: =SUM(S38:W38) -> 0 | Y38: 1
A39: ='Exhibiciones '!$A$4 -> ECATEPEC | B39: =DUrb!$E$15 -> 0 | C39: =DUrb!AH28 | D39: =IFERROR(VLOOKUP(C39,'Plantilla y Concentrado'!$B$4:$C$677,2,0),"") | E39: =DUrb!B28 -> 0 | F39: =DUrb!E28 -> 0 | G39: =DUrb!N28 -> 0 | J39: =DUrb!V28 -> 0 | K39: =DUrb!W28 -> 0 | L39: =SUM(F39:K39) -> 0 | M39: 1 | N39: ='Exhibiciones '!$A$4 -> ECATEPEC | O39: =DMes1!$E$4 -> Ropa Doblada | P39: =DMes1!AC45 -> 34379 | Q39: =DMes1!AD45 -> Gamboa Soto Concepcion del Carmen | R39: =DMes1!B45 -> Mesa 48 | S39: - | T39: =DMes1!G45 -> 0 | U39: =DMes1!T45 -> 0 | V39: =DMes1!R45 -> 0 | W39: =DMes1!S45 -> 0 | X39: =SUM(S39:W39) -> 0 | Y39: 1
A40: ='Exhibiciones '!$A$4 -> ECATEPEC | B40: =DUrb!$E$15 -> 0 | C40: =DUrb!AH29 | D40: =IFERROR(VLOOKUP(C40,'Plantilla y Concentrado'!$B$4:$C$677,2,0),"") | E40: =DUrb!B29 -> 0 | F40: =DUrb!E29 -> 0 | G40: =DUrb!N29 -> 0 | J40: =DUrb!V29 -> 0 | K40: =DUrb!W29 -> 0 | L40: =SUM(F40:K40) -> 0 | M40: 1 | N40: ='Exhibiciones '!$A$4 -> ECATEPEC | O40: =DMes1!$E$4 -> Ropa Doblada | P40: =DMes1!AC46 -> 151655 | Q40: =DMes1!AD46 -> Mireles Saucedo Fabiola Alehandra | R40: =DMes1!B46 -> Mesa 49 | S40: - | T40: =DMes1!G46 -> 0 | U40: =DMes1!T46 -> 0 | V40: =DMes1!R46 -> 0 | W40: =DMes1!S46 -> 0 | X40: =SUM(S40:W40) -> 0 | Y40: 1
A41: ='Exhibiciones '!$A$4 -> ECATEPEC | B41: =DUrb!$E$15 -> 0 | C41: =DUrb!AH30 -> 0 | D41: =IFERROR(VLOOKUP(C41,'Plantilla y Concentrado'!$B$4:$C$677,2,0),"") | E41: =DUrb!B30 -> 8864 | F41: =DUrb!E30 -> 0 | G41: =DUrb!N30 -> 0 | J41: =DUrb!V30 -> 9 | K41: =DUrb!W30 -> 0 | L41: =SUM(F41:K41) -> 9 | M41: 1 | N41: ='Exhibiciones '!$A$4 -> ECATEPEC | O41: =DMes1!$E$4 -> Ropa Doblada | P41: =DMes1!AC47 -> 151655 | Q41: =DMes1!AD47 -> Mireles Saucedo Fabiola Alehandra | R41: =DMes1!B47 -> Mesa 50 | S41: - | T41: =DMes1!G47 -> 0 | U41: =DMes1!T47 -> 0 | V41: =DMes1!R47 -> 0 | W41: =DMes1!S47 -> 0 | X41: =SUM(S41:W41) -> 0 | Y41: 1
A42: ='Exhibiciones '!$A$4 -> ECATEPEC | B42: =DUrb!$E$15 -> 0 | C42: =DUrb!AH31 -> 0 | D42: =IFERROR(VLOOKUP(C42,'Plantilla y Concentrado'!$B$4:$C$677,2,0),"") | E42: =DUrb!B31 -> 0 | F42: =DUrb!E31 -> 0 | G42: =DUrb!N31 -> 0 | J42: =DUrb!V31 -> 0 | K42: =DUrb!W31 -> 0 | L42: =SUM(F42:K42) -> 0 | M42: 1 | N42: ='Exhibiciones '!$A$4 -> ECATEPEC | O42: =DMes1!$E$4 -> Ropa Doblada | P42: =DMes1!AC48 -> 151655 | Q42: =DMes1!AD48 -> Mireles Saucedo Fabiola Alehandra | R42: =DMes1!B48 -> Mesa 51 | S42: - | T42: =DMes1!G48 -> 0 | U42: =DMes1!T48 -> 0 | V42: =DMes1!R48 -> 0 | W42: =DMes1!S48 -> 0 | X42: =SUM(S42:W42) -> 0 | Y42: 1
A43: ='Exhibiciones '!$A$4 -> ECATEPEC | B43: =DUrb!$E$15 -> 0 | C43: =DUrb!AH32 -> 0 | D43: =IFERROR(VLOOKUP(C43,'Plantilla y Concentrado'!$B$4:$C$677,2,0),"") | E43: =DUrb!B32 -> 0 | F43: =DUrb!E32 -> 0 | G43: =DUrb!N32 -> 0 | J43: =DUrb!V32 -> 0 | K43: =DUrb!W32 -> 0 | L43: =SUM(F43:K43) -> 0 | M43: 1 | N43: ='Exhibiciones '!$A$4 -> ECATEPEC | O43: =DMes1!$E$4 -> Ropa Doblada | P43: =DMes1!AC49 -> 0 | Q43: =DMes1!AD49 | R43: =DMes1!B49 -> 0 | S43: - | T43: =DMes1!G49 -> 0 | U43: =DMes1!T49 -> 0 | V43: =DMes1!R49 -> 0 | W43: =DMes1!S49 -> 0 | X43: =SUM(S43:W43) -> 0 | Y43: 1
... A51: ='Exhibiciones '!$A$4 -> ECATEPEC | B51: =DUrb!$E$15 -> 0 | C51: =DUrb!AH40 -> 0 | D51: =IFERROR(VLOOKUP(C51,'Plantilla y Concentrado'!$B$4:$C$677,2,0),"") | E51: =DUrb!B40 -> 0 | F51: =DUrb!E40 -> 0 | G51: =DUrb!N40 -> 0 | J51: =DUrb!V40 -> 0 | K51: =DUrb!W40 -> 0 | L51: =SUM(F51:K51) -> 0 | M51: 1 | N51: ='Exhibiciones '!$A$4 -> ECATEPEC | O51: =DMes1!$E$4 -> Ropa Doblada | P51: =DMes1!AC57 -> 0 | Q51: =DMes1!AD57 | R51: =DMes1!B57 -> 0 | S51: - | T51: =DMes1!G57 -> 0 | U51: =DMes1!T57 -> 0 | V51: =DMes1!R57 -> 0 | W51: =DMes1!S57 -> 0 | X51: =SUM(S51:W51) -> 0 | Y51: 1
A52: ='Exhibiciones '!$A$4 -> ECATEPEC | B52: =DEsc!$D$4 -> Escolar | C52: =DEsc!AG9 -> 127209 | D52: =IFERROR(VLOOKUP(C52,'Plantilla y Concentrado'!$B$4:$C$677,2,0),"") -> Castillo Ramirez Tania Mayeli | E52: =DEsc!A9 -> 41A | F52: =DEsc!D9 -> 0 | G52: =DEsc!M9 -> 0 | J52: =DEsc!U9 -> 1 | K52: =DEsc!V9 -> 0 | L52: =SUM(F52:K52) -> 1 | M52: 1 | N52: ='Exhibiciones '!$A$4 -> ECATEPEC | O52: =DMes1!$E$4 -> Ropa Doblada | P52: =DMes1!AC58 -> 0 | Q52: =DMes1!AD58 | R52: =DMes1!B58 -> 0 | S52: - | T52: =DMes1!G58 -> 0 | U52: =DMes1!T58 -> 0 | V52: =DMes1!R58 -> 0 | W52: =DMes1!S58 -> 0 | X52: =SUM(S52:W52) -> 0 | Y52: 1
A53: ='Exhibiciones '!$A$4 -> ECATEPEC | B53: =DEsc!$D$4 -> Escolar | C53: =DEsc!AG10 -> 136675 | D53: =IFERROR(VLOOKUP(C53,'Plantilla y Concentrado'!$B$4:$C$677,2,0),"") -> Montiel Ramirez Cintya Elizabeth | E53: =DEsc!A10 -> 42 | F53: =DEsc!D10 -> 0 | G53: =DEsc!M10 -> 0 | J53: =DEsc!U10 -> 0 | K53: =DEsc!V10 -> 0 | L53: =SUM(F53:K53) -> 0 | M53: 1 | N53: ='Exhibiciones '!$A$4 -> ECATEPEC | O53: =DMes1!$E$4 -> Ropa Doblada | P53: =DMes1!AC59 -> 0 | Q53: =DMes1!AD59 | R53: =DMes1!B59 -> 0 | S53: - | T53: =DMes1!G59 -> 0 | U53: =DMes1!T59 -> 0 | V53: =DMes1!R59 -> 0 | W53: =DMes1!S59 -> 0 | X53: =SUM(S53:W53) -> 0 | Y53: 1
A54: ='Exhibiciones '!$A$4 -> ECATEPEC | B54: =DEsc!$D$4 -> Escolar | C54: =DEsc!AG11 -> 151630 | D54: =IFERROR(VLOOKUP(C54,'Plantilla y Concentrado'!$B$4:$C$677,2,0),"") -> Muñoz Lara Karla Paola | E54: =DEsc!A11 -> 43 | F54: =DEsc!D11 -> 0 | G54: =DEsc!M11 -> 0 | J54: =DEsc!U11 -> 1 | K54: =DEsc!V11 -> 0 | L54: =SUM(F54:K54) -> 1 | M54: 1 | N54: ='Exhibiciones '!$A$4 -> ECATEPEC | O54: =DMes1!$E$4 -> Ropa Doblada | P54: =DMes1!AC60 -> 0 | Q54: =DMes1!AD60 | R54: =DMes1!B60 -> 0 | S54: - | T54: =DMes1!G60 -> 0 | U54: =DMes1!T60 -> 0 | V54: =DMes1!R60 -> 0 | W54: =DMes1!S60 -> 0 | X54: =SUM(S54:W54) -> 0 | Y54: 1
A55: ='Exhibiciones '!$A$4 -> ECATEPEC | B55: =DEsc!$D$4 -> Escolar | C55: =DEsc!AG12 -> 154648 | D55: =IFERROR(VLOOKUP(C55,'Plantilla y Concentrado'!$B$4:$C$677,2,0),"") -> Sanchez Vazquez Anayareli | E55: =DEsc!A12 -> 44 | F55: =DEsc!D12 -> 0 | G55: =DEsc!M12 -> 0 | J55: =DEsc!U12 -> 0 | K55: =DEsc!V12 -> 0 | L55: =SUM(F55:K55) -> 0 | M55: 1 | N55: ='Exhibiciones '!$A$4 -> ECATEPEC | O55: =DMes1!$E$4 -> Ropa Doblada | P55: =DMes1!AC61 -> 0 | Q55: =DMes1!AD61 | R55: =DMes1!B61 -> 0 | S55: - | T55: =DMes1!G61 -> 0 | U55: =DMes1!T61 -> 0 | V55: =DMes1!R61 -> 0 | W55: =DMes1!S61 -> 0 | X55: =SUM(S55:W55) -> 0 | Y55: 1
A56: ='Exhibiciones '!$A$4 -> ECATEPEC | B56: =DEsc!$D$4 -> Escolar | C56: =DEsc!AG13 -> 136675 | D56: =IFERROR(VLOOKUP(C56,'Plantilla y Concentrado'!$B$4:$C$677,2,0),"") -> Montiel Ramirez Cintya Elizabeth | E56: =DEsc!A13 -> 45 | F56: =DEsc!D13 -> 0 | G56: =DEsc!M13 -> 0 | J56: =DEsc!U13 -> 0 | K56: =DEsc!V13 -> 0 | L56: =SUM(F56:K56) -> 0 | M56: 1 | N56: ='Exhibiciones '!$A$4 -> ECATEPEC | O56: =DMes1!$E$4 -> Ropa Doblada | P56: =DMes1!AC62 -> 0 | Q56: =DMes1!AD62 | R56: =DMes1!B62 -> 0 | S56: - | T56: =DMes1!G62 -> 0 | U56: =DMes1!T62 -> 0 | V56: =DMes1!R62 -> 0 | W56: =DMes1!S62 -> 0 | X56: =SUM(S56:W56) -> 0 | Y56: 1
A57: ='Exhibiciones '!$A$4 -> ECATEPEC | B57: =DEsc!$D$4 -> Escolar | C57: =DEsc!AG14 -> 155938 | D57: =IFERROR(VLOOKUP(C57,'Plantilla y Concentrado'!$B$4:$C$677,2,0),"") -> Aguilar Flores Erika Jazmin | E57: =DEsc!A14 -> 46 | F57: =DEsc!D14 -> 0 | G57: =DEsc!M14 -> 0 | J57: =DEsc!U14 -> 0 | K57: =DEsc!V14 -> 0 | L57: =SUM(F57:K57) -> 0 | M57: 1 | N57: ='Exhibiciones '!$A$4 -> ECATEPEC | O57: =DMes1!$E$4 -> Ropa Doblada | P57: =DMes1!AC63 -> 0 | Q57: =DMes1!AD63 | R57: =DMes1!B63 -> 0 | S57: - | T57: =DMes1!G63 -> 0 | U57: =DMes1!T63 -> 0 | V57: =DMes1!R63 -> 0 | W57: =DMes1!S63 -> 0 | X57: =SUM(S57:W57) -> 0 | Y57: 1
A58: ='Exhibiciones '!$A$4 -> ECATEPEC | B58: =DEsc!$D$4 -> Escolar | C58: =DEsc!AG15 -> 154648 | D58: =IFERROR(VLOOKUP(C58,'Plantilla y Concentrado'!$B$4:$C$677,2,0),"") -> Sanchez Vazquez Anayareli | E58: =DEsc!A15 -> 47B | F58: =DEsc!D15 -> 0 | G58: =DEsc!M15 -> 0 | J58: =DEsc!U15 -> 0 | K58: =DEsc!V15 -> 0 | L58: =SUM(F58:K58) -> 0 | M58: 1 | N58: ='Exhibiciones '!$A$4 -> ECATEPEC | O58: =DMes1!$E$4 -> Ropa Doblada | P58: =DMes1!AC64 -> 0 | Q58: =DMes1!AD64 | R58: =DMes1!B64 -> 0 | S58: - | T58: =DMes1!G64 -> 0 | U58: =DMes1!T64 -> 0 | V58: =DMes1!R64 -> 0 | W58: =DMes1!S64 -> 0 | X58: =SUM(S58:W58) -> 0 | Y58: 1
A59: ='Exhibiciones '!$A$4 -> ECATEPEC | B59: =DEsc!$D$4 -> Escolar | C59: =DEsc!AG19 -> 0 | D59: =IFERROR(VLOOKUP(C59,'Plantilla y Concentrado'!$B$4:$C$677,2,0),"") | E59: =DEsc!A19 -> 0 | F59: =DEsc!D19 -> 0 | G59: =DEsc!M19 -> 0 | J59: =DEsc!U19 -> 0 | K59: =DEsc!V19 -> 0 | L59: =SUM(F59:K59) -> 0 | M59: 1 | N59: ='Exhibiciones '!$A$4 -> ECATEPEC | O59: ='DColg1 '!$D$4 -> Ropa Colgada | P59: ='DColg1 '!AB9 -> 122694 | Q59: ='DColg1 '!AC9 -> Garcia Jimenez Maria Elena | R59: ='DColg1 '!A9 -> R. COLGADA 01 | S59: ='DColg1 '!D9 -> 0 | T59: ='DColg1 '!H9 -> 0 | U59: ='DColg1 '!R9 -> 0 | V59: ='DColg1 '!S9 -> 0 | W59: ='DColg1 '!T9 -> 0 | X59: =SUM(S59:W59) -> 0 | Y59: 1
A60: ='Exhibiciones '!$A$4 -> ECATEPEC | B60: =DEsc!$D$4 -> Escolar | C60: =DEsc!AG17 -> 0 | D60: =IFERROR(VLOOKUP(C60,'Plantilla y Concentrado'!$B$4:$C$677,2,0),"") | E60: =DEsc!A17 -> 0 | F60: =DEsc!D17 -> 0 | G60: =DEsc!M17 -> 0 | J60: =DEsc!U17 -> 0 | K60: =DEsc!V17 -> 0 | L60: =SUM(F60:K60) -> 0 | M60: 1 | N60: ='Exhibiciones '!$A$4 -> ECATEPEC | O60: ='DColg1 '!$D$4 -> Ropa Colgada | P60: ='DColg1 '!AB10 -> 122694 | Q60: ='DColg1 '!AC10 -> Garcia Jimenez Maria Elena | R60: ='DColg1 '!A10 -> R. COLGADA 02 | S60: ='DColg1 '!D10 -> 0 | T60: ='DColg1 '!H10 -> 1 | U60: ='DColg1 '!R10 -> 0 | V60: ='DColg1 '!S10 -> 0 | W60: ='DColg1 '!T10 -> 0 | X60: =SUM(S60:W60) -> 1 | Y60: 1
A61: ='Exhibiciones '!$A$4 -> ECATEPEC | B61: =DEsc!$D$4 -> Escolar | C61: =DEsc!AG18 -> 0 | D61: =IFERROR(VLOOKUP(C61,'Plantilla y Concentrado'!$B$4:$C$677,2,0),"") | E61: =DEsc!A18 -> 0 | F61: =DEsc!D18 -> 0 | G61: =DEsc!M18 -> 0 | J61: =DEsc!U18 -> 0 | K61: =DEsc!V18 -> 0 | L61: =SUM(F61:K61) -> 0 | M61: 1 | N61: ='Exhibiciones '!$A$4 -> ECATEPEC | O61: ='DColg1 '!$D$4 -> Ropa Colgada | P61: ='DColg1 '!AB11 -> 152181 | Q61: ='DColg1 '!AC11 -> Hernandez Flores Ana Guadalupe | R61: ='DColg1 '!A11 -> R. COLGADA 03 | S61: ='DColg1 '!D11 -> 0 | T61: ='DColg1 '!H11 -> 0 | U61: ='DColg1 '!R11 -> 0 | V61: ='DColg1 '!S11 -> 0 | W61: ='DColg1 '!T11 -> 0 | X61: =SUM(S61:W61) -> 0 | Y61: 1
A62: ='Exhibiciones '!$A$4 -> ECATEPEC | B62: =DEsc!$D$4 -> Escolar | C62: =DEsc!AG19 -> 0 | D62: =IFERROR(VLOOKUP(C62,'Plantilla y Concentrado'!$B$4:$C$677,2,0),"") | E62: =DEsc!A19 -> 0 | F62: =DEsc!D19 -> 0 | G62: =DEsc!M19 -> 0 | J62: =DEsc!U19 -> 0 | K62: =DEsc!V19 -> 0 | L62: =SUM(F62:K62) -> 0 | M62: 1 | N62: ='Exhibiciones '!$A$4 -> ECATEPEC | O62: ='DColg1 '!$D$4 -> Ropa Colgada | P62: ='DColg1 '!AB12 -> 152181 | Q62: ='DColg1 '!AC12 -> Hernandez Flores Ana Guadalupe | R62: ='DColg1 '!A12 -> R. COLGADA 04 | S62: ='DColg1 '!D12 -> 3 | T62: ='DColg1 '!H12 -> 0 | U62: ='DColg1 '!R12 -> 0 | V62: ='DColg1 '!S12 -> 0 | W62: ='DColg1 '!T12 -> 0 | X62: =SUM(S62:W62) -> 3 | Y62: 1
A63: ='Exhibiciones '!$A$4 -> ECATEPEC | B63: =DEsc!$D$4 -> Escolar | C63: =DEsc!AG20 -> 0 | D63: =IFERROR(VLOOKUP(C63,'Plantilla y Concentrado'!$B$4:$C$677,2,0),"") | E63: =DEsc!A20 -> 0 | F63: =DEsc!D20 -> 0 | G63: =DEsc!M20 -> 0 | J63: =DEsc!U20 -> 0 | K63: =DEsc!V20 -> 0 | L63: =SUM(F63:K63) -> 0 | M63: 1 | N63: ='Exhibiciones '!$A$4 -> ECATEPEC | O63: ='DColg1 '!$D$4 -> Ropa Colgada | P63: ='DColg1 '!AB13 -> 149651 | Q63: ='DColg1 '!AC13 -> Celis Popocatl Daniela | R63: ='DColg1 '!A13 -> R. COLGADA 05 | S63: ='DColg1 '!D13 -> 1 | T63: ='DColg1 '!H13 -> 0 | U63: ='DColg1 '!R13 -> 0 | V63: ='DColg1 '!S13 -> 0 | W63: ='DColg1 '!T13 -> 0 | X63: =SUM(S63:W63) -> 1 | Y63: 1
A64: ='Exhibiciones '!$A$4 -> ECATEPEC | B64: =DEsc!$D$4 -> Escolar | C64: =DEsc!AG21 -> 0 | D64: =IFERROR(VLOOKUP(C64,'Plantilla y Concentrado'!$B$4:$C$677,2,0),"") | E64: =DEsc!A21 -> 0 | F64: =DEsc!D21 -> 0 | G64: =DEsc!M21 -> 0 | J64: =DEsc!U21 -> 0 | K64: =DEsc!V21 -> 0 | L64: =SUM(F64:K64) -> 0 | M64: 1 | N64: ='Exhibiciones '!$A$4 -> ECATEPEC | O64: ='DColg1 '!$D$4 -> Ropa Colgada | P64: ='DColg1 '!AB14 -> 149651 | Q64: ='DColg1 '!AC14 -> Celis Popocatl Daniela | R64: ='DColg1 '!A14 -> R. COLGADA 06 | S64: ='DColg1 '!D14 -> 0 | T64: ='DColg1 '!H14 -> 0 | U64: ='DColg1 '!R14 -> 0 | V64: ='DColg1 '!S14 -> 0 | W64: ='DColg1 '!T14 -> 0 | X64: =SUM(S64:W64) -> 0 | Y64: 1
A65: ='Exhibiciones '!$A$4 -> ECATEPEC | B65: =DEsc!$D$4 -> Escolar | C65: =DEsc!AG22 -> 0 | D65: =IFERROR(VLOOKUP(C65,'Plantilla y Concentrado'!$B$4:$C$677,2,0),"") | E65: =DEsc!A22 -> 0 | F65: =DEsc!D22 -> 0 | G65: =DEsc!M22 -> 0 | J65: =DEsc!U22 -> 0 | K65: =DEsc!V22 -> 0 | L65: =SUM(F65:K65) -> 0 | M65: 1 | N65: ='Exhibiciones '!$A$4 -> ECATEPEC | O65: ='DColg1 '!$D$4 -> Ropa Colgada | P65: ='DColg1 '!AB15 -> 146899 | Q65: ='DColg1 '!AC15 -> Lopez Leon Sofia Victoria | R65: ='DColg1 '!A15 -> R. COLGADA 07 | S65: ='DColg1 '!D15 -> 0 | T65: ='DColg1 '!H15 -> 0 | U65: ='DColg1 '!R15 -> 0 | V65: ='DColg1 '!S15 -> 0 | W65: ='DColg1 '!T15 -> 0 | X65: =SUM(S65:W65) -> 0 | Y65: 1
A66: ='Exhibiciones '!$A$4 -> ECATEPEC | B66: =DEsc!$D$4 -> Escolar | C66: =DEsc!AG23 -> 0 | D66: =IFERROR(VLOOKUP(C66,'Plantilla y Concentrado'!$B$4:$C$677,2,0),"") | E66: =DEsc!A23 -> 0 | F66: =DEsc!D23 -> 0 | G66: =DEsc!M23 -> 0 | J66: =DEsc!U23 -> 0 | K66: =DEsc!V23 -> 0 | L66: =SUM(F66:K66) -> 0 | M66: 1 | N66: ='Exhibiciones '!$A$4 -> ECATEPEC | O66: ='DColg1 '!$D$4 -> Ropa Colgada | P66: ='DColg1 '!AB16 -> 146899 | Q66: ='DColg1 '!AC16 -> Lopez Leon Sofia Victoria | R66: ='DColg1 '!A16 -> R. COLGADA 08 | S66: ='DColg1 '!D16 -> 0 | T66: ='DColg1 '!H16 -> 0 | U66: ='DColg1 '!R16 -> 0 | V66: ='DColg1 '!S16 -> 0 | W66: ='DColg1 '!T16 -> 0 | X66: =SUM(S66:W66) -> 0 | Y66: 1
A67: ='Exhibiciones '!$A$4 -> ECATEPEC | B67: =DEsc!$D$4 -> Escolar | C67: =DEsc!AG24 -> 0 | D67: =IFERROR(VLOOKUP(C67,'Plantilla y Concentrado'!$B$4:$C$677,2,0),"") | E67: =DEsc!A24 -> 0 | F67: =DEsc!D24 -> 0 | G67: =DEsc!M24 -> 0 | J67: =DEsc!U24 -> 0 | K67: =DEsc!V24 -> 0 | L67: =SUM(F67:K67) -> 0 | M67: 1 | N67: ='Exhibiciones '!$A$4 -> ECATEPEC | O67: ='DColg1 '!$D$4 -> Ropa Colgada | P67: ='DColg1 '!AB17 -> 158799 | Q67: ='DColg1 '!AC17 | R67: ='DColg1 '!A17 -> R. COLGADA 09 | S67: ='DColg1 '!D17 -> 0 | T67: ='DColg1 '!H17 -> 0 | U67: ='DColg1 '!R17 -> 0 | V67: ='DColg1 '!S17 -> 0 | W67: ='DColg1 '!T17 -> 0 | X67: =SUM(S67:W67) -> 0 | Y67: 1
A68: ='Exhibiciones '!$A$4 -> ECATEPEC | B68: =DEsc!$D$4 -> Escolar | C68: =DEsc!AG25 -> 0 | D68: =IFERROR(VLOOKUP(C68,'Plantilla y Concentrado'!$B$4:$C$677,2,0),"") | E68: =DEsc!A25 -> 0 | F68: =DEsc!D25 -> 0 | G68: =DEsc!M25 -> 0 | J68: =DEsc!U25 -> 0 | K68: =DEsc!V25 -> 0 | L68: =SUM(F68:K68) -> 0 | M68: 1 | N68: ='Exhibiciones '!$A$4 -> ECATEPEC | O68: ='DColg1 '!$D$4 -> Ropa Colgada | P68: ='DColg1 '!AB18 -> 158799 | Q68: ='DColg1 '!AC18 | R68: ='DColg1 '!A18 -> R. COLGADA 10 | S68: ='DColg1 '!D18 -> 0 | T68: ='DColg1 '!H18 -> 0 | U68: ='DColg1 '!R18 -> 0 | V68: ='DColg1 '!S18 -> 0 | W68: ='DColg1 '!T18 -> 0 | X68: =SUM(S68:W68) -> 0 | Y68: 1
A69: ='Exhibiciones '!$A$4 -> ECATEPEC | B69: =DEsc!$D$4 -> Escolar | C69: =DEsc!AG26 -> 0 | D69: =IFERROR(VLOOKUP(C69,'Plantilla y Concentrado'!$B$4:$C$677,2,0),"") | E69: =DEsc!A26 -> 0 | F69: =DEsc!D26 -> 0 | G69: =DEsc!M26 -> 0 | J69: =DEsc!U26 -> 0 | K69: =DEsc!V26 -> 0 | L69: =SUM(F69:K69) -> 0 | M69: 1 | N69: ='Exhibiciones '!$A$4 -> ECATEPEC | O69: ='DColg1 '!$D$4 -> Ropa Colgada | P69: ='DColg1 '!AB19 -> 158799 | Q69: ='DColg1 '!AC19 | R69: ='DColg1 '!A19 -> R. COLGADA 11 | S69: ='DColg1 '!D19 -> 0 | T69: ='DColg1 '!H19 -> 0 | U69: ='DColg1 '!R19 -> 0 | V69: ='DColg1 '!S19 -> 0 | W69: ='DColg1 '!T19 -> 0 | X69: =SUM(S69:W69) -> 0 | Y69: 1
A70: ='Exhibiciones '!$A$4 -> ECATEPEC | B70: =DEsc!$D$4 -> Escolar | C70: =DEsc!AG27 -> 0 | D70: =IFERROR(VLOOKUP(C70,'Plantilla y Concentrado'!$B$4:$C$677,2,0),"") | E70: =DEsc!A27 -> 0 | F70: =DEsc!D27 -> 0 | G70: =DEsc!M27 -> 0 | J70: =DEsc!U27 -> 0 | K70: =DEsc!V27 -> 0 | L70: =SUM(F70:K70) -> 0 | M70: 1 | N70: ='Exhibiciones '!$A$4 -> ECATEPEC | O70: ='DColg1 '!$D$4 -> Ropa Colgada | P70: ='DColg1 '!AB20 -> 159100 | Q70: ='DColg1 '!AC20 | R70: ='DColg1 '!A20 -> R. COLGADA 12 | S70: ='DColg1 '!D20 -> 0 | T70: ='DColg1 '!H20 -> 0 | U70: ='DColg1 '!R20 -> 0 | V70: ='DColg1 '!S20 -> 0 | W70: ='DColg1 '!T20 -> 0 | X70: =SUM(S70:W70) -> 0 | Y70: 1
A71: ='Exhibiciones '!$A$4 -> ECATEPEC | B71: =DEsc!$D$4 -> Escolar | C71: =DEsc!AG28 -> 0 | D71: =IFERROR(VLOOKUP(C71,'Plantilla y Concentrado'!$B$4:$C$677,2,0),"") | E71: =DEsc!A28 -> 0 | F71: =DEsc!D28 -> 0 | G71: =DEsc!M28 -> 0 | J71: =DEsc!U28 -> 0 | K71: =DEsc!V28 -> 0 | L71: =SUM(F71:K71) -> 0 | M71: 1 | N71: ='Exhibiciones '!$A$4 -> ECATEPEC | O71: ='DColg1 '!$D$4 -> Ropa Colgada | P71: ='DColg1 '!AB21 -> 159100 | Q71: ='DColg1 '!AC21 | R71: ='DColg1 '!A21 -> R. COLGADA 13 | S71: ='DColg1 '!D21 -> 0 | T71: ='DColg1 '!H21 -> 0 | U71: ='DColg1 '!R21 -> 0 | V71: ='DColg1 '!S21 -> 0 | W71: ='DColg1 '!T21 -> 0 | X71: =SUM(S71:W71) -> 0 | Y71: 1
... A73: ='Exhibiciones '!$A$4 -> ECATEPEC | B73: =DEsc!$D$4 -> Escolar | C73: =DEsc!AG30 -> 0 | D73: =IFERROR(VLOOKUP(C73,'Plantilla y Concentrado'!$B$4:$C$677,2,0),"") | E73: =DEsc!A30 -> 0 | F73: =DEsc!D30 -> 0 | G73: =DEsc!M30 -> 0 | J73: =DEsc!U30 -> 0 | K73: =DEsc!V30 -> 0 | L73: =SUM(F73:K73) -> 0 | M73: 1 | N73: ='Exhibiciones '!$A$4 -> ECATEPEC | O73: ='DColg1 '!$D$4 -> Ropa Colgada | P73: ='DColg1 '!AB23 -> 0 | Q73: ='DColg1 '!AC23 | R73: ='DColg1 '!A23 -> 0 | S73: ='DColg1 '!D23 -> 0 | T73: ='DColg1 '!H23 -> 0 | U73: ='DColg1 '!R23 -> 0 | V73: ='DColg1 '!S23 -> 0 | W73: ='DColg1 '!T23 -> 0 | X73: =SUM(S73:W73) -> 0 | Y73: 1
A74: ='Exhibiciones '!$A$4 -> ECATEPEC | B74: =DSan!$D$4 -> SANDALIAS | C74: =DSan!AG9 -> 144695 | D74: =IFERROR(VLOOKUP(C74,'Plantilla y Concentrado'!$B$4:$C$677,2,0),"") -> Alvarez Becerra Emiliano | E74: =DSan!A9 -> 3 | F74: =DSan!D9 -> 0 | G74: =DSan!M9 -> 0 | J74: =DSan!U9 -> 0 | K74: =DSan!V9 -> 0 | L74: =SUM(F74:K74) -> 0 | M74: 1 | N74: ='Exhibiciones '!$A$4 -> ECATEPEC | O74: ='DColg1 '!$D$4 -> Ropa Colgada | P74: ='DColg1 '!AB24 -> 0 | Q74: ='DColg1 '!AC24 | R74: ='DColg1 '!A24 -> 0 | S74: ='DColg1 '!D24 -> 0 | T74: ='DColg1 '!H24 -> 0 | U74: ='DColg1 '!R24 -> 0 | V74: ='DColg1 '!S24 -> 0 | W74: ='DColg1 '!T24 -> 0 | X74: =SUM(S74:W74) -> 0 | Y74: 1
A75: ='Exhibiciones '!$A$4 -> ECATEPEC | B75: =DSan!$D$4 -> SANDALIAS | C75: =DSan!AG10 -> 154648 | D75: =IFERROR(VLOOKUP(C75,'Plantilla y Concentrado'!$B$4:$C$677,2,0),"") -> Sanchez Vazquez Anayareli | E75: =DSan!A10 -> 4 | F75: =DSan!D10 -> 0 | G75: =DSan!M10 -> 0 | J75: =DSan!U10 -> 1 | K75: =DSan!V10 -> 1 | L75: =SUM(F75:K75) -> 2 | M75: 1 | N75: ='Exhibiciones '!$A$4 -> ECATEPEC | O75: ='DColg1 '!$D$4 -> Ropa Colgada | P75: ='DColg1 '!AB25 -> 0 | Q75: ='DColg1 '!AC25 | R75: ='DColg1 '!A25 -> 0 | S75: ='DColg1 '!D25 -> 0 | T75: ='DColg1 '!H25 -> 0 | U75: ='DColg1 '!R25 -> 0 | V75: ='DColg1 '!S25 -> 0 | W75: ='DColg1 '!T25 -> 0 | X75: =SUM(S75:W75) -> 0 | Y75: 1
A76: ='Exhibiciones '!$A$4 -> ECATEPEC | B76: =DSan!$D$4 -> SANDALIAS | C76: =DSan!AG11 -> 158001 | D76: =IFERROR(VLOOKUP(C76,'Plantilla y Concentrado'!$B$4:$C$677,2,0),"") -> Nuñez Garcia Clarissa Naomi | E76: =DSan!A11 -> 5 | F76: =DSan!D11 -> 1 | G76: =DSan!M11 -> 0 | J76: =DSan!U15 -> 0 | K76: =DSan!V15 -> 0 | L76: =SUM(F76:K76) -> 1 | M76: 1 | N76: ='Exhibiciones '!$A$4 -> ECATEPEC | O76: ='DColg1 '!$D$4 -> Ropa Colgada | P76: ='DColg1 '!AB26 -> 0 | Q76: ='DColg1 '!AC26 | R76: ='DColg1 '!A26 -> 0 | S76: ='DColg1 '!D26 -> 0 | T76: ='DColg1 '!H26 -> 0 | U76: ='DColg1 '!R26 -> 0 | V76: ='DColg1 '!S26 -> 0 | W76: ='DColg1 '!T26 -> 0 | X76: =SUM(S76:W76) -> 0 | Y76: 1
A77: ='Exhibiciones '!$A$4 -> ECATEPEC | B77: =DSan!$D$4 -> SANDALIAS | C77: =DSan!AG12 -> 155938 | D77: =IFERROR(VLOOKUP(C77,'Plantilla y Concentrado'!$B$4:$C$677,2,0),"") -> Aguilar Flores Erika Jazmin | E77: =DSan!A12 -> 6 | F77: =DSan!D12 -> 1 | G77: =DSan!M12 -> 0 | J77: =DSan!U16 -> 0 | K77: =DSan!V16 -> 0 | L77: =SUM(F77:K77) -> 1 | M77: 1 | N77: ='Exhibiciones '!$A$4 -> ECATEPEC | O77: ='DColg1 '!$D$4 -> Ropa Colgada | P77: ='DColg1 '!AB27 -> 0 | Q77: ='DColg1 '!AC27 | R77: ='DColg1 '!A27 -> 0 | S77: ='DColg1 '!D27 -> 0 | T77: ='DColg1 '!H27 -> 0 | U77: ='DColg1 '!R27 -> 0 | V77: ='DColg1 '!S27 -> 0 | W77: ='DColg1 '!T27 -> 0 | X77: =SUM(S77:W77) -> 0 | Y77: 1
A78: ='Exhibiciones '!$A$4 -> ECATEPEC | B78: =DSan!$D$4 -> SANDALIAS | C78: =DSan!AG13 -> 136867 | D78: =IFERROR(VLOOKUP(C78,'Plantilla y Concentrado'!$B$4:$C$677,2,0),"") -> Barba Ramirez Jatziri Lizeth | E78: =DSan!A13 -> 7 | F78: =DSan!D13 -> 0 | G78: =DSan!M13 -> 0 | J78: =DSan!U17 -> 0 | K78: =DSan!V17 -> 0 | L78: =SUM(F78:K78) -> 0 | M78: 1 | N78: ='Exhibiciones '!$A$4 -> ECATEPEC | O78: ='DColg1 '!$D$4 -> Ropa Colgada | P78: ='DColg1 '!AB28 -> 0 | Q78: ='DColg1 '!AC28 | R78: ='DColg1 '!A28 -> 0 | S78: ='DColg1 '!D28 -> 0 | T78: ='DColg1 '!H28 -> 0 | U78: ='DColg1 '!R28 -> 0 | V78: ='DColg1 '!S28 -> 0 | W78: ='DColg1 '!T28 -> 0 | X78: =SUM(S78:W78) -> 0 | Y78: 1
A79: ='Exhibiciones '!$A$4 -> ECATEPEC | B79: =DSan!$D$4 -> SANDALIAS | C79: =DSan!AG14 -> 0 | D79: =IFERROR(VLOOKUP(C79,'Plantilla y Concentrado'!$B$4:$C$677,2,0),"") | E79: =DSan!A14 -> 0 | F79: =DSan!D14 -> 0 | G79: =DSan!M14 -> 0 | J79: =DSan!U18 -> 0 | K79: =DSan!V18 -> 0 | L79: =SUM(F79:K79) -> 0 | M79: 1 | N79: ='Exhibiciones '!$A$4 -> ECATEPEC | O79: ='DColg1 '!$D$4 -> Ropa Colgada | P79: ='DColg1 '!AB29 -> 0 | Q79: ='DColg1 '!AC29 | R79: ='DColg1 '!A29 -> 0 | S79: ='DColg1 '!D29 -> 0 | T79: ='DColg1 '!H29 -> 0 | U79: ='DColg1 '!R29 -> 0 | V79: ='DColg1 '!S29 -> 0 | W79: ='DColg1 '!T29 -> 0 | X79: =SUM(S79:W79) -> 0 | Y79: 1
A80: ='Exhibiciones '!$A$4 -> ECATEPEC | B80: =DSan!$D$4 -> SANDALIAS | C80: =DSan!AG15 -> 0 | D80: =IFERROR(VLOOKUP(C80,'Plantilla y Concentrado'!$B$4:$C$677,2,0),"") | E80: =DSan!A15 -> 0 | F80: =DSan!D15 -> 0 | G80: =DSan!M15 -> 0 | J80: =DSan!U19 -> 0 | K80: =DSan!V19 -> 0 | L80: =SUM(F80:K80) -> 0 | M80: 1 | N80: ='Exhibiciones '!$A$4 -> ECATEPEC | O80: ='DColg1 '!$D$4 -> Ropa Colgada | P80: ='DColg1 '!AB30 -> 0 | Q80: ='DColg1 '!AC30 | R80: ='DColg1 '!A30 -> 0 | S80: ='DColg1 '!D30 -> 0 | T80: ='DColg1 '!H30 -> 0 | U80: ='DColg1 '!R30 -> 0 | V80: ='DColg1 '!S30 -> 0 | W80: ='DColg1 '!T30 -> 0 | X80: =SUM(S80:W80) -> 0 | Y80: 1
A81: ='Exhibiciones '!$A$4 -> ECATEPEC | B81: =DSan!$D$4 -> SANDALIAS | C81: =DSan!AG16 -> 0 | D81: =IFERROR(VLOOKUP(C81,'Plantilla y Concentrado'!$B$4:$C$677,2,0),"") | E81: =DSan!A16 -> 0 | F81: =DSan!D16 -> 0 | G81: =DSan!M16 -> 0 | J81: =DSan!U16 -> 0 | K81: =DSan!V16 -> 0 | L81: =SUM(F81:K81) -> 0 | M81: 1 | N81: ='Exhibiciones '!$A$4 -> ECATEPEC | O81: ='DColg1 '!$D$4 -> Ropa Colgada | P81: ='DColg1 '!AB31 -> 0 | Q81: ='DColg1 '!AC31 | R81: ='DColg1 '!A31 -> 0 | S81: ='DColg1 '!D31 -> 0 | T81: ='DColg1 '!H31 -> 0 | U81: ='DColg1 '!R31 -> 0 | V81: ='DColg1 '!S31 -> 0 | W81: ='DColg1 '!T31 -> 0 | X81: =SUM(S81:W81) -> 0 | Y81: 1
A82: ='Exhibiciones '!$A$4 -> ECATEPEC | B82: =DSan!$D$4 -> SANDALIAS | C82: =DSan!AG17 -> 0 | D82: =IFERROR(VLOOKUP(C82,'Plantilla y Concentrado'!$B$4:$C$677,2,0),"") | E82: =DSan!A17 -> 0 | F82: =DSan!D17 -> 0 | G82: =DSan!M17 -> 0 | J82: =DSan!U17 -> 0 | K82: =DSan!V17 -> 0 | L82: =SUM(F82:K82) -> 0 | M82: 1 | N82: ='Exhibiciones '!$A$4 -> ECATEPEC | O82: ='DColg1 '!$D$4 -> Ropa Colgada | P82: ='DColg1 '!AB32 -> 0 | Q82: ='DColg1 '!AC32 | R82: ='DColg1 '!A32 -> 0 | S82: ='DColg1 '!D32 -> 0 | T82: ='DColg1 '!H32 -> 0 | U82: ='DColg1 '!R32 -> 0 | V82: ='DColg1 '!S32 -> 0 | W82: ='DColg1 '!T32 -> 0 | X82: =SUM(S82:W82) -> 0 | Y82: 1
A83: ='Exhibiciones '!$A$4 -> ECATEPEC | B83: =DSan!$D$4 -> SANDALIAS | C83: =DSan!AG18 -> 0 | D83: =IFERROR(VLOOKUP(C83,'Plantilla y Concentrado'!$B$4:$C$677,2,0),"") | E83: =DSan!A18 -> 0 | F83: =DSan!D18 -> 0 | G83: =DSan!M18 -> 0 | J83: =DSan!U18 -> 0 | K83: =DSan!V18 -> 0 | L83: =SUM(F83:K83) -> 0 | M83: 1 | N83: ='Exhibiciones '!$A$4 -> ECATEPEC | O83: ='DColg1 '!$D$4 -> Ropa Colgada | P83: ='DColg1 '!AB33 -> 0 | Q83: ='DColg1 '!AC33 | R83: ='DColg1 '!A33 -> 0 | S83: ='DColg1 '!D33 -> 0 | T83: ='DColg1 '!H33 -> 0 | U83: ='DColg1 '!R33 -> 0 | V83: ='DColg1 '!S33 -> 0 | W83: ='DColg1 '!T33 -> 0 | X83: =SUM(S83:W83) -> 0 | Y83: 1
A84: ='Exhibiciones '!$A$4 -> ECATEPEC | B84: =DSan!$D$4 -> SANDALIAS | C84: =DSan!AG19 -> 0 | D84: =IFERROR(VLOOKUP(C84,'Plantilla y Concentrado'!$B$4:$C$677,2,0),"") | E84: =DSan!A19 -> 0 | F84: =DSan!D19 -> 0 | G84: =DSan!M19 -> 0 | J84: =DSan!U19 -> 0 | K84: =DSan!V19 -> 0 | L84: =SUM(F84:K84) -> 0 | M84: 1 | N84: ='Exhibiciones '!$A$4 -> ECATEPEC | O84: ='DColg1 '!$D$4 -> Ropa Colgada | P84: ='DColg1 '!AB34 -> 0 | Q84: ='DColg1 '!AC34 | R84: ='DColg1 '!A34 -> 0 | S84: ='DColg1 '!D34 -> 0 | T84: ='DColg1 '!H34 -> 0 | U84: ='DColg1 '!R34 -> 0 | V84: ='DColg1 '!S34 -> 0 | W84: ='DColg1 '!T34 -> 0 | X84: =SUM(S84:W84) -> 0 | Y84: 1
A85: ='Exhibiciones '!$A$4 -> ECATEPEC | B85: =DSan!$D$4 -> SANDALIAS | C85: =DSan!AG20 -> 0 | D85: =IFERROR(VLOOKUP(C85,'Plantilla y Concentrado'!$B$4:$C$677,2,0),"") | E85: =DSan!A20 -> 0 | F85: =DSan!D20 -> 0 | G85: =DSan!M20 -> 0 | J85: =DSan!U20 -> 0 | K85: =DSan!V20 -> 0 | L85: =SUM(F85:K85) -> 0 | M85: 1 | N85: ='Exhibiciones '!$A$4 -> ECATEPEC | O85: ='DColg1 '!$D$4 -> Ropa Colgada | P85: ='DColg1 '!AB35 -> 0 | Q85: ='DColg1 '!AC35 | R85: ='DColg1 '!A35 -> 0 | S85: ='DColg1 '!D35 -> 0 | T85: ='DColg1 '!H35 -> 0 | U85: ='DColg1 '!R35 -> 0 | V85: ='DColg1 '!S35 -> 0 | W85: ='DColg1 '!T35 -> 0 | X85: =SUM(S85:W85) -> 0 | Y85: 1
A86: ='Exhibiciones '!$A$4 -> ECATEPEC | B86: =DSan!$D$4 -> SANDALIAS | C86: =DSan!AG21 -> 0 | D86: =IFERROR(VLOOKUP(C86,'Plantilla y Concentrado'!$B$4:$C$677,2,0),"") | E86: =DSan!A21 -> 0 | F86: =DSan!D21 -> 0 | G86: =DSan!M21 -> 0 | J86: =DSan!U21 -> 0 | K86: =DSan!V21 -> 0 | L86: =SUM(F86:K86) -> 0 | M86: 1 | N86: ='Exhibiciones '!$A$4 -> ECATEPEC | O86: ='DColg1 '!$D$4 -> Ropa Colgada | P86: ='DColg1 '!AB36 -> 0 | Q86: ='DColg1 '!AC36 | R86: ='DColg1 '!A36 -> 0 | S86: ='DColg1 '!D36 -> 0 | T86: ='DColg1 '!H36 -> 0 | U86: ='DColg1 '!R36 -> 0 | V86: ='DColg1 '!S36 -> 0 | W86: ='DColg1 '!T36 -> 0 | X86: =SUM(S86:W86) -> 0 | Y86: 1
A87: ='Exhibiciones '!$A$4 -> ECATEPEC | B87: =DSan!$D$4 -> SANDALIAS | C87: =DSan!AG22 -> 0 | D87: =IFERROR(VLOOKUP(C87,'Plantilla y Concentrado'!$B$4:$C$677,2,0),"") | E87: =DSan!A22 -> 0 | F87: =DSan!D22 -> 0 | G87: =DSan!M22 -> 0 | J87: =DSan!U22 -> 0 | K87: =DSan!V22 -> 0 | L87: =SUM(F87:K87) -> 0 | M87: 1 | N87: ='Exhibiciones '!$A$4 -> ECATEPEC | O87: ='DColg1 '!$D$4 -> Ropa Colgada | P87: ='DColg1 '!AB37 -> 0 | Q87: ='DColg1 '!AC37 | R87: ='DColg1 '!A37 -> 0 | S87: ='DColg1 '!D37 -> 0 | T87: ='DColg1 '!H37 -> 0 | U87: ='DColg1 '!R37 -> 0 | V87: ='DColg1 '!S37 -> 0 | W87: ='DColg1 '!T37 -> 0 | X87: =SUM(S87:W87) -> 0 | Y87: 1
A88: ='Exhibiciones '!$A$4 -> ECATEPEC | B88: =DSan!$D$4 -> SANDALIAS | C88: =DSan!AG23 -> 0 | D88: =IFERROR(VLOOKUP(C88,'Plantilla y Concentrado'!$B$4:$C$677,2,0),"") | E88: =DSan!A23 -> 0 | F88: =DSan!D23 -> 0 | G88: =DSan!M23 -> 0 | J88: =DSan!U23 -> 0 | K88: =DSan!V23 -> 0 | L88: =SUM(F88:K88) -> 0 | M88: 1 | N88: ='Exhibiciones '!$A$4 -> ECATEPEC | O88: ='DColg1 '!$D$4 -> Ropa Colgada | P88: ='DColg1 '!AB38 -> 0 | Q88: ='DColg1 '!AC38 | R88: ='DColg1 '!A38 -> 0 | S88: ='DColg1 '!D38 -> 0 | T88: ='DColg1 '!H38 -> 0 | U88: ='DColg1 '!R38 -> 0 | V88: ='DColg1 '!S38 -> 0 | W88: ='DColg1 '!T38 -> 0 | X88: =SUM(S88:W88) -> 0 | Y88: 1
A89: ='Exhibiciones '!$A$4 -> ECATEPEC | B89: =DSan!$D$4 -> SANDALIAS | C89: =DSan!AG24 -> 0 | D89: =IFERROR(VLOOKUP(C89,'Plantilla y Concentrado'!$B$4:$C$677,2,0),"") | E89: =DSan!A24 -> 0 | F89: =DSan!D24 -> 0 | G89: =DSan!M24 -> 0 | J89: =DSan!U24 -> 0 | K89: =DSan!V24 -> 0 | L89: =SUM(F89:K89) -> 0 | M89: 1 | N89: ='Exhibiciones '!$A$4 -> ECATEPEC | O89: ='DColg1 '!$D$4 -> Ropa Colgada | P89: ='DColg1 '!AB39 -> 0 | Q89: ='DColg1 '!AC39 | R89: ='DColg1 '!A39 -> 0 | S89: ='DColg1 '!D39 -> 0 | T89: ='DColg1 '!H39 -> 0 | U89: ='DColg1 '!R39 -> 0 | V89: ='DColg1 '!S39 -> 0 | W89: ='DColg1 '!T39 -> 0 | X89: =SUM(S89:W89) -> 0 | Y89: 1
A90: ='Exhibiciones '!$A$4 -> ECATEPEC | B90: =DSan!$D$4 -> SANDALIAS | C90: =DSan!AG25 -> 0 | D90: =IFERROR(VLOOKUP(C90,'Plantilla y Concentrado'!$B$4:$C$677,2,0),"") | E90: =DSan!A25 -> 0 | F90: =DSan!D25 -> 0 | G90: =DSan!M25 -> 0 | J90: =DSan!U25 -> 0 | K90: =DSan!V25 -> 0 | L90: =SUM(F90:K90) -> 0 | M90: 1 | N90: ='Exhibiciones '!$A$4 -> ECATEPEC | O90: ='DColg1 '!$D$4 -> Ropa Colgada | P90: ='DColg1 '!AB40 -> 0 | Q90: ='DColg1 '!AC40 | R90: ='DColg1 '!A40 -> 0 | S90: ='DColg1 '!D40 -> 0 | T90: ='DColg1 '!H40 -> 0 | U90: ='DColg1 '!R40 -> 0 | V90: ='DColg1 '!S40 -> 0 | W90: ='DColg1 '!T40 -> 0 | X90: =SUM(S90:W90) -> 0 | Y90: 1
A91: ='Exhibiciones '!$A$4 -> ECATEPEC | B91: =DSan!$D$4 -> SANDALIAS | C91: =DSan!AG26 -> 0 | D91: =IFERROR(VLOOKUP(C91,'Plantilla y Concentrado'!$B$4:$C$677,2,0),"") | E91: =DSan!A26 -> 0 | F91: =DSan!D26 -> 0 | G91: =DSan!M26 -> 0 | J91: =DSan!U26 -> 0 | K91: =DSan!V26 -> 0 | L91: =SUM(F91:K91) -> 0 | M91: 1 | N91: ='Exhibiciones '!$A$4 -> ECATEPEC | O91: ='DColg1 '!$D$4 -> Ropa Colgada | P91: ='DColg1 '!AB41 -> 0 | Q91: ='DColg1 '!AC41 | R91: ='DColg1 '!A41 -> 0 | S91: ='DColg1 '!D41 -> 0 | T91: ='DColg1 '!H41 -> 0 | U91: ='DColg1 '!R41 -> 0 | V91: ='DColg1 '!S41 -> 0 | W91: ='DColg1 '!T41 -> 0 | X91: =SUM(S91:W91) -> 0 | Y91: 1
A92: ='Exhibiciones '!$A$4 -> ECATEPEC | B92: =DSan!$D$4 -> SANDALIAS | C92: =DSan!AG27 -> 0 | D92: =IFERROR(VLOOKUP(C92,'Plantilla y Concentrado'!$B$4:$C$677,2,0),"") | E92: =DSan!A27 -> 0 | F92: =DSan!D27 -> 0 | G92: =DSan!M27 -> 0 | J92: =DSan!U27 -> 0 | K92: =DSan!V27 -> 0 | L92: =SUM(F92:K92) -> 0 | M92: 1 | N92: ='Exhibiciones '!$A$4 -> ECATEPEC | O92: ='DColg1 '!$D$4 -> Ropa Colgada | P92: ='DColg1 '!AB42 -> 0 | Q92: ='DColg1 '!AC42 | R92: ='DColg1 '!A42 -> 0 | S92: ='DColg1 '!D42 -> 0 | T92: ='DColg1 '!H42 -> 0 | U92: ='DColg1 '!R42 -> 0 | V92: ='DColg1 '!S42 -> 0 | W92: ='DColg1 '!T42 -> 0 | X92: =SUM(S92:W92) -> 0 | Y92: 1
... A94: ='Exhibiciones '!$A$4 -> ECATEPEC | B94: =DSan!$D$4 -> SANDALIAS | C94: =DSan!AG29 -> 0 | D94: =IFERROR(VLOOKUP(C94,'Plantilla y Concentrado'!$B$4:$C$677,2,0),"") | E94: =DSan!A29 -> 0 | F94: =DSan!D29 -> 0 | G94: =DSan!M29 -> 0 | J94: =DSan!U29 -> 0 | K94: =DSan!V29 -> 0 | L94: =SUM(F94:K94) -> 0 | M94: 1 | N94: ='Exhibiciones '!$A$4 -> ECATEPEC | O94: ='DColg1 '!$D$4 -> Ropa Colgada | P94: ='DColg1 '!AB44 -> 0 | Q94: ='DColg1 '!AC44 | R94: ='DColg1 '!A44 -> 0 | S94: ='DColg1 '!D44 -> 0 | T94: ='DColg1 '!H44 -> 0 | U94: ='DColg1 '!R44 -> 0 | V94: ='DColg1 '!S44 -> 0 | W94: ='DColg1 '!T44 -> 0 | X94: =SUM(S94:W94) -> 0 | Y94: 1
A95: ='Exhibiciones '!$A$4 -> ECATEPEC | B95: =DSan!$D$4 -> SANDALIAS | C95: =DSan!AG30 -> 0 | D95: =IFERROR(VLOOKUP(C95,'Plantilla y Concentrado'!$B$4:$C$677,2,0),"") | E95: =DSan!A30 -> 0 | F95: =DSan!D30 -> 0 | G95: =DSan!M30 -> 0 | J95: =DSan!U30 -> 0 | K95: =DSan!V30 -> 0 | L95: =SUM(F95:K95) -> 0 | M95: 1 | N95: ='Exhibiciones '!$A$4 -> ECATEPEC | O95: =Jeans!$E$4 -> Jeans | P95: =Jeans!AC10 -> 0 | Q95: =Jeans!AD10 | R95: =Jeans!B10 -> 26 | S95: - | T95: =Jeans!G10 -> 0 | U95: =Jeans!T10 -> 0 | V95: =Jeans!R10 -> 0 | W95: =Jeans!S10 -> 0 | X95: =SUM(S95:W95) -> 0 | Y95: 1
A96: ='Exhibiciones '!$A$4 -> ECATEPEC | B96: =DCon!$D$4 -> Confort | C96: =DCon!AG9 -> 136675 | D96: =IFERROR(VLOOKUP(C96,'Plantilla y Concentrado'!$B$4:$C$677,2,0),"") -> Montiel Ramirez Cintya Elizabeth | E96: =DCon!A9 -> 32B | F96: =DCon!D9 -> 0 | G96: =DCon!M9 -> 0 | J96: =DCon!U9 -> 0 | K96: =DCon!V9 -> 0 | L96: =SUM(F96:K96) -> 0 | M96: 1 | N96: ='Exhibiciones '!$A$4 -> ECATEPEC | O96: =Jeans!$E$4 -> Jeans | P96: =Jeans!AC11 -> 0 | Q96: =Jeans!AD11 | R96: =Jeans!B11 -> 27 | S96: - | T96: =Jeans!G11 -> 0 | U96: =Jeans!T11 -> 0 | V96: =Jeans!R11 -> 0 | W96: =Jeans!S11 -> 0 | X96: =SUM(S96:W96) -> 0 | Y96: 1
A97: ='Exhibiciones '!$A$4 -> ECATEPEC | B97: =DCon!$D$4 -> Confort | C97: =DCon!AG10 -> 151630 | D97: =IFERROR(VLOOKUP(C97,'Plantilla y Concentrado'!$B$4:$C$677,2,0),"") -> Muñoz Lara Karla Paola | E97: =DCon!A10 -> 33 | F97: =DCon!D10 -> 0 | G97: =DCon!M10 -> 0 | J97: =DCon!U10 -> 3 | K97: =DCon!V10 -> 0 | L97: =SUM(F97:K97) -> 3 | M97: 1 | N97: ='Exhibiciones '!$A$4 -> ECATEPEC | O97: =Jeans!$E$4 -> Jeans | P97: =Jeans!AC12 -> 0 | Q97: =Jeans!AD12 | R97: =Jeans!B12 -> 28 | S97: - | T97: =Jeans!G12 -> 0 | U97: =Jeans!T12 -> 0 | V97: =Jeans!R12 -> 0 | W97: =Jeans!S12 -> 0 | X97: =SUM(S97:W97) -> 0 | Y97: 1
A98: ='Exhibiciones '!$A$4 -> ECATEPEC | B98: =DCon!$D$4 -> Confort | C98: =DCon!AG11 -> 155938 | D98: =IFERROR(VLOOKUP(C98,'Plantilla y Concentrado'!$B$4:$C$677,2,0),"") -> Aguilar Flores Erika Jazmin | E98: =DCon!A11 -> 34 | F98: =DCon!D11 -> 0 | G98: =DCon!M11 -> 0 | J98: =DCon!U11 -> 1 | K98: =DCon!V11 -> 0 | L98: =SUM(F98:K98) -> 1 | M98: 1 | N98: ='Exhibiciones '!$A$4 -> ECATEPEC | O98: =Jeans!$E$4 -> Jeans | P98: =Jeans!AC13 -> 0 | Q98: =Jeans!AD13 | R98: =Jeans!B13 -> 29 | S98: - | T98: =Jeans!G13 -> 0 | U98: =Jeans!T13 -> 0 | V98: =Jeans!R13 -> 0 | W98: =Jeans!S13 -> 0 | X98: =SUM(S98:W98) -> 0 | Y98: 1
A99: ='Exhibiciones '!$A$4 -> ECATEPEC | B99: =DCon!$D$4 -> Confort | C99: =DCon!AG12 -> 136867 | D99: =IFERROR(VLOOKUP(C99,'Plantilla y Concentrado'!$B$4:$C$677,2,0),"") -> Barba Ramirez Jatziri Lizeth | E99: =DCon!A12 -> 35 | F99: =DCon!D12 -> 0 | G99: =DCon!M12 -> 0 | J99: =DCon!U12 -> 0 | K99: =DCon!V12 -> 0 | L99: =SUM(F99:K99) -> 0 | M99: 1 | N99: ='Exhibiciones '!$A$4 -> ECATEPEC | O99: =Jeans!$E$4 -> Jeans | P99: =Jeans!AC14 -> 0 | Q99: =Jeans!AD14 | R99: =Jeans!B14 -> 30 | S99: - | T99: =Jeans!G14 -> 0 | U99: =Jeans!T14 -> 0 | V99: =Jeans!R14 -> 0 | W99: =Jeans!S14 -> 0 | X99: =SUM(S99:W99) -> 0 | Y99: 1
A100: ='Exhibiciones '!$A$4 -> ECATEPEC | B100: =DCon!$D$4 -> Confort | C100: =DCon!AG13 -> 158001 | D100: =IFERROR(VLOOKUP(C100,'Plantilla y Concentrado'!$B$4:$C$677,2,0),"") -> Nuñez Garcia Clarissa Naomi | E100: =DCon!A13 -> 36 | F100: =DCon!D13 -> 0 | G100: =DCon!M13 -> 0 | J100: =DCon!U13 -> 0 | K100: =DCon!V13 -> 0 | L100: =SUM(F100:K100) -> 0 | M100: 1 | N100: ='Exhibiciones '!$A$4 -> ECATEPEC | O100: =Jeans!$E$4 -> Jeans | P100: =Jeans!AC15 -> 0 | Q100: =Jeans!AD15 | R100: =Jeans!B15 -> 31 | S100: - | T100: =Jeans!G15 -> 1 | U100: =Jeans!T15 -> 0 | V100: =Jeans!R15 -> 0 | W100: =Jeans!S15 -> 0 | X100: =SUM(S100:W100) -> 1 | Y100: 1
A101: ='Exhibiciones '!$A$4 -> ECATEPEC | B101: =DCon!$D$4 -> Confort | C101: =DCon!AG14 -> 141072 | D101: =IFERROR(VLOOKUP(C101,'Plantilla y Concentrado'!$B$4:$C$677,2,0),"") -> Ramirez Vazquez Lizeth Mariel | E101: =DCon!A14 -> 37A | F101: =DCon!D14 -> 0 | G101: =DCon!M14 -> 0 | J101: =DCon!U14 -> 0 | K101: =DCon!V14 -> 0 | L101: =SUM(F101:K101) -> 0 | M101: 1 | N101: ='Exhibiciones '!$A$4 -> ECATEPEC | O101: =Jeans!$E$4 -> Jeans | P101: =Jeans!AC16 -> 0 | Q101: =Jeans!AD16 | R101: =Jeans!B16 -> 32 | S101: - | T101: =Jeans!G16 -> 0 | U101: =Jeans!T16 -> 0 | V101: =Jeans!R16 -> 0 | W101: =Jeans!S16 -> 0 | X101: =SUM(S101:W101) -> 0 | Y101: 1
A102: ='Exhibiciones '!$A$4 -> ECATEPEC | B102: =DCon!$D$4 -> Confort | C102: =DCon!AG15 -> 0 | D102: =IFERROR(VLOOKUP(C102,'Plantilla y Concentrado'!$B$4:$C$677,2,0),"") | E102: =DCon!A15 -> 0 | F102: =DCon!D15 -> 0 | G102: =DCon!M15 -> 0 | J102: =DCon!U15 -> 0 | K102: =DCon!V15 -> 0 | L102: =SUM(F102:K102) -> 0 | M102: 1 | N102: ='Exhibiciones '!$A$4 -> ECATEPEC | O102: =Jeans!$E$4 -> Jeans | P102: =Jeans!AC17 -> 0 | Q102: =Jeans!AD17 | R102: =Jeans!B17 -> 33 | S102: - | T102: =Jeans!G17 -> 0 | U102: =Jeans!T17 -> 0 | V102: =Jeans!R17 -> 0 | W102: =Jeans!S17 -> 0 | X102: =SUM(S102:W102) -> 0 | Y102: 1
A103: ='Exhibiciones '!$A$4 -> ECATEPEC | B103: =DCon!$D$4 -> Confort | C103: =DCon!AG16 -> 0 | D103: =IFERROR(VLOOKUP(C103,'Plantilla y Concentrado'!$B$4:$C$677,2,0),"") | E103: =DCon!A16 -> 0 | F103: =DCon!D16 -> 0 | G103: =DCon!M16 -> 0 | J103: =DCon!U16 -> 0 | K103: =DCon!V16 -> 0 | L103: =SUM(F103:K103) -> 0 | M103: 1 | N103: ='Exhibiciones '!$A$4 -> ECATEPEC | O103: =Jeans!$E$4 -> Jeans | P103: =Jeans!AC18 -> 0 | Q103: =Jeans!AD18 | R103: =Jeans!B18 -> 34 | S103: - | T103: =Jeans!G18 -> 0 | U103: =Jeans!T18 -> 0 | V103: =Jeans!R18 -> 0 | W103: =Jeans!S18 -> 0 | X103: =SUM(S103:W103) -> 0 | Y103: 1
A104: ='Exhibiciones '!$A$4 -> ECATEPEC | B104: =DCon!$D$4 -> Confort | C104: =DCon!AG17 -> 0 | D104: =IFERROR(VLOOKUP(C104,'Plantilla y Concentrado'!$B$4:$C$677,2,0),"") | E104: =DCon!A17 -> 0 | F104: =DCon!D17 -> 0 | G104: =DCon!M17 -> 0 | J104: =DCon!U17 -> 0 | K104: =DCon!V17 -> 0 | L104: =SUM(F104:K104) -> 0 | M104: 1 | N104: ='Exhibiciones '!$A$4 -> ECATEPEC | O104: =Jeans!$E$4 -> Jeans | P104: =Jeans!AC19 -> 0 | Q104: =Jeans!AD19 | R104: =Jeans!B19 -> 35 | S104: - | T104: =Jeans!G19 -> 0 | U104: =Jeans!T19 -> 0 | V104: =Jeans!R19 -> 0 | W104: =Jeans!S19 -> 0 | X104: =SUM(S104:W104) -> 0 | Y104: 1
A105: ='Exhibiciones '!$A$4 -> ECATEPEC | B105: =DCon!$D$4 -> Confort | C105: =DCon!AG18 -> 0 | D105: =IFERROR(VLOOKUP(C105,'Plantilla y Concentrado'!$B$4:$C$677,2,0),"") | E105: =DCon!A18 -> 0 | F105: =DCon!D18 -> 0 | G105: =DCon!M18 -> 0 | J105: =DCon!U18 -> 0 | K105: =DCon!V18 -> 0 | L105: =SUM(F105:K105) -> 0 | M105: 1 | N105: ='Exhibiciones '!$A$4 -> ECATEPEC | O105: =Jeans!$E$4 -> Jeans | P105: =Jeans!AC20 -> 0 | Q105: =Jeans!AD20 | R105: =Jeans!B20 -> 36 | S105: - | T105: =Jeans!G20 -> 0 | U105: =Jeans!T20 -> 0 | V105: =Jeans!R20 -> 0 | W105: =Jeans!S20 -> 0 | X105: =SUM(S105:W105) -> 0 | Y105: 1
A106: ='Exhibiciones '!$A$4 -> ECATEPEC | B106: =DCon!$D$4 -> Confort | C106: =DCon!AG19 -> 0 | D106: =IFERROR(VLOOKUP(C106,'Plantilla y Concentrado'!$B$4:$C$677,2,0),"") | E106: =DCon!A19 -> 0 | F106: =DCon!D19 -> 0 | G106: =DCon!M19 -> 0 | J106: =DCon!U19 -> 0 | K106: =DCon!V19 -> 0 | L106: =SUM(F106:K106) -> 0 | M106: 1 | N106: ='Exhibiciones '!$A$4 -> ECATEPEC | O106: =Jeans!$E$4 -> Jeans | P106: =Jeans!AC21 -> 0 | Q106: =Jeans!AD21 | R106: =Jeans!B21 -> SEVEN | S106: - | T106: =Jeans!G21 -> 0 | U106: =Jeans!T21 -> 0 | V106: =Jeans!R21 -> 0 | W106: =Jeans!S21 -> 0 | X106: =SUM(S106:W106) -> 0 | Y106: 1
A107: ='Exhibiciones '!$A$4 -> ECATEPEC | B107: =DCon!$D$4 -> Confort | C107: =DCon!AG20 -> 0 | D107: =IFERROR(VLOOKUP(C107,'Plantilla y Concentrado'!$B$4:$C$677,2,0),"") | E107: =DCon!A20 -> 0 | F107: =DCon!D20 -> 0 | G107: =DCon!M20 -> 0 | J107: =DCon!U20 -> 0 | K107: =DCon!V20 -> 0 | L107: =SUM(F107:K107) -> 0 | M107: 1 | N107: ='Exhibiciones '!$A$4 -> ECATEPEC | O107: =Jeans!$E$4 -> Jeans | P107: =Jeans!AC22 -> 0 | Q107: =Jeans!AD22 | R107: =Jeans!B22 -> FERGINO | S107: - | T107: =Jeans!G22 -> 0 | U107: =Jeans!T22 -> 0 | V107: =Jeans!R22 -> 0 | W107: =Jeans!S22 -> 0 | X107: =SUM(S107:W107) -> 0 | Y107: 1
... A117: ='Exhibiciones '!$A$4 -> ECATEPEC | B117: =DCon!$D$4 -> Confort | C117: =DCon!AG30 -> 0 | D117: =IFERROR(VLOOKUP(C117,'Plantilla y Concentrado'!$B$4:$C$677,2,0),"") | E117: =DCon!A30 -> 0 | F117: =DCon!D30 -> 0 | G117: =DCon!M30 -> 0 | J117: =DCon!U30 -> 0 | K117: =DCon!V30 -> 0 | L117: =SUM(F117:K117) -> 0 | M117: 1 | N117: ='Exhibiciones '!$A$4 -> ECATEPEC | O117: =Jeans!$E$4 -> Jeans | P117: =Jeans!AC32 -> 0 | Q117: =Jeans!AD32 | R117: =Jeans!B32 -> 0 | S117: - | T117: =Jeans!G32 -> 0 | U117: =Jeans!T32 -> 0 | V117: =Jeans!R32 -> 0 | W117: =Jeans!S32 -> 0 | X117: =SUM(S117:W117) -> 0 | Y117: 1
A118: ='Exhibiciones '!$A$4 -> ECATEPEC | B118: =DVes!$D$4 -> Vestir Casual | C118: =DVes!AG9 -> 127209 | D118: =IFERROR(VLOOKUP(C118,'Plantilla y Concentrado'!$B$4:$C$677,2,0),"") -> Castillo Ramirez Tania Mayeli | E118: =DVes!A9 -> 37B | F118: =DVes!D9 -> 0 | G118: =DVes!M9 -> 0 | J118: =DVes!U10 -> 0 | K118: =DVes!V10 -> 0 | L118: =SUM(F118:K118) -> 0 | M118: 1 | N118: ='Exhibiciones '!$A$4 -> ECATEPEC | O118: =Jeans!$E$4 -> Jeans | P118: =Jeans!AC33 -> 0 | Q118: =Jeans!AD33 | R118: =Jeans!B33 -> 0 | S118: - | T118: =Jeans!G33 -> 0 | U118: =Jeans!T33 -> 0 | V118: =Jeans!R33 -> 0 | W118: =Jeans!S33 -> 0 | X118: =SUM(S118:W118) -> 0 | Y118: 1
A119: ='Exhibiciones '!$A$4 -> ECATEPEC | B119: =DVes!$D$4 -> Vestir Casual | C119: =DVes!AG10 -> 136675 | D119: =IFERROR(VLOOKUP(C119,'Plantilla y Concentrado'!$B$4:$C$677,2,0),"") -> Montiel Ramirez Cintya Elizabeth | E119: =DVes!A10 -> 38 | F119: =DVes!D10 -> 0 | G119: =DVes!M10 -> 0 | J119: =DVes!U11 -> 0 | K119: =DVes!V11 -> 0 | L119: =SUM(F119:K119) -> 0 | M119: 1 | N119: ='Exhibiciones '!$A$4 -> ECATEPEC | O119: =Jeans!$E$4 -> Jeans | P119: =Jeans!AC34 -> 0 | Q119: =Jeans!AD34 | R119: =Jeans!B34 -> 0 | S119: - | T119: =Jeans!G34 -> 0 | U119: =Jeans!T34 -> 0 | V119: =Jeans!R34 -> 0 | W119: =Jeans!S34 -> 0 | X119: =SUM(S119:W119) -> 0 | Y119: 1
A120: ='Exhibiciones '!$A$4 -> ECATEPEC | B120: =DVes!$D$4 -> Vestir Casual | C120: =DVes!AG11 -> 155938 | D120: =IFERROR(VLOOKUP(C120,'Plantilla y Concentrado'!$B$4:$C$677,2,0),"") -> Aguilar Flores Erika Jazmin | E120: =DVes!A11 -> 39 | F120: =DVes!D11 -> 1 | G120: =DVes!M11 -> 0 | J120: =DVes!U12 -> 0 | K120: =DVes!V12 -> 0 | L120: =SUM(F120:K120) -> 1 | M120: 1 | N120: ='Exhibiciones '!$A$4 -> ECATEPEC | O120: =Jeans!$E$4 -> Jeans | P120: =Jeans!AC35 -> 0 | Q120: =Jeans!AD35 | R120: =Jeans!B35 -> 0 | S120: - | T120: =Jeans!G35 -> 0 | U120: =Jeans!T35 -> 0 | V120: =Jeans!R35 -> 0 | W120: =Jeans!S35 -> 0 | X120: =SUM(S120:W120) -> 0 | Y120: 1
A121: ='Exhibiciones '!$A$4 -> ECATEPEC | B121: =DVes!$D$4 -> Vestir Casual | C121: =DVes!AG12 -> 144695 | D121: =IFERROR(VLOOKUP(C121,'Plantilla y Concentrado'!$B$4:$C$677,2,0),"") -> Alvarez Becerra Emiliano | E121: =DVes!A12 -> 40 | F121: =DVes!D12 -> 0 | G121: =DVes!M12 -> 0 | J121: =DVes!U12 -> 0 | K121: =DVes!V12 -> 0 | L121: =SUM(F121:K121) -> 0 | M121: 1 | N121: ='Exhibiciones '!$A$4 -> ECATEPEC | O121: =Jeans!$E$4 -> Jeans | P121: =Jeans!AC36 -> 0 | Q121: =Jeans!AD36 | R121: =Jeans!B36 -> 0 | S121: - | T121: =Jeans!G36 -> 0 | U121: =Jeans!T36 -> 0 | V121: =Jeans!R36 -> 0 | W121: =Jeans!S36 -> 0 | X121: =SUM(S121:W121) -> 0 | Y121: 1
A122: ='Exhibiciones '!$A$4 -> ECATEPEC | B122: =DVes!$D$4 -> Vestir Casual | C122: =DVes!AG13 -> 0 | D122: =IFERROR(VLOOKUP(C122,'Plantilla y Concentrado'!$B$4:$C$677,2,0),"") | E122: =DVes!A13 -> 0 | F122: =DVes!D13 -> 0 | G122: =DVes!M13 -> 0 | J122: =DVes!U13 -> 0 | K122: =DVes!V13 -> 0 | L122: =SUM(F122:K122) -> 0 | M122: 1 | N122: ='Exhibiciones '!$A$4 -> ECATEPEC | O122: =Jeans!$E$4 -> Jeans | P122: =Jeans!AC37 -> 0 | Q122: =Jeans!AD37 | R122: =Jeans!B37 -> 0 | S122: - | T122: =Jeans!G37 -> 0 | U122: =Jeans!T37 -> 0 | V122: =Jeans!R37 -> 0 | W122: =Jeans!S37 -> 0 | X122: =SUM(S122:W122) -> 0 | Y122: 1
A123: ='Exhibiciones '!$A$4 -> ECATEPEC | B123: =DVes!$D$4 -> Vestir Casual | C123: =DVes!AG14 -> 0 | D123: =IFERROR(VLOOKUP(C123,'Plantilla y Concentrado'!$B$4:$C$677,2,0),"") | E123: =DVes!A14 -> 0 | F123: =DVes!D14 -> 0 | G123: =DVes!M14 -> 0 | J123: =DVes!U14 -> 0 | K123: =DVes!V14 -> 0 | L123: =SUM(F123:K123) -> 0 | M123: 1
A124: ='Exhibiciones '!$A$4 -> ECATEPEC | B124: =DVes!$D$4 -> Vestir Casual | C124: =DVes!AG15 -> 0 | D124: =IFERROR(VLOOKUP(C124,'Plantilla y Concentrado'!$B$4:$C$677,2,0),"") | E124: =DVes!A15 -> 0 | F124: =DVes!D15 -> 0 | G124: =DVes!M15 -> 0 | J124: =DVes!U15 -> 0 | K124: =DVes!V15 -> 0 | L124: =SUM(F124:K124) -> 0 | M124: 1
A125: ='Exhibiciones '!$A$4 -> ECATEPEC | B125: =DVes!$D$4 -> Vestir Casual | C125: =DVes!AG16 -> 0 | D125: =IFERROR(VLOOKUP(C125,'Plantilla y Concentrado'!$B$4:$C$677,2,0),"") | E125: =DVes!A16 -> 0 | F125: =DVes!D16 -> 0 | G125: =DVes!M16 -> 0 | J125: =DVes!U16 -> 0 | K125: =DVes!V16 -> 0 | L125: =SUM(F125:K125) -> 0 | M125: 1
A126: ='Exhibiciones '!$A$4 -> ECATEPEC | B126: =DVes!$D$4 -> Vestir Casual | C126: =DVes!AG17 -> 0 | D126: =IFERROR(VLOOKUP(C126,'Plantilla y Concentrado'!$B$4:$C$677,2,0),"") | E126: =DVes!A17 -> 0 | F126: =DVes!D17 -> 0 | G126: =DVes!M17 -> 0 | J126: =DVes!U17 -> 0 | K126: =DVes!V17 -> 0 | L126: =SUM(F126:K126) -> 0 | M126: 1
A127: ='Exhibiciones '!$A$4 -> ECATEPEC | B127: =DVes!$D$4 -> Vestir Casual | C127: =DVes!AG18 -> 0 | D127: =IFERROR(VLOOKUP(C127,'Plantilla y Concentrado'!$B$4:$C$677,2,0),"") | E127: =DVes!A18 -> 0 | F127: =DVes!D18 -> 0 | G127: =DVes!M18 -> 0 | J127: =DVes!U18 -> 0 | K127: =DVes!V18 -> 0 | L127: =SUM(F127:K127) -> 0 | M127: 1
A128: ='Exhibiciones '!$A$4 -> ECATEPEC | B128: =DVes!$D$4 -> Vestir Casual | C128: =DVes!AG19 -> 0 | D128: =IFERROR(VLOOKUP(C128,'Plantilla y Concentrado'!$B$4:$C$677,2,0),"") | E128: =DVes!A19 -> 0 | F128: =DVes!D19 -> 0 | G128: =DVes!M19 -> 0 | J128: =DVes!U19 -> 0 | K128: =DVes!V19 -> 0 | L128: =SUM(F128:K128) -> 0 | M128: 1
A129: ='Exhibiciones '!$A$4 -> ECATEPEC | B129: =DVes!$D$4 -> Vestir Casual | C129: =DVes!AG20 -> 0 | D129: =IFERROR(VLOOKUP(C129,'Plantilla y Concentrado'!$B$4:$C$677,2,0),"") | E129: =DVes!A20 -> 0 | F129: =DVes!D20 -> 0 | G129: =DVes!M20 -> 0 | J129: =DVes!U20 -> 0 | K129: =DVes!V20 -> 0 | L129: =SUM(F129:K129) -> 0 | M129: 1
A130: ='Exhibiciones '!$A$4 -> ECATEPEC | B130: =DVes!$D$4 -> Vestir Casual | C130: =DVes!AG21 -> 0 | D130: =IFERROR(VLOOKUP(C130,'Plantilla y Concentrado'!$B$4:$C$677,2,0),"") | E130: =DVes!A21 -> 0 | F130: =DVes!D21 -> 0 | G130: =DVes!M21 -> 0 | J130: =DVes!U21 -> 0 | K130: =DVes!V21 -> 0 | L130: =SUM(F130:K130) -> 0 | M130: 1
A131: ='Exhibiciones '!$A$4 -> ECATEPEC | B131: =DVes!$D$4 -> Vestir Casual | C131: =DVes!AG22 -> 0 | D131: =IFERROR(VLOOKUP(C131,'Plantilla y Concentrado'!$B$4:$C$677,2,0),"") | E131: =DVes!A22 -> 0 | F131: =DVes!D22 -> 0 | G131: =DVes!M22 -> 0 | J131: =DVes!U22 -> 0 | K131: =DVes!V22 -> 0 | L131: =SUM(F131:K131) -> 0 | M131: 1
...

Sheet Plantilla y Concentrado
A4: 09.02.2026 | M4: 1
B5: 66 | C5: Gomez Cardenas Laura Minerva | D5: Estado de México | E5: Tienda Ecatepec | F5: Administrativo Quin | G5: PST002G501 | H5: Recursos Humanos | I5: 30000004 | J5: Analista | K5: Dir Capital Humano
B6: 194 | C6: Arellano Arellano Cyntia Elizabeth | D6: Estado de México | E6: Tienda Ecatepec | F6: Operativo Quin | G6: PST002G301 | H6: Gerencia Servicios | I6: 30000069 | J6: Supervisor | K6: Gerencia General
B7: 233 | C7: Vidaurri Morales Yareni | D7: Estado de México | E7: Tienda Ecatepec | F7: Operativo Quin | G7: PST002G181 | H7: Golden | I7: 30000069 | J7: Supervisor | K7: Comercial
B8: 240 | C8: Hernandez Gonzalez Anita | D8: Estado de México | E8: Tienda Ecatepec | F8: Operativo Quin | G8: PST002G404 | H8: Verific Garantías | I8: 30000074 | J8: Verificador | K8: Operaciones
B9: 376 | C9: Fernandez Galeana Rafael | D9: Estado de México | E9: Tienda Ecatepec | F9: Gerencia | G9: PST002G001 | H9: Gerencia General | I9: 30000036 | J9: Gerente | K9: Dir Comercial Operativa
B10: 483 | C10: Alvarado Hernandez Irma | D10: Estado de México | E10: Tienda Ecatepec | F10: Operativo Quin | G10: PST002G309 | H10: Cambios y Devolucion | I10: 30000074 | J10: Verificador | K10: Operaciones
B11: 646 | C11: Hernandez Gonzalez Israel | D11: Estado de México | E11: Tienda Ecatepec | F11: Operativo Sem | G11: PST002G204 | H11: Etiquetado | I11: 30000009 | J11: Auxiliar | K11: Operaciones
B12: 758 | C12: Lopez Martinez Jannet | D12: Estado de México | E12: Tienda Ecatepec | F12: Administrativo Quin | G12: PST002G021 | H12: Caja General | I12: 30000043 | J12: Jefe | K12: Tesoreria
B13: 937 | C13: Garcia Moreno Enrique | D13: Estado de México | E13: Tienda Ecatepec | F13: Operativo Sem | G13: PST002G206 | H13: Bodegas | I13: 30000009 | J13: Auxiliar | K13: Operaciones
B14: 971 | C14: Cordova Ramirez Elizabeth Edith | D14: Estado de México | E14: Tienda Ecatepec | F14: Gerencia | G14: PST002G118 | H14: Producto | I14: 30000036 | J14: Gerente | K14: Gerencia General
B15: 998 | C15: Vargas Guadalupe Maria de Jesus Alicia | D15: Estado de México | E15: Tienda Ecatepec | F15: Operativo Sem | G15: PST002G160 | H15: Ropa | I15: 30000006 | J15: Asesor | K15: Comercial
B16: 1183 | C16: Muñoz Sanchez Yesmet Wendy | D16: Estado de México | E16: Tienda Ecatepec | F16: Operativo Sem | G16: PST002G192 | H16: Cambios Piso | I16: 30000009 | J16: Auxiliar | K16: Operaciones
... B438: 158262 | C438: Sanchez Toledo Fatima Azul | D438: Estado de México | E438: Tienda Ecatepec | F438: Operativo Sem | G438: PST073G000 | H438: Outlet Ecatepec | I438: 30000006 | J438: Asesor | K438: Outlet Comercial

Sheet Bot
D1: Formato para el registro del Check list del Supervisor | I1: Código: MS-CLS/01-18
I2: Versión: 001
I3: Vigencia a partir : Mayo 2022
B4: Tienda | D4: Ecatepec
B5: Fecha de auditoria: | D5: 30/Junio/2026 | E5: Gerente Comercial | F5: Luis ALberto Pérez
B6: Catálogo: | D6: BOTAS | E6: Gerente Com. Operativo | F6: Alejandro Balleza Gómez | M6: SI
B7: Supervisor de Catalogo | D7: Hazminda Garcia | E7: Gerente de Servicios | M7: NO
B8: # de Nomina | D8: 1752 | E8: Gerente de Operaciones | F8: Alejandro Balleza Gómez | M8: NA
B11: Responsable | C11: Definición de Servicio | D11: Indicador | E11: Criterio de Evaluación | F11: Número | G11: Alcance | H11: Valor | I11: Logro x actividad | J11: Logro x departamento | K11: Que dato se captura? | L11: Como obtengo este dato o cual es el entregable?
B12: Informativo | D12: Total de Tallas del Catálogo | F12: =DBot!B36 -> 5112
B13: Informativo | D13: Total de Tallas auditadas | F13: =DBot!C36 -> 4958 | G13: =IF(F12=0,"",F13/F12) -> 0.9698748
B14: Informativo | D14: Número de pasillos
B15: Informativo | D15: Sugerido del catálogo a 7 días
B16: Resurtido | C16: Producto | D16: Pasillos y piso de venta libre de mercancia por suvir a bodega. ( bodegas en el piso sin quien las trabaje ) | E16: Si cumple "Si" , si no cumple coloca "No" | F16: Na | G16: =IF(F16="NA","",IF(F16="SI",1,0)) | H16: 100 | I16: =IF(G16="","",IF(G16=0,0,IF(G16>0,(H16*G16)))) | J16: =IF(SUM(M16)=0,"-",SUM(I16)/SUM(M16)) -> - | K16: Cumple=100%, No cumple=0% | L16: Recorrido – Auditoría de Check List | M16: =IF(F16="NA","No aplica",H16) -> No aplica
B17: Auxiliar de Zona DEN | C17: Comercial | D17: Zona DEN en orden y con calzado del día (validar la entrega diaria de Lunes a Sábado) | E17: Si se realiza la entrega diaria = "Si", sino = "No" | F17: Na | G17: =IF(F17="NA","",IF(F17="SI",1,0)) | H17: 100 | I17: =IF(G17="","",IF(G17=0,0,IF(G17>0,(H17*G17)))) | J17: =IF(SUM(M17)=0,"-",SUM(I17)/SUM(M17)) -> - | K17: Cumple=100%, No cumple=0% | L17: Zona Den muestra reporte de entrega de mercancía ya sea de Nones o defectos | M17: =IF(F17="NA","No aplica",H17) -> No aplica
B18: Cambios Operativo | C18: Producto | D18: Pasillos y piso de venta libre de cambios. (cambios en el piso sin quien lo ubique = 0) | E18: Si hay cambios en el piso, Valida nombre de la persona destinada para subirlos, si esta la persona coloca "Si" , si no cumple coloca "No" | F18: Na | G18: =IF(F18="NA","",IF(F18="SI",1,0)) | H18: 50 | I18: =IF(G18="","",IF(G18=0,0,IF(G18>0,(H18*G18)))) | J18: =IF(SUM(M18:M19)=0,"-",SUM(I18:I19)/SUM(M18:M19)) -> - | K18: Cumple=100%, No cumple=0% | L18: Recorrido – Auditoría de Check List | M18: =IF(F18="NA","No aplica",H18) -> No aplica
D19: Personal de cambios ubicando el calzado en el modelo correcto | E19: Si hay personal ubicando cambios valida alguno, si los coloca en el modelo correcto, Si cumple "Si" , si no cumple coloca "No" | F19: Na | G19: =IF(F19="NA","",IF(F19="SI",1,0)) | H19: 50 | I19: =IF(G19="","",IF(G19=0,0,IF(G19>0,(H19*G19)))) | K19: Cumple=100%, No cumple=0% | L19: Recorrido – Auditoría de Check List | M19: =IF(F19="NA","No aplica",H19) -> No aplica
B20: Supervisor Calzado | C20: Comercial | D20: Se tiene evidencia de recorrido diario de revisión de exhibiciones | E20: Debe estar documentado el recorrido, si cumple coloca "Si" sino coloca cero "No" | F20: Na | G20: =IF(F20="NA","",IF(F20="SI",1,0)) | H20: 10 | I20: =IF(G20="","",IF(G20=0,0,IF(G20>0,(H20*G20)))) | J20: =IF(SUM(M20:M30)=0,"-",SUM(I20:I30)/SUM(M20:M30)) -> - | K20: Cumple=100%, No cumple=0% | L20: Supervisor de Piso muestra evidencia de recorrido | M20: =IF(F20="NA","No aplica",H20) -> No aplica
D21: # de frenteos encontrados en auditoria | E21: Por cada negado detectado como frenteo detectado en auditoria -5% | F21: Na | G21: =IF(F21="NA","",IF(F21<20,1-(F21*5/100),IF(F21>10,0))) | H21: 12 | I21: =IF(G21="","",IF(G21=0,0,IF(G21>0,(H21*G21)))) | K21: Total de Modelos revueltos | L21: Recorrido – Auditoría de Check List | M21: =IF(F21="NA","No aplica",H21) -> No aplica
D23: # de Pasillos con mercancía desalineada | E23: # pasillos NO alineados / Total de pasillos | F23: Na | G23: =IF(F23="NA","",1-(F23/F14)) | H23: 10 | I23: =IF(G23="","",IF(G23=0,0,IF(G23>0,(H23*G23)))) | K23: Cumple=100%, No cumple=0% | L23: Recorrido – Auditoría de Check List | M23: =IF(F23="NA","No aplica",H23) -> No aplica
D24: Muestra evidencia de la validación de curvas al día (Si se realiza Check List antes de las 12am puede mostrar evidencia del día anterior) | E24: Si cumple "Si" , si no cumple coloca "No" | F24: Na | G24: =IF(F24="NA","",IF(F24="SI",1,0)) | H24: 21 | I24: =IF(G24="","",IF(G24=0,0,IF(G24>0,(H24*G24)))) | K24: Cumple=SI, No cumple=NO | L24: Reporte de Certificacion de curvas | M24: =IF(F24="NA","No aplica",H24) -> No aplica
I25: =IF(G25="","",IF(G25=0,0,IF(G25>0,(H25*G25))))
D26: El colaborador conoce o da opciones de modelos similares de los modelos Agotados en su totalidad | E26: Si cumple "Si" , si no cumple coloca "No" ( Se valida a 2 colaboradores ) | F26: Na | G26: =IF(F26="NA","",IF(F26="SI",1,0)) | H26: 11 | I26: =IF(G26="","",IF(G26=0,0,IF(G26>0,(H26*G26)))) | K26: Cumple=SI, No cumple=NO | L26: Recorrido – Auditoría de Check List | M26: =IF(F26="NA","No aplica",H26) -> No aplica
D27: Colaboradores conocen sus funciones que vienen en su Rutina. | E27: Si cumple "Si" , si no cumple coloca "No" | F27: Na | G27: =IF(F27="NA","",IF(F27="Si",1,0)) | H27: 11 | I27: =IF(G27="","",IF(G27=0,0,IF(G27>0,(H27*G27)))) | K27: Cumple=SI, No cumple=NO | L27: Recorrido – Auditoría de Check List | M27: =IF(F27="NA","No aplica",H27) -> No aplica
D28: Colaboradores conocen sus resultados de su ultima auditoria. | E28: Si cumple "Si" , si no cumple coloca "No" | F28: Na | G28: =IF(F28="NA","",IF(F28="Si",1,0)) | H28: 9 | I28: =IF(G28="","",IF(G28=0,0,IF(G28>0,(H28*G28)))) | K28: Cumple=SI, No cumple=NO | L28: Recorrido – Auditoría de Check List | M28: =IF(F28="NA","No aplica",H28) -> No aplica
D29: El supervisor cuenta con evidencia de que ya entrego su rutina a sus colaboradores | E29: Si cumple "Si" , si no cumple coloca "No" | F29: Na | G29: =IF(F29="NA","",IF(F29="Si",1,0)) | H29: 8 | I29: =IF(G29="","",IF(G29=0,0,IF(G29>0,(H29*G29)))) | K29: Cumple=SI, No cumple=NO | L29: Evidencia de listado de entrega de rutinas | M29: =IF(F29="NA","No aplica",H29) -> No aplica
C30: Producto | D30: Se cuenta con listado de Cajas Maltratadas que entrega a Zona DEN, para ser solicitadas al área de Compras | E30: Si cumple "Si" , si no cumple coloca "No" | F30: Na | G30: =IF(F30="NA","",IF(F30="SI",1,0)) | H30: 8 | I30: =IF(G30="","",IF(G30=0,0,IF(G30>0,(H30*G30)))) | K30: Cumple=SI, No cumple=NO | L30: Listado actualizado de cajas | M30: =IF(F30="NA","No aplica",H30) -> No aplica
B31: Visual Merchandising | C31: Auto conducción | D31: Publicidad en buen estado y vigente | E31: Si cumple "Si" , si no cumple coloca "No" | F31: Na | G31: =IF(F31="NA","",IF(F31="SI",1,0)) | H31: 30 | I31: =IF(G31="","",IF(G31=0,0,IF(G31>0,(H31*G31)))) | J31: =IF(SUM(M31:M33)=0,"-",SUM(I31:I33)/SUM(M31:M33)) -> - | K31: Cumple=SI, No cumple=NO | L31: Recorrido – Auditoría de Check List | M31: =IF(F31="NA","No aplica",H31) -> No aplica
D32: La numeración del pasillo en buenas condiciones | E32: Si cumple "Si" , si no cumple coloca "No" | F32: Na | G32: =IF(F32="NA","",IF(F32="SI",1,0)) | H32: 30 | I32: =IF(G32="","",IF(G32=0,0,IF(G32>0,(H32*G32)))) | K32: Cumple=SI, No cumple=NO | L32: Recorrido – Auditoría de Check List | M32: =IF(F32="NA","No aplica",H32) -> No aplica
D33: Los pendones visibles al socio , en buenas condiciones, alineados y limpios | E33: Si cumple "Si" , si no cumple coloca "No" | F33: Na | G33: =IF(F33="NA","",IF(F33="SI",1,0)) | H33: 40 | I33: =IF(G33="","",IF(G33=0,0,IF(G33>0,(H33*G33)))) | K33: Cumple=SI, No cumple=NO | L33: Recorrido – Auditoría de Check List | M33: =IF(F33="NA","No aplica",H33) -> No aplica
B34: Recibo | C34: Comercial | D34: Se recibió el reporte Hot list (Origen) | E34: Si cumple "Si" , si no cumple coloca "No" | F34: Na | G34: =IF(F34="NA","",IF(F34="SI",1,0)) | H34: 100 | I34: =IF(G34="","",IF(G34=0,0,IF(G34>0,(H34*G34)))) | J34: =IF(SUM(M34)=0,"-",SUM(I34)/SUM(M34)) -> - | K34: Cumple=SI, No cumple=NO | L34: Reporte de Origen actualizado | M34: =IF(F34="NA","No aplica",H34) -> No aplica
B35: Sistemas | C35: Auto conducción | D35: Revisión de kioscos encendidos y limpios funcion | E35: Si cumple "Si" , si no cumple coloca "No" | F35: Na | G35: =IF(F35="NA","",IF(F35="SI",1,0)) | H35: 100 | I35: =IF(G35="","",IF(G35=0,0,IF(G35>0,(H35*G35)))) | J35: =IF(SUM(M35)=0,"-",SUM(I35)/SUM(M35)) -> - | K35: Recorrido – Auditoría de Check List | L35: Recorrido – Auditoría de Check List | M35: =IF(F35="NA","No aplica",H35) -> No aplica
B36: Indicadores | C36: Comercial | D36: % del check list de cabeceras de catalogo | E36: % de calificación que se obtuvo el la revision de las cabeceras en base a las fichas de instruccion | F36: Na | G36: =IF(F36="Na","",F36) | H36: 50 | I36: =IF(G36="","",IF(G36=0,0,IF(G36>0,(H36*G36)))) | J36: =IF(SUM(M36:M38)=0,"-",SUM(I36:I38)/SUM(M36:M38)) -> - | K36: Recorrido – Auditoría de Check List | L36: Recorrido – Auditoría de Check List | M36: =IF(F36="NA","No aplica",H36) -> No aplica
D37: % de check list de supervisor de calzado | E37: % de calificación de check list de supervisor, (Semana Anterior o ultima auditoria) | F37: Na | G37: =IF(F37="Na","",F37) | H37: 50 | I37: =IF(G37="","",IF(G37=0,0,IF(G37>0,(H37*G37)))) | K37: Recorrido – Auditoría de Check List | L37: Recorrido – Auditoría de Check List | M37: =IF(F37="NA","No aplica",H37) -> No aplica
E40: =D6 -> BOTAS
E41: Resurtido | F41: =J16 -> -
E42: Auxiliar de Zona DEN | F42: =J17 -> -
E43: Cambios Operativo | F43: =J18 -> -
E44: Supervisor Calzado | F44: =J20 -> -
E45: Imagen | F45: =J31 -> -
E46: Recibo | F46: =J34 -> -
E47: Sistemas | F47: =J35 -> -
E48: Indicadores | F48: =J36 -> -
E49: TOTAL: | F49: =IF(COUNT(F41:F48)>0,AVERAGE(F41:F48),"-") -> -

Sheet DBot
D1: Dictamen de Auditoría a pasillos calzado | AH1: Código: MS-APC/01-17
AH2: Versión: 001
AH3: Vigencia a partir : Mayo 2022
C4: Catalogo: | D4: =Bot!D6 -> BOTAS | R4: Precio promedio por pieza: | W4: 542 | AD4: Fecha de auditoria: | AG4: =Bot!D5 -> 30/Junio/2026
C5: Supervisor de Catalogo: | D5: =Bot!D7 -> Hazminda Garcia | R5: Sugerido de Catalogo | W5: =Bot!F15 -> 0
R6: Tallas del catalogo (linea y linea x inventario) | W6: =B36 -> 5112
D7: Causas de Negado | S7: Incidencias de Auditoria
A8: Pasillo | B8: TOTAL DE TALLAS POR PASILLO | C8: TALLAS AUDITADAS | D8: Frenteos | E8: Revueltos | F8: Bodega Venta | G8: Bodega Tapanco | H8: Doble Ubicación | I8: Excedente | J8: Origen | K8: Cambios / Probadores | L8: Negados sin Recuperar | M8: Exhibiciones | N8: Bodega Aclaración | O8: Aduanas | P8: Golden o apartados | Q8: Control de calidad | R8: Costo por pasillo | S8: Sin Exhibición | T8: Exhibición fuera de Política | U8: Modelos revuelto | V8: Modelos mal entallados | W8: Modelos con error de ubicación | X8: Curva con diferencia en frentes | Y8: Curva con diferencia en fondos | Z8: Curva con diferencia en altura | AA8: Curvas vencidas | AB8: Curvas que no coincide Price Soft vs Piso de Venta | AC8: Curvas faltantes | AD8: Cenefas faltantes | AE8: Cenefas de precio Promoción faltantes | AF8: Cartas disculpa / destallados faltantes | AG8: Nómina | AH8: Asesor de venta responsable del pasillo
A9: 1 | B9: 327 | C9: 327 | D9: 0 | E9: 0 | F9: 0 | G9: 0 | H9: 0 | I9: 0 | J9: 0 | K9: 0 | L9: 0 | M9: 0 | N9: 0 | O9: 0 | P9: 0 | Q9: 0 | R9: =($W$4*(SUM(D9:Q9))) -> 0 | S9: =IFERROR(SUMIF('Exhibiciones '!$E$5:$E$550,A9,'Exhibiciones '!$AF$5:$AF$550),"") -> 0 | T9: =IFERROR(SUMIF('Exhibiciones '!$E$5:$E$550,A9,'Exhibiciones '!$AG$5:$AG$550),"-") -> 0 | U9: 0 | V9: 0 | W9: 0 | X9: 0 | Y9: 0 | Z9: 0 | AA9: 0 | AB9: 0 | AC9: 0 | AD9: 0 | AE9: 0 | AF9: 0 | AG9: 127209 | AH9: =IFERROR(VLOOKUP(AG9,'Plantilla y Concentrado'!$B$4:$C$677,2,0),"") -> Castillo Ramirez Tania Mayeli
A10: 2 | B10: 464 | C10: 464 | D10: 0 | E10: 0 | F10: 0 | G10: 0 | H10: 0 | I10: 0 | J10: 0 | K10: 0 | L10: 3 | M10: 0 | N10: 0 | O10: 0 | P10: 0 | Q10: 0 | R10: =($W$4*(SUM(D10:Q10))) -> 1626 | S10: 0 | T10: =IFERROR(SUMIF('Exhibiciones '!$E$5:$E$550,A10,'Exhibiciones '!$AG$5:$AG$550),"-") -> 0 | U10: 0 | V10: 0 | W10: 0 | X10: 0 | Y10: 0 | Z10: 0 | AA10: 0 | AB10: 0 | AC10: 0 | AD10: 0 | AE10: 0 | AF10: 0 | AG10: 144695 | AH10: =IFERROR(VLOOKUP(AG10,'Plantilla y Concentrado'!$B$4:$C$677,2,0),"") -> Alvarez Becerra Emiliano
A11: 3 | B11: 306 | C11: 306 | D11: 0 | E11: 0 | F11: 0 | G11: 0 | H11: 0 | I11: 0 | J11: 0 | K11: 0 | L11: 0 | M11: 0 | N11: 0 | O11: 0 | P11: 0 | Q11: 0 | R11: =($W$4*(SUM(D11:Q11))) -> 0 | S11: =IFERROR(SUMIF('Exhibiciones '!$E$5:$E$550,A11,'Exhibiciones '!$AF$5:$AF$550),"") -> 0 | T11: =IFERROR(SUMIF('Exhibiciones '!$E$5:$E$550,A11,'Exhibiciones '!$AG$5:$AG$550),"-") -> 0 | U11: 0 | V11: 0 | W11: 0 | X11: 0 | Y11: 0 | Z11: 0 | AA11: 0 | AB11: 0 | AC11: 0 | AD11: 0 | AE11: 0 | AF11: 0 | AG11: 144695 | AH11: =IFERROR(VLOOKUP(AG11,'Plantilla y Concentrado'!$B$4:$C$677,2,0),"") -> Alvarez Becerra Emiliano
A12: 15 | B12: 361 | C12: 361 | D12: 0 | E12: 0 | F12: 0 | G12: 0 | H12: 0 | I12: 0 | J12: 0 | K12: 0 | L12: 0 | M12: 0 | N12: 0 | O12: 0 | P12: 0 | Q12: 0 | R12: =($W$4*(SUM(D12:Q12))) -> 0 | S12: =IFERROR(SUMIF('Exhibiciones '!$E$5:$E$550,A12,'Exhibiciones '!$AF$5:$AF$550),"") -> 0 | T12: =IFERROR(SUMIF('Exhibiciones '!$E$5:$E$550,A12,'Exhibiciones '!$AG$5:$AG$550),"-") -> 0 | U12: 0 | V12: 0 | W12: 0 | X12: 0 | Y12: 0 | Z12: 0 | AA12: 0 | AB12: 0 | AC12: 0 | AD12: 0 | AE12: 0 | AF12: 0 | AG12: 155938 | AH12: =IFERROR(VLOOKUP(AG12,'Plantilla y Concentrado'!$B$4:$C$677,2,0),"") -> Aguilar Flores Erika Jazmin
A13: 16 | B13: 330 | C13: 324 | D13: 0 | E13: 0 | F13: 0 | G13: 0 | H13: 0 | I13: 0 | J13: 0 | K13: 0 | L13: 0 | M13: 0 | N13: 0 | O13: 0 | P13: 0 | Q13: 0 | R13: =($W$4*(SUM(D13:Q13))) -> 0 | S13: =IFERROR(SUMIF('Exhibiciones '!$E$5:$E$550,A13,'Exhibiciones '!$AF$5:$AF$550),"") -> 0 | T13: =IFERROR(SUMIF('Exhibiciones '!$E$5:$E$550,A13,'Exhibiciones '!$AG$5:$AG$550),"-") -> 0 | U13: 0 | V13: 0 | W13: 0 | X13: 0 | Y13: 0 | Z13: 0 | AA13: 0 | AB13: 0 | AC13: 0 | AD13: 0 | AE13: 0 | AF13: 0 | AG13: 158001 | AH13: =IFERROR(VLOOKUP(AG13,'Plantilla y Concentrado'!$B$4:$C$677,2,0),"") -> Nuñez Garcia Clarissa Naomi
A14: 17 | B14: 240 | C14: 217 | D14: 0 | E14: 0 | F14: 0 | G14: 0 | H14: 0 | I14: 0 | J14: 0 | K14: 0 | L14: 1 | M14: 0 | N14: 0 | O14: 0 | P14: 0 | Q14: 0 | R14: =($W$4*(SUM(D14:Q14))) -> 542 | S14: =IFERROR(SUMIF('Exhibiciones '!$E$5:$E$550,A14,'Exhibiciones '!$AF$5:$AF$550),"") -> 0 | T14: =IFERROR(SUMIF('Exhibiciones '!$E$5:$E$550,A14,'Exhibiciones '!$AG$5:$AG$550),"-") -> 0 | U14: 0 | V14: 0 | W14: 0 | X14: 0 | Y14: 0 | Z14: 0 | AA14: 0 | AB14: 0 | AC14: 0 | AD14: 0 | AE14: 0 | AF14: 0 | AG14: 154648 | AH14: =IFERROR(VLOOKUP(AG14,'Plantilla y Concentrado'!$B$4:$C$677,2,0),"") -> Sanchez Vazquez Anayareli
A15: 18 | B15: 264 | C15: 264 | D15: 0 | E15: 0 | F15: 0 | G15: 0 | H15: 0 | I15: 0 | J15: 0 | K15: 0 | L15: 0 | M15: 0 | N15: 0 | O15: 0 | P15: 0 | Q15: 0 | R15: =($W$4*(SUM(D15:Q15))) -> 0 | S15: =IFERROR(SUMIF('Exhibiciones '!$E$5:$E$550,A15,'Exhibiciones '!$AF$5:$AF$550),"") -> 0 | T15: 0 | U15: 0 | V15: 0 | W15: 0 | X15: 0 | Y15: 0 | Z15: 0 | AA15: 0 | AB15: 0 | AC15: 0 | AD15: 0 | AE15: 0 | AF15: 0 | AG15: 144695 | AH15: =IFERROR(VLOOKUP(AG15,'Plantilla y Concentrado'!$B$4:$C$677,2,0),"") -> Alvarez Becerra Emiliano
A16: 19 | B16: 377 | C16: 377 | D16: 0 | E16: 0 | F16: 0 | G16: 0 | H16: 0 | I16: 0 | J16: 0 | K16: 0 | L16: 0 | M16: 0 | N16: 0 | O16: 0 | P16: 0 | Q16: 0 | R16: =($W$4*(SUM(D16:Q16))) -> 0 | S16: =IFERROR(SUMIF('Exhibiciones '!$E$5:$E$550,A16,'Exhibiciones '!$AF$5:$AF$550),"") -> 0 | T16: =IFERROR(SUMIF('Exhibiciones '!$E$5:$E$550,A16,'Exhibiciones '!$AG$5:$AG$550),"-") -> 0 | U16: 0 | V16: 0 | W16: 0 | X16: 0 | Y16: 0 | Z16: 0 | AA16: 0 | AB16: 0 | AC16: 0 | AD16: 0 | AE16: 0 | AF16: 0 | AG16: 136867 | AH16: =IFERROR(VLOOKUP(AG16,'Plantilla y Concentrado'!$B$4:$C$677,2,0),"") -> Barba Ramirez Jatziri Lizeth
A17: 20 | B17: 252 | C17: 231 | D17: 1 | E17: 0 | F17: 0 | G17: 0 | H17: 0 | I17: 0 | J17: 0 | K17: 0 | L17: 1 | M17: 0 | N17: 0 | O17: 0 | P17: 0 | Q17: 0 | R17: =($W$4*(SUM(D17:Q17))) -> 1084 | S17: =IFERROR(SUMIF('Exhibiciones '!$E$5:$E$550,A17,'Exhibiciones '!$AF$5:$AF$550),"") -> 0 | T17: =IFERROR(SUMIF('Exhibiciones '!$E$5:$E$550,A17,'Exhibiciones '!$AG$5:$AG$550),"-") -> 0 | U17: 0 | V17: 3 | W17: 0 | X17: 0 | Y17: 0 | Z17: 0 | AA17: 0 | AB17: 0 | AC17: 0 | AD17: 0 | AE17: 0 | AF17: 0 | AG17: 155938 | AH17: =IFERROR(VLOOKUP(AG17,'Plantilla y Concentrado'!$B$4:$C$677,2,0),"") -> Aguilar Flores Erika Jazmin
A18: 21 | B18: 199 | C18: 199 | D18: 0 | E18: 0 | F18: 0 | G18: 0 | H18: 0 | I18: 0 | J18: 0 | K18: 0 | L18: 0 | M18: 0 | N18: 0 | O18: 0 | P18: 0 | Q18: 0 | R18: =($W$4*(SUM(D18:Q18))) -> 0 | S18: =IFERROR(SUMIF('Exhibiciones '!$E$5:$E$550,A18,'Exhibiciones '!$AF$5:$AF$550),"") -> 0 | T18: =IFERROR(SUMIF('Exhibiciones '!$E$5:$E$550,A18,'Exhibiciones '!$AG$5:$AG$550),"-") -> 0 | U18: 0 | V18: 0 | W18: 0 | X18: 0 | Y18: 0 | Z18: 0 | AA18: 0 | AB18: 0 | AC18: 0 | AD18: 0 | AE18: 0 | AF18: 0 | AG18: 154648 | AH18: =IFERROR(VLOOKUP(AG18,'Plantilla y Concentrado'!$B$4:$C$677,2,0),"") -> Sanchez Vazquez Anayareli
A19: 22 | B19: 284 | C19: 232 | D19: 0 | E19: 0 | F19: 0 | G19: 0 | H19: 0 | I19: 0 | J19: 0 | K19: 0 | L19: 0 | M19: 0 | N19: 0 | O19: 0 | P19: 0 | Q19: 0 | R19: =($W$4*(SUM(D19:Q19))) -> 0 | S19: =IFERROR(SUMIF('Exhibiciones '!$E$5:$E$550,A19,'Exhibiciones '!$AF$5:$AF$550),"") -> 0 | T19: =IFERROR(SUMIF('Exhibiciones '!$E$5:$E$550,A19,'Exhibiciones '!$AG$5:$AG$550),"-") -> 0 | U19: 1 | V19: 0 | W19: 0 | X19: 0 | Y19: 0 | Z19: 0 | AA19: 0 | AB19: 0 | AC19: 0 | AD19: 0 | AE19: 0 | AF19: 0 | AG19: 158001 | AH19: =IFERROR(VLOOKUP(AG19,'Plantilla y Concentrado'!$B$4:$C$677,2,0),"") -> Nuñez Garcia Clarissa Naomi
A20: 23 | B20: 263 | C20: 263 | D20: 0 | E20: 0 | F20: 0 | G20: 0 | H20: 0 | I20: 0 | J20: 0 | K20: 0 | L20: 0 | M20: 0 | N20: 0 | O20: 0 | P20: 0 | Q20: 0 | R20: =($W$4*(SUM(D20:Q20))) -> 0 | S20: =IFERROR(SUMIF('Exhibiciones '!$E$5:$E$550,A20,'Exhibiciones '!$AF$5:$AF$550),"") -> 0 | T20: =IFERROR(SUMIF('Exhibiciones '!$E$5:$E$550,A20,'Exhibiciones '!$AG$5:$AG$550),"-") -> 0 | U20: 0 | V20: 0 | W20: 0 | X20: 0 | Y20: 0 | Z20: 0 | AA20: 0 | AB20: 0 | AC20: 0 | AD20: 0 | AE20: 0 | AF20: 0 | AG20: 155938 | AH20: =IFERROR(VLOOKUP(AG20,'Plantilla y Concentrado'!$B$4:$C$677,2,0),"") -> Aguilar Flores Erika Jazmin
A21: 24 | B21: 193 | C21: 193 | D21: 0 | E21: 0 | F21: 0 | G21: 0 | H21: 0 | I21: 0 | J21: 0 | K21: 0 | L21: 0 | M21: 0 | N21: 0 | O21: 0 | P21: 0 | Q21: 0 | R21: =($W$4*(SUM(D21:Q21))) -> 0 | S21: =IFERROR(SUMIF('Exhibiciones '!$E$5:$E$550,A21,'Exhibiciones '!$AF$5:$AF$550),"") -> 0 | T21: 0 | U21: 0 | V21: 0 | W21: 0 | X21: 0 | Y21: 0 | Z21: 0 | AA21: 0 | AB21: 0 | AC21: 0 | AD21: 0 | AE21: 0 | AF21: 0 | AG21: 136867 | AH21: =IFERROR(VLOOKUP(AG21,'Plantilla y Concentrado'!$B$4:$C$677,2,0),"") -> Barba Ramirez Jatziri Lizeth
A22: 25 | B22: 199 | C22: 193 | D22: 0 | E22: 0 | F22: 0 | G22: 0 | H22: 0 | I22: 0 | J22: 0 | K22: 0 | L22: 0 | M22: 0 | N22: 0 | O22: 0 | P22: 0 | Q22: 0 | R22: =($W$4*(SUM(D22:Q22))) -> 0 | S22: =IFERROR(SUMIF('Exhibiciones '!$E$5:$E$550,A22,'Exhibiciones '!$AF$5:$AF$550),"") -> 0 | T22: =IFERROR(SUMIF('Exhibiciones '!$E$5:$E$550,A22,'Exhibiciones '!$AG$5:$AG$550),"-") -> 0 | U22: 0 | V22: 0 | W22: 0 | X22: 0 | Y22: 0 | Z22: 0 | AA22: 0 | AB22: 0 | AC22: 0 | AD22: 0 | AE22: 0 | AF22: 0 | AG22: 144695 | AH22: =IFERROR(VLOOKUP(AG22,'Plantilla y Concentrado'!$B$4:$C$677,2,0),"") -> Alvarez Becerra Emiliano
A23: 26 | B23: 263 | C23: 248 | D23: 0 | E23: 0 | F23: 0 | G23: 0 | H23: 0 | I23: 0 | J23: 0 | K23: 0 | L23: 0 | M23: 0 | N23: 0 | O23: 0 | P23: 0 | Q23: 0 | R23: =($W$4*(SUM(D23:Q23))) -> 0 | S23: =IFERROR(SUMIF('Exhibiciones '!$E$5:$E$550,A23,'Exhibiciones '!$AF$5:$AF$550),"") -> 0 | T23: 0 | U23: 0 | V23: 0 | W23: 0 | X23: 0 | Y23: 0 | Z23: 0 | AA23: 0 | AB23: 0 | AC23: 0 | AD23: 0 | AE23: 0 | AF23: 0 | AG23: 127209 | AH23: =IFERROR(VLOOKUP(AG23,'Plantilla y Concentrado'!$B$4:$C$677,2,0),"") -> Castillo Ramirez Tania Mayeli
A24: 27 | B24: 357 | C24: 353 | D24: 0 | E24: 0 | F24: 0 | G24: 0 | H24: 0 | I24: 0 | J24: 0 | K24: 0 | L24: 0 | M24: 0 | N24: 0 | O24: 0 | P24: 0 | Q24: 0 | R24: =($W$4*(SUM(D24:Q24))) -> 0 | S24: =IFERROR(SUMIF('Exhibiciones '!$E$5:$E$550,A24,'Exhibiciones '!$AF$5:$AF$550),"") -> 0 | T24: =IFERROR(SUMIF('Exhibiciones '!$E$5:$E$550,A24,'Exhibiciones '!$AG$5:$AG$550),"-") -> 0 | U24: 0 | V24: 0 | W24: 0 | X24: 0 | Y24: 0 | Z24: 0 | AA24: 0 | AB24: 0 | AC24: 0 | AD24: 0 | AE24: 0 | AF24: 0 | AG24: 151630 | AH24: =IFERROR(VLOOKUP(AG24,'Plantilla y Concentrado'!$B$4:$C$677,2,0),"") -> Muñoz Lara Karla Paola
A25: 28 | B25: 210 | C25: 209 | D25: 0 | E25: 0 | F25: 0 | G25: 0 | H25: 0 | I25: 0 | J25: 0 | K25: 0 | L25: 0 | M25: 0 | N25: 0 | O25: 0 | P25: 0 | Q25: 0 | R25: =($W$4*(SUM(D25:Q25))) -> 0 | S25: =IFERROR(SUMIF('Exhibiciones '!$E$5:$E$550,A25,'Exhibiciones '!$AF$5:$AF$550),"") -> 0 | T25: 0 | U25: 0 | V25: 1 | W25: 0 | X25: 0 | Y25: 0 | Z25: 0 | AA25: 0 | AB25: 0 | AC25: 0 | AD25: 0 | AE25: 0 | AF25: 0 | AG25: 136867 | AH25: =IFERROR(VLOOKUP(AG25,'Plantilla y Concentrado'!$B$4:$C$677,2,0),"") -> Barba Ramirez Jatziri Lizeth
A26: 29 | B26: 223 | C26: 197 | D26: 0 | E26: 0 | F26: 0 | G26: 0 | H26: 0 | I26: 0 | J26: 0 | K26: 0 | L26: 0 | M26: 0 | N26: 0 | O26: 0 | P26: 0 | Q26: 0 | R26: =($W$4*(SUM(D26:Q26))) -> 0 | S26: =IFERROR(SUMIF('Exhibiciones '!$E$5:$E$550,A26,'Exhibiciones '!$AF$5:$AF$550),"") -> 0 | T26: =IFERROR(SUMIF('Exhibiciones '!$E$5:$E$550,A26,'Exhibiciones '!$AG$5:$AG$550),"-") -> 0 | U26: 0 | V26: 0 | W26: 0 | X26: 0 | Y26: 0 | Z26: 0 | AA26: 0 | AB26: 0 | AC26: 0 | AD26: 0 | AE26: 0 | AF26: 0 | AH26: =IFERROR(VLOOKUP(AG26,'Plantilla y Concentrado'!$B$4:$C$677,2,0),"")
D27: 0 | E27: 0 | F27: 0 | G27: 0 | H27: 0 | I27: 0 | J27: 0 | K27: 0 | L27: 0 | M27: 0 | N27: 0 | O27: 0 | P27: 0 | Q27: 0 | R27: =($W$4*(SUM(D27:Q27))) -> 0 | S27: =IFERROR(SUMIF('Exhibiciones '!$E$5:$E$550,A27,'Exhibiciones '!$AF$5:$AF$550),"") -> 0 | T27: =IFERROR(SUMIF('Exhibiciones '!$E$5:$E$550,A27,'Exhibiciones '!$AG$5:$AG$550),"-") -> 0 | U27: 0 | V27: 0 | W27: 0 | X27: 0 | Y27: 0 | Z27: 0 | AA27: 0 | AB27: 0 | AC27: 0 | AD27: 0 | AE27: 0 | AF27: 0 | AH27: =IFERROR(VLOOKUP(AG27,'Plantilla y Concentrado'!$B$4:$C$677,2,0),"")
D28: 0 | E28: 0 | F28: 0 | G28: 0 | H28: 0 | I28: 0 | J28: 0 | K28: 0 | L28: 0 | M28: 0 | N28: 0 | O28: 0 | P28: 0 | Q28: 0 | R28: =($W$4*(SUM(D28:Q28))) -> 0 | S28: =IFERROR(SUMIF('Exhibiciones '!$E$5:$E$550,A28,'Exhibiciones '!$AF$5:$AF$550),"") -> 0 | T28: =IFERROR(SUMIF('Exhibiciones '!$E$5:$E$550,A28,'Exhibiciones '!$AG$5:$AG$550),"-") -> 0 | U28: 0 | V28: 0 | W28: 0 | X28: 0 | Y28: 0 | Z28: 0 | AA28: 0 | AB28: 0 | AC28: 0 | AD28: 0 | AE28: 0 | AF28: 0 | AH28: =IFERROR(VLOOKUP(AG28,'Plantilla y Concentrado'!$B$4:$C$677,2,0),"")
D29: 0 | E29: 0 | F29: 0 | G29: 0 | H29: 0 | I29: 0 | J29: 0 | K29: 0 | L29: 0 | M29: 0 | N29: 0 | O29: 0 | P29: 0 | Q29: 0 | R29: =($W$4*(SUM(D29:Q29))) -> 0 | S29: =IFERROR(SUMIF('Exhibiciones '!$E$5:$E$550,A29,'Exhibiciones '!$AF$5:$AF$550),"") -> 0 | T29: =IFERROR(SUMIF('Exhibiciones '!$E$5:$E$550,A29,'Exhibiciones '!$AG$5:$AG$550),"-") -> 0 | U29: 0 | V29: 0 | W29: 0 | X29: 0 | Y29: 0 | Z29: 0 | AA29: 0 | AB29: 0 | AC29: 0 | AD29: 0 | AE29: 0 | AF29: 0 | AH29: =IFERROR(VLOOKUP(AG29,'Plantilla y Concentrado'!$B$4:$C$677,2,0),"")
D30: 0 | E30: 0 | F30: 0 | G30: 0 | H30: 0 | I30: 0 | J30: 0 | K30: 0 | L30: 0 | M30: 0 | N30: 0 | O30: 0 | P30: 0 | Q30: 0 | R30: =($W$4*(SUM(D30:Q30))) -> 0 | S30: =IFERROR(SUMIF('Exhibiciones '!$E$5:$E$550,A30,'Exhibiciones '!$AF$5:$AF$550),"") -> 0 | T30: =IFERROR(SUMIF('Exhibiciones '!$E$5:$E$550,A30,'Exhibiciones '!$AG$5:$AG$550),"-") -> 0 | U30: 0 | V30: 0 | W30: 0 | X30: 0 | Y30: 0 | Z30: 0 | AA30: 0 | AB30: 0 | AC30: 0 | AD30: 0 | AE30: 0 | AF30: 0 | AH30: =IFERROR(VLOOKUP(AG30,'Plantilla y Concentrado'!$B$4:$C$677,2,0),"")
D31: 0 | E31: 0 | F31: 0 | G31: 0 | H31: 0 | I31: 0 | J31: 0 | K31: 0 | L31: 0 | M31: 0 | N31: 0 | O31: 0 | P31: 0 | Q31: 0 | R31: =($W$4*(SUM(D31:Q31))) -> 0 | S31: =IFERROR(SUMIF('Exhibiciones '!$E$5:$E$550,A31,'Exhibiciones '!$AF$5:$AF$550),"") -> 0 | T31: =IFERROR(SUMIF('Exhibiciones '!$E$5:$E$550,A31,'Exhibiciones '!$AG$5:$AG$550),"-") -> 0 | U31: 0 | V31: 0 | W31: 0 | X31: 0 | Y31: 0 | Z31: 0 | AA31: 0 | AB31: 0 | AC31: 0 | AD31: 0 | AE31: 0 | AF31: 0 | AH31: =IFERROR(VLOOKUP(AG31,'Plantilla y Concentrado'!$B$4:$C$677,2,0),"")
D32: 0 | E32: 0 | F32: 0 | G32: 0 | H32: 0 | I32: 0 | J32: 0 | K32: 0 | L32: 0 | M32: 0 | N32: 0 | O32: 0 | P32: 0 | Q32: 0 | R32: =($W$4*(SUM(D32:Q32))) -> 0 | S32: =IFERROR(SUMIF('Exhibiciones '!$E$5:$E$550,A32,'Exhibiciones '!$AF$5:$AF$550),"") -> 0 | T32: =IFERROR(SUMIF('Exhibiciones '!$E$5:$E$550,A32,'Exhibiciones '!$AG$5:$AG$550),"-") -> 0 | U32: 0 | V32: 0 | W32: 0 | X32: 0 | Y32: 0 | Z32: 0 | AA32: 0 | AB32: 0 | AC32: 0 | AD32: 0 | AE32: 0 | AF32: 0 | AH32: =IFERROR(VLOOKUP(AG32,'Plantilla y Concentrado'!$B$4:$C$677,2,0),"")
D33: 0 | E33: 0 | F33: 0 | G33: 0 | H33: 0 | I33: 0 | J33: 0 | K33: 0 | L33: 0 | M33: 0 | N33: 0 | O33: 0 | P33: 0 | Q33: 0 | R33: =($W$4*(SUM(D33:Q33))) -> 0 | S33: =IFERROR(SUMIF('Exhibiciones '!$E$5:$E$550,A33,'Exhibiciones '!$AF$5:$AF$550),"") -> 0 | T33: =IFERROR(SUMIF('Exhibiciones '!$E$5:$E$550,A33,'Exhibiciones '!$AG$5:$AG$550),"-") -> 0 | U33: 0 | V33: 0 | W33: 0 | X33: 0 | Y33: 0 | Z33: 0 | AA33: 0 | AB33: 0 | AC33: 0 | AD33: 0 | AE33: 0 | AF33: 0 | AH33: =IFERROR(VLOOKUP(AG33,'Plantilla y Concentrado'!$B$4:$C$677,2,0),"")
D34: 0 | E34: 0 | F34: 0 | G34: 0 | H34: 0 | I34: 0 | J34: 0 | K34: 0 | L34: 0 | M34: 0 | N34: 0 | O34: 0 | P34: 0 | Q34: 0 | R34: =($W$4*(SUM(D34:Q34))) -> 0 | S34: =IFERROR(SUMIF('Exhibiciones '!$E$5:$E$550,A34,'Exhibiciones '!$AF$5:$AF$550),"") -> 0 | T34: =IFERROR(SUMIF('Exhibiciones '!$E$5:$E$550,A34,'Exhibiciones '!$AG$5:$AG$550),"-") -> 0 | U34: 0 | V34: 0 | W34: 0 | X34: 0 | Y34: 0 | Z34: 0 | AA34: 0 | AB34: 0 | AC34: 0 | AD34: 0 | AE34: 0 | AF34: 0 | AH34: =IFERROR(VLOOKUP(AG34,'Plantilla y Concentrado'!$B$4:$C$677,2,0),"")
D35: 0 | E35: 0 | F35: 0 | G35: 0 | H35: 0 | I35: 0 | J35: 0 | K35: 0 | L35: 0 | M35: 0 | N35: 0 | O35: 0 | P35: 0 | Q35: 0 | R35: =($W$4*(SUM(D35:Q35))) -> 0 | S35: =IFERROR(SUMIF('Exhibiciones '!$E$5:$E$550,A35,'Exhibiciones '!$AF$5:$AF$550),"") -> 0 | T35: =IFERROR(SUMIF('Exhibiciones '!$E$5:$E$550,A35,'Exhibiciones '!$AG$5:$AG$550),"-") -> 0 | U35: 0 | V35: 0 | W35: 0 | X35: 0 | Y35: 0 | Z35: 0 | AA35: 0 | AB35: 0 | AC35: 0 | AD35: 0 | AE35: 0 | AF35: 0 | AH35: =IFERROR(VLOOKUP(AG35,'Plantilla y Concentrado'!$B$4:$C$677,2,0),"")
A36: Total | B36: =SUM(B9:B35) -> 5112 | C36: =SUM(C9:C35) -> 4958 | D36: =SUM(D9:D35) -> 1 | E36: =SUM(E9:E35) -> 0 | F36: =SUM(F9:F35) -> 0 | G36: =SUM(G9:G35) -> 0 | H36: =SUM(H9:H35) -> 0 | I36: =SUM(I9:I35) -> 0 | ... Q36: =SUM(Q9:Q35) -> 0 | R36: =SUM(D36:Q36) -> 6 | S36: =SUM(S9:S35) -> 0 | T36: =SUM(T9:T35) -> 0 | U36: =SUM(U9:U35) -> 1 | V36: =SUM(V9:V35) -> 4 | W36: =SUM(W9:W35) -> 0 | X36: =SUM(X9:X35) -> 0 | Y36: =SUM(Y9:Y35) -> 0 | Z36: =SUM(Z9:Z35) -> 0 | ... AF36: =SUM(AF9:AF35) -> 0
A37: Costo de Oportunidad | D37: =($W$4*R36) -> 3252 | S37: Incidencias corregidas durante la auditoria
A38: Piezas recuperadas | C38: =A9 -> 1 | D38: 0 | E38: 0 | F38: 0 | G38: 0 | H38: 0 | I38: 0 | J38: 0 | K38: 0 | L38: 0 | M38: 0 | N38: 0 | O38: 0 | P38: 0 | Q38: 0 | R38: =($W$4*(SUM(D38:Q38))) -> 0 | S38: 0 | T38: 0 | U38: 0 | V38: 0 | W38: 0 | X38: 0 | Y38: 0 | Z38: 0 | AA38: 0 | AB38: 0 | AC38: 0 | AD38: 0 | AE38: 0 | AF38: 0
C39: =A10 -> 2 | D39: 0 | E39: 0 | F39: 0 | G39: 0 | H39: 0 | I39: 0 | J39: 0 | K39: 0 | L39: 0 | M39: 0 | N39: 0 | O39: 0 | P39: 0 | Q39: 0 | R39: =($W$4*(SUM(D39:Q39))) -> 0 | S39: 0 | T39: 0 | U39: 0 | V39: 0 | W39: 0 | X39: 0 | Y39: 0 | Z39: 0 | AA39: 0 | AB39: 0 | AC39: 0 | AD39: 0 | AE39: 0 | AF39: 0
C40: =A11 -> 3 | D40: 0 | E40: 0 | F40: 0 | G40: 0 | H40: 0 | I40: 0 | J40: 0 | K40: 0 | L40: 0 | M40: 0 | N40: 0 | O40: 0 | P40: 0 | Q40: 0 | R40: =($W$4*(SUM(D40:Q40))) -> 0 | S40: 0 | T40: 0 | U40: 0 | V40: 0 | W40: 0 | X40: 0 | Y40: 0 | Z40: 0 | AA40: 0 | AB40: 0 | AC40: 0 | AD40: 0 | AE40: 0 | AF40: 0
C41: =A12 -> 15 | D41: 0 | E41: 0 | F41: 0 | G41: 0 | H41: 0 | I41: 0 | J41: 0 | K41: 0 | L41: 0 | M41: 0 | N41: 0 | O41: 0 | P41: 0 | Q41: 0 | R41: =($W$4*(SUM(D41:Q41))) -> 0 | S41: 0 | T41: 0 | U41: 0 | V41: 0 | W41: 0 | X41: 0 | Y41: 0 | Z41: 0 | AA41: 0 | AB41: 0 | AC41: 0 | AD41: 0 | AE41: 0 | AF41: 0
C42: =A13 -> 16 | D42: 0 | E42: 0 | F42: 0 | G42: 0 | H42: 0 | I42: 0 | J42: 0 | K42: 0 | L42: 0 | M42: 0 | N42: 0 | O42: 0 | P42: 0 | Q42: 0 | R42: =($W$4*(SUM(D42:Q42))) -> 0 | S42: 0 | T42: 0 | U42: 0 | V42: 0 | W42: 0 | X42: 0 | Y42: 0 | Z42: 0 | AA42: 0 | AB42: 0 | AC42: 0 | AD42: 0 | AE42: 0 | AF42: 0
C43: =A14 -> 17 | D43: 0 | E43: 0 | F43: 0 | G43: 0 | H43: 0 | I43: 0 | J43: 0 | K43: 0 | L43: 0 | M43: 0 | N43: 0 | O43: 0 | P43: 0 | Q43: 0 | R43: =($W$4*(SUM(D43:Q43))) -> 0 | S43: 0 | T43: 0 | U43: 0 | V43: 0 | W43: 0 | X43: 0 | Y43: 0 | Z43: 0 | AA43: 0 | AB43: 0 | AC43: 0 | AD43: 0 | AE43: 0 | AF43: 0
C44: =A15 -> 18 | D44: 0 | E44: 0 | F44: 0 | G44: 0 | H44: 0 | I44: 0 | J44: 0 | K44: 0 | L44: 0 | M44: 0 | N44: 0 | O44: 0 | P44: 0 | Q44: 0 | R44: =($W$4*(SUM(D44:Q44))) -> 0 | S44: 0 | T44: 0 | U44: 0 | V44: 0 | W44: 0 | X44: 0 | Y44: 0 | Z44: 0 | AA44: 0 | AB44: 0 | AC44: 0 | AD44: 0 | AE44: 0 | AF44: 0
C45: =A16 -> 19 | D45: 0 | E45: 0 | F45: 0 | G45: 0 | H45: 0 | I45: 0 | J45: 0 | K45: 0 | L45: 0 | M45: 0 | N45: 0 | O45: 0 | P45: 0 | Q45: 0 | R45: =($W$4*(SUM(D45:Q45))) -> 0 | S45: 0 | T45: 0 | U45: 0 | V45: 0 | W45: 0 | X45: 0 | Y45: 0 | Z45: 0 | AA45: 0 | AB45: 0 | AC45: 0 | AD45: 0 | AE45: 0 | AF45: 0
C46: =A17 -> 20 | D46: 1 | E46: 0 | F46: 0 | G46: 0 | H46: 0 | I46: 0 | J46: 0 | K46: 0 | L46: 0 | M46: 0 | N46: 0 | O46: 0 | P46: 0 | Q46: 0 | R46: =($W$4*(SUM(D46:Q46))) -> 542 | S46: 0 | T46: 0 | U46: 0 | V46: 3 | W46: 0 | X46: 0 | Y46: 0 | Z46: 0 | AA46: 0 | AB46: 0 | AC46: 0 | AD46: 0 | AE46: 0 | AF46: 0
C47: =A18 -> 21 | D47: 0 | E47: 0 | F47: 0 | G47: 0 | H47: 0 | I47: 0 | J47: 0 | K47: 0 | L47: 0 | M47: 0 | N47: 0 | O47: 0 | P47: 0 | Q47: 0 | R47: =($W$4*(SUM(D47:Q47))) -> 0 | S47: 0 | T47: 0 | U47: 0 | V47: 0 | W47: 0 | X47: 0 | Y47: 0 | Z47: 0 | AA47: 0 | AB47: 0 | AC47: 0 | AD47: 0 | AE47: 0 | AF47: 0
C48: =A19 -> 22 | D48: 0 | E48: 0 | F48: 0 | G48: 0 | H48: 0 | I48: 0 | J48: 0 | K48: 0 | L48: 0 | M48: 0 | N48: 0 | O48: 0 | P48: 0 | Q48: 0 | R48: =($W$4*(SUM(D48:Q48))) -> 0 | S48: 0 | T48: 0 | U48: 1 | V48: 0 | W48: 0 | X48: 0 | Y48: 0 | Z48: 0 | AA48: 0 | AB48: 0 | AC48: 0 | AD48: 0 | AE48: 0 | AF48: 0
C49: =A20 -> 23 | D49: 0 | E49: 0 | F49: 0 | G49: 0 | H49: 0 | I49: 0 | J49: 0 | K49: 0 | L49: 0 | M49: 0 | N49: 0 | O49: 0 | P49: 0 | Q49: 0 | R49: =($W$4*(SUM(D49:Q49))) -> 0 | S49: 0 | T49: 0 | U49: 0 | V49: 0 | W49: 0 | X49: 0 | Y49: 0 | Z49: 0 | AA49: 0 | AB49: 0 | AC49: 0 | AD49: 0 | AE49: 0 | AF49: 0
C50: =A21 -> 24 | D50: 0 | E50: 0 | F50: 0 | G50: 0 | H50: 0 | I50: 0 | J50: 0 | K50: 0 | L50: 0 | M50: 0 | N50: 0 | O50: 0 | P50: 0 | Q50: 0 | R50: =($W$4*(SUM(D50:Q50))) -> 0 | S50: 0 | T50: 0 | U50: 0 | V50: 0 | W50: 0 | X50: 0 | Y50: 0 | Z50: 0 | AA50: 0 | AB50: 0 | AC50: 0 | AD50: 0 | AE50: 0 | AF50: 0
... C64: =A35 -> 0 | D64: 0 | E64: 0 | F64: 0 | G64: 0 | H64: 0 | I64: 0 | J64: 0 | K64: 0 | L64: 0 | M64: 0 | N64: 0 | O64: 0 | P64: 0 | Q64: 0 | R64: =($W$4*(SUM(D64:Q64))) -> 0 | S64: 0 | T64: 0 | U64: 0 | V64: 0 | W64: 0 | X64: 0 | Y64: 0 | Z64: 0 | AA64: 0 | AB64: 0 | AC64: 0 | AD64: 0 | AE64: 0 | AF64: 0
A65: Total de Recuperacion | C65: =A36 -> Total | D65: =SUM(D38:D64) -> 1 | E65: =SUM(E38:E64) -> 0 | F65: =SUM(F38:F64) -> 0 | G65: =SUM(G38:G64) -> 0 | H65: =SUM(H38:H64) -> 0 | I65: =SUM(I38:I64) -> 0 | J65: =SUM(J38:J64) -> 0 | K65: =SUM(K38:K64) -> 0 | ... Q65: =SUM(Q38:Q64) -> 0 | R65: =SUM(D65:Q65) -> 1 | S65: =SUM(S38:S64) -> 0 | T65: =SUM(T38:T64) -> 0 | U65: =SUM(U38:U64) -> 1 | V65: =SUM(V38:V64) -> 4 | W65: =SUM(W38:W64) -> 0 | X65: =SUM(X38:X64) -> 0 | Y65: =SUM(Y38:Y64) -> 0 | Z65: =SUM(Z38:Z64) -> 0 | ... AF65: =SUM(AF38:AF64) -> 0 | AG65: % de tallas negadas
A66: % de Recuperación | D66: =IF(D36>0,D65/D36,"") -> 1 | F66: =IF(F36>0,F65/F36,"") | G66: =IF(G36>0,G65/G36,"") | H66: =IF(H36>0,H65/H36,"") | I66: =IF(I36>0,I65/I36,"") | J66: =IF(J36>0,J65/J36,"") | L66: =IF(L36>0,L65/L36,"") -> 0 | M66: =IF(M36>0,M65/M36,"") | N66: =IF(N36>0,N65/N36,"") | O66: =IF(O36>0,O65/O36,"") | P66: =IF(P36>0,P65/P36,"") | Q66: =IF(Q36>0,Q65/Q36,"") | R66: =IF(R36=0,"",R65/R36) -> 0.16666667 | S66: =IF(S36>0,S65/S36,"") | T66: =IF(T36>0,T65/T36,"") | U66: =IF(U36>0,U65/U36,"") -> 1 | V66: =IF(V36>0,V65/V36,"") -> 1 | W66: =IF(W36>0,W65/W36,"") | X66: =IF(X36>0,X65/X36,"") | Y66: =IF(Y36>0,Y65/Y36,"") | Z66: =IF(Z36>0,Z65/Z36,"") | ... AF66: =IF(AF36>0,AF65/AF36,"") | AG66: =IF(OR(C36=0,C36=""),"",R36/C36) -> 0.0012101654
A67: Costo Recuperado durante la auditoria | D67: =($W$4*R65) -> 542 | AF67: =SUM(S65:AF65) -> 5
A69: # | B69: Incidencia | L69: Área responsable | S69: Punto de Rutina | AE69: Plan de acción del Supervisor del área: | AI69: Resultado de Check List Operativo | AJ69: %
A70: 1 | L70: Supervisor de Piso de Venta | AI70: =Bot!E41 -> Resurtido | AJ70: =Bot!F41 -> -
A71: 2 | AI71: =Bot!E42 -> Auxiliar de Zona DEN | AJ71: =Bot!F42 -> -
A72: 3 | AI72: =Bot!E43 -> Cambios Operativo | AJ72: =Bot!F43 -> -
A73: 4 | AI73: =Bot!E44 -> Supervisor Calzado | AJ73: =Bot!F44 -> -
A74: 5 | L74: Resurtido / Operativo / Negados | AE74: Plan de acción de Mercaderías: | AI74: =Bot!E45 -> Imagen | AJ74: =Bot!F45 -> -
A75: 6 | AI75: =Bot!E46 -> Recibo | AJ75: =Bot!F46 -> -
A76: 7 | L76: Mercaderias / Administrativos | AI76: =Bot!E47 -> Sistemas | AJ76: =Bot!F47 -> -
A77: 8 | AI77: =Bot!E48 -> Indicadores | AJ77: =Bot!F48 -> -
A78: 9 | AI78: TOTAL | AJ78: =IF(COUNT(AJ70:AJ77)>0,AVERAGE(AJ70:AJ77),"-") -> -
A79: 10 | AE79: Plan de acción del Gerente Comercial
A80: 11
AE84: Plan de acción del Gerente Comercial Operativo
AI86: Solo se bajaron tallas
A89: Firmas:
G91: (Mejoras entregó Dummy y Check List) | S91: (Mejoras entregó Dummy) | AG91: (Mejoras entregó Dummy)
B92: Mejoras | G92: Supervisor de Área | S92: Mercaderías | W92: Gerente de Nave | AB92: Gerente Comercial | AG92: Gerente Comercial Operativo | AJ92: Gerente General

Sheet CBot
C1: Carta de cierre de incidencias | K1: Código: MS-CCI/01-19
K2: Versión: 001
K3: Vigencia a partir : Mayo 2022
C4: CATALOGO AUDITADO | D4: =DBot!D4 -> BOTAS | G4: =DBot!AG4 -> 30/Junio/2026
A5: N° | B5: Área | C5: Area de Oportunidad | D5: Tiempo de Solucion en minutos | E5: Número de Incidencias | F5: Tiempo estimado de solución | G5: Responsable | H5: Hora de Aviso a Responsables | I5: Hora de Compromiso | J5: Firma | K5: Numero de Incidencias corregidas | L5: % DE AVANCE | M5: Observaciones
A6: 1 | B6: Mercaderías | C6: Cartas de Disculpa y/o Carta de Destallado Faltantes | D6: 0.013888889 | E6: =DBot!AF36-DBot!AF65 -> 0 | F6: =D6*E6 -> 0 | H6: 0.625 | I6: =IF(E6=0,"",H$6+F6) | L6: =IF(E6=0,"",K6/E6)
A7: 3 | C7: Curvas vencidas | D7: 0.0069444444 | E7: =DBot!AA36-DBot!AA65 -> 0 | F7: =D7*E7 -> 0 | I7: =IF(E7=0,"",H$6+F7) | L7: =IF(E7=0,"",K7/E7)
A8: 4 | C8: Curvas que no cuadran Price Soft vs Fisico | D8: 1.0069444 | E8: =DBot!AB36-DBot!AB65 -> 0 | F8: =D8*E8 -> 0 | I8: =IF(E8=0,"",H$6+F8) | L8: =IF(E8=0,"",K8/E8)
A9: 5 | C9: Curva con Diferencia en Frentes | D9: 1.0069444 | E9: =DBot!X36-DBot!X65 -> 0 | F9: =D9*E9 -> 0 | I9: =IF(E9=0,"",H$6+F9) | L9: =IF(E9=0,"",K9/E9)
A10: 6 | C10: Curva con Diferencia en Fondos | D10: 1.0069444 | E10: =DBot!Y36-DBot!Y65 -> 0 | F10: =D10*E10 -> 0 | I10: =IF(E10=0,"",H$6+F10) | L10: =IF(E10=0,"",K10/E10)
A11: 7 | C11: Curva con Diferencia en Altura | D11: 1.0069444 | E11: =DBot!Z36-DBot!Z65 -> 0 | F11: =D11*E11 -> 0 | I11: =IF(E11=0,"",H$6+F11) | L11: =IF(E11=0,"",K11/E11)
A12: 8 | C12: Modelos con error en ubicación en sistema | D12: 0.0069444444 | E12: =DBot!W36-DBot!W65 -> 0 | F12: =D12*E12 -> 0 | I12: =IF(E12=0,"",H$6+F12) | L12: =IF(E12=0,"",K12/E12)
A13: 9 | C13: Modelos sin Cenefa | D13: 0.0069444444 | E13: =DBot!AC36-DBot!AC65 -> 0 | F13: =D13*E13 -> 0 | I13: =IF(E13=0,"",H$6+F13) | L13: =IF(E13=0,"",K13/E13)
A14: 10 | C14: Modelos sin Cenefa de Precio Promocion | D14: 0.0069444444 | E14: =DBot!AE36-DBot!AE65 -> 0 | F14: =D14*E14 -> 0 | I14: =IF(E14=0,"",H$6+F14) | L14: =IF(E14=0,"",K14/E14)
A15: 11 | C15: Curvas faltantes | D15: 0.0069444444 | E15: =DBot!AC36-DBot!AC65 -> 0 | F15: =D15*E15 -> 0 | I15: =IF(E15=0,"",H$6+F15) | L15: =IF(E15=0,"",K15/E15)
A16: 12 | B16: Surtido/Resurtido | C16: Número de tallas negadas de bodega de rack | D16: 0.0020833333 | E16: =DBot!F36-DBot!F65 -> 0 | F16: =D16*E16 -> 0 | I16: =IF(E16=0,"",H$6+F16) | L16: =IF(E16=0,"",K16/E16)
A17: 13 | C17: Número de tallas negadas de Excedente | D17: 0.013888889 | E17: =DBot!I36-DBot!I65 -> 0 | F17: =D17*E17 -> 0 | I17: =IF(E17=0,"",H$6+F17) | L17: =IF(E17=0,"",K17/E17)
A18: 14 | C18: Número de tallas negadas de origen | D18: 0.013888889 | E18: =DBot!J36-DBot!J65 -> 0 | F18: =D18*E18 -> 0 | I18: =IF(E18=0,"",H$6+F18) | L18: =IF(E18=0,"",K18/E18)
A19: 15 | C19: Numero de tallas negadas de bodega recepción | D19: 0.013888889 | E19: =DBot!N36-DBot!N65 -> 0 | F19: =D19*E19 -> 0 | I19: =IF(E19=0,"",H$6+F19) | L19: =IF(E19=0,"",K19/E19)
A20: 16 | C20: Número de tallas negadas por estibas y 7mos | D20: 0.013888889 | E20: =DBot!L36-DBot!L65 -> 5 | F20: =D20*E20 -> 0.069444444 | I20: =IF(E20=0,"",H$6+F20) -> 0.69444444 | L20: =IF(E20=0,"",K20/E20) -> 0
A21: 17 | C21: Número de tallas negadas por cambios | D21: 0.013888889 | E21: =DBot!K36-DBot!K65 -> 0 | F21: =D21*E21 -> 0
A22: 18 | B22: Auxiliar Doble Ubicación | C22: Número de Negados de Doble Ubicación | D22: 0.0034722222 | E22: =DBot!H36-DBot!H65 -> 0 | F22: =D22*E22 -> 0 | I22: =IF(E22=0,"",H$6+F22) | L22: =IF(E22=0,"",K22/E22)
A23: 19 | B23: Bodega Calzado | C23: Número de talla Negadas de Bodega (consulta del reporte comparativo entre dos bodegas) | D23: 0.0069444444 | E23: =DBot!G36-DBot!G65 -> 0 | F23: =D23*E23 -> 0 | I23: =IF(E23=0,"",H$6+F23) | L23: =IF(E23=0,"",K23/E23)
A24: 20 | B24: Supervisor Calzado | C24: Número de exhibiciones faltantes de Calzado en pasillo | D24: 0.013888889 | E24: =DBot!S36-DBot!S65 -> 0 | F24: =D24*E24 -> 0 | I24: =IF(E24=0,"",H$6+F24) | L24: =IF(E24=0,"",K24/E24)
A25: 21 | C25: Número de tallas negadas por Frenteo | D25: 0.0013888889 | E25: =DBot!D36-DBot!D65 -> 0 | F25: =D25*E25 -> 0 | I25: =IF(E25=0,"",H$6+F25) | L25: =IF(E25=0,"",K25/E25)
A26: 22 | C26: Número de tallas negadas por Revuelto | D26: 0.0013888889 | E26: =DBot!E36-DBot!E65 -> 0 | F26: =D26*E26 -> 0
E27: =SUM(E6:E24) -> 5 | L27: =IF(E27=0,"",AVERAGE(L6:L25)) -> 0
B30: GERENCIA | D30: RESPONSABLE | F30: DESVIACIONES | G30: FIRMA | I30: Realizo Supervisor de Mejoras
B31: GERENCIA COMERCIAL DE PRODUCTO
B32: GERENCIA COMERCIAL OPERATIVA

Sheet Urb
D1: Formato para el registro del Check list del Supervisor | I1: Código: MS-CLS/01-18
I2: Versión: 001
I3: Vigencia a partir : Mayo 2022
B4: Tienda | D4: Ecatepec
B5: Fecha de auditoria: | D5: 30/Junio/2026 | E5: Gerente Comercial | F5: Luis Alberto Pérez
B6: Catálogo: | D6: URBANO | E6: Gerente Com. Operativo | F6: Alejandro Balleza Gómez | M6: SI
B7: Supervisor de Catalogo | D7: Rosario García V. | E7: Gerente de Servicios | M7: NO
B8: # de Nomina | D8: 43660 | E8: Gerente de Operaciones | F8: Alejandro Balleza Gómez | M8: NA
B11: Responsable | C11: Definición de Servicio | D11: Indicador | E11: Criterio de Evaluación | F11: Número | G11: Alcance | H11: Valor | I11: Logro x actividad | J11: Logro x departamento | K11: Que dato se captura? | L11: Como obtengo este dato o cual es el entregable?
B12: Informativo | D12: Total de Tallas del Catálogo | F12: =DUrb!C41 -> 69
B13: Informativo | D13: Total de Tallas auditadas | F13: =DUrb!D41 -> 0 | G13: =IF(F12=0,"",F13/F12) -> 0
B14: Informativo | D14: Número de pasillos
B15: Informativo | D15: Sugerido del catálogo a 7 días
B16: Resurtido | C16: Producto | D16: Pasillos y piso de venta libre de mercancia por suvir a bodega. ( bodegas en el piso sin quien las trabaje ) | E16: Si cumple "Si" , si no cumple coloca "No" | F16: Na | G16: =IF(F16="NA","",IF(F16="SI",1,0)) | H16: 100 | I16: =IF(G16="","",IF(G16=0,0,IF(G16>0,(H16*G16)))) | J16: =IF(SUM(M16)=0,"-",SUM(I16)/SUM(M16)) -> - | K16: Cumple=100%, No cumple=0% | L16: Recorrido – Auditoría de Check List | M16: =IF(F16="NA","No aplica",H16) -> No aplica
B17: Auxiliar de Zona DEN | C17: Comercial | D17: Zona DEN en orden y con calzado del día (validar la entrega diaria de Lunes a Sábado) | E17: Si se realiza la entrega diaria = "Si", sino = "No" | F17: Na | G17: =IF(F17="NA","",IF(F17="SI",1,0)) | H17: 100 | I17: =IF(G17="","",IF(G17=0,0,IF(G17>0,(H17*G17)))) | J17: =IF(SUM(M17)=0,"-",SUM(I17)/SUM(M17)) -> - | K17: Cumple=100%, No cumple=0% | L17: Zona Den muestra reporte de entrega de mercancía ya sea de Nones o defectos | M17: =IF(F17="NA","No aplica",H17) -> No aplica
B18: Cambios Operativo | C18: Producto | D18: Pasillos y piso de venta libre de cambios. (cambios en el piso sin quien lo ubique = 0) | E18: Si hay cambios en el piso, Valida nombre de la persona destinada para subirlos, si esta la persona coloca "Si" , si no cumple coloca "No" | F18: Na | G18: =IF(F18="NA","",IF(F18="SI",1,0)) | H18: 50 | I18: =IF(G18="","",IF(G18=0,0,IF(G18>0,(H18*G18)))) | J18: =IF(SUM(M18:M19)=0,"-",SUM(I18:I19)/SUM(M18:M19)) -> - | K18: Cumple=100%, No cumple=0% | L18: Recorrido – Auditoría de Check List | M18: =IF(F18="NA","No aplica",H18) -> No aplica
D19: Personal de cambios ubicando el calzado en el modelo correcto | E19: Si hay personal ubicando cambios valida alguno, si los coloca en el modelo correcto, Si cumple "Si" , si no cumple coloca "No" | F19: Na | G19: =IF(F19="NA","",IF(F19="SI",1,0)) | H19: 50 | I19: =IF(G19="","",IF(G19=0,0,IF(G19>0,(H19*G19)))) | K19: Cumple=100%, No cumple=0% | L19: Recorrido – Auditoría de Check List | M19: =IF(F19="NA","No aplica",H19) -> No aplica
B20: Supervisor Calzado | C20: Comercial | D20: Se tiene evidencia de recorrido diario de revisión de exhibiciones | E20: Debe estar documentado el recorrido, si cumple coloca "Si" sino coloca cero "No" | F20: Na | G20: =IF(F20="NA","",IF(F20="SI",1,0)) | H20: 10 | I20: =IF(G20="","",IF(G20=0,0,IF(G20>0,(H20*G20)))) | J20: =IF(SUM(M20:M30)=0,"-",SUM(I20:I30)/SUM(M20:M30)) -> - | K20: Cumple=100%, No cumple=0% | L20: Supervisor de Piso muestra evidencia de recorrido | M20: =IF(F20="NA","No aplica",H20) -> No aplica
D21: # de frenteos encontrados en auditoria | E21: Por cada negado detectado como frenteo detectado en auditoria -5% | F21: Na | G21: =IF(F21="NA","",IF(F21<20,1-(F21*5/100),IF(F21>10,0))) | H21: 12 | I21: =IF(G21="","",IF(G21=0,0,IF(G21>0,(H21*G21)))) | K21: Total de Modelos revueltos | L21: Recorrido – Auditoría de Check List | M21: =IF(F21="NA","No aplica",H21) -> No aplica
D23: # de Pasillos con mercancía desalineada | E23: # pasillos NO alineados / Total de pasillos | F23: Na | G23: =IF(F23="NA","",1-(F23/F14)) | H23: 10 | I23: =IF(G23="","",IF(G23=0,0,IF(G23>0,(H23*G23)))) | K23: Cumple=100%, No cumple=0% | L23: Recorrido – Auditoría de Check List | M23: =IF(F23="NA","No aplica",H23) -> No aplica
D24: Muestra evidencia de la validación de curvas al día (Si se realiza Check List antes de las 12am puede mostrar evidencia del día anterior) | E24: Si cumple "Si" , si no cumple coloca "No" | F24: Na | G24: =IF(F24="NA","",IF(F24="SI",1,0)) | H24: 21 | I24: =IF(G24="","",IF(G24=0,0,IF(G24>0,(H24*G24)))) | K24: Cumple=SI, No cumple=NO | L24: Reporte de Certificacion de curvas | M24: =IF(F24="NA","No aplica",H24) -> No aplica
D26: El colaborador conoce o da opciones de modelos similares de los modelos Agotados en su totalidad | E26: Si cumple "Si" , si no cumple coloca "No" ( Se valida a 2 colaboradores ) | F26: Na | G26: =IF(F26="NA","",IF(F26="SI",1,0)) | H26: 11 | I26: =IF(G26="","",IF(G26=0,0,IF(G26>0,(H26*G26)))) | K26: Cumple=SI, No cumple=NO | L26: Recorrido – Auditoría de Check List | M26: =IF(F26="NA","No aplica",H26) -> No aplica
D27: Colaboradores conocen sus funciones que vienen en su Rutina. | E27: Si cumple "Si" , si no cumple coloca "No" | F27: Na | G27: =IF(F27="NA","",IF(F27="Si",1,0)) | H27: 11 | I27: =IF(G27="","",IF(G27=0,0,IF(G27>0,(H27*G27)))) | K27: Cumple=SI, No cumple=NO | L27: Recorrido – Auditoría de Check List | M27: =IF(F27="NA","No aplica",H27) -> No aplica
D28: Colaboradores conocen sus resultados de su ultima auditoria. | E28: Si cumple "Si" , si no cumple coloca "No" | F28: Na | G28: =IF(F28="NA","",IF(F28="Si",1,0)) | H28: 9 | I28: =IF(G28="","",IF(G28=0,0,IF(G28>0,(H28*G28)))) | K28: Cumple=SI, No cumple=NO | L28: Recorrido – Auditoría de Check List | M28: =IF(F28="NA","No aplica",H28) -> No aplica
D29: El supervisor cuenta con evidencia de que ya entrego su rutina a sus colaboradores | E29: Si cumple "Si" , si no cumple coloca "No" | F29: Na | G29: =IF(F29="NA","",IF(F29="Si",1,0)) | H29: 8 | I29: =IF(G29="","",IF(G29=0,0,IF(G29>0,(H29*G29)))) | K29: Cumple=SI, No cumple=NO | L29: Evidencia de listado de entrega de rutinas | M29: =IF(F29="NA","No aplica",H29) -> No aplica
C30: Producto | D30: Se cuenta con listado de Cajas Maltratadas que entrega a Zona DEN, para ser solicitadas al área de Compras | E30: Si cumple "Si" , si no cumple coloca "No" | F30: Na | G30: =IF(F30="NA","",IF(F30="SI",1,0)) | H30: 8 | I30: =IF(G30="","",IF(G30=0,0,IF(G30>0,(H30*G30)))) | K30: Cumple=SI, No cumple=NO | L30: Listado actualizado de cajas | M30: =IF(F30="NA","No aplica",H30) -> No aplica
B31: Visual Merchandising | C31: Auto conducción | D31: Publicidad en buen estado y vigente | E31: Si cumple "Si" , si no cumple coloca "No" | F31: Na | G31: =IF(F31="NA","",IF(F31="SI",1,0)) | H31: 30 | I31: =IF(G31="","",IF(G31=0,0,IF(G31>0,(H31*G31)))) | J31: =IF(SUM(M31:M33)=0,"-",SUM(I31:I33)/SUM(M31:M33)) -> - | K31: Cumple=SI, No cumple=NO | L31: Recorrido – Auditoría de Check List | M31: =IF(F31="NA","No aplica",H31) -> No aplica
D32: La numeración del pasillo en buenas condiciones | E32: Si cumple "Si" , si no cumple coloca "No" | F32: Na | G32: =IF(F32="NA","",IF(F32="SI",1,0)) | H32: 30 | I32: =IF(G32="","",IF(G32=0,0,IF(G32>0,(H32*G32)))) | K32: Cumple=SI, No cumple=NO | L32: Recorrido – Auditoría de Check List | M32: =IF(F32="NA","No aplica",H32) -> No aplica
D33: Los pendones visibles al socio , en buenas condiciones, alineados y limpios | E33: Si cumple "Si" , si no cumple coloca "No" | F33: Na | G33: =IF(F33="NA","",IF(F33="SI",1,0)) | H33: 40 | I33: =IF(G33="","",IF(G33=0,0,IF(G33>0,(H33*G33)))) | K33: Cumple=SI, No cumple=NO | L33: Recorrido – Auditoría de Check List | M33: =IF(F33="NA","No aplica",H33) -> No aplica
B34: Recibo | C34: Comercial | D34: Se recibió el reporte Hot list (Origen) | E34: Si cumple "Si" , si no cumple coloca "No" | F34: Na | G34: =IF(F34="NA","",IF(F34="SI",1,0)) | H34: 100 | I34: =IF(G34="","",IF(G34=0,0,IF(G34>0,(H34*G34)))) | J34: =IF(SUM(M34)=0,"-",SUM(I34)/SUM(M34)) -> - | K34: Cumple=SI, No cumple=NO | L34: Reporte de Origen actualizado | M34: =IF(F34="NA","No aplica",H34) -> No aplica
B35: Sistemas | C35: Auto conducción | D35: Revisión de kioscos encendidos y limpios funcion | E35: Si cumple "Si" , si no cumple coloca "No" | F35: Na | G35: =IF(F35="NA","",IF(F35="SI",1,0)) | H35: 100 | I35: =IF(G35="","",IF(G35=0,0,IF(G35>0,(H35*G35)))) | J35: =IF(SUM(M35)=0,"-",SUM(I35)/SUM(M35)) -> - | K35: Recorrido – Auditoría de Check List | L35: Recorrido – Auditoría de Check List | M35: =IF(F35="NA","No aplica",H35) -> No aplica
B36: Indicadores | C36: Comercial | D36: % del check list de cabeceras de catalogo | E36: % de calificación que se obtuvo el la revision de las cabeceras en base a las fichas de instruccion | F36: Na | G36: =IF(F36="Na","",F36) | H36: 50 | I36: =IF(G36="","",IF(G36=0,0,IF(G36>0,(H36*G36)))) | J36: =IF(SUM(M36:M38)=0,"-",SUM(I36:I38)/SUM(M36:M38)) -> - | K36: Recorrido – Auditoría de Check List | L36: Recorrido – Auditoría de Check List | M36: =IF(F36="NA","No aplica",H36) -> No aplica
D37: % de check list de supervisor de calzado | E37: % de calificación de check list de supervisor, (Semana Anterior o ultima auditoria) | F37: Na | G37: =IF(F37="Na","",F37) | H37: 50 | I37: =IF(G37="","",IF(G37=0,0,IF(G37>0,(H37*G37)))) | K37: Recorrido – Auditoría de Check List | L37: Recorrido – Auditoría de Check List | M37: =IF(F37="NA","No aplica",H37) -> No aplica
K38: Cumple=SI, No cumple=NO | L38: Recorrido – Auditoría de Check List | M38: =IF(F38="NA","No aplica",H38) -> 0
E40: =D6 -> URBANO
E41: Resurtido | F41: =J16 -> -
E42: Auxiliar de Zona DEN | F42: =J17 -> -
E43: Cambios Operativo | F43: =J18 -> -
E44: Supervisor Calzado | F44: =J20 -> -
E45: Imagen | F45: =J31 -> -
E46: Recibo | F46: =J34 -> -
E47: Sistemas | F47: =J35 -> -
E48: Indicadores | F48: =J36 -> -
E49: TOTAL: | F49: =IF(COUNT(F41:F48)>0,AVERAGE(F41:F48),"-") -> -

Sheet DUrb
D1: Dictamen de Auditoría a pasillos calzado | AH1: Código: MS-APC/01-17
AH2: Versión: 001
AH3: Vigencia a partir : Mayo 2022
C4: Catalogo: | D4: =Urb!D6 -> URBANO | R4: Precio promedio por pieza: | W4: 513 | AE4: Fecha de auditoria: | AG4: =Urb!D5 -> 30/Junio/2026
C5: Supervisor de Catalogo: | D5: =Urb!D7 -> Rosario García V. | R5: Sugerido de Catalogo | W5: =Urb!F15 -> 0
R6: Tallas del catalogo (linea y linea x inventario) | W6: =B30 -> 8864
D7: Causas de Negado | S7: Incidencias de Auditoria
A8: Pasillo | B8: TOTAL DE TALLAS POR PASILLO | C8: TALLAS AUDITADAS | D8: Frenteos | E8: Revueltos | F8: Bodega Venta | G8: Bodega Tapanco | H8: Doble Ubicación | I8: Excedente | J8: Origen | K8: Cambios / Probadores | L8: Negados sin Recuperar | M8: Exhibiciones | N8: Bodega Aclaración | O8: Aduanas | P8: Golden o apartados | Q8: Control de calidad | R8: Costo por pasillo | S8: Sin Exhibición | T8: Exhibición fuera de Política | U8: Modelos revuelto | V8: Modelos mal entallados | W8: Modelos con error de ubicación | X8: Curva con diferencia en frentes | Y8: Curva con diferencia en fondos | Z8: Curva con diferencia en altura | AA8: Curvas vencidas | AB8: Curvas que no coincide Price Soft vs Piso de Venta | AC8: Curvas faltantes | AD8: Cenefas faltantes | AE8: Cenefas de precio Promoción faltantes | AF8: Cartas disculpa / destallados faltantes | AG8: Nómina | AH8: Asesor de venta responsable del pasillo
A9: 60 | B9: 726 | C9: 726 | D9: 0 | E9: 0 | F9: 0 | G9: 0 | H9: 0 | I9: 0 | J9: 0 | K9: 0 | L9: 0 | M9: 0 | N9: 0 | O9: 0 | P9: 0 | Q9: 0 | R9: =($W$4*(SUM(D9:Q9))) -> 0 | S9: =IFERROR(SUMIF('Exhibiciones '!$E$5:$E$550,A9,'Exhibiciones '!$AF$5:$AF$550),"") -> 0 | T9: 0 | U9: 1 | V9: 0 | W9: 0 | X9: 0 | Y9: 0 | Z9: 0 | AA9: 0 | AB9: 0 | AC9: 0 | AD9: 0 | AE9: 0 | AF9: 0 | AG9: 137339 | AH9: =IFERROR(VLOOKUP(AG9,'Plantilla y Concentrado'!$B$4:$C$677,2,0),"") -> Nicolas De German Nadia Ivonne
A10: 61 | B10: 809 | C10: 809 | D10: 0 | E10: 0 | F10: 0 | G10: 0 | H10: 0 | I10: 0 | J10: 0 | K10: 0 | L10: 0 | M10: 0 | N10: 0 | O10: 0 | P10: 0 | Q10: 0 | R10: =($W$4*(SUM(D10:Q10))) -> 0 | S10: =IFERROR(SUMIF('Exhibiciones '!$E$5:$E$550,A10,'Exhibiciones '!$AF$5:$AF$550),"") -> 0 | T10: 0 | U10: 0 | V10: 1 | W10: 0 | X10: 0 | Y10: 0 | Z10: 0 | AA10: 0 | AB10: 0 | AC10: 0 | AD10: 0 | AE10: 0 | AF10: 0 | AG10: 145279 | AH10: =IFERROR(VLOOKUP(AG10,'Plantilla y Concentrado'!$B$4:$C$677,2,0),"") -> Ferrusca Solis Karla Marcela
A11: 62 | B11: 1006 | C11: 1006 | D11: 1 | E11: 0 | F11: 0 | G11: 0 | H11: 0 | I11: 0 | J11: 0 | K11: 0 | L11: 1 | M11: 0 | N11: 0 | O11: 0 | P11: 0 | Q11: 0 | R11: =($W$4*(SUM(D11:Q11))) -> 1026 | S11: =IFERROR(SUMIF('Exhibiciones '!$E$5:$E$550,A11,'Exhibiciones '!$AF$5:$AF$550),"") -> 0 | T11: 0 | U11: 1 | V11: 0 | W11: 0 | X11: 0 | Y11: 0 | Z11: 0 | AA11: 0 | AB11: 0 | AC11: 0 | AD11: 0 | AE11: 0 | AF11: 0 | AG11: 159880 | AH11: =IFERROR(VLOOKUP(AG11,'Plantilla y Concentrado'!$B$4:$C$677,2,0),"")
A12: 63 | B12: 391 | C12: 391 | D12: 0 | E12: 0 | F12: 0 | G12: 0 | H12: 0 | I12: 0 | J12: 0 | K12: 0 | L12: 0 | M12: 0 | N12: 0 | O12: 0 | P12: 0 | Q12: 0 | R12: =($W$4*(SUM(D12:Q12))) -> 0 | S12: =IFERROR(SUMIF('Exhibiciones '!$E$5:$E$550,A12,'Exhibiciones '!$AF$5:$AF$550),"") -> 0 | T12: 0 | U12: 0 | V12: 0 | W12: 0 | X12: 0 | Y12: 0 | Z12: 0 | AA12: 0 | AB12: 0 | AC12: 0 | AD12: 0 | AE12: 0 | AF12: 0 | AG12: 155312 | AH12: =IFERROR(VLOOKUP(AG12,'Plantilla y Concentrado'!$B$4:$C$677,2,0),"") -> Rosas Paniagua Elizabeth
A13: 64 | B13: 898 | C13: 898 | D13: 1 | E13: 0 | F13: 0 | G13: 0 | H13: 0 | I13: 0 | J13: 0 | K13: 0 | L13: 0 | M13: 0 | N13: 0 | O13: 0 | P13: 0 | Q13: 0 | R13: =($W$4*(SUM(D13:Q13))) -> 513 | S13: =IFERROR(SUMIF('Exhibiciones '!$E$5:$E$550,A13,'Exhibiciones '!$AF$5:$AF$550),"") -> 0 | T13: =IFERROR(SUMIF('Exhibiciones '!$E$5:$E$550,A13,'Exhibiciones '!$AG$5:$AG$550),"-") -> 0 | U13: 0 | V13: 0 | W13: 0 | X13: 0 | Y13: 0 | Z13: 0 | AA13: 0 | AB13: 0 | AC13: 0 | AD13: 0 | AE13: 0 | AF13: 0 | AG13: 160212 | AH13: =IFERROR(VLOOKUP(AG13,'Plantilla y Concentrado'!$B$4:$C$677,2,0),"")
A14: 65 | B14: 345 | C14: 338 | D14: 0 | E14: 0 | F14: 0 | G14: 0 | H14: 0 | I14: 0 | J14: 0 | K14: 0 | L14: 0 | M14: 0 | N14: 0 | O14: 0 | P14: 0 | Q14: 0 | R14: =($W$4*(SUM(D14:Q14))) -> 0 | S14: =IFERROR(SUMIF('Exhibiciones '!$E$5:$E$550,A14,'Exhibiciones '!$AF$5:$AF$550),"") -> 0 | T14: =IFERROR(SUMIF('Exhibiciones '!$E$5:$E$550,A14,'Exhibiciones '!$AG$5:$AG$550),"-") -> 0 | U14: 0 | V14: 0 | W14: 0 | X14: 0 | Y14: 0 | Z14: 0 | AA14: 0 | AB14: 0 | AC14: 0 | AD14: 0 | AE14: 0 | AF14: 0 | AG14: 150549 | AH14: =IFERROR(VLOOKUP(AG14,'Plantilla y Concentrado'!$B$4:$C$677,2,0),"") -> Vargas Villegas Mariana
A15: 66 | B15: 502 | C15: 502 | D15: 0 | E15: 0 | F15: 0 | G15: 0 | H15: 0 | I15: 0 | J15: 0 | K15: 0 | L15: 0 | M15: 0 | N15: 0 | O15: 0 | P15: 0 | Q15: 0 | R15: =($W$4*(SUM(D15:Q15))) -> 0 | S15: =IFERROR(SUMIF('Exhibiciones '!$E$5:$E$550,A15,'Exhibiciones '!$AF$5:$AF$550),"") -> 0 | T15: 0 | U15: 0 | V15: 0 | W15: 0 | X15: 0 | Y15: 0 | Z15: 0 | AA15: 0 | AB15: 0 | AC15: 0 | AD15: 0 | AE15: 0 | AF15: 0 | AG15: 139272 | AH15: =IFERROR(VLOOKUP(AG15,'Plantilla y Concentrado'!$B$4:$C$677,2,0),"") -> Guzman Navarrete Arlen Esmeralda
A16: 67 | B16: 659 | C16: 642 | D16: 0 | E16: 0 | F16: 0 | G16: 0 | H16: 0 | I16: 0 | J16: 0 | K16: 0 | L16: 0 | M16: 0 | N16: 0 | O16: 0 | P16: 0 | Q16: 0 | R16: =($W$4*(SUM(D16:Q16))) -> 0 | S16: =IFERROR(SUMIF('Exhibiciones '!$E$5:$E$550,A16,'Exhibiciones '!$AF$5:$AF$550),"") -> 0 | T16: =IFERROR(SUMIF('Exhibiciones '!$E$5:$E$550,A16,'Exhibiciones '!$AG$5:$AG$550),"-") -> 0 | U16: 0 | V16: 0 | W16: 0 | X16: 0 | Y16: 0 | Z16: 0 | AA16: 0 | AB16: 0 | AC16: 0 | AD16: 0 | AE16: 0 | AF16: 0 | AG16: 138679 | AH16: =IFERROR(VLOOKUP(AG16,'Plantilla y Concentrado'!$B$4:$C$677,2,0),"") -> Lopez Sebastian Karen Jazmin
A17: 68 | B17: 793 | C17: 793 | D17: 0 | E17: 0 | F17: 1 | G17: 0 | H17: 0 | I17: 0 | J17: 0 | K17: 0 | L17: 0 | M17: 0 | N17: 0 | O17: 0 | P17: 0 | Q17: 0 | R17: =($W$4*(SUM(D17:Q17))) -> 513 | S17: 0 | T17: =IFERROR(SUMIF('Exhibiciones '!$E$5:$E$550,A17,'Exhibiciones '!$AG$5:$AG$550),"-") -> 0 | U17: 0 | V17: 0 | W17: 0 | X17: 0 | Y17: 0 | Z17: 0 | AA17: 0 | AB17: 0 | AC17: 0 | AD17: 0 | AE17: 0 | AF17: 0 | AG17: 137339 | AH17: =IFERROR(VLOOKUP(AG17,'Plantilla y Concentrado'!$B$4:$C$677,2,0),"") -> Nicolas De German Nadia Ivonne
A18: 69 | B18: 925 | C18: 925 | D18: 0 | E18: 0 | F18: 0 | G18: 0 | H18: 0 | I18: 0 | J18: 0 | K18: 0 | L18: 0 | M18: 0 | N18: 0 | O18: 0 | P18: 0 | Q18: 0 | R18: =($W$4*(SUM(D18:Q18))) -> 0 | S18: 0 | T18: =IFERROR(SUMIF('Exhibiciones '!$E$5:$E$550,A18,'Exhibiciones '!$AG$5:$AG$550),"-") -> 0 | U18: 0 | V18: 0 | W18: 0 | X18: 0 | Y18: 0 | Z18: 0 | AA18: 0 | AB18: 0 | AC18: 0 | AD18: 0 | AE18: 0 | AF18: 0 | AG18: 150549 | AH18: =IFERROR(VLOOKUP(AG18,'Plantilla y Concentrado'!$B$4:$C$677,2,0),"") -> Vargas Villegas Mariana
A19: 70 | B19: 643 | C19: 643 | D19: 0 | E19: 0 | F19: 0 | G19: 0 | H19: 0 | I19: 0 | J19: 0 | K19: 0 | L19: 0 | M19: 0 | N19: 0 | O19: 0 | P19: 0 | Q19: 0 | R19: =($W$4*(SUM(D19:Q19))) -> 0 | S19: =IFERROR(SUMIF('Exhibiciones '!$E$5:$E$550,A19,'Exhibiciones '!$AF$5:$AF$550),"") -> 0 | T19: =IFERROR(SUMIF('Exhibiciones '!$E$5:$E$550,A19,'Exhibiciones '!$AG$5:$AG$550),"-") -> 0 | U19: 1 | V19: 3 | W19: 0 | X19: 0 | Y19: 0 | Z19: 0 | AA19: 0 | AB19: 0 | AC19: 0 | AD19: 0 | AE19: 0 | AF19: 0 | AG19: 159880 | AH19: =IFERROR(VLOOKUP(AG19,'Plantilla y Concentrado'!$B$4:$C$677,2,0),"")
A20: 71 | B20: 800 | C20: 772 | D20: 0 | E20: 0 | F20: 0 | G20: 0 | H20: 0 | I20: 0 | J20: 0 | K20: 0 | L20: 1 | M20: 0 | N20: 0 | O20: 0 | P20: 0 | Q20: 0 | R20: =($W$4*(SUM(D20:Q20))) -> 513 | S20: =IFERROR(SUMIF('Exhibiciones '!$E$5:$E$550,A20,'Exhibiciones '!$AF$5:$AF$550),"") -> 0 | T20: =IFERROR(SUMIF('Exhibiciones '!$E$5:$E$550,A20,'Exhibiciones '!$AG$5:$AG$550),"-") -> 0 | U20: 1 | V20: 5 | W20: 0 | X20: 0 | Y20: 0 | Z20: 0 | AA20: 0 | AB20: 0 | AC20: 0 | AD20: 0 | AE20: 0 | AF20: 0 | AG20: 155312 | AH20: =IFERROR(VLOOKUP(AG20,'Plantilla y Concentrado'!$B$4:$C$677,2,0),"") -> Rosas Paniagua Elizabeth
A21: 72 | B21: 367 | C21: 367 | D21: 0 | E21: 0 | F21: 0 | G21: 0 | H21: 0 | I21: 0 | J21: 0 | K21: 0 | L21: 0 | M21: 0 | N21: 0 | O21: 0 | P21: 0 | Q21: 0 | R21: =($W$4*(SUM(D21:Q21))) -> 0 | S21: 0 | T21: =IFERROR(SUMIF('Exhibiciones '!$E$5:$E$550,A21,'Exhibiciones '!$AG$5:$AG$550),"-") -> 0 | U21: 0 | V21: 0 | W21: 0 | X21: 0 | Y21: 0 | Z21: 0 | AA21: 0 | AB21: 0 | AC21: 0 | AD21: 0 | AE21: 0 | AF21: 0 | AG21: 138679 | AH21: =IFERROR(VLOOKUP(AG21,'Plantilla y Concentrado'!$B$4:$C$677,2,0),"") -> Lopez Sebastian Karen Jazmin
D22: 0 | E22: 0 | F22: 0 | G22: 0 | H22: 0 | I22: 0 | J22: 0 | K22: 0 | L22: 0 | M22: 0 | N22: 0 | O22: 0 | P22: 0 | Q22: 0 | R22: =($W$4*(SUM(D22:Q22))) -> 0 | S22: =IFERROR(SUMIF('Exhibiciones '!$E$5:$E$550,A22,'Exhibiciones '!$AF$5:$AF$550),"") -> 0 | T22: =IFERROR(SUMIF('Exhibiciones '!$E$5:$E$550,A22,'Exhibiciones '!$AG$5:$AG$550),"-") -> 0 | U22: 0 | V22: 0 | W22: 0 | X22: 0 | Y22: 0 | Z22: 0 | AA22: 0 | AB22: 0 | AC22: 0 | AD22: 0 | AE22: 0 | AF22: 0 | AH22: =IFERROR(VLOOKUP(AG22,'Plantilla y Concentrado'!$B$4:$C$677,2,0),"")
D23: 0 | E23: 0 | F23: 0 | G23: 0 | H23: 0 | I23: 0 | J23: 0 | K23: 0 | L23: 0 | M23: 0 | N23: 0 | O23: 0 | P23: 0 | Q23: 0 | R23: =($W$4*(SUM(D23:Q23))) -> 0 | S23: =IFERROR(SUMIF('Exhibiciones '!$E$5:$E$550,A23,'Exhibiciones '!$AF$5:$AF$550),"") -> 0 | T23: =IFERROR(SUMIF('Exhibiciones '!$E$5:$E$550,A23,'Exhibiciones '!$AG$5:$AG$550),"-") -> 0 | U23: 0 | V23: 0 | W23: 0 | X23: 0 | Y23: 0 | Z23: 0 | AA23: 0 | AB23: 0 | AC23: 0 | AD23: 0 | AE23: 0 | AF23: 0 | AH23: =IFERROR(VLOOKUP(AG23,'Plantilla y Concentrado'!$B$4:$C$677,2,0),"")
D24: 0 | E24: 0 | F24: 0 | G24: 0 | H24: 0 | I24: 0 | J24: 0 | K24: 0 | L24: 0 | M24: 0 | N24: 0 | O24: 0 | P24: 0 | Q24: 0 | R24: =($W$4*(SUM(D24:Q24))) -> 0 | S24: =IFERROR(SUMIF('Exhibiciones '!$E$5:$E$550,A24,'Exhibiciones '!$AF$5:$AF$550),"") -> 0 | T24: =IFERROR(SUMIF('Exhibiciones '!$E$5:$E$550,A24,'Exhibiciones '!$AG$5:$AG$550),"-") -> 0 | U24: 0 | V24: 0 | W24: 0 | X24: 0 | Y24: 0 | Z24: 0 | AA24: 0 | AB24: 0 | AC24: 0 | AD24: 0 | AE24: 0 | AF24: 0 | AH24: =IFERROR(VLOOKUP(AG24,'Plantilla y Concentrado'!$B$4:$C$677,2,0),"")
D25: 0 | E25: 0 | F25: 0 | G25: 0 | H25: 0 | I25: 0 | J25: 0 | K25: 0 | L25: 0 | M25: 0 | N25: 0 | O25: 0 | P25: 0 | Q25: 0 | R25: =($W$4*(SUM(D25:Q25))) -> 0 | S25: =IFERROR(SUMIF('Exhibiciones '!$E$5:$E$550,A25,'Exhibiciones '!$AF$5:$AF$550),"") -> 0 | T25: =IFERROR(SUMIF('Exhibiciones '!$E$5:$E$550,A25,'Exhibiciones '!$AG$5:$AG$550),"-") -> 0 | U25: 0 | V25: 0 | W25: 0 | X25: 0 | Y25: 0 | Z25: 0 | AA25: 0 | AB25: 0 | AC25: 0 | AD25: 0 | AE25: 0 | AF25: 0 | AH25: =IFERROR(VLOOKUP(AG25,'Plantilla y Concentrado'!$B$4:$C$677,2,0),"")
D26: 0 | E26: 0 | F26: 0 | G26: 0 | H26: 0 | I26: 0 | J26: 0 | K26: 0 | L26: 0 | M26: 0 | N26: 0 | O26: 0 | P26: 0 | Q26: 0 | R26: =($W$4*(SUM(D26:Q26))) -> 0 | S26: =IFERROR(SUMIF('Exhibiciones '!$E$5:$E$550,A26,'Exhibiciones '!$AF$5:$AF$550),"") -> 0 | T26: =IFERROR(SUMIF('Exhibiciones '!$E$5:$E$550,A26,'Exhibiciones '!$AG$5:$AG$550),"-") -> 0 | U26: 0 | V26: 0 | W26: 0 | X26: 0 | Y26: 0 | Z26: 0 | AA26: 0 | AB26: 0 | AC26: 0 | AD26: 0 | AE26: 0 | AF26: 0 | AH26: =IFERROR(VLOOKUP(AG26,'Plantilla y Concentrado'!$B$4:$C$677,2,0),"")
D27: 0 | E27: 0 | F27: 0 | G27: 0 | H27: 0 | I27: 0 | J27: 0 | K27: 0 | L27: 0 | M27: 0 | N27: 0 | O27: 0 | P27: 0 | Q27: 0 | R27: =($W$4*(SUM(D27:Q27))) -> 0 | S27: =IFERROR(SUMIF('Exhibiciones '!$E$5:$E$550,A27,'Exhibiciones '!$AF$5:$AF$550),"") -> 0 | T27: =IFERROR(SUMIF('Exhibiciones '!$E$5:$E$550,A27,'Exhibiciones '!$AG$5:$AG$550),"-") -> 0 | U27: 0 | V27: 0 | W27: 0 | X27: 0 | Y27: 0 | Z27: 0 | AA27: 0 | AB27: 0 | AC27: 0 | AD27: 0 | AE27: 0 | AF27: 0 | AH27: =IFERROR(VLOOKUP(AG27,'Plantilla y Concentrado'!$B$4:$C$677,2,0),"")
D28: 0 | E28: 0 | F28: 0 | G28: 0 | H28: 0 | I28: 0 | J28: 0 | K28: 0 | L28: 0 | M28: 0 | N28: 0 | O28: 0 | P28: 0 | Q28: 0 | R28: =($W$4*(SUM(D28:Q28))) -> 0 | S28: =IFERROR(SUMIF('Exhibiciones '!$E$5:$E$550,A28,'Exhibiciones '!$AF$5:$AF$550),"") -> 0 | T28: =IFERROR(SUMIF('Exhibiciones '!$E$5:$E$550,A28,'Exhibiciones '!$AG$5:$AG$550),"-") -> 0 | U28: 0 | V28: 0 | W28: 0 | X28: 0 | Y28: 0 | Z28: 0 | AA28: 0 | AB28: 0 | AC28: 0 | AD28: 0 | AE28: 0 | AF28: 0 | AH28: =IFERROR(VLOOKUP(AG28,'Plantilla y Concentrado'!$B$4:$C$677,2,0),"")
D29: 0 | E29: 0 | F29: 0 | G29: 0 | H29: 0 | I29: 0 | J29: 0 | K29: 0 | L29: 0 | M29: 0 | N29: 0 | O29: 0 | P29: 0 | Q29: 0 | R29: =($W$4*(SUM(D29:Q29))) -> 0 | S29: =IFERROR(SUMIF('Exhibiciones '!$E$5:$E$550,A29,'Exhibiciones '!$AF$5:$AF$550),"") -> 0 | T29: =IFERROR(SUMIF('Exhibiciones '!$E$5:$E$550,A29,'Exhibiciones '!$AG$5:$AG$550),"-") -> 0 | U29: 0 | V29: 0 | W29: 0 | X29: 0 | Y29: 0 | Z29: 0 | AA29: 0 | AB29: 0 | AC29: 0 | AD29: 0 | AE29: 0 | AF29: 0 | AH29: =IFERROR(VLOOKUP(AG29,'Plantilla y Concentrado'!$B$4:$C$677,2,0),"")
A30: Total | B30: =SUM(B9:B29) -> 8864 | C30: =SUM(C9:C29) -> 8812 | D30: =SUM(D9:D29) -> 2 | E30: =SUM(E9:E29) -> 0 | F30: =SUM(F9:F29) -> 1 | G30: =SUM(G9:G29) -> 0 | H30: =SUM(H9:H29) -> 0 | I30: =SUM(I9:I29) -> 0 | ... Q30: =SUM(Q9:Q29) -> 0 | R30: =SUM(D30:Q30) -> 5 | S30: =SUM(S9:S29) -> 0 | T30: =SUM(T9:T29) -> 0 | U30: =SUM(U9:U29) -> 4 | V30: =SUM(V9:V29) -> 9 | W30: =SUM(W9:W29) -> 0 | X30: =SUM(X9:X29) -> 0 | Y30: =SUM(Y9:Y29) -> 0 | Z30: =SUM(Z9:Z29) -> 0 | ... AF30: =SUM(AF9:AF29) -> 0
A31: Costo de Oportunidad | D31: =($W$4*R30) -> 2565 | M31: =IFERROR(VLOOKUP(#REF!,#REF!,11,0)+VLOOKUP(#REF!,#REF!,11,0)+VLOOKUP(#REF!,#REF!,11,0)+VLOOKUP(#REF!,#REF!,11,0)+VLOOKUP(#REF!,#REF!,11,0),"") | S31: Incidencias corregidas durante la auditoria
C32: =A9 -> 60 | D32: 0 | E32: 0 | F32: 0 | G32: 0 | H32: 0 | I32: 0 | J32: 0 | K32: 0 | L32: 0 | M32: 0 | N32: 0 | O32: 0 | P32: 0 | Q32: 0 | R32: =($W$4*(SUM(D32:Q32))) -> 0 | S32: 0 | T32: 0 | U32: 1 | V32: 0 | W32: 0 | X32: 0 | Y32: 0 | Z32: 0 | AA32: 0 | AB32: 0 | AC32: 0 | AD32: 0 | AE32: 0 | AF32: 0
C33: =A10 -> 61 | D33: 0 | E33: 0 | F33: 0 | G33: 0 | H33: 0 | I33: 0 | J33: 0 | K33: 0 | L33: 0 | M33: 0 | N33: 0 | O33: 0 | P33: 0 | Q33: 0 | R33: =($W$4*(SUM(D33:Q33))) -> 0 | S33: 0 | T33: 0 | U33: 0 | V33: 1 | W33: 0 | X33: 0 | Y33: 0 | Z33: 0 | AA33: 0 | AB33: 0 | AC33: 0 | AD33: 0 | AE33: 0 | AF33: 0
C34: =A11 -> 62 | D34: 1 | E34: 0 | F34: 0 | G34: 0 | H34: 0 | I34: 0 | J34: 0 | K34: 0 | L34: 0 | M34: 0 | N34: 0 | O34: 0 | P34: 0 | Q34: 0 | R34: =($W$4*(SUM(D34:Q34))) -> 513 | S34: 0 | T34: 0 | U34: 1 | V34: 0 | W34: =IFERROR(SUMIF('Exhibiciones '!$E$5:$E$550,E34,'Exhibiciones '!$AF$5:$AF$550),"") -> 0 | X34: 0 | Y34: 0 | Z34: 0 | AA34: 0 | AB34: 0 | AC34: 0 | AD34: 0 | AE34: 0 | AF34: 0
C35: =A12 -> 63 | D35: 0 | E35: 0 | F35: 0 | G35: 0 | H35: 0 | I35: 0 | J35: 0 | K35: 0 | L35: 0 | M35: 0 | N35: 0 | O35: 0 | P35: 0 | Q35: 0 | R35: =($W$4*(SUM(D35:Q35))) -> 0 | S35: 0 | T35: 0 | U35: 0 | V35: 0 | W35: =IFERROR(SUMIF('Exhibiciones '!$E$5:$E$550,E35,'Exhibiciones '!$AF$5:$AF$550),"") -> 0 | X35: =IFERROR(SUMIF('Exhibiciones '!$E$5:$E$550,E35,'Exhibiciones '!$AG$5:$AG$550),"-") -> 0 | Y35: 0 | Z35: 0 | AA35: 0 | AB35: 0 | AC35: 0 | AD35: 0 | AE35: 0 | AF35: 0
C36: =A13 -> 64 | D36: 1 | E36: 0 | F36: 0 | G36: 0 | H36: 0 | I36: 0 | J36: 0 | K36: 0 | L36: 0 | M36: 0 | N36: 0 | O36: 0 | P36: 0 | Q36: 0 | R36: =($W$4*(SUM(D36:Q36))) -> 513 | S36: 0 | T36: 0 | U36: 0 | V36: 0 | W36: =IFERROR(SUMIF('Exhibiciones '!$E$5:$E$550,E36,'Exhibiciones '!$AF$5:$AF$550),"") -> 0 | X36: 0 | Y36: 0 | Z36: 0 | AA36: 0 | AB36: 0 | AC36: 0 | AD36: 0 | AE36: 0 | AF36: 0
C37: =A14 -> 65 | D37: 0 | E37: 0 | F37: 0 | G37: 0 | H37: 0 | I37: 0 | J37: 0 | K37: 0 | L37: 0 | M37: 0 | N37: 0 | O37: 0 | P37: 0 | Q37: 0 | R37: =($W$4*(SUM(D37:Q37))) -> 0 | S37: 0 | T37: 0 | U37: 0 | V37: 0 | W37: =IFERROR(SUMIF('Exhibiciones '!$E$5:$E$550,E37,'Exhibiciones '!$AF$5:$AF$550),"") -> 0 | X37: 0 | Y37: 0 | Z37: 0 | AA37: 0 | AB37: 0 | AC37: 0 | AD37: 0 | AE37: 0 | AF37: 0
C38: =A15 -> 66 | D38: 0 | E38: 0 | F38: 0 | G38: 0 | H38: 0 | I38: 0 | J38: 0 | K38: 0 | L38: 0 | M38: 0 | N38: 0 | O38: 0 | P38: 0 | Q38: 0 | R38: =($W$4*(SUM(D38:Q38))) -> 0 | S38: 0 | T38: 0 | U38: 0 | V38: 0 | W38: =IFERROR(SUMIF('Exhibiciones '!$E$5:$E$550,E38,'Exhibiciones '!$AF$5:$AF$550),"") -> 0 | X38: =IFERROR(SUMIF('Exhibiciones '!$E$5:$E$550,E38,'Exhibiciones '!$AG$5:$AG$550),"-") -> 0 | Y38: 0 | Z38: 0 | AA38: 0 | AB38: 0 | AC38: 0 | AD38: 0 | AE38: 0 | AF38: 0
C39: =A16 -> 67 | D39: 0 | E39: 0 | F39: 0 | G39: 0 | H39: 0 | I39: 0 | J39: 0 | K39: 0 | L39: 0 | M39: 0 | N39: 0 | O39: 0 | P39: 0 | Q39: 0 | R39: =($W$4*(SUM(D39:Q39))) -> 0 | S39: 0 | T39: 0 | U39: 0 | V39: 0 | W39: =IFERROR(SUMIF('Exhibiciones '!$E$5:$E$550,E39,'Exhibiciones '!$AF$5:$AF$550),"") -> 0 | X39: =IFERROR(SUMIF('Exhibiciones '!$E$5:$E$550,E39,'Exhibiciones '!$AG$5:$AG$550),"-") -> 0 | Y39: 0 | Z39: 0 | AA39: 0 | AB39: 0 | AC39: 0 | AD39: 0 | AE39: 0 | AF39: 0
C40: =A17 -> 68 | D40: 0 | E40: 0 | F40: 1 | G40: 0 | H40: 0 | I40: 0 | J40: 0 | K40: 0 | L40: 0 | M40: 0 | N40: 0 | O40: 0 | P40: 0 | Q40: 0 | R40: =($W$4*(SUM(D40:Q40))) -> 513 | S40: 0 | T40: 0 | U40: 0 | V40: 0 | W40: =IFERROR(SUMIF('Exhibiciones '!$E$5:$E$550,E40,'Exhibiciones '!$AF$5:$AF$550),"") -> 0 | X40: =IFERROR(SUMIF('Exhibiciones '!$E$5:$E$550,E40,'Exhibiciones '!$AG$5:$AG$550),"-") -> 0 | Y40: 0 | Z40: 0 | AA40: 0 | AB40: 0 | AC40: 0 | AD40: 0 | AE40: 0 | AF40: 0
C41: =A18 -> 69 | D41: 0 | E41: 0 | F41: 0 | G41: 0 | H41: 0 | I41: 0 | J41: 0 | K41: 0 | L41: 0 | M41: 0 | N41: 0 | O41: 0 | P41: 0 | Q41: 0 | R41: =($W$4*(SUM(D41:Q41))) -> 0 | S41: 0 | T41: 0 | U41: 0 | V41: 0 | W41: =IFERROR(SUMIF('Exhibiciones '!$E$5:$E$550,E41,'Exhibiciones '!$AF$5:$AF$550),"") -> 0 | X41: =IFERROR(SUMIF('Exhibiciones '!$E$5:$E$550,E41,'Exhibiciones '!$AG$5:$AG$550),"-") -> 0 | Y41: 0 | Z41: 0 | AA41: 0 | AB41: 0 | AC41: 0 | AD41: 0 | AE41: 0 | AF41: 0
C42: =A19 -> 70 | D42: 0 | E42: 0 | F42: 0 | G42: 0 | H42: 0 | I42: 0 | J42: 0 | K42: 0 | L42: 0 | M42: 0 | N42: 0 | O42: 0 | P42: 0 | Q42: 0 | R42: =($W$4*(SUM(D42:Q42))) -> 0 | S42: 0 | T42: 0 | U42: 1 | V42: 3 | W42: =IFERROR(SUMIF('Exhibiciones '!$E$5:$E$550,E42,'Exhibiciones '!$AF$5:$AF$550),"") -> 0 | X42: =IFERROR(SUMIF('Exhibiciones '!$E$5:$E$550,E42,'Exhibiciones '!$AG$5:$AG$550),"-") -> 0 | Y42: 0 | Z42: 0 | AA42: 0 | AB42: 0 | AC42: 0 | AD42: 0 | AE42: 0 | AF42: 0
C43: =A20 -> 71 | D43: 0 | E43: 0 | F43: 0 | G43: 0 | H43: 0 | I43: 0 | J43: 0 | K43: 0 | L43: 0 | M43: 0 | N43: 0 | O43: 0 | P43: 0 | Q43: 0 | R43: =($W$4*(SUM(D43:Q43))) -> 0 | S43: 0 | T43: 0 | U43: 1 | V43: 5 | W43: =IFERROR(SUMIF('Exhibiciones '!$E$5:$E$550,E43,'Exhibiciones '!$AF$5:$AF$550),"") -> 0 | X43: 0 | Y43: 0 | Z43: 0 | AA43: 0 | AB43: 0 | AC43: 0 | AD43: 0 | AE43: 0 | AF43: 0
C44: =A21 -> 72 | D44: 0 | E44: 0 | F44: 0 | G44: 0 | H44: 0 | I44: 0 | J44: 0 | K44: 0 | L44: 0 | M44: 0 | N44: 0 | O44: 0 | P44: 0 | Q44: 0 | R44: =($W$4*(SUM(D44:Q44))) -> 0 | S44: 0 | T44: 0 | U44: 0 | V44: 0 | W44: =IFERROR(SUMIF('Exhibiciones '!$E$5:$E$550,E44,'Exhibiciones '!$AF$5:$AF$550),"") -> 0 | X44: =IFERROR(SUMIF('Exhibiciones '!$E$5:$E$550,E44,'Exhibiciones '!$AG$5:$AG$550),"-") -> 0 | Y44: 0 | Z44: 0 | AA44: 0 | AB44: 0 | AC44: 0 | AD44: 0 | AE44: 0 | AF44: 0
C45: =A22 -> 0 | D45: 0 | E45: 0 | F45: 0 | G45: 0 | H45: 0 | I45: 0 | J45: 0 | K45: 0 | L45: 0 | M45: 0 | N45: 0 | O45: 0 | P45: 0 | Q45: 0 | R45: =($W$4*(SUM(D45:Q45))) -> 0 | S45: 0 | T45: 0 | U45: 0 | V45: 0 | W45: =IFERROR(SUMIF('Exhibiciones '!$E$5:$E$550,E45,'Exhibiciones '!$AF$5:$AF$550),"") -> 0 | X45: =IFERROR(SUMIF('Exhibiciones '!$E$5:$E$550,E45,'Exhibiciones '!$AG$5:$AG$550),"-") -> 0 | Y45: 0 | Z45: 0 | AA45: 0 | AB45: 0 | AC45: 0 | AD45: 0 | AE45: 0 | AF45: 0
C46: =A23 -> 0 | D46: 0 | E46: 0 | F46: 0 | G46: 0 | H46: 0 | I46: 0 | J46: 0 | K46: 0 | L46: 0 | M46: 0 | N46: 0 | O46: 0 | P46: 0 | Q46: 0 | R46: =($W$4*(SUM(D46:Q46))) -> 0 | S46: 0 | T46: 0 | U46: 0 | V46: 0 | W46: =IFERROR(SUMIF('Exhibiciones '!$E$5:$E$550,E46,'Exhibiciones '!$AF$5:$AF$550),"") -> 0 | X46: =IFERROR(SUMIF('Exhibiciones '!$E$5:$E$550,E46,'Exhibiciones '!$AG$5:$AG$550),"-") -> 0 | Y46: 0 | Z46: 0 | AA46: 0 | AB46: 0 | AC46: 0 | AD46: 0 | AE46: 0 | AF46: 0
C47: =A24 -> 0 | D47: 0 | E47: 0 | F47: 0 | G47: 0 | H47: 0 | I47: 0 | J47: 0 | K47: 0 | L47: 0 | M47: 0 | N47: 0 | O47: 0 | P47: 0 | Q47: 0 | R47: =($W$4*(SUM(D47:Q47))) -> 0 | S47: 0 | T47: 0 | U47: 0 | V47: 0 | W47: 0 | X47: 0 | Y47: 0 | Z47: 0 | AA47: 0 | AB47: 0 | AC47: 0 | AD47: 0 | AE47: 0 | AF47: 0
C48: =A25 -> 0 | D48: 0 | E48: 0 | F48: 0 | G48: 0 | H48: 0 | I48: 0 | J48: 0 | K48: 0 | L48: 0 | M48: 0 | N48: 0 | O48: 0 | P48: 0 | Q48: 0 | R48: =($W$4*(SUM(D48:Q48))) -> 0 | S48: 0 | T48: 0 | U48: 0 | V48: 0 | W48: 0 | X48: 0 | Y48: 0 | Z48: 0 | AA48: 0 | AB48: 0 | AC48: 0 | AD48: 0 | AE48: 0 | AF48: 0
C49: =A26 -> 0 | D49: 0 | E49: 0 | F49: 0 | G49: 0 | H49: 0 | I49: 0 | J49: 0 | K49: 0 | L49: 0 | M49: 0 | N49: 0 | O49: 0 | P49: 0 | Q49: 0 | R49: =($W$4*(SUM(D49:Q49))) -> 0 | S49: 0 | T49: 0 | U49: 0 | V49: 0 | W49: 0 | X49: 0 | Y49: 0 | Z49: 0 | AA49: 0 | AB49: 0 | AC49: 0 | AD49: 0 | AE49: 0 | AF49: 0
C50: =A27 -> 0 | D50: 0 | E50: 0 | F50: 0 | G50: 0 | H50: 0 | I50: 0 | J50: 0 | K50: 0 | L50: 0 | M50: 0 | N50: 0 | O50: 0 | P50: 0 | Q50: 0 | R50: =($W$4*(SUM(D50:Q50))) -> 0 | S50: 0 | T50: 0 | U50: 0 | V50: 0 | W50: 0 | X50: 0 | Y50: 0 | Z50: 0 | AA50: 0 | AB50: 0 | AC50: 0 | AD50: 0 | AE50: 0 | AF50: 0 | AM50: 0
C51: =A28 -> 0 | D51: 0 | E51: 0 | F51: 0 | G51: 0 | H51: 0 | I51: 0 | J51: 0 | K51: 0 | L51: 0 | M51: 0 | N51: 0 | O51: 0 | P51: 0 | Q51: 0 | R51: =($W$4*(SUM(D51:Q51))) -> 0 | S51: 0 | T51: 0 | U51: 0 | V51: 0 | W51: 0 | X51: 0 | Y51: 0 | Z51: 0 | AA51: 0 | AB51: 0 | AC51: 0 | AD51: 0 | AE51: 0 | AF51: 0
C52: =A29 -> 0 | D52: 0 | E52: 0 | F52: 0 | G52: 0 | H52: 0 | I52: 0 | J52: 0 | K52: 0 | L52: 0 | M52: 0 | N52: 0 | O52: 0 | P52: 0 | Q52: 0 | R52: =($W$4*(SUM(D52:Q52))) -> 0 | S52: 0 | T52: 0 | U52: 0 | V52: 0 | W52: 0 | X52: 0 | Y52: 0 | Z52: 0 | AA52: 0 | AB52: 0 | AC52: 0 | AD52: 0 | AE52: 0 | AF52: 0
A53: Piezas recuperadas | D53: =SUM(D32:D52) -> 2 | E53: =SUM(E32:E52) -> 0 | F53: =SUM(F32:F52) -> 1 | G53: =SUM(G32:G52) -> 0 | H53: =SUM(H32:H52) -> 0 | I53: =SUM(I32:I52) -> 0 | J53: =SUM(J32:J52) -> 0 | K53: =SUM(K32:K52) -> 0 | ... Q53: =SUM(Q32:Q52) -> 0 | R53: =SUM(D53:Q53) -> 3 | S53: =SUM(S32:S52) -> 0 | T53: =SUM(T32:T52) -> 0 | U53: =SUM(U32:U52) -> 4 | V53: =SUM(V32:V52) -> 9 | W53: =SUM(W32:W52) -> 0 | X53: =SUM(X32:X52) -> 0 | Y53: =SUM(Y32:Y52) -> 0 | Z53: =SUM(Z32:Z52) -> 0 | ... AF53: =SUM(AF32:AF52) -> 0 | AG53: % de tallas negadas
A54: % de Recuperación | D54: =IF(D30>0,D53/D30,"") -> 1 | E54: =IF(E30>0,E53/E30,"") | F54: =IF(F30>0,F53/F30,"") -> 1 | G54: =IF(G30>0,G53/G30,"") | H54: =IF(H30>0,H53/H30,"") | I54: =IF(I30>0,I53/I30,"") | J54: =IF(J30>0,J53/J30,"") | K54: =IF(K30>0,K53/K30,"") | ... Q54: =IF(Q30>0,Q53/Q30,"") | R54: =IF(R30=0,"",R53/R30) -> 0.6 | S54: =IF(S30>0,S53/S30,"") | T54: =IF(T30>0,T53/T30,"") | U54: =IF(U30>0,U53/U30,"") -> 1 | V54: =IF(V30>0,V53/V30,"") -> 1 | W54: =IF(W30>0,W53/W30,"") | X54: =IF(X30>0,X53/X30,"") | Y54: =IF(Y30>0,Y53/Y30,"") | Z54: =IF(Z30>0,Z53/Z30,"") | ... AF54: =IF(AF30>0,AF53/AF30,"") | AG54: =IF(OR(C30=0,C30=""),"",R30/C30) -> 0.00056740808
A55: Costo Recuperado durante la auditoria | D55: =($W$4*R53) -> 1539 | AF55: =SUM(S53:AF53) -> 13
A57: # | B57: Incidencia | L57: Área responsable | S57: Punto de Rutina | AD57: Plan de acción del Supervisor del área: | AI57: Resultado de Check List Operativo | AJ57: %
A58: 1 | L58: Supervisor de Piso de Venta | AI58: =Bot!E41 -> Resurtido | AJ58: =Urb!F41 -> -
A59: 2 | AI59: =Bot!E42 -> Auxiliar de Zona DEN | AJ59: =Urb!F42 -> -
A60: 3 | AI60: =Bot!E43 -> Cambios Operativo | AJ60: =Urb!F43 -> -
A61: 4 | AI61: =Bot!E44 -> Supervisor Calzado | AJ61: =Urb!F44 -> -
A62: 5 | L62: Resurtido / Operativo / Negados | AD62: Plan de acción de Mercaderías: | AI62: =Bot!E45 -> Imagen | AJ62: =Urb!F45 -> -
A63: 6 | AI63: =Bot!E46 -> Recibo | AJ63: =Urb!F46 -> -
A64: 7 | AI64: =Bot!E47 -> Sistemas | AJ64: =Urb!F47 -> -
A65: 8 | AI65: =Bot!E48 -> Indicadores | AJ65: =Urb!F48 -> -
A66: 9 | L66: Mercaderias / Administrativos | AI66: TOTAL | AJ66: =IF(COUNT(AJ58:AJ65)>0,AVERAGE(AJ58:AJ65),"-") -> -
A67: 10 | AD67: Plan de acción del Gerente Comercial
A69: 12
AD72: Plan de acción del Gerente Comercial Operativo
A77: Firmas:
G79: (Mejoras entregó Dummy y Check List) | S79: (Mejoras entregó Dummy) | AG79: (Mejoras entregó Dummy)
B80: Mejoras | G80: Supervisor de Área | S80: Mercaderías | W80: Gerente de Nave | AB80: Gerente Comercial | AG80: Gerente Comercial Operativo | AJ80: Gerente General

Sheet CUrb
C1: Carta de cierre de incidencias | K1: Código: MS-CCI/01-19
K2: Versión: 001
K3: Vigencia a partir : Mayo 2022
C4: CATALOGO AUDITADO | D4: =DUrb!E15 -> 0 | G4: =DUrb!AH15 -> Guzman Navarrete Arlen Esmeralda
A5: N° | B5: Área | C5: Area de Oportunidad | D5: Tiempo de Solucion en minutos | E5: Número de Incidencias | F5: Tiempo estimado de solución | G5: Responsable | H5: Hora de Aviso a Responsables | I5: Hora de Compromiso | J5: Firma | K5: Numero de Incidencias corregidas | L5: % DE AVANCE | M5: Observaciones
A6: 1 | B6: Mercaderías | C6: Cartas de Disculpa y/o Carta de Destallado Faltantes | D6: 0.013888889 | E6: =DUrb!AG41-DUrb!AG64 -> 0 | F6: =D6*E6 -> 0 | H6: 0.58333333 | I6: =IF(E6=0,"",H$6+F6) | L6: =IF(E6=0,"",K6/E6)
A7: 3 | C7: Curvas vencidas | D7: 0.0069444444 | E7: =DUrb!AB41-DUrb!AB64 -> 0 | F7: =D7*E7 -> 0 | I7: =IF(E7=0,"",H$6+F7) | L7: =IF(E7=0,"",K7/E7)
A8: 4 | C8: Curvas que no cuadran Price Soft vs Fisico | D8: 1.0069444 | E8: =DUrb!AC41-DUrb!AC64 -> 0 | F8: =D8*E8 -> 0 | I8: =IF(E8=0,"",H$6+F8) | L8: =IF(E8=0,"",K8/E8)
A9: 5 | C9: Curva con Diferencia en Frentes | D9: 1.0069444 | E9: =DUrb!Y41-DUrb!Y64 -> 0 | F9: =D9*E9 -> 0 | I9: =IF(E9=0,"",H$6+F9) | L9: =IF(E9=0,"",K9/E9)
A10: 6 | C10: Curva con Diferencia en Fondos | D10: 1.0069444 | E10: =DUrb!Z41-DUrb!Z64 -> 0 | F10: =D10*E10 -> 0 | I10: =IF(E10=0,"",H$6+F10) | L10: =IF(E10=0,"",K10/E10)
A11: 7 | C11: Curva con Diferencia en Altura | D11: 1.0069444 | E11: =DUrb!AA41-DUrb!AA64 -> 0 | F11: =D11*E11 -> 0 | I11: =IF(E11=0,"",H$6+F11) | L11: =IF(E11=0,"",K11/E11)
A12: 8 | C12: Modelos con error en ubicación en sistema | D12: 0.0069444444 | E12: =DUrb!X41-DUrb!X64 -> 0 | F12: =D12*E12 -> 0 | I12: =IF(E12=0,"",H$6+F12) | L12: =IF(E12=0,"",K12/E12)
A13: 9 | C13: Modelos sin Cenefa | D13: 0.0069444444 | E13: =DUrb!AE41-DUrb!AE64 -> 0 | F13: =D13*E13 -> 0 | I13: =IF(E13=0,"",H$6+F13) | L13: =IF(E13=0,"",K13/E13)
A14: 10 | C14: Modelos sin Cenefa de Precio Promocion | D14: 0.0069444444 | E14: =DUrb!AF41-DUrb!AF64 -> 0 | F14: =D14*E14 -> 0 | I14: =IF(E14=0,"",H$6+F14) | L14: =IF(E14=0,"",K14/E14)
A15: 11 | C15: Curvas faltantes | D15: 0.0069444444 | E15: =DUrb!AD41-DUrb!AD64 -> 0 | F15: =D15*E15 -> 0 | I15: =IF(E15=0,"",H$6+F15) | L15: =IF(E15=0,"",K15/E15)
A16: 12 | B16: Surtido/Resurtido | C16: Número de tallas negadas de bodega de rack | D16: 0.0020833333 | E16: =DUrb!G41-DUrb!G64 -> 0 | F16: =D16*E16 -> 0 | I16: =IF(E16=0,"",H$6+F16) | L16: =IF(E16=0,"",K16/E16)
A17: 13 | C17: Número de tallas negadas de Excedente | D17: 0.013888889 | E17: =DUrb!J41-DUrb!J64 -> 0 | F17: =D17*E17 -> 0 | I17: =IF(E17=0,"",H$6+F17) | L17: =IF(E17=0,"",K17/E17)
A18: 14 | C18: Numero de tallas negadas de bodega recepción | D18: 0.013888889 | E18: =DUrb!R41-DUrb!R64 -> 0 | F18: =D18*E18 -> 0 | I18: =IF(E18=0,"",H$6+F18) | L18: =IF(E18=0,"",K18/E18)
A19: 15 | C19: Número de tallas negadas de origen | D19: 0.013888889 | E19: =DUrb!K41-DUrb!K64 -> 0 | F19: =D19*E19 -> 0 | I19: =IF(E19=0,"",H$6+F19) | L19: =IF(E19=0,"",K19/E19)
A20: 16 | C20: Número de tallas negadas por estibas y 7mos | D20: 0.013888889 | E20: =DUrb!M41-DUrb!M64 -> 0 | F20: =D20*E20 -> 0 | I20: =IF(E20=0,"",H$6+F20) | L20: =IF(E20=0,"",K20/E20)
A21: 17 | C21: Número de tallas negadas por cambios | D21: 0.013888889 | E21: =DUrb!K30-DUrb!K53 -> 0 | F21: =D21*E21 -> 0
A22: 18 | B22: Auxiliar Doble Ubicación | C22: Número de Negados de Doble Ubicación | D22: 0.0034722222 | E22: =DUrb!I41-DUrb!I64 -> 0 | F22: =D22*E22 -> 0 | I22: =IF(E22=0,"",H$6+F22) | L22: =IF(E22=0,"",K22/E22)
A23: 19 | B23: Bodega Calzado | C23: Número de talla Negadas de Bodega (consulta del reporte comparativo entre dos bodegas) | D23: 0.0069444444 | E23: =DUrb!H41-DUrb!H64 -> 0 | F23: =D23*E23 -> 0 | I23: =IF(E23=0,"",H$6+F23) | L23: =IF(E23=0,"",K23/E23)
A24: 20 | B24: Supervisor Calzado | C24: Número de exhibiciones faltantes de Calzado en pasillo | D24: 0.013888889 | E24: =DUrb!T41-DUrb!T64 -> 0 | F24: =D24*E24 -> 0 | I24: =IF(E24=0,"",H$6+F24) | L24: =IF(E24=0,"",K24/E24)
A25: 21 | C25: Número de tallas negadas por Frenteo | D25: 0.0013888889 | E25: =DUrb!E41-DUrb!E64 -> 0 | F25: =D25*E25 -> 0 | I25: =IF(E25=0,"",H$6+F25) | L25: =IF(E25=0,"",K25/E25)
A26: 22 | C26: Número de tallas negadas por Revuelto | D26: 0.0013888889 | E26: =DUrb!E30-DUrb!E53 -> 0 | F26: =D26*E26 -> 0
E27: =SUM(E6:E25) -> 0 | L27: =IF(E27=0,"",AVERAGE(L6:L25))
B30: GERENCIA | D30: RESPONSABLE | F30: DESVIACIONES | G30: FIRMA | I30: Realizo Supervisor de Mejoras
B31: GERENCIA COMERCIAL DE PRODUCTO
B32: GERENCIA COMERCIAL OPERATIVA

Sheet Esc
D1: Formato para el registro del Check list del Supervisor | I1: Código: MS-CLS/01-18
I2: Versión: 001
I3: Vigencia a partir : Mayo 2022
B4: Tienda | D4: Ecatepec
B5: Fecha de auditoria: | D5: 46204 | E5: Gerente Comercial | F5: Luis Alberto Pérez
B6: Catálogo: | D6: Escolar | E6: Gerente Com. Operativo | F6: Alejandro Balleza Gómez | M6: SI
B7: Supervisor de Catalogo | D7: Hazminda Garcia | E7: Gerente de Servicios | M7: NO
B8: # de Nomina | D8: 1752 | E8: Gerente de Operaciones | F8: Alejandro Balleza Gómez | M8: NA
B11: Responsable | C11: Definición de Servicio | D11: Indicador | E11: Criterio de Evaluación | F11: Número | G11: Alcance | H11: Valor | I11: Logro x actividad | J11: Logro x departamento | K11: Que dato se captura? | L11: Como obtengo este dato o cual es el entregable?
B12: Informativo | D12: Total de Tallas del Catálogo | F12: =DEsc!B31 -> 2111
B13: Informativo | D13: Total de Tallas auditadas | F13: =DEsc!C31 -> 2085 | G13: =IF(F12=0,"",F13/F12) -> 0.98768356
B14: Informativo | D14: Número de pasillos
B15: Informativo | D15: Sugerido del catálogo a 7 días
