Workbook

Sheet MACHOTE SEM
A2: Concentrado por Tienda de Dictamen de Auditoria de Dummy | BV2: Recuperación por tienda y rubro
H3: Semana: | J3: "Semana " | V3: Periodo de evaluación: | BZ3: Semana: | CB3: =J3 -> "Semana " | CN3: Periodo de evaluación: | CQ3: =Y3 -> 0
F5: Causas de Negado | U5: Incidencias de Auditoria | BX5: Causas de Negado | CM5: Incidencias de Auditoria
A6: Tiendas | B6: Calzado | C6: Tallas por pasillo | D6: Tallas por modelo | E6: % de Cobertura de auditoria | F6: Frenteos | G6: Ubicación Revuelta | H6: Bodega Venta (Sin marcar) | I6: Bodega Tapanco | J6: Doble Ubicación | K6: Excedente | L6: Origen | M6: Cambios/Probadores | N6: Negados Sin Recuperar | O6: Exhibición | P6: Bodega Aclaración | Q6: Aduanas | R6: Golden o apartados | S6: Control de calidad | T6: Costo por pasillo | U6: Sin Exhibición | V6: Exhibición fuera de Política | W6: Modelos revuelto | X6: Modelos mal entallados | Y6: Modelos con error de ubicación | Z6: Curva con diferencia en frentes | AA6: Curva con diferencia en fondos | AB6: Curva con diferencia en altura | AC6: Curvas vencidas | AD6: Curvas que no coincide Price Soft vs Piso de Venta | AE6: Curvas faltantes | AF6: Cenefas faltantes | AG6: Cenefas de precio Promoción faltantes | AH6: Cartas disculpa / destallados faltantes | AI6: Fechas de llegada faltantes | AJ6: Resultado de Check List | AK6: Resultado de banderazo surtido | BV6: Tiendas | BW6: Calzado | BX6: Frenteos | BY6: Ubicación Revuelta | BZ6: Bodega Venta (Sin marcar) | CA6: Bodega Tapanco | CB6: Doble Ubicación | CC6: Excedente | CD6: Origen | CE6: Cambios/Probadores | CF6: Negados Sin Recuperar | CG6: Exhibición | CH6: Bodega Aclaración | CI6: Aduanas | CJ6: Golden o apartados | CK6: Control de calidad | CL6: Costo por pasillo | CM6: Sin Exhibición | CN6: Exhibición fuera de Política | CO6: Modelos revuelto | CP6: Modelos mal entallados | CQ6: Modelos con error de ubicación | CR6: Curva con diferencia en frentes | CS6: Curva con diferencia en fondos | CT6: Curva con diferencia en altura | CU6: Curvas vencidas | CV6: Curvas que no coincide Price Soft vs Piso de Venta | CW6: Curvas faltantes | CX6: Cenefas faltantes | CY6: Cenefas de precio Promoción faltantes | CZ6: Cartas disculpa / destallados faltantes | DA6: Fechas de llegada faltantes | EK6: Frenteos | EL6: Ubicación Revuelta | EM6: Bodega Venta (Sin marcar) | EN6: Bodega Tapanco | EO6: Doble Ubicación | EP6: Excedente | EQ6: Origen | ER6: Cambios/Probadores | ES6: Negados Sin Recuperar | ET6: Exhibición | EU6: Bodega Aclaración | EV6: Aduanas | EW6: Golden o apartados | EX6: Control de calidad | EZ6: Frenteos | FA6: Ubicación Revuelta | FB6: Bodega Venta (Sin marcar) | FC6: Bodega Tapanco | FD6: Doble Ubicación | FE6: Excedente | FF6: Origen | FG6: Cambios/Probadores | FH6: Negados Sin Recuperar | FI6: Exhibición | FJ6: Bodega Aclaración | FK6: Aduanas | FL6: Golden o apartados | FM6: Control de calidad
A7: Aguascalientes | C7: =AM56 -> 0 | D7: =AN56 -> 0 | E7: =D7/C7 -> #DIV/0! | F7: =AP56 -> 0 | G7: =AQ56 -> 0 | H7: =AR56 -> 0 | I7: =AS56 -> 0 | J7: =AT56 -> 0 | K7: =AU56 -> 0 | L7: =AV56 -> 0 | M7: =AW56 -> 0 | ... AI7: =BS56 -> 0 | BV7: Aguascalientes | BX7: =DE56 -> 0 | BY7: =DF56 -> 0 | BZ7: =DG56 -> 0 | CA7: =DH56 -> 0 | CB7: =DI56 -> 0 | CC7: =DJ56 -> 0 | CD7: =DK56 -> 0 | CE7: =DL56 -> 0 | ... DA7: =EH56 -> 0 | EJ7: Aguascalientes | EK7: =EK72 -> 0 | EL7: =EL72 -> 0 | EM7: =EM72 -> 0 | EN7: =EN72 -> 0 | EO7: =EO72 -> 0 | EP7: =EP72 -> 0 | EQ7: =EQ72 -> 0 | ER7: =ER72 -> 0 | ... FN7: =FN72 -> 0
A8: Arco Norte | C8: =AM78 -> 0 | D8: =AN78 -> 0 | E8: =D8/C8 -> #DIV/0! | F8: =AP78 -> 0 | G8: =AQ78 -> 0 | H8: =AR78 -> 0 | I8: =AS78 -> 0 | J8: =AT78 -> 0 | K8: =AU78 -> 0 | L8: =AV78 -> 0 | M8: =AW78 -> 0 | ... AI8: =BS78 -> 0 | BV8: Arco Norte | BX8: =DE78 -> 0 | BY8: =DF78 -> 0 | BZ8: =DG78 -> 0 | CA8: =DH78 -> 0 | CB8: =DI78 -> 0 | CC8: =DJ78 -> 0 | CD8: =DK78 -> 0 | CE8: =DL78 -> 0 | ... DA8: =EH78 -> 0 | EJ8: Arco Norte | EK8: =EK94 -> 0 | EL8: =EL94 -> 0 | EM8: =EM94 -> 0 | EN8: =EN94 -> 0 | EO8: =EO94 -> 0 | EP8: =EP94 -> 0 | EQ8: =EQ94 -> 0 | ER8: =ER94 -> 0 | ... FN8: =FN94 -> 0
A9: Centro Historico | C9: =AM100 -> 0 | D9: =AN100 -> 0 | E9: =D9/C9 -> #DIV/0! | F9: =AP100 -> 0 | G9: =AQ100 -> 0 | H9: =AR100 -> 0 | I9: =AS100 -> 0 | J9: =AT100 -> 0 | K9: =AU100 -> 0 | L9: =AV100 -> 0 | M9: =AW100 -> 0 | ... AI9: =BS100 -> 0 | BV9: Centro Historico | BX9: =DE100 -> 0 | BY9: =DF100 -> 0 | BZ9: =DG100 -> 0 | CA9: =DH100 -> 0 | CB9: =DI100 -> 0 | CC9: =DJ100 -> 0 | CD9: =DK100 -> 0 | CE9: =DL100 -> 0 | ... DA9: =EH100 -> 0 | EJ9: Centro Historico | EK9: =EK116 -> 0 | EL9: =EL116 -> 0 | EM9: =EM116 -> 0 | EN9: =EN116 -> 0 | EO9: =EO116 -> 0 | EP9: =EP116 -> 0 | EQ9: =EQ116 -> 0 | ER9: =ER116 -> 0 | ... FN9: =FN116 -> 0
A10: Ecatepec | C10: =AM122 -> 0 | D10: =AN122 -> 0 | E10: =D10/C10 -> #DIV/0! | F10: =AP122 -> 0 | G10: =AQ122 -> 0 | H10: =AR122 -> 0 | I10: =AS122 -> 0 | J10: =AT122 -> 0 | K10: =AU122 -> 0 | L10: =AV122 -> 0 | M10: =AW122 -> 0 | ... AI10: =BS122 -> 0 | BV10: Ecatepec | BX10: =DE122 -> 0 | BY10: =DF122 -> 0 | BZ10: =DG122 -> 0 | CA10: =DH122 -> 0 | CB10: =DI122 -> 0 | CC10: =DJ122 -> 0 | CD10: =DK122 -> 0 | CE10: =DL122 -> 0 | ... DA10: =EH122 -> 0 | EJ10: Ecatepec | EK10: =EK138 -> 0 | EL10: =EL138 -> 0 | EM10: =EM138 -> 0 | EN10: =EN138 -> 0 | EO10: =EO138 -> 0 | EP10: =EP138 -> 0 | EQ10: =EQ138 -> 0 | ER10: =ER138 -> 0 | ... FN10: =FN138 -> 0
A11: Guadalajara | C11: =AM144 -> 0 | D11: =AN144 -> 0 | E11: =D11/C11 -> #DIV/0! | F11: =AP144 -> 0 | G11: =AQ144 -> 0 | H11: =AR144 -> 0 | I11: =AS144 -> 0 | J11: =AT144 -> 0 | K11: =AU144 -> 0 | L11: =AV144 -> 0 | M11: =AW144 -> 0 | ... AI11: =BS144 -> 0 | BV11: Guadalajara | BX11: =DE144 -> 0 | BY11: =DF144 -> 0 | BZ11: =DG144 -> 0 | CA11: =DH144 -> 0 | CB11: =DI144 -> 0 | CC11: =DJ144 -> 0 | CD11: =DK144 -> 0 | CE11: =DL144 -> 0 | ... DA11: =EH144 -> 0 | EJ11: Guadalajara | EK11: =EK160 -> 0 | EL11: =EL160 -> 0 | EM11: =EM160 -> 0 | EN11: =EN160 -> 0 | EO11: =EO160 -> 0 | EP11: =EP160 -> 0 | EQ11: =EQ160 -> 0 | ER11: =ER160 -> 0 | ... FN11: =FN160 -> 0
A12: Ixtapaluca | C12: =AM166 -> 0 | D12: =AN166 -> 0 | E12: =D12/C12 -> #DIV/0! | F12: =AP166 -> 0 | G12: =AQ166 -> 0 | H12: =AR166 -> 0 | I12: =AS166 -> 0 | J12: =AT166 -> 0 | K12: =AU166 -> 0 | L12: =AV166 -> 0 | M12: =AW166 -> 0 | ... AI12: =BS166 -> 0 | BV12: Ixtapaluca | BX12: =DE166 -> 0 | BY12: =DF166 -> 0 | BZ12: =DG166 -> 0 | CA12: =DH166 -> 0 | CB12: =DI166 -> 0 | CC12: =DJ166 -> 0 | CD12: =DK166 -> 0 | CE12: =DL166 -> 0 | ... DA12: =EH166 -> 0 | EJ12: Ixtapaluca | EK12: =EK182 -> 0 | EL12: =EL182 -> 0 | EM12: =EM182 -> 0 | EN12: =EN182 -> 0 | EO12: =EO182 -> 0 | EP12: =EP182 -> 0 | EQ12: =EQ182 -> 0 | ER12: =ER182 -> 0 | ... FN12: =FN182 -> 0
A13: Iztapalapa | C13: =AM188 -> 0 | D13: =AN188 -> 0 | E13: =D13/C13 -> #DIV/0! | F13: =AP188 -> 0 | G13: =AQ188 -> 0 | H13: =AR188 -> 0 | I13: =AS188 -> 0 | J13: =AT188 -> 0 | K13: =AU188 -> 0 | L13: =AV188 -> 0 | M13: =AW188 -> 0 | ... AI13: =BS188 -> 0 | BV13: Iztapalapa | BX13: =DE188 -> 0 | BY13: =DF188 -> 0 | BZ13: =DG188 -> 0 | CA13: =DH188 -> 0 | CB13: =DI188 -> 0 | CC13: =DJ188 -> 0 | CD13: =DK188 -> 0 | CE13: =DL188 -> 0 | ... DA13: =EH188 -> 0 | EJ13: Iztapalapa | EK13: =EK204 -> 0 | EL13: =EL204 -> 0 | EM13: =EM204 -> 0 | EN13: =EN204 -> 0 | EO13: =EO204 -> 0 | EP13: =EP204 -> 0 | EQ13: =EQ204 -> 0 | ER13: =ER204 -> 0 | ... FN13: =FN204 -> 0
A14: León | C14: =AM210 -> 0 | D14: =AN210 -> 0 | E14: =D14/C14 -> #DIV/0! | F14: =AP210 -> 0 | G14: =AQ210 -> 0 | H14: =AR210 -> 0 | I14: =AS210 -> 0 | J14: =AT210 -> 0 | K14: =AU210 -> 0 | L14: =AV210 -> 0 | M14: =AW210 -> 0 | ... AI14: =BS210 -> 0 | BV14: León | BX14: =DE210 -> 0 | BY14: =DF210 -> 0 | BZ14: =DG210 -> 0 | CA14: =DH210 -> 0 | CB14: =DI210 -> 0 | CC14: =DJ210 -> 0 | CD14: =DK210 -> 0 | CE14: =DL210 -> 0 | ... DA14: =EH210 -> 0 | EJ14: León | EK14: =EK226 -> 0 | EL14: =EL226 -> 0 | EM14: =EM226 -> 0 | EN14: =EN226 -> 0 | EO14: =EO226 -> 0 | EP14: =EP226 -> 0 | EQ14: =EQ226 -> 0 | ER14: =ER226 -> 0 | ... FN14: =FN226 -> 0
A15: Miravalle | C15: =AM232 -> 0 | D15: =AN232 -> 0 | E15: =D15/C15 -> #DIV/0! | F15: =AP232 -> 0 | G15: =AQ232 -> 0 | H15: =AR232 -> 0 | I15: =AS232 -> 0 | J15: =AT232 -> 0 | K15: =AU232 -> 0 | L15: =AV232 -> 0 | M15: =AW232 -> 0 | ... AI15: =BS232 -> 0 | BV15: Miravalle | BX15: =DE232 -> 0 | BY15: =DF232 -> 0 | BZ15: =DG232 -> 0 | CA15: =DH232 -> 0 | CB15: =DI232 -> 0 | CC15: =DJ232 -> 0 | CD15: =DK232 -> 0 | CE15: =DL232 -> 0 | ... DA15: =EH232 -> 0 | EJ15: Miravalle | EK15: =EK248 -> 0 | EL15: =EL248 -> 0 | EM15: =EM248 -> 0 | EN15: =EN248 -> 0 | EO15: =EO248 -> 0 | EP15: =EP248 -> 0 | EQ15: =EQ248 -> 0 | ER15: =ER248 -> 0 | ... FN15: =FN248 -> 0
A16: Naucalpan | C16: =AM254 -> 0 | D16: =AN254 -> 0 | E16: =D16/C16 -> #DIV/0! | F16: =AP254 -> 0 | G16: =AQ254 -> 0 | H16: =AR254 -> 0 | I16: =AS254 -> 0 | J16: =AT254 -> 0 | K16: =AU254 -> 0 | L16: =AV254 -> 0 | M16: =AW254 -> 0 | ... AI16: =BS254 -> 0 | BV16: Naucalpan | BX16: =DE254 -> 0 | BY16: =DF254 -> 0 | BZ16: =DG254 -> 0 | CA16: =DH254 -> 0 | CB16: =DI254 -> 0 | CC16: =DJ254 -> 0 | CD16: =DK254 -> 0 | CE16: =DL254 -> 0 | ... DA16: =EH254 -> 0 | EJ16: Naucalpan | EK16: =EK270 -> 0 | EL16: =EL270 -> 0 | EM16: =EM270 -> 0 | EN16: =EN270 -> 0 | EO16: =EO270 -> 0 | EP16: =EP270 -> 0 | EQ16: =EQ270 -> 0 | ER16: =ER270 -> 0 | ... FN16: =FN270 -> 0
A17: Olivar del Conde | C17: =AM276 -> 0 | D17: =AN276 -> 0 | E17: =D17/C17 -> #DIV/0! | F17: =AP276 -> 0 | G17: =AQ276 -> 0 | H17: =AR276 -> 0 | I17: =AS276 -> 0 | J17: =AT276 -> 0 | K17: =AU276 -> 0 | L17: =AV276 -> 0 | M17: =AW276 -> 0 | ... AI17: =BS276 -> 0 | BV17: Olivar del Conde | BX17: =DE276 -> 0 | BY17: =DF276 -> 0 | BZ17: =DG276 -> 0 | CA17: =DH276 -> 0 | CB17: =DI276 -> 0 | CC17: =DJ276 -> 0 | CD17: =DK276 -> 0 | CE17: =DL276 -> 0 | ... DA17: =EH276 -> 0 | EJ17: Olivar del Conde | EK17: =EK292 -> 0 | EL17: =EL292 -> 0 | EM17: =EM292 -> 0 | EN17: =EN292 -> 0 | EO17: =EO292 -> 0 | EP17: =EP292 -> 0 | EQ17: =EQ292 -> 0 | ER17: =ER292 -> 0 | ... FN17: =FN292 -> 0
A18: Puebla | C18: =AM298 -> 0 | D18: =AN298 -> 0 | E18: =D18/C18 -> #DIV/0! | F18: =AP298 -> 0 | G18: =AQ298 -> 0 | H18: =AR298 -> 0 | I18: =AS298 -> 0 | J18: =AT298 -> 0 | K18: =AU298 -> 0 | L18: =AV298 -> 0 | M18: =AW298 -> 0 | ... AI18: =BS298 -> 0 | BV18: Puebla | BX18: =DE298 -> 0 | BY18: =DF298 -> 0 | BZ18: =DG298 -> 0 | CA18: =DH298 -> 0 | CB18: =DI298 -> 0 | CC18: =DJ298 -> 0 | CD18: =DK298 -> 0 | CE18: =DL298 -> 0 | ... DA18: =EH298 -> 0 | EJ18: Puebla | EK18: =EK314 -> 0 | EL18: =EL314 -> 0 | EM18: =EM314 -> 0 | EN18: =EN314 -> 0 | EO18: =EO314 -> 0 | EP18: =EP314 -> 0 | EQ18: =EQ314 -> 0 | ER18: =ER314 -> 0 | ... FN18: =FN314 -> 0
A19: Queretaro | C19: =AM320 -> 0 | D19: =AN320 -> 0 | E19: =D19/C19 -> #DIV/0! | F19: =AP320 -> 0 | G19: =AQ320 -> 0 | H19: =AR320 -> 0 | I19: =AS320 -> 0 | J19: =AT320 -> 0 | K19: =AU320 -> 0 | L19: =AV320 -> 0 | M19: =AW320 -> 0 | ... AI19: =BS320 -> 0 | BV19: Queretaro | BX19: =DE320 -> 0 | BY19: =DF320 -> 0 | BZ19: =DG320 -> 0 | CA19: =DH320 -> 0 | CB19: =DI320 -> 0 | CC19: =DJ320 -> 0 | CD19: =DK320 -> 0 | CE19: =DL320 -> 0 | ... DA19: =EH320 -> 0 | EJ19: Queretaro | EK19: =EK336 -> 0 | EL19: =EL336 -> 0 | EM19: =EM336 -> 0 | EN19: =EN336 -> 0 | EO19: =EO336 -> 0 | EP19: =EP336 -> 0 | EQ19: =EQ336 -> 0 | ER19: =ER336 -> 0 | ... FN19: =FN336 -> 0
A20: Puebla Sur | C20: =AM408 -> 0 | D20: =AN408 -> 0 | E20: =D20/C20 -> #DIV/0! | F20: =AP408 -> 0 | G20: =AQ408 -> 0 | H20: =AR408 -> 0 | I20: =AS408 -> 0 | J20: =AT408 -> 0 | K20: =AU408 -> 0 | L20: =AV408 -> 0 | M20: =AW408 -> 0 | ... AI20: =BS408 -> 0 | BV20: Tijuna | BX20: =DE408 -> 0 | BY20: =DF408 -> 0 | BZ20: =DG408 -> 0 | CA20: =DH408 -> 0 | CB20: =DI408 -> 0 | CC20: =DJ408 -> 0 | CD20: =DK408 -> 0 | CE20: =DL408 -> 0 | ... DA20: =EH408 -> 0 | EJ20: Tijuna | EK20: =EK424 -> 0 | EL20: =EL424 -> 0 | EM20: =EM424 -> 0 | EN20: =EN424 -> 0 | EO20: =EO424 -> 0 | EP20: =EP424 -> 0 | EQ20: =EQ424 -> 0 | ER20: =ER424 -> 0 | ... FN20: =FN424 -> 0
A21: Toluca | C21: =AM342 -> 0 | D21: =AN342 -> 0 | E21: =D21/C21 -> #DIV/0! | F21: =AP342 -> 0 | G21: =AQ342 -> 0 | H21: =AR342 -> 0 | I21: =AS342 -> 0 | J21: =AT342 -> 0 | K21: =AU342 -> 0 | L21: =AV342 -> 0 | M21: =AW342 -> 0 | ... AI21: =BS342 -> 0 | BV21: Toluca | BX21: =DE342 -> 0 | BY21: =DF342 -> 0 | BZ21: =DG342 -> 0 | CA21: =DH342 -> 0 | CB21: =DI342 -> 0 | CC21: =DJ342 -> 0 | CD21: =DK342 -> 0 | CE21: =DL342 -> 0 | ... DA21: =EH342 -> 0 | EJ21: Toluca | EK21: =EK358 -> 0 | EL21: =EL358 -> 0 | EM21: =EM358 -> 0 | EN21: =EN358 -> 0 | EO21: =EO358 -> 0 | EP21: =EP358 -> 0 | EQ21: =EQ358 -> 0 | ER21: =ER358 -> 0 | ... FN21: =FN358 -> 0
A22: Vallejo | C22: =AM364 -> 0 | D22: =AN364 -> 0 | E22: =D22/C22 -> #DIV/0! | F22: =AP364 -> 0 | G22: =AQ364 -> 0 | H22: =AR364 -> 0 | I22: =AS364 -> 0 | J22: =AT364 -> 0 | K22: =AU364 -> 0 | L22: =AV364 -> 0 | M22: =AW364 -> 0 | ... AI22: =BS364 -> 0 | BV22: Vallejo | BX22: =DE364 -> 0 | BY22: =DF364 -> 0 | BZ22: =DG364 -> 0 | CA22: =DH364 -> 0 | CB22: =DI364 -> 0 | CC22: =DJ364 -> 0 | CD22: =DK364 -> 0 | CE22: =DL364 -> 0 | ... DA22: =EH364 -> 0 | EJ22: Vallejo | EK22: =EK380 -> 0 | EL22: =EL380 -> 0 | EM22: =EM380 -> 0 | EN22: =EN380 -> 0 | EO22: =EO380 -> 0 | EP22: =EP380 -> 0 | EQ22: =EQ380 -> 0 | ER22: =ER380 -> 0 | ... FN22: =FN380 -> 0
A23: Veracruz | C23: =AM386 -> 0 | D23: =AN386 -> 0 | E23: =D23/C23 -> #DIV/0! | F23: =AP386 -> 0 | G23: =AQ386 -> 0 | H23: =AR386 -> 0 | I23: =AS386 -> 0 | J23: =AT386 -> 0 | K23: =AU386 -> 0 | L23: =AV386 -> 0 | M23: =AW386 -> 0 | ... AI23: =BS386 -> 0 | BV23: Veracruz | BX23: =DE386 -> 0 | BY23: =DF386 -> 0 | BZ23: =DG386 -> 0 | CA23: =DH386 -> 0 | CB23: =DI386 -> 0 | CC23: =DJ386 -> 0 | CD23: =DK386 -> 0 | CE23: =DL386 -> 0 | ... DA23: =EH386 -> 0 | EJ23: Veracruz | EK23: =EK402 -> 0 | EL23: =EL402 -> 0 | EM23: =EM402 -> 0 | EN23: =EN402 -> 0 | EO23: =EO402 -> 0 | EP23: =EP402 -> 0 | EQ23: =EQ402 -> 0 | ER23: =ER402 -> 0 | ... FN23: =FN402 -> 0
B24: Total | C24: =SUM(C7:C23) -> 0 | D24: =SUM(D7:D23) -> 0 | E24: =D24/C24 -> #DIV/0! | F24: =SUM(F7:F23) -> 0 | H24: =SUM(H7:H23) -> 0 | I24: =SUM(I7:I23) -> 0 | J24: =SUM(J7:J23) -> 0 | K24: =SUM(K7:K23) -> 0 | L24: =SUM(L7:L23) -> 0 | N24: =SUM(N7:N23) -> 0 | O24: =SUM(O7:O23) -> 0 | P24: =SUM(P7:P23) -> 0 | T24: =SUM(F24:P24) -> 0 | U24: =SUM(U7:U23) -> 0 | V24: =SUM(V7:V23) -> 0 | W24: =SUM(W7:W23) -> 0 | X24: =SUM(X7:X23) -> 0 | Y24: =SUM(Y7:Y23) -> 0 | Z24: =SUM(Z7:Z23) -> 0 | AA24: =SUM(AA7:AA23) -> 0 | AB24: =SUM(AB7:AB23) -> 0 | ... AI24: =SUM(AI7:AI23) -> 0 | AJ24: =AVERAGE(AJ7:AJ22) -> #DIV/0! | AK24: =AVERAGE(AK7:AK22) -> #DIV/0! | BW24: Total | BX24: =SUM(BX7:BX23) -> 0 | BZ24: =SUM(BZ7:BZ23) -> 0 | CA24: =SUM(CA7:CA23) -> 0 | CB24: =SUM(CB7:CB23) -> 0 | CC24: =SUM(CC7:CC23) -> 0 | CD24: =SUM(CD7:CD23) -> 0 | CF24: =SUM(CF7:CF23) -> 0 | CG24: =SUM(CG7:CG23) -> 0 | CH24: =SUM(CH7:CH23) -> 0 | CL24: =SUM(BX24:CH24) -> 0 | CM24: =SUM(CM7:CM22) -> 0 | CN24: =SUM(CN7:CN22) -> 0 | CO24: =SUM(CO7:CO22) -> 0 | CP24: =SUM(CP7:CP22) -> 0 | CQ24: =SUM(CQ7:CQ22) -> 0 | CR24: =SUM(CR7:CR22) -> 0 | CS24: =SUM(CS7:CS22) -> 0 | CT24: =SUM(CT7:CT22) -> 0 | ... DA24: =SUM(DA7:DA22) -> 0
C25: Costo de Oportunidad | F25: =SUM(T7:T23) -> 0 | BX25: =SUM(CL7:CL22) -> 0
A27: Concentrado por Tienda de Dictamen de Auditoria de Dummy | BV27: Recuperación por tienda y rubro
F30: Causas de Negado | U30: Incidencias de Auditoria | BX30: Causas de Negado | CM30: Incidencias de Auditoria
A31: Tiendas | B31: Ropa | C31: Tallas por pasillo | D31: Tallas por modelo | E31: % de Cobertura de auditoria | F31: Frenteos | G31: Ubicación Revuelta | H31: Bodega Venta (Sin marcar) | I31: Bodega Tapanco | J31: Doble Ubicación | K31: Excedente | L31: Origen | M31: Cambios/Probadores | N31: Negados Sin Recuperar | O31: Exhibición | P31: Bodega Aclaración | Q31: Aduanas | R31: Golden o apartados | S31: Control de calidad | T31: Costo por pasillo | U31: Sin Exhibición | V31: Exhibición fuera de Política | W31: Modelos revuelto | X31: Modelos mal entallados | Y31: Modelos con error de ubicación | Z31: Curva con diferencia en frentes | AA31: Curva con diferencia en fondos | AB31: Curva con diferencia en altura | AC31: Curvas vencidas | AD31: Curvas que no coincide Price Soft vs Piso de Venta | AE31: Curvas faltantes | AF31: Cenefas faltantes | AG31: Cenefas de precio Promoción faltantes | AH31: Cartas disculpa / destallados faltantes | AI31: Fechas de llegada faltantes | BV31: Tiendas | BW31: Responsable de Catalogo | BX31: Frenteos | BY31: Ubicación Revuelta | BZ31: Bodega Venta (Sin marcar) | CA31: Bodega Tapanco | CB31: Doble Ubicación | CC31: Excedente | CD31: Origen | CE31: Cambios/Probadores | CF31: Negados Sin Recuperar | CG31: Exhibición | CH31: Bodega Aclaración | CI31: Aduanas | CJ31: Golden o apartados | CK31: Control de calidad | CL31: Costo por pasillo | CM31: Sin Exhibición | CN31: Exhibición fuera de Política | CO31: Modelos revuelto | CP31: Modelos mal entallados | CQ31: Modelos con error de ubicación | CR31: Curva con diferencia en frentes | CS31: Curva con diferencia en fondos | CT31: Curva con diferencia en altura | CU31: Curvas vencidas | CV31: Curvas que no coincide Price Soft vs Piso de Venta | CW31: Curvas faltantes | CX31: Cenefas faltantes | CY31: Cenefas de precio Promoción faltantes | CZ31: Cartas disculpa / destallados faltantes | DA31: Fechas de llegada faltantes | EK31: Frenteos | EL31: Ubicación Revuelta | EM31: Bodega Venta (Sin marcar) | EN31: Bodega Tapanco | EO31: Doble Ubicación | EP31: Excedente | EQ31: Origen | ER31: Cambios/Probadores | ES31: Negados Sin Recuperar | ET31: Exhibición | EU31: Bodega Aclaración | EV31: Aduanas | EW31: Golden o apartados | EX31: Control de calidad | EZ31: Frenteos | FA31: Ubicación Revuelta | FB31: Bodega Venta (Sin marcar) | FC31: Bodega Tapanco | FD31: Doble Ubicación | FE31: Excedente | FF31: Origen | FG31: Cambios/Probadores | FH31: Negados Sin Recuperar | FI31: Exhibición | FJ31: Bodega Aclaración | FK31: Aduanas | FL31: Golden o apartados | FM31: Control de calidad
A32: Aguascalientes | C32: =AM58 -> 0 | D32: =AN58 -> 0 | E32: =D32/C32 -> #DIV/0! | F32: =AP58 -> 0 | G32: =AQ58 -> 0 | H32: =AR58 -> 0 | I32: =AS58 -> 0 | J32: =AT58 -> 0 | K32: =AU58 -> 0 | L32: =AV58 -> 0 | M32: =AW58 -> 0 | ... AI32: =BS58 -> 0 | BV32: Aguascalientes | BX32: =DE58 -> 0 | BY32: =DF58 -> 0 | BZ32: =DG58 -> 0 | CA32: =DH58 -> 0 | CB32: =DI58 -> 0 | CC32: =DJ58 -> 0 | CD32: =DK58 -> 0 | CE32: =DL58 -> 0 | ... DA32: =EH58 -> 0 | EJ32: Aguascalientes | EK32: =EK73 -> 0 | EL32: =EL73 -> 0 | EM32: =EM73 -> 0 | EN32: =EN73 -> 0 | EO32: =EO73 -> 0 | EP32: =EP73 -> 0 | EQ32: =EQ73 -> 0 | ER32: =ER73 -> 0 | ... FN32: =FN73 -> 0
A33: Arco Norte | C33: =AM80 -> 0 | D33: =AN80 -> 0 | E33: =D33/C33 -> #DIV/0! | F33: =AP80 -> 0 | G33: =AQ80 -> 0 | H33: =AR80 -> 0 | I33: =AS80 -> 0 | J33: =AT80 -> 0 | K33: =AU80 -> 0 | L33: =AV80 -> 0 | M33: =AW80 -> 0 | ... AI33: =BS80 -> 0 | BV33: Arco Norte | BX33: =DE80 -> 0 | BY33: =DF80 -> 0 | BZ33: =DG80 -> 0 | CA33: =DH80 -> 0 | CB33: =DI80 -> 0 | CC33: =DJ80 -> 0 | CD33: =DK80 -> 0 | CE33: =DL80 -> 0 | ... DA33: =EH80 -> 0 | EJ33: Arco Norte | EK33: =EK95 -> 0 | EL33: =EL95 -> 0 | EM33: =EM95 -> 0 | EN33: =EN95 -> 0 | EO33: =EO95 -> 0 | EP33: =EP95 -> 0 | EQ33: =EQ95 -> 0 | ER33: =ER95 -> 0 | ... FN33: =FN95 -> 0
A34: Centro Historico | C34: =AM102 -> 0 | D34: =AN102 -> 0 | E34: =D34/C34 -> #DIV/0! | F34: =AP102 -> 0 | G34: =AQ102 -> 0 | H34: =AR102 -> 0 | I34: =AS102 -> 0 | J34: =AT102 -> 0 | K34: =AU102 -> 0 | L34: =AV102 -> 0 | M34: =AW102 -> 0 | ... AI34: =BS102 -> 0 | BV34: Centro Historico | BX34: =DE102 -> 0 | BY34: =DF102 -> 0 | BZ34: =DG102 -> 0 | CA34: =DH102 -> 0 | CB34: =DI102 -> 0 | CC34: =DJ102 -> 0 | CD34: =DK102 -> 0 | CE34: =DL102 -> 0 | ... DA34: =EH102 -> 0 | EJ34: Centro Historico | EK34: =EK117 -> 0 | EL34: =EL117 -> 0 | EM34: =EM117 -> 0 | EN34: =EN117 -> 0 | EO34: =EO117 -> 0 | EP34: =EP117 -> 0 | EQ34: =EQ117 -> 0 | ER34: =ER117 -> 0 | ... FN34: =FN117 -> 0
A35: Ecatepec | C35: =AM124 -> 0 | D35: =AN124 -> 0 | E35: =D35/C35 -> #DIV/0! | F35: =AP124 -> 0 | G35: =AQ124 -> 0 | H35: =AR124 -> 0 | I35: =AS124 -> 0 | J35: =AT124 -> 0 | K35: =AU124 -> 0 | L35: =AV124 -> 0 | M35: =AW124 -> 0 | ... AI35: =BS124 -> 0 | BV35: Ecatepec | BX35: =DE124 -> 0 | BY35: =DF124 -> 0 | BZ35: =DG124 -> 0 | CA35: =DH124 -> 0 | CB35: =DI124 -> 0 | CC35: =DJ124 -> 0 | CD35: =DK124 -> 0 | CE35: =DL124 -> 0 | ... DA35: =EH124 -> 0 | EJ35: Ecatepec | EK35: =EK139 -> 0 | EL35: =EL139 -> 0 | EM35: =EM139 -> 0 | EN35: =EN139 -> 0 | EO35: =EO139 -> 0 | EP35: =EP139 -> 0 | EQ35: =EQ139 -> 0 | ER35: =ER139 -> 0 | ... FN35: =FN139 -> 0
A36: Guadalajara | C36: =AM146 -> 0 | D36: =AN146 -> 0 | E36: =D36/C36 -> #DIV/0! | F36: =AP146 -> 0 | G36: =AQ146 -> 0 | H36: =AR146 -> 0 | I36: =AS146 -> 0 | J36: =AT146 -> 0 | K36: =AU146 -> 0 | L36: =AV146 -> 0 | M36: =AW146 -> 0 | ... AI36: =BS146 -> 0 | BV36: Guadalajara | BX36: =DE146 -> 0 | BY36: =DF146 -> 0 | BZ36: =DG146 -> 0 | CA36: =DH146 -> 0 | CB36: =DI146 -> 0 | CC36: =DJ146 -> 0 | CD36: =DK146 -> 0 | CE36: =DL146 -> 0 | ... DA36: =EH146 -> 0 | EJ36: Guadalajara | EK36: =EK161 -> 0 | EL36: =EL161 -> 0 | EM36: =EM161 -> 0 | EN36: =EN161 -> 0 | EO36: =EO161 -> 0 | EP36: =EP161 -> 0 | EQ36: =EQ161 -> 0 | ER36: =ER161 -> 0 | ... FN36: =FN161 -> 0
A37: Ixtapaluca | C37: =AM168 -> 0 | D37: =AN168 -> 0 | E37: =D37/C37 -> #DIV/0! | F37: =AP168 -> 0 | G37: =AQ168 -> 0 | H37: =AR168 -> 0 | I37: =AS168 -> 0 | J37: =AT168 -> 0 | K37: =AU168 -> 0 | L37: =AV168 -> 0 | M37: =AW168 -> 0 | ... AI37: =BS168 -> 0 | BV37: Ixtapaluca | BX37: =DE168 -> 0 | BY37: =DF168 -> 0 | BZ37: =DG168 -> 0 | CA37: =DH168 -> 0 | CB37: =DI168 -> 0 | CC37: =DJ168 -> 0 | CD37: =DK168 -> 0 | CE37: =DL168 -> 0 | ... DA37: =EH168 -> 0 | EJ37: Ixtapaluca | EK37: =EK183 -> 0 | EL37: =EL183 -> 0 | EM37: =EM183 -> 0 | EN37: =EN183 -> 0 | EO37: =EO183 -> 0 | EP37: =EP183 -> 0 | EQ37: =EQ183 -> 0 | ER37: =ER183 -> 0 | ... FN37: =FN183 -> 0
A38: Iztapalapa | C38: =AM190 -> 0 | D38: =AN190 -> 0 | E38: =D38/C38 -> #DIV/0! | F38: =AP190 -> 0 | G38: =AQ190 -> 0 | H38: =AR190 -> 0 | I38: =AS190 -> 0 | J38: =AT190 -> 0 | K38: =AU190 -> 0 | L38: =AV190 -> 0 | M38: =AW190 -> 0 | ... AI38: =BS190 -> 0 | BV38: Iztapalapa | BX38: =DE190 -> 0 | BY38: =DF190 -> 0 | BZ38: =DG190 -> 0 | CA38: =DH190 -> 0 | CB38: =DI190 -> 0 | CC38: =DJ190 -> 0 | CD38: =DK190 -> 0 | CE38: =DL190 -> 0 | ... DA38: =EH190 -> 0 | EJ38: Iztapalapa | EK38: =EK205 -> 0 | EL38: =EL205 -> 0 | EM38: =EM205 -> 0 | EN38: =EN205 -> 0 | EO38: =EO205 -> 0 | EP38: =EP205 -> 0 | EQ38: =EQ205 -> 0 | ER38: =ER205 -> 0 | ... FN38: =FN205 -> 0
A39: León | C39: =AM212 -> 0 | D39: =AN212 -> 0 | E39: =D39/C39 -> #DIV/0! | F39: =AP212 -> 0 | G39: =AQ212 -> 0 | H39: =AR212 -> 0 | I39: =AS212 -> 0 | J39: =AT212 -> 0 | K39: =AU212 -> 0 | L39: =AV212 -> 0 | M39: =AW212 -> 0 | ... AI39: =BS212 -> 0 | BV39: León | BX39: =DE212 -> 0 | BY39: =DF212 -> 0 | BZ39: =DG212 -> 0 | CA39: =DH212 -> 0 | CB39: =DI212 -> 0 | CC39: =DJ212 -> 0 | CD39: =DK212 -> 0 | CE39: =DL212 -> 0 | ... DA39: =EH212 -> 0 | EJ39: León | EK39: =EK227 -> 0 | EL39: =EL227 -> 0 | EM39: =EM227 -> 0 | EN39: =EN227 -> 0 | EO39: =EO227 -> 0 | EP39: =EP227 -> 0 | EQ39: =EQ227 -> 0 | ER39: =ER227 -> 0 | ... FN39: =FN227 -> 0
A40: Miravalle | C40: =AM234 -> 0 | D40: =AN234 -> 0 | E40: =D40/C40 -> #DIV/0! | F40: =AP234 -> 0 | G40: =AQ234 -> 0 | H40: =AR234 -> 0 | I40: =AS234 -> 0 | J40: =AT234 -> 0 | K40: =AU234 -> 0 | L40: =AV234 -> 0 | M40: =AW234 -> 0 | ... AI40: =BS234 -> 0 | BV40: Miravalle | BX40: =DE234 -> 0 | BY40: =DF234 -> 0 | BZ40: =DG234 -> 0 | CA40: =DH234 -> 0 | CB40: =DI234 -> 0 | CC40: =DJ234 -> 0 | CD40: =DK234 -> 0 | CE40: =DL234 -> 0 | ... DA40: =EH234 -> 0 | EJ40: Miravalle | EK40: =EK249 -> 0 | EL40: =EL249 -> 0 | EM40: =EM249 -> 0 | EN40: =EN249 -> 0 | EO40: =EO249 -> 0 | EP40: =EP249 -> 0 | EQ40: =EQ249 -> 0 | ER40: =ER249 -> 0 | ... FN40: =FN249 -> 0
A41: Naucalpan | C41: =AM256 -> 0 | D41: =AN256 -> 0 | E41: =D41/C41 -> #DIV/0! | F41: =AP256 -> 0 | G41: =AQ256 -> 0 | H41: =AR256 -> 0 | I41: =AS256 -> 0 | J41: =AT256 -> 0 | K41: =AU256 -> 0 | L41: =AV256 -> 0 | M41: =AW256 -> 0 | ... AI41: =BS256 -> 0 | BV41: Naucalpan | BX41: =DE256 -> 0 | BY41: =DF256 -> 0 | BZ41: =DG256 -> 0 | CA41: =DH256 -> 0 | CB41: =DI256 -> 0 | CC41: =DJ256 -> 0 | CD41: =DK256 -> 0 | CE41: =DL256 -> 0 | ... DA41: =EH256 -> 0 | EJ41: Naucalpan | EK41: =EK271 -> 0 | EL41: =EL271 -> 0 | EM41: =EM271 -> 0 | EN41: =EN271 -> 0 | EO41: =EO271 -> 0 | EP41: =EP271 -> 0 | EQ41: =EQ271 -> 0 | ER41: =ER271 -> 0 | ... FN41: =FN271 -> 0
A42: Olivar del Conde | C42: =AM278 -> 0 | D42: =AN278 -> 0 | E42: =D42/C42 -> #DIV/0! | F42: =AP278 -> 0 | G42: =AQ278 -> 0 | H42: =AR278 -> 0 | I42: =AS278 -> 0 | J42: =AT278 -> 0 | K42: =AU278 -> 0 | L42: =AV278 -> 0 | M42: =AW278 -> 0 | ... AI42: =BS278 -> 0 | BV42: Olivar del Conde | BX42: =DE278 -> 0 | BY42: =DF278 -> 0 | BZ42: =DG278 -> 0 | CA42: =DH278 -> 0 | CB42: =DI278 -> 0 | CC42: =DJ278 -> 0 | CD42: =DK278 -> 0 | CE42: =DL278 -> 0 | ... DA42: =EH278 -> 0 | EJ42: Olivar del Conde | EK42: =EK293 -> 0 | EL42: =EL293 -> 0 | EM42: =EM293 -> 0 | EN42: =EN293 -> 0 | EO42: =EO293 -> 0 | EP42: =EP293 -> 0 | EQ42: =EQ293 -> 0 | ER42: =ER293 -> 0 | ... FN42: =FN293 -> 0
A43: Puebla | C43: =AM300 -> 0 | D43: =AN300 -> 0 | E43: =D43/C43 -> #DIV/0! | F43: =AP300 -> 0 | G43: =AQ300 -> 0 | H43: =AR300 -> 0 | I43: =AS300 -> 0 | J43: =AT300 -> 0 | K43: =AU300 -> 0 | L43: =AV300 -> 0 | M43: =AW300 -> 0 | ... AI43: =BS300 -> 0 | BV43: Puebla | BX43: =DE300 -> 0 | BY43: =DF300 -> 0 | BZ43: =DG300 -> 0 | CA43: =DH300 -> 0 | CB43: =DI300 -> 0 | CC43: =DJ300 -> 0 | CD43: =DK300 -> 0 | CE43: =DL300 -> 0 | ... DA43: =EH300 -> 0 | EJ43: Puebla | EK43: =EK315 -> 0 | EL43: =EL315 -> 0 | EM43: =EM315 -> 0 | EN43: =EN315 -> 0 | EO43: =EO315 -> 0 | EP43: =EP315 -> 0 | EQ43: =EQ315 -> 0 | ER43: =ER315 -> 0 | ... FN43: =FN315 -> 0
A44: Queretaro | C44: =AM322 -> 0 | D44: =AN322 -> 0 | E44: =D44/C44 -> #DIV/0! | F44: =AP322 -> 0 | G44: =AQ322 -> 0 | H44: =AR322 -> 0 | I44: =AS322 -> 0 | J44: =AT322 -> 0 | K44: =AU322 -> 0 | L44: =AV322 -> 0 | M44: =AW322 -> 0 | ... AI44: =BS322 -> 0 | BV44: Queretaro | BX44: =DE322 -> 0 | BY44: =DF322 -> 0 | BZ44: =DG322 -> 0 | CA44: =DH322 -> 0 | CB44: =DI322 -> 0 | CC44: =DJ322 -> 0 | CD44: =DK322 -> 0 | CE44: =DL322 -> 0 | ... DA44: =EH322 -> 0 | EJ44: Queretaro | EK44: =EK337 -> 0 | EL44: =EL337 -> 0 | EM44: =EM337 -> 0 | EN44: =EN337 -> 0 | EO44: =EO337 -> 0 | EP44: =EP337 -> 0 | EQ44: =EQ337 -> 0 | ER44: =ER337 -> 0 | ... FN44: =FN337 -> 0
A45: Puebla Sur | C45: =AM410 -> 0 | D45: =AN410 -> 0 | E45: =D45/C45 -> #DIV/0! | F45: =AP410 -> 0 | G45: =AQ410 -> 0 | H45: =AR410 -> 0 | I45: =AS410 -> 0 | J45: =AT410 -> 0 | K45: =AU410 -> 0 | L45: =AV410 -> 0 | M45: =AW410 -> 0 | ... AI45: =BS410 -> 0 | BV45: Tijuna | BX45: =DE410 -> 0 | BY45: =DF410 -> 0 | BZ45: =DG410 -> 0 | CA45: =DH410 -> 0 | CB45: =DI410 -> 0 | CC45: =DJ410 -> 0 | CD45: =DK410 -> 0 | CE45: =DL410 -> 0 | ... DA45: =EH410 -> 0 | EJ45: Tijuna | EK45: =EK425 -> 0 | EL45: =EL425 -> 0 | EM45: =EM425 -> 0 | EN45: =EN425 -> 0 | EO45: =EO425 -> 0 | EP45: =EP425 -> 0 | EQ45: =EQ425 -> 0 | ER45: =ER425 -> 0 | ... FN45: =FN425 -> 0
A46: Toluca | C46: =AM344 -> 0 | D46: =AN344 -> 0 | E46: =D46/C46 -> #DIV/0! | F46: =AP344 -> 0 | G46: =AQ344 -> 0 | H46: =AR344 -> 0 | I46: =AS344 -> 0 | J46: =AT344 -> 0 | K46: =AU344 -> 0 | L46: =AV344 -> 0 | M46: =AW344 -> 0 | ... AI46: =BS344 -> 0 | BV46: Toluca | BX46: =DE344 -> 0 | BY46: =DF344 -> 0 | BZ46: =DG344 -> 0 | CA46: =DH344 -> 0 | CB46: =DI344 -> 0 | CC46: =DJ344 -> 0 | CD46: =DK344 -> 0 | CE46: =DL344 -> 0 | ... DA46: =EH344 -> 0 | EJ46: Toluca | EK46: =EK359 -> 0 | EL46: =EL359 -> 0 | EM46: =EM359 -> 0 | EN46: =EN359 -> 0 | EO46: =EO359 -> 0 | EP46: =EP359 -> 0 | EQ46: =EQ359 -> 0 | ER46: =ER359 -> 0 | ... FN46: =FN359 -> 0
A47: Vallejo | C47: =AM366 -> 0 | D47: =AN366 -> 0 | E47: =D47/C47 -> #DIV/0! | F47: =AP366 -> 0 | G47: =AQ366 -> 0 | H47: =AR366 -> 0 | I47: =AS366 -> 0 | J47: =AT366 -> 0 | K47: =AU366 -> 0 | L47: =AV366 -> 0 | M47: =AW366 -> 0 | ... AI47: =BS366 -> 0 | BV47: Vallejo | BX47: =DE366 -> 0 | BY47: =DF366 -> 0 | BZ47: =DG366 -> 0 | CA47: =DH366 -> 0 | CB47: =DI366 -> 0 | CC47: =DJ366 -> 0 | CD47: =DK366 -> 0 | CE47: =DL366 -> 0 | ... DA47: =EH366 -> 0 | EJ47: Vallejo | EK47: =EK381 -> 0 | EL47: =EL381 -> 0 | EM47: =EM381 -> 0 | EN47: =EN381 -> 0 | EO47: =EO381 -> 0 | EP47: =EP381 -> 0 | EQ47: =EQ381 -> 0 | ER47: =ER381 -> 0 | ... FN47: =FN381 -> 0
A48: Veracruz | C48: =AM388 -> 0 | D48: =AN388 -> 0 | E48: =D48/C48 -> #DIV/0! | F48: =AP388 -> 0 | G48: =AQ388 -> 0 | H48: =AR388 -> 0 | I48: =AS388 -> 0 | J48: =AT388 -> 0 | K48: =AU388 -> 0 | L48: =AV388 -> 0 | M48: =AW388 -> 0 | ... AI48: =BS388 -> 0 | BV48: Veracruz | BX48: =DE388 -> 0 | BY48: =DF388 -> 0 | BZ48: =DG388 -> 0 | CA48: =DH388 -> 0 | CB48: =DI388 -> 0 | CC48: =DJ388 -> 0 | CD48: =DK388 -> 0 | CE48: =DL388 -> 0 | ... DA48: =EH388 -> 0 | EJ48: Veracruz | EK48: =EK403 -> 0 | EL48: =EL403 -> 0 | EM48: =EM403 -> 0 | EN48: =EN403 -> 0 | EO48: =EO403 -> 0 | EP48: =EP403 -> 0 | EQ48: =EQ403 -> 0 | ER48: =ER403 -> 0 | ... FN48: =FN403 -> 0
B49: Total | C49: =SUM(C32:C48) -> 0 | D49: =SUM(D32:D48) -> 0 | E49: =D49/C49 -> #DIV/0! | F49: =SUM(F32:F48) -> 0 | H49: =SUM(H32:H48) -> 0 | I49: =SUM(I32:I48) -> 0 | J49: =SUM(J32:J48) -> 0 | K49: =SUM(K32:K48) -> 0 | L49: =SUM(L32:L48) -> 0 | N49: =SUM(N32:N48) -> 0 | O49: =SUM(O32:O48) -> 0 | P49: =SUM(P32:P48) -> 0 | T49: =SUM(F49:P49) -> 0 | U49: =SUM(U32:U48) -> 0 | V49: =SUM(V32:V48) -> 0 | W49: =SUM(W32:W48) -> 0 | X49: =SUM(X32:X48) -> 0 | Y49: =SUM(Y32:Y48) -> 0 | Z49: =SUM(Z32:Z48) -> 0 | AA49: =SUM(AA32:AA48) -> 0 | AB49: =SUM(AB32:AB48) -> 0 | ... AI49: =SUM(AI32:AI48) -> 0 | BW49: Total | BX49: =SUM(BX32:BX48) -> 0 | BZ49: =SUM(BZ32:BZ48) -> 0 | CA49: =SUM(CA32:CA48) -> 0 | CB49: =SUM(CB32:CB48) -> 0 | CC49: =SUM(CC32:CC48) -> 0 | CD49: =SUM(CD32:CD48) -> 0 | CF49: =SUM(CF32:CF48) -> 0 | CG49: =SUM(CG32:CG48) -> 0 | CH49: =SUM(CH32:CH48) -> 0 | CL49: =SUM(BX49:CH49) -> 0 | CM49: =SUM(CM32:CM47) -> 0 | CN49: =SUM(CN32:CN47) -> 0 | CO49: =SUM(CO32:CO47) -> 0 | CP49: =SUM(CP32:CP47) -> 0 | CQ49: =SUM(CQ32:CQ47) -> 0 | CR49: =SUM(CR32:CR47) -> 0 | CS49: =SUM(CS32:CS47) -> 0 | CT49: =SUM(CT32:CT47) -> 0 | ... DA49: =SUM(DA32:DA47) -> 0
BX50: =SUM(CL32:CL47) -> 0
A51: Concentrado de Dictamen de Auditoria de Dummy | BV51: Concentrado de Dictamen de Auditoria de Dummy
F54: Causas de Negado | U54: Incidencias de Auditoria | AJ54: =BT309 -> 0 | BX54: Causas de Negado | CM54: Incidencias de Auditoria | EK54: $ negados | FU54: Incidencias administrativas
A55: Aguascalientes | B55: Responsable De Catalogo | C55: Tallas por pasillo | D55: Tallas por modelo | E55: % de Cobertura de auditoria | F55: Frenteos | G55: Ubicación Revuelta | H55: Bodega Venta (Sin marcar) | I55: Bodega Tapanco | J55: Doble Ubicación | K55: Excedente | L55: Origen | M55: Cambios/Probadores | N55: Negados Sin Recuperar | O55: Exhibición | P55: Bodega Aclaración | Q55: Aduanas | R55: Golden o apartados | S55: Control de calidad | T55: Costo por pasillo | U55: Sin Exhibición | V55: Exhibición fuera de Política | W55: Modelos revuelto | X55: Modelos mal entallados | Y55: Modelos con error de ubicación | Z55: Curva con diferencia en frentes | AA55: Curva con diferencia en fondos | AB55: Curva con diferencia en altura | AC55: Curvas vencidas | AD55: Curvas que no coincide Price Soft vs Piso de Venta | AE55: Curvas faltantes | AF55: Cenefas faltantes | AG55: Cenefas de precio Promoción faltantes | AH55: Cartas disculpa / destallados faltantes | AI55: modelos que no cadran con planograma | AJ55: Resultado de Check List | AK55: Resultado de banderazo surtido | AM55: Tallas por pasillo | AN55: Tallas por modelo | AO55: % de Cobertura de auditoria | AP55: Frenteos | AQ55: Ubicación Revuelta | AR55: Bodega Venta (Sin marcar) | AS55: Bodega Tapanco | AT55: Doble Ubicación | AU55: Excedente | AV55: Origen | AW55: Cambios/Probadores | AX55: Negados Sin Recuperar | AY55: Exhibición | AZ55: Bodega Aclaración | BA55: Aduanas | BB55: Golden o apartados | BC55: Control de calidad | BD55: Costo por pasillo | BE55: Sin Exhibición | BF55: Exhibición fuera de Política | BG55: Modelos revuelto | BH55: Modelos mal entallados | BI55: Modelos con error de ubicación | BJ55: Curva con diferencia en frentes | BK55: Curva con diferencia en fondos | BL55: Curva con diferencia en altura | BM55: Curvas vencidas | BN55: Curvas que no coincide Price Soft vs Piso de Venta | BO55: Curvas faltantes | BP55: Cenefas faltantes | BQ55: Cenefas de precio Promoción faltantes | BR55: Cartas disculpa / destallados faltantes | BS55: Fechas de llegada faltantes | BT55: Resultado de Check List | BU55: Resultado de banderazo surtido | BV55: Aguascalientes | BW55: Responsable de Catalogo | BX55: Frenteos | BY55: Ubicación Revuelta | BZ55: Bodega Venta (Sin marcar) | CA55: Bodega Tapanco | CB55: Doble Ubicación | CC55: Excedente | CD55: Origen | CE55: Cambios/Probadores | CF55: Negados Sin Recuperar | CG55: Exhibición | CH55: Bodega Aclaración | CI55: Aduanas | CJ55: Golden o apartados | CK55: Control de calidad | CL55: Costo por pasillo | CM55: Sin Exhibición | CN55: Exhibición fuera de Política | CO55: Modelos revuelto | CP55: Modelos mal entallados | CQ55: Modelos con error de ubicación | CR55: Curva con diferencia en frentes | CS55: Curva con diferencia en fondos | CT55: Curva con diferencia en altura | CU55: Curvas vencidas | CV55: Curvas que no coincide Price Soft vs Piso de Venta | CW55: Curvas faltantes | CX55: Cenefas faltantes | CY55: Cenefas de precio Promoción faltantes | CZ55: Cartas disculpa / destallados faltantes | DA55: Fechas de llegada faltantes | DB55: Resultado de Check List | DE55: Frenteos | DF55: Ubicación Revuelta | DG55: Bodega Venta (Sin marcar) | DH55: Bodega Tapanco | DI55: Doble Ubicación | DJ55: Excedente | DK55: Origen | DL55: Cambios/Probadores | DM55: Negados Sin Recuperar | DN55: Exhibición | DO55: Bodega Aclaración | DP55: Aduanas | DQ55: Golden o apartados | DR55: Control de calidad | DS55: Costo por pasillo | DT55: Sin Exhibición | DU55: Exhibición fuera de Política | DV55: Modelos revuelto | DW55: Modelos mal entallados | DX55: Modelos con error de ubicación | DY55: Curva con diferencia en frentes | DZ55: Curva con diferencia en fondos | EA55: Curva con diferencia en altura | EB55: Curvas vencidas | EC55: Curvas que no coincide Price Soft vs Piso de Venta | ED55: Curvas faltantes | EE55: Cenefas faltantes | EF55: Cenefas de precio Promoción faltantes | EG55: Cartas disculpa / destallados faltantes | EH55: Fechas de llegada faltantes | EK55: Frenteos | EL55: Ubicación Revuelta | EM55: Bodega Venta (Sin marcar) | EN55: Bodega Tapanco | EO55: Doble Ubicación | EP55: Excedente | EQ55: Origen | ER55: Cambios/Probadores | ES55: Negados Sin Recuperar | ET55: Exhibición | EU55: Bodega Aclaración | EV55: Aduanas | EW55: Golden o apartados | EX55: Control de calidad | EZ55: Frenteos | FA55: Ubicación Revuelta | FB55: Bodega Venta (Sin marcar) | FC55: Bodega Tapanco | FD55: Doble Ubicación | FE55: Excedente | FF55: Origen | FG55: Cambios/Probadores | FH55: Negados Sin Recuperar | FI55: Exhibición | FJ55: Bodega Aclaración | FK55: Aduanas | FL55: Golden o apartados | FM55: Control de calidad | FU55: Sin Exhibición | FV55: Exhibición fuera de Política | FW55: Modelos revuelto | FX55: Modelos mal entallados | FY55: Modelos con error de ubicación | FZ55: Curva con diferencia en frentes | GA55: Curva con diferencia en fondos | GB55: Curva con diferencia en altura | GC55: Curvas vencidas | GD55: Curvas que no coincide Price Soft vs Piso de Venta | GE55: Curvas faltantes | GF55: Cenefas faltantes | GG55: Cenefas de precio Promoción faltantes | GH55: Cartas disculpa / destallados faltantes | GI55: modelos que no cadran con planograma | GK55: Sin Exhibición | GL55: Exhibición fuera de Política | GM55: Modelos revuelto | GN55: Modelos mal entallados | GO55: Modelos con error de ubicación | GP55: Curva con diferencia en frentes | GQ55: Curva con diferencia en fondos | GR55: Curva con diferencia en altura | GS55: Curvas vencidas | GT55: Curvas que no coincide Price Soft vs Piso de Venta | GU55: Curvas faltantes | GV55: Cenefas faltantes | GW55: Cenefas de precio Promoción faltantes | GX55: Cartas disculpa / destallados faltantes | GY55: modelos que no cadran con planograma
AM56: =SUM(C56,C57,C58,C59,C60,C61,C62,C63,C64,C67,C68,C70,C71) -> 0 | AN56: =SUM(D56,D57,D58,D59,D60,D61,D62,D63,D64,D67,D68,D70,D71) -> 0 | AO56: =IF(AN56=0,"",AN56/AM56) | AP56: =SUM(F56,F57,F58,F59,F60,F61,F62,F63,F64,F67,F68,F70,F71) -> 0 | AQ56: =SUM(G56,G57,G58,G59,G60,G61,G62,G63,G64,G67,G68,G70,G71) -> 0 | AR56: =SUM(H56,H57,H58,H59,H60,H61,H62,H63,H64,H67,H68,H70,H71) -> 0 | AS56: =SUM(I56,I57,I58,I59,I60,I61,I62,I63,I64,I67,I68,I70,I71) -> 0 | AT56: =SUM(J56,J57,J58,J59,J60,J61,J62,J63,J64,J67,J68,J70,J71) -> 0 | AU56: =SUM(K56,K57,K58,K59,K60,K61,K62,K63,K64,K67,K68,K70,K71) -> 0 | AV56: =SUM(L56,L57,L58,L59,L60,L61,L62,L63,L64,L67,L68,L70,L71) -> 0 | AW56: =SUM(M56,M57,M58,M59,M60,M61,M62,M63,M64,M67,M68,M70,M71) -> 0 | ... BU56: =SUM(AK56,AK57,AK58,AK59,AK60,AK61,AK62,AK63,AK64,AK67,AK68,AK70,AK71) -> 0 | DE56: =SUM(BX56,BX57,BX58,BX59,BX60,BX61,BX62,BX63,BX64,BX67,BX68,BX70,BX71) -> 0 | DF56: =SUM(BY56,BY57,BY58,BY59,BY60,BY61,BY62,BY63,BY64,BY67,BY68,BY70,BY71) -> 0 | DG56: =SUM(BZ56,BZ57,BZ58,BZ59,BZ60,BZ61,BZ62,BZ63,BZ64,BZ67,BZ68,BZ70,BZ71) -> 0 | DH56: =SUM(CA56,CA57,CA58,CA59,CA60,CA61,CA62,CA63,CA64,CA67,CA68,CA70,CA71) -> 0 | DI56: =SUM(CB56,CB57,CB58,CB59,CB60,CB61,CB62,CB63,CB64,CB67,CB68,CB70,CB71) -> 0 | DJ56: =SUM(CC56,CC57,CC58,CC59,CC60,CC61,CC62,CC63,CC64,CC67,CC68,CC70,CC71) -> 0 | DK56: =SUM(CD56,CD57,CD58,CD59,CD60,CD61,CD62,CD63,CD64,CD67,CD68,CD70,CD71) -> 0 | DL56: =SUM(CE56,CE57,CE58,CE59,CE60,CE61,CE62,CE63,CE64,CE67,CE68,CE70,CE71) -> 0 | ... EH56: =SUM(DA56,DA57,DA58,DA59,DA60,DA61,DA62,DA63,DA64,DA67,DA68,DA70,DA71) -> 0 | EI56: BOTAS | EJ56: 521 | EK56: =$EJ56*F56 -> 0 | EL56: =$EJ56*G56 -> 0 | EM56: =$EJ56*H56 -> 0 | EN56: =$EJ56*I56 -> 0 | EO56: =$EJ56*J56 -> 0 | EP56: =$EJ56*K56 -> 0 | EQ56: =$EJ56*L56 -> 0 | ER56: =$EJ56*M56 -> 0 | ES56: =EJ56*N56 -> 0 | ET56: =EJ56*O56 -> 0 | EU56: =$EJ56*P56 -> 0 | EV56: =$EJ56*Q56 -> 0 | EW56: =$EJ56*R56 -> 0 | EX56: =$EJ56*S56 -> 0 | EY56: =SUM(EK56:EX56) -> 0 | EZ56: =BX56*$EJ56 -> 0 | FA56: =BY56*$EJ56 -> 0 | FB56: =BZ56*$EJ56 -> 0 | FC56: =CA56*$EJ56 -> 0 | FD56: =CB56*$EJ56 -> 0 | FE56: =CC56*$EJ56 -> 0 | FF56: =CD56*$EJ56 -> 0 | FG56: =CE56*$EJ56 -> 0 | ... FM56: =CK56*$EJ56 -> 0 | FN56: =SUM(EZ56:FM56) -> 0 | FO56: =SUM(EZ56:FJ56) -> 0 | FS56: BOTAS | FU56: =U56 -> 0 | FV56: =V56 -> 0 | FW56: =W56 -> 0 | FX56: =X56 -> 0 | FY56: =Y56 -> 0 | FZ56: =Z56 -> 0 | GA56: =AA56 -> 0 | GB56: =AB56 -> 0 | ... GH56: =AH56 -> 0 | GI56: 0 | GJ56: =SUM(FU56:GI56) -> 0 | GK56: =CM56 -> 0 | GL56: =CN56 -> 0 | GM56: =CO56 -> 0 | GN56: =CP56 -> 0 | GO56: =CQ56 -> 0 | GP56: =CR56 -> 0 | GQ56: =CS56 -> 0 | GR56: =CT56 -> 0 | ... GX56: =CZ56 -> 0 | GY56: 0 | GZ56: =SUM(GK56:GY56) -> 0 | HA56: =SUM(GK56:GY56) -> 0
AO57: =IF(AN57=0,"",AN57/AM57) | EI57: URBANO | EJ57: 540 | EK57: =$EJ57*F57 -> 0 | EL57: =$EJ57*G57 -> 0 | EM57: =$EJ57*H57 -> 0 | EN57: =$EJ57*I57 -> 0 | EO57: =$EJ57*J57 -> 0 | EP57: =$EJ57*K57 -> 0 | EQ57: =$EJ57*L57 -> 0 | ER57: =$EJ57*M57 -> 0 | ES57: =EJ57*N57 -> 0 | ET57: =EJ57*O57 -> 0 | EU57: =$EJ57*P57 -> 0 | EV57: =$EJ57*Q57 -> 0 | EW57: =$EJ57*R57 -> 0 | EX57: =$EJ57*S57 -> 0 | EY57: =SUM(EK57:EX57) -> 0 | EZ57: =BX57*$EJ57 -> 0 | FA57: =BY57*$EJ57 -> 0 | FB57: =BZ57*$EJ57 -> 0 | FC57: =CA57*$EJ57 -> 0 | FD57: =CB57*$EJ57 -> 0 | FE57: =CC57*$EJ57 -> 0 | FF57: =CD57*$EJ57 -> 0 | FG57: =CE57*$EJ57 -> 0 | ... FM57: =CK57*$EJ57 -> 0 | FN57: =SUM(EZ57:FM57) -> 0 | FO57: =SUM(EZ57:FJ57) -> 0 | FS57: URBANO | FU57: =U57 -> 0 | FV57: =V57 -> 0 | FW57: =W57 -> 0 | FX57: =X57 -> 0 | FY57: =Y57 -> 0 | FZ57: =Z57 -> 0 | GA57: =AA57 -> 0 | GB57: =AB57 -> 0 | ... GH57: =AH57 -> 0 | GI57: 0 | GJ57: =SUM(FU57:GI57) -> 0 | GK57: =CM57 -> 0 | GL57: =CN57 -> 0 | GM57: =CO57 -> 0 | GN57: =CP57 -> 0 | GO57: =CQ57 -> 0 | GP57: =CR57 -> 0 | GQ57: =CS57 -> 0 | GR57: =CT57 -> 0 | ... GX57: =CZ57 -> 0 | GY57: 0 | GZ57: =SUM(GK57:GY57) -> 0 | HA57: =SUM(GK57:GY57) -> 0
AL58: % de tallas negadas | AM58: =SUM(C65,C66,C69) -> 0 | AN58: =SUM(D65,D66,D69) -> 0 | AO58: =IF(AN58=0,"",AN58/AM58) | AP58: =SUM(F65,F66,F69) -> 0 | AQ58: =SUM(G65,G66,G69) -> 0 | AR58: =SUM(H65,H66,H69) -> 0 | AS58: =SUM(I65,I66,I69) -> 0 | AT58: =SUM(J65,J66,J69) -> 0 | AU58: =SUM(K65,K66,K69) -> 0 | AV58: =SUM(L65,L66,L69) -> 0 | AW58: =SUM(M65,M66,M69) -> 0 | ... BS58: =SUM(AI65,AI66,AI69) -> 0 | BT58: =AVERAGE(AJ65,AJ66,AJ69) -> #DIV/0! | DC58: % de tallas recuperadas | DE58: =SUM(BX65,BX66,BX69) -> 0 | DF58: =SUM(BY65,BY66,BY69) -> 0 | DG58: =SUM(BZ65,BZ66,BZ69) -> 0 | DH58: =SUM(CA65,CA66,CA69) -> 0 | DI58: =SUM(CB65,CB66,CB69) -> 0 | DJ58: =SUM(CC65,CC66,CC69) -> 0 | DK58: =SUM(CD65,CD66,CD69) -> 0 | DL58: =SUM(CE65,CE66,CE69) -> 0 | ... EH58: =SUM(DA65,DA66,DA69) -> 0 | EI58: ESCOLAR | EJ58: 441.24 | EK58: =$EJ58*F58 -> 0 | EL58: =$EJ58*G58 -> 0 | EM58: =$EJ58*H58 -> 0 | EN58: =$EJ58*I58 -> 0 | EO58: =$EJ58*J58 -> 0 | EP58: =$EJ58*K58 -> 0 | EQ58: =$EJ58*L58 -> 0 | ER58: =$EJ58*M58 -> 0 | ES58: =EJ58*N58 -> 0 | ET58: =EJ58*O58 -> 0 | EU58: =$EJ58*P58 -> 0 | EV58: =$EJ58*Q58 -> 0 | EW58: =$EJ58*R58 -> 0 | EX58: =$EJ58*S58 -> 0 | EY58: =SUM(EK58:EX58) -> 0 | EZ58: =BX58*$EJ58 -> 0 | FA58: =BY58*$EJ58 -> 0 | FB58: =BZ58*$EJ58 -> 0 | FC58: =CA58*$EJ58 -> 0 | FD58: =CB58*$EJ58 -> 0 | FE58: =CC58*$EJ58 -> 0 | FF58: =CD58*$EJ58 -> 0 | FG58: =CE58*$EJ58 -> 0 | ... FM58: =CK58*$EJ58 -> 0 | FN58: =SUM(EZ58:FM58) -> 0 | FO58: =SUM(EZ58:FJ58) -> 0 | FS58: ESCOLAR | FU58: =U58 -> 0 | FV58: =V58 -> 0 | FW58: =W58 -> 0 | FX58: =X58 -> 0 | FY58: =Y58 -> 0 | FZ58: =Z58 -> 0 | GA58: =AA58 -> 0 | GB58: =AB58 -> 0 | ... GH58: =AH58 -> 0 | GI58: 0 | GJ58: =SUM(FU58:GI58) -> 0 | GK58: =CM58 -> 0 | GL58: =CN58 -> 0 | GM58: =CO58 -> 0 | GN58: =CP58 -> 0 | GO58: =CQ58 -> 0 | GP58: =CR58 -> 0 | GQ58: =CS58 -> 0 | GR58: =CT58 -> 0 | ... GX58: =CZ58 -> 0 | GY58: 0 | GZ58: =SUM(GK58:GY58) -> 0 | HA58: =SUM(GK58:GY58) -> 0
EI59: SANDALIAS | EJ59: 294.47 | EK59: =$EJ59*F59 -> 0 | EL59: =$EJ59*G59 -> 0 | EM59: =$EJ59*H59 -> 0 | EN59: =$EJ59*I59 -> 0 | EO59: =$EJ59*J59 -> 0 | EP59: =$EJ59*K59 -> 0 | EQ59: =$EJ59*L59 -> 0 | ER59: =$EJ59*M59 -> 0 | ES59: =EJ59*N59 -> 0 | ET59: =EJ59*O59 -> 0 | EU59: =$EJ59*P59 -> 0 | EV59: =$EJ59*Q59 -> 0 | EW59: =$EJ59*R59 -> 0 | EX59: =$EJ59*S59 -> 0 | EY59: =SUM(EK59:EX59) -> 0 | EZ59: =BX59*$EJ59 -> 0 | FA59: =BY59*$EJ59 -> 0 | FB59: =BZ59*$EJ59 -> 0 | FC59: =CA59*$EJ59 -> 0 | FD59: =CB59*$EJ59 -> 0 | FE59: =CC59*$EJ59 -> 0 | FF59: =CD59*$EJ59 -> 0 | FG59: =CE59*$EJ59 -> 0 | ... FM59: =CK59*$EJ59 -> 0 | FN59: =SUM(EZ59:FM59) -> 0 | FO59: =SUM(EZ59:FJ59) -> 0 | FS59: SANDALIAS | FU59: =U59 -> 0 | FV59: =V59 -> 0 | FW59: =W59 -> 0 | FX59: =X59 -> 0 | FY59: =Y59 -> 0 | FZ59: =Z59 -> 0 | GA59: =AA59 -> 0 | GB59: =AB59 -> 0 | ... GH59: =AH59 -> 0 | GI59: 0 | GJ59: =SUM(FU59:GI59) -> 0 | GK59: =CM59 -> 0 | GL59: =CN59 -> 0 | GM59: =CO59 -> 0 | GN59: =CP59 -> 0 | GO59: =CQ59 -> 0 | GP59: =CR59 -> 0 | GQ59: =CS59 -> 0 | GR59: =CT59 -> 0 | ... GX59: =CZ59 -> 0 | GY59: 0 | GZ59: =SUM(GK59:GY59) -> 0 | HA59: =SUM(GK59:GY59) -> 0
AL60: =T72/D72 -> #DIV/0! | DC60: =CL72/T72 -> #DIV/0! | EI60: CONFORT | EJ60: 422 | EK60: =$EJ60*F60 -> 0 | EL60: =$EJ60*G60 -> 0 | EM60: =$EJ60*H60 -> 0 | EN60: =$EJ60*I60 -> 0 | EO60: =$EJ60*J60 -> 0 | EP60: =$EJ60*K60 -> 0 | EQ60: =$EJ60*L60 -> 0 | ER60: =$EJ60*M60 -> 0 | ES60: =EJ60*N60 -> 0 | ET60: =EJ60*O60 -> 0 | EU60: =$EJ60*P60 -> 0 | EV60: =$EJ60*Q60 -> 0 | EW60: =$EJ60*R60 -> 0 | EX60: =$EJ60*S60 -> 0 | EY60: =SUM(EK60:EX60) -> 0 | EZ60: =BX60*$EJ60 -> 0 | FA60: =BY60*$EJ60 -> 0 | FB60: =BZ60*$EJ60 -> 0 | FC60: =CA60*$EJ60 -> 0 | FD60: =CB60*$EJ60 -> 0 | FE60: =CC60*$EJ60 -> 0 | FF60: =CD60*$EJ60 -> 0 | FG60: =CE60*$EJ60 -> 0 | ... FM60: =CK60*$EJ60 -> 0 | FN60: =SUM(EZ60:FM60) -> 0 | FO60: =SUM(EZ60:FJ60) -> 0 | FS60: CONFORT | FU60: =U60 -> 0 | FV60: =V60 -> 0 | FW60: =W60 -> 0 | FX60: =X60 -> 0 | FY60: =Y60 -> 0 | FZ60: =Z60 -> 0 | GA60: =AA60 -> 0 | GB60: =AB60 -> 0 | ... GH60: =AH60 -> 0 | GI60: 0 | GJ60: =SUM(FU60:GI60) -> 0 | GK60: =CM60 -> 0 | GL60: =CN60 -> 0 | GM60: =CO60 -> 0 | GN60: =CP60 -> 0 | GO60: =CQ60 -> 0 | GP60: =CR60 -> 0 | GQ60: =CS60 -> 0 | GR60: =CT60 -> 0 | ... GX60: =CZ60 -> 0 | GY60: 0 | GZ60: =SUM(GK60:GY60) -> 0 | HA60: =SUM(GK60:GY60) -> 0
EI61: VESTIR CASUAL | EJ61: 416.19 | EK61: =$EJ61*F61 -> 0 | EL61: =$EJ61*G61 -> 0 | EM61: =$EJ61*H61 -> 0 | EN61: =$EJ61*I61 -> 0 | EO61: =$EJ61*J61 -> 0 | EP61: =$EJ61*K61 -> 0 | EQ61: =$EJ61*L61 -> 0 | ER61: =$EJ61*M61 -> 0 | ES61: =EJ61*N61 -> 0 | ET61: =EJ61*O61 -> 0 | EU61: =$EJ61*P61 -> 0 | EV61: =$EJ61*Q61 -> 0 | EW61: =$EJ61*R61 -> 0 | EX61: =$EJ61*S61 -> 0 | EY61: =SUM(EK61:EX61) -> 0 | EZ61: =BX61*$EJ61 -> 0 | FA61: =BY61*$EJ61 -> 0 | FB61: =BZ61*$EJ61 -> 0 | FC61: =CA61*$EJ61 -> 0 | FD61: =CB61*$EJ61 -> 0 | FE61: =CC61*$EJ61 -> 0 | FF61: =CD61*$EJ61 -> 0 | FG61: =CE61*$EJ61 -> 0 | ... FM61: =CK61*$EJ61 -> 0 | FN61: =SUM(EZ61:FM61) -> 0 | FO61: =SUM(EZ61:FJ61) -> 0 | FS61: VESTIR CASUAL | FU61: =U61 -> 0 | FV61: =V61 -> 0 | FW61: =W61 -> 0 | FX61: =X61 -> 0 | FY61: =Y61 -> 0 | FZ61: =Z61 -> 0 | GA61: =AA61 -> 0 | GB61: =AB61 -> 0 | ... GH61: =AH61 -> 0 | GI61: 0 | GJ61: =SUM(FU61:GI61) -> 0 | GK61: =CM61 -> 0 | GL61: =CN61 -> 0 | GM61: =CO61 -> 0 | GN61: =CP61 -> 0 | GO61: =CQ61 -> 0 | GP61: =CR61 -> 0 | GQ61: =CS61 -> 0 | GR61: =CT61 -> 0 | ... GX61: =CZ61 -> 0 | GY61: 0 | GZ61: =SUM(GK61:GY61) -> 0 | HA61: =SUM(GK61:GY61) -> 0
AL62: Diferencia Negado VS Recuperado | EI62: INFANTILES | EJ62: 375 | EK62: =$EJ62*F62 -> 0 | EL62: =$EJ62*G62 -> 0 | EM62: =$EJ62*H62 -> 0 | EN62: =$EJ62*I62 -> 0 | EO62: =$EJ62*J62 -> 0 | EP62: =$EJ62*K62 -> 0 | EQ62: =$EJ62*L62 -> 0 | ER62: =$EJ62*M62 -> 0 | ES62: =EJ62*N62 -> 0 | ET62: =EJ62*O62 -> 0 | EU62: =$EJ62*P62 -> 0 | EV62: =$EJ62*Q62 -> 0 | EW62: =$EJ62*R62 -> 0 | EX62: =$EJ62*S62 -> 0 | EY62: =SUM(EK62:EX62) -> 0 | EZ62: =BX62*$EJ62 -> 0 | FA62: =BY62*$EJ62 -> 0 | FB62: =BZ62*$EJ62 -> 0 | FC62: =CA62*$EJ62 -> 0 | FD62: =CB62*$EJ62 -> 0 | FE62: =CC62*$EJ62 -> 0 | FF62: =CD62*$EJ62 -> 0 | FG62: =CE62*$EJ62 -> 0 | ... FM62: =CK62*$EJ62 -> 0 | FN62: =SUM(EZ62:FM62) -> 0 | FO62: =SUM(EZ62:FJ62) -> 0 | FS62: INFANTILES | FU62: =U62 -> 0 | FV62: =V62 -> 0 | FW62: =W62 -> 0 | FX62: =X62 -> 0 | FY62: =Y62 -> 0 | FZ62: =Z62 -> 0 | GA62: =AA62 -> 0 | GB62: =AB62 -> 0 | ... GH62: =AH62 -> 0 | GI62: 0 | GJ62: =SUM(FU62:GI62) -> 0 | GK62: =CM62 -> 0 | GL62: =CN62 -> 0 | GM62: =CO62 -> 0 | GN62: =CP62 -> 0 | GO62: =CQ62 -> 0 | GP62: =CR62 -> 0 | GQ62: =CS62 -> 0 | GR62: =CT62 -> 0 | ... GX62: =CZ62 -> 0 | GY62: 0 | GZ62: =SUM(GK62:GY62) -> 0 | HA62: =SUM(GK62:GY62) -> 0
EI63: CABALLEROS | EJ63: 730 | EK63: =$EJ63*F63 -> 0 | EL63: =$EJ63*G63 -> 0 | EM63: =$EJ63*H63 -> 0 | EN63: =$EJ63*I63 -> 0 | EO63: =$EJ63*J63 -> 0 | EP63: =$EJ63*K63 -> 0 | EQ63: =$EJ63*L63 -> 0 | ER63: =$EJ63*M63 -> 0 | ES63: =EJ63*N63 -> 0 | ET63: =EJ63*O63 -> 0 | EU63: =$EJ63*P63 -> 0 | EV63: =$EJ63*Q63 -> 0 | EW63: =$EJ63*R63 -> 0 | EX63: =$EJ63*S63 -> 0 | EY63: =SUM(EK63:EX63) -> 0 | EZ63: =BX63*$EJ63 -> 0 | FA63: =BY63*$EJ63 -> 0 | FB63: =BZ63*$EJ63 -> 0 | FC63: =CA63*$EJ63 -> 0 | FD63: =CB63*$EJ63 -> 0 | FE63: =CC63*$EJ63 -> 0 | FF63: =CD63*$EJ63 -> 0 | FG63: =CE63*$EJ63 -> 0 | ... FM63: =CK63*$EJ63 -> 0 | FN63: =SUM(EZ63:FM63) -> 0 | FO63: =SUM(EZ63:FJ63) -> 0 | FS63: CABALLEROS | FU63: =U63 -> 0 | FV63: =V63 -> 0 | FW63: =W63 -> 0 | FX63: =X63 -> 0 | FY63: =Y63 -> 0 | FZ63: =Z63 -> 0 | GA63: =AA63 -> 0 | GB63: =AB63 -> 0 | ... GH63: =AH63 -> 0 | GI63: 0 | GJ63: =SUM(FU63:GI63) -> 0 | GK63: =CM63 -> 0 | GL63: =CN63 -> 0 | GM63: =CO63 -> 0 | GN63: =CP63 -> 0 | GO63: =CQ63 -> 0 | GP63: =CR63 -> 0 | GQ63: =CS63 -> 0 | GR63: =CT63 -> 0 | ... GX63: =CZ63 -> 0 | GY63: 0 | GZ63: =SUM(GK63:GY63) -> 0 | HA63: =SUM(GK63:GY63) -> 0
AL64: =f730bn73 -> #NAME? | EI64: CHANCLERO | EJ64: 178 | EK64: =$EJ64*F64 -> 0 | EL64: =$EJ64*G64 -> 0 | EM64: =$EJ64*H64 -> 0 | EN64: =$EJ64*I64 -> 0 | EO64: =$EJ64*J64 -> 0 | EP64: =$EJ64*K64 -> 0 | EQ64: =$EJ64*L64 -> 0 | ER64: =$EJ64*M64 -> 0 | ES64: =EJ64*N64 -> 0 | ET64: =EJ64*O64 -> 0 | EU64: =$EJ64*P64 -> 0 | EV64: =$EJ64*Q64 -> 0 | EW64: =$EJ64*R64 -> 0 | EX64: =$EJ64*S64 -> 0 | EY64: =SUM(EK64:EX64) -> 0 | EZ64: =BX64*$EJ64 -> 0 | FA64: =BY64*$EJ64 -> 0 | FB64: =BZ64*$EJ64 -> 0 | FC64: =CA64*$EJ64 -> 0 | FD64: =CB64*$EJ64 -> 0 | FE64: =CC64*$EJ64 -> 0 | FF64: =CD64*$EJ64 -> 0 | FG64: =CE64*$EJ64 -> 0 | ... FM64: =CK64*$EJ64 -> 0 | FN64: =SUM(EZ64:FM64) -> 0 | FO64: =SUM(EZ64:FJ64) -> 0 | FS64: CHANCLERO | FU64: =U64 -> 0 | FV64: =V64 -> 0 | FW64: =W64 -> 0 | FX64: =X64 -> 0 | FY64: =Y64 -> 0 | FZ64: =Z64 -> 0 | GA64: =AA64 -> 0 | GB64: =AB64 -> 0 | ... GH64: =AH64 -> 0 | GI64: 0 | GJ64: =SUM(FU64:GI64) -> 0 | GK64: =CM64 -> 0 | GL64: =CN64 -> 0 | GM64: =CO64 -> 0 | GN64: =CP64 -> 0 | GO64: =CQ64 -> 0 | GP64: =CR64 -> 0 | GQ64: =CS64 -> 0 | GR64: =CT64 -> 0 | ... GX64: =CZ64 -> 0 | GY64: 0 | GZ64: =SUM(GK64:GY64) -> 0 | HA64: =SUM(GK64:GY64) -> 0
EI65: ROPA DOBLADA | EJ65: 263 | EK65: =$EJ65*F65 -> 0 | EL65: =$EJ65*G65 -> 0 | EM65: =$EJ65*H65 -> 0 | EN65: =$EJ65*I65 -> 0 | EO65: =$EJ65*J65 -> 0 | EP65: =$EJ65*K65 -> 0 | EQ65: =$EJ65*L65 -> 0 | ER65: =$EJ65*M65 -> 0 | ES65: =EJ65*N65 -> 0 | ET65: =EJ65*O65 -> 0 | EU65: =$EJ65*P65 -> 0 | EV65: =$EJ65*Q65 -> 0 | EW65: =$EJ65*R65 -> 0 | EX65: =$EJ65*S65 -> 0 | EY65: =SUM(EK65:EX65) -> 0 | EZ65: =BX65*$EJ65 -> 0 | FA65: =BY65*$EJ65 -> 0 | FB65: =BZ65*$EJ65 -> 0 | FC65: =CA65*$EJ65 -> 0 | FD65: =CB65*$EJ65 -> 0 | FE65: =CC65*$EJ65 -> 0 | FF65: =CD65*$EJ65 -> 0 | FG65: =CE65*$EJ65 -> 0 | ... FM65: =CK65*$EJ65 -> 0 | FN65: =SUM(EZ65:FM65) -> 0 | FO65: =SUM(EZ65:FJ65) -> 0 | FS65: ROPA DOBLADA | FU65: 0 | FV65: 0 | FW65: =W65 -> 0 | FX65: =X65 -> 0 | FY65: =Y65 -> 0 | FZ65: 0 | GA65: 0 | GB65: 0 | GC65: =AC65 -> 0 | GD65: =AD65 -> 0 | GE65: =AE65 -> 0 | GF65: =AF65 -> 0 | GG65: =AG65 -> 0 | GH65: 0 | GI65: =AI65 -> 0 | GJ65: =SUM(FU65:GI65) -> 0 | GK65: 0 | GL65: 0 | GM65: =CO65 -> 0 | GN65: =CP65 -> 0 | GO65: =CQ65 -> 0 | GP65: 0 | GQ65: 0 | GR65: 0 | GS65: =CU65 -> 0 | GT65: =CV65 -> 0 | GU65: =CW65 -> 0 | GV65: =CX65 -> 0 | GW65: =CY65 -> 0 | GX65: 0 | GY65: =DA65 -> 0 | GZ65: =SUM(GK65:GY65) -> 0 | HA65: =SUM(GK65:GY65) -> 0
AL66: % de Costo no recuperado | EI66: ROPA COLGADA | EJ66: 405 | EK66: =$EJ66*F66 -> 0 | EL66: =$EJ66*G66 -> 0 | EM66: =$EJ66*H66 -> 0 | EN66: =$EJ66*I66 -> 0 | EO66: =$EJ66*J66 -> 0 | EP66: =$EJ66*K66 -> 0 | EQ66: =$EJ66*L66 -> 0 | ER66: =$EJ66*M66 -> 0 | ES66: =EJ66*N66 -> 0 | ET66: =EJ66*O66 -> 0 | EU66: =$EJ66*P66 -> 0 | EV66: =$EJ66*Q66 -> 0 | EW66: =$EJ66*R66 -> 0 | EX66: =$EJ66*S66 -> 0 | EY66: =SUM(EK66:EX66) -> 0 | EZ66: =BX66*$EJ66 -> 0 | FA66: =BY66*$EJ66 -> 0 | FB66: =BZ66*$EJ66 -> 0 | FC66: =CA66*$EJ66 -> 0 | FD66: =CB66*$EJ66 -> 0 | FE66: =CC66*$EJ66 -> 0 | FF66: =CD66*$EJ66 -> 0 | FG66: =CE66*$EJ66 -> 0 | ... FM66: =CK66*$EJ66 -> 0 | FN66: =SUM(EZ66:FM66) -> 0 | FO66: =SUM(EZ66:FJ66) -> 0 | FS66: ROPA COLGADA | FU66: 0 | FV66: 0 | FW66: =W66 -> 0 | FX66: =X66 -> 0 | FY66: =Y66 -> 0 | FZ66: 0 | GA66: 0 | GB66: 0 | GC66: =AC66 -> 0 | GD66: =AD66 -> 0 | GE66: =AE66 -> 0 | GF66: =AF66 -> 0 | GG66: =AG66 -> 0 | GH66: 0 | GI66: =AI66 -> 0 | GJ66: =SUM(FU66:GI66) -> 0 | GK66: 0 | GL66: 0 | GM66: =CO66 -> 0 | GN66: =CP66 -> 0 | GO66: =CQ66 -> 0 | GP66: 0 | GQ66: 0 | GR66: 0 | GS66: =CU66 -> 0 | GT66: =CV66 -> 0 | GU66: =CW66 -> 0 | GV66: =CX66 -> 0 | GW66: =CY66 -> 0 | GX66: =CZ66 -> 0 | GY66: =DA66 -> 0 | GZ66: =SUM(GK66:GY66) -> 0 | HA66: =SUM(GK66:GY66) -> 0
EI67: IMPORTADOS | EJ67: 1287 | EK67: =$EJ67*F67 -> 0 | EL67: =$EJ67*G67 -> 0 | EM67: =$EJ67*H67 -> 0 | EN67: =$EJ67*I67 -> 0 | EO67: =$EJ67*J67 -> 0 | EP67: =$EJ67*K67 -> 0 | EQ67: =$EJ67*L67 -> 0 | ER67: =$EJ67*M67 -> 0 | ES67: =EJ67*N67 -> 0 | ET67: =EJ67*O67 -> 0 | EU67: =$EJ67*P67 -> 0 | EV67: =$EJ67*Q67 -> 0 | EW67: =$EJ67*R67 -> 0 | EX67: =$EJ67*S67 -> 0 | EY67: =SUM(EK67:EX67) -> 0 | EZ67: =BX67*$EJ67 -> 0 | FA67: =BY67*$EJ67 -> 0 | FB67: =BZ67*$EJ67 -> 0 | FC67: =CA67*$EJ67 -> 0 | FD67: =CB67*$EJ67 -> 0 | FE67: =CC67*$EJ67 -> 0 | FF67: =CD67*$EJ67 -> 0 | FG67: =CE67*$EJ67 -> 0 | ... FM67: =CK67*$EJ67 -> 0 | FN67: =SUM(EZ67:FM67) -> 0 | FO67: =SUM(EZ67:FJ67) -> 0 | FS67: IMPORTADOS | FU67: 0 | FV67: 0 | FW67: =W67 -> 0 | FX67: =X67 -> 0 | FY67: =Y67 -> 0 | FZ67: =Z67 -> 0 | GA67: =AA67 -> 0 | GB67: =AB67 -> 0 | GC67: =AC67 -> 0 | GD67: =AD67 -> 0 | ... GH67: =AH67 -> 0 | GI67: 0 | GJ67: =SUM(FU67:GI67) -> 0 | GK67: 0 | GL67: 0 | GM67: =CO67 -> 0 | GN67: =CP67 -> 0 | GO67: =CQ67 -> 0 | GP67: =CR67 -> 0 | GQ67: =CS67 -> 0 | GR67: =CT67 -> 0 | GS67: =CU67 -> 0 | GT67: =CV67 -> 0 | ... GX67: =CZ67 -> 0 | GY67: 0 | GZ67: =SUM(GK67:GY67) -> 0 | HA67: =SUM(GK67:GY67) -> 0
AL68: =(AL64/F73) -> #NAME? | EI68: BARRA DE BEBES | EJ68: 326.07 | EK68: =$EJ68*F68 -> 0 | EL68: =$EJ68*G68 -> 0 | EM68: =$EJ68*H68 -> 0 | EN68: =$EJ68*I68 -> 0 | EO68: =$EJ68*J68 -> 0 | EP68: =$EJ68*K68 -> 0 | EQ68: =$EJ68*L68 -> 0 | ER68: =$EJ68*M68 -> 0 | ES68: =EJ68*N68 -> 0 | ET68: =EJ68*O68 -> 0 | EU68: =$EJ68*P68 -> 0 | EV68: =$EJ68*Q68 -> 0 | EW68: =$EJ68*R68 -> 0 | EX68: =$EJ68*S68 -> 0 | EY68: =SUM(EK68:EX68) -> 0 | EZ68: =BX68*$EJ68 -> 0 | FA68: =BY68*$EJ68 -> 0 | FB68: =BZ68*$EJ68 -> 0 | FC68: =CA68*$EJ68 -> 0 | FD68: =CB68*$EJ68 -> 0 | FE68: =CC68*$EJ68 -> 0 | FF68: =CD68*$EJ68 -> 0 | FG68: =CE68*$EJ68 -> 0 | ... FM68: =CK68*$EJ68 -> 0 | FN68: =SUM(EZ68:FM68) -> 0 | FO68: =SUM(EZ68:FJ68) -> 0 | FS68: BARRA DE BEBES | FU68: 0 | FV68: 0 | FW68: =W68 -> 0 | FX68: =X68 -> 0 | FY68: =Y68 -> 0 | FZ68: =Z68 -> 0 | GA68: =AA68 -> 0 | GB68: =AB68 -> 0 | GC68: =AC68 -> 0 | GD68: =AD68 -> 0 | ... GH68: =AH68 -> 0 | GI68: 0 | GJ68: =SUM(FU68:GI68) -> 0 | GK68: 0 | GL68: 0 | GM68: =CO68 -> 0 | GN68: =CP68 -> 0 | GO68: =CQ68 -> 0 | GP68: =CR68 -> 0 | GQ68: =CS68 -> 0 | GR68: =CT68 -> 0 | GS68: =CU68 -> 0 | GT68: =CV68 -> 0 | ... GX68: =CZ68 -> 0 | GY68: 0 | GZ68: =SUM(GK68:GY68) -> 0 | HA68: =SUM(GK68:GY68) -> 0
EI69: JEANS | EJ69: 357 | EK69: =$EJ69*F69 -> 0 | EL69: =$EJ69*G69 -> 0 | EM69: =$EJ69*H69 -> 0 | EN69: =$EJ69*I69 -> 0 | EO69: =$EJ69*J69 -> 0 | EP69: =$EJ69*K69 -> 0 | EQ69: =$EJ69*L69 -> 0 | ER69: =$EJ69*M69 -> 0 | ES69: =EJ69*N69 -> 0 | ET69: =EJ69*O69 -> 0 | EU69: =$EJ69*P69 -> 0 | EV69: =$EJ69*Q69 -> 0 | EW69: =$EJ69*R69 -> 0 | EX69: =$EJ69*S69 -> 0 | EY69: =SUM(EK69:EX69) -> 0 | EZ69: =BX69*$EJ69 -> 0 | FA69: =BY69*$EJ69 -> 0 | FB69: =BZ69*$EJ69 -> 0 | FC69: =CA69*$EJ69 -> 0 | FD69: =CB69*$EJ69 -> 0 | FE69: =CC69*$EJ69 -> 0 | FF69: =CD69*$EJ69 -> 0 | FG69: =CE69*$EJ69 -> 0 | ... FM69: =CK69*$EJ69 -> 0 | FN69: =SUM(EZ69:FM69) -> 0 | FO69: =SUM(EZ69:FJ69) -> 0 | FS69: JEANS | FU69: 0 | FV69: 0 | FW69: =W69 -> 0 | FX69: =X69 -> 0 | FY69: =Y69 -> 0 | FZ69: 0 | GA69: 0 | GB69: 0 | GC69: =AC69 -> 0 | GD69: =AD69 -> 0 | GE69: =AE69 -> 0 | GF69: =AF69 -> 0 | GG69: =AG69 -> 0 | GH69: 0 | GI69: =AI69 -> 0 | GJ69: =SUM(FU69:GI69) -> 0 | GK69: 0 | GL69: 0 | GM69: =CO69 -> 0 | GN69: =CP69 -> 0 | GO69: =CQ69 -> 0 | GP69: 0 | GQ69: 0 | GR69: 0 | GS69: =CU69 -> 0 | GT69: =CV69 -> 0 | GU69: =CW69 -> 0 | GV69: =CX69 -> 0 | GW69: =CY69 -> 0 | GX69: 0 | GY69: =DA69 -> 0 | GZ69: =SUM(GK69:GY69) -> 0 | HA69: =SUM(GK69:GY69) -> 0
EI70: MOCHILAS | EJ70: 482 | EK70: =$EJ70*F70 -> 0 | EL70: =$EJ70*G70 -> 0 | EM70: =$EJ70*H70 -> 0 | EN70: =$EJ70*I70 -> 0 | EO70: =$EJ70*J70 -> 0 | EP70: =$EJ70*K70 -> 0 | EQ70: =$EJ70*L70 -> 0 | ER70: =$EJ70*M70 -> 0 | ES70: =EJ70*N70 -> 0 | ET70: =EJ70*O70 -> 0 | EU70: =$EJ70*P70 -> 0 | EV70: =$EJ70*Q70 -> 0 | EW70: =$EJ70*R70 -> 0 | EX70: =$EJ70*S70 -> 0 | EY70: =SUM(EK70:EX70) -> 0 | EZ70: =BX70*$EJ70 -> 0 | FA70: =BY70*$EJ70 -> 0 | FB70: =BZ70*$EJ70 -> 0 | FC70: =CA70*$EJ70 -> 0 | FD70: =CB70*$EJ70 -> 0 | FE70: =CC70*$EJ70 -> 0 | FF70: =CD70*$EJ70 -> 0 | FG70: =CE70*$EJ70 -> 0 | ... FM70: =CK70*$EJ70 -> 0 | FN70: =SUM(EZ70:FM70) -> 0 | FO70: =SUM(EZ70:FJ70) -> 0 | FS70: MOCHILAS | FU70: =U70 -> 0 | FV70: =V70 -> 0 | FW70: =W70 -> 0 | FX70: =X70 -> 0 | FY70: =Y70 -> 0 | FZ70: =Z70 -> 0 | GA70: =AA70 -> 0 | GB70: =AB70 -> 0 | ... GI70: =AI70 -> 0 | GJ70: =SUM(FU70:GI70) -> 0 | GK70: =CM70 -> 0 | GL70: =CN70 -> 0 | GM70: =CO70 -> 0 | GN70: =CP70 -> 0 | GO70: =CQ70 -> 0 | GP70: =CR70 -> 0 | GQ70: =CS70 -> 0 | GR70: =CT70 -> 0 | ... GX70: =CZ70 -> 0 | GY70: 0 | GZ70: =SUM(GK70:GY70) -> 0 | HA70: =SUM(GK70:GY70) -> 0
EI71: HASTA | EJ71: 275.36 | EK71: =$EJ71*F71 -> 0 | EL71: =$EJ71*G71 -> 0 | EM71: =$EJ71*H71 -> 0 | EN71: =$EJ71*I71 -> 0 | EO71: =$EJ71*J71 -> 0 | EP71: =$EJ71*K71 -> 0 | EQ71: =$EJ71*L71 -> 0 | ER71: =$EJ71*M71 -> 0 | ES71: =EJ71*N71 -> 0 | ET71: =EJ71*O71 -> 0 | EU71: =$EJ71*P71 -> 0 | EV71: =$EJ71*Q71 -> 0 | EW71: =$EJ71*R71 -> 0 | EX71: =$EJ71*S71 -> 0 | EY71: =SUM(EK71:EX71) -> 0 | EZ71: =BX71*$EJ71 -> 0 | FA71: =BY71*$EJ71 -> 0 | FB71: =BZ71*$EJ71 -> 0 | FC71: =CA71*$EJ71 -> 0 | FD71: =CB71*$EJ71 -> 0 | FE71: =CC71*$EJ71 -> 0 | FF71: =CD71*$EJ71 -> 0 | FG71: =CE71*$EJ71 -> 0 | ... FM71: =CK71*$EJ71 -> 0 | FN71: =SUM(EZ71:FM71) -> 0 | FO71: =SUM(EZ71:FJ71) -> 0 | FS71: HASTA | FU71: =U71 -> 0 | FV71: =V71 -> 0 | FW71: =W71 -> 0 | FX71: =X71 -> 0 | FY71: =Y71 -> 0 | FZ71: =Z71 -> 0 | GA71: =AA71 -> 0 | GB71: =AB71 -> 0 | ... GH71: =AH71 -> 0 | GI71: 0 | GJ71: =SUM(FU71:GI71) -> 0 | GK71: =CM71 -> 0 | GL71: =CN71 -> 0 | GM71: =CO71 -> 0 | GN71: =CP71 -> 0 | GO71: =CQ71 -> 0 | GP71: =CR71 -> 0 | GQ71: =CS71 -> 0 | GR71: =CT71 -> 0 | ... GX71: =CZ71 -> 0 | GY71: 0 | GZ71: =SUM(GK71:GY71) -> 0 | HA71: =SUM(GK71:GY71) -> 0
B72: Total | C72: =SUM(C56:C71) -> 0 | D72: =SUM(D56:D71) -> 0 | E72: =D72/C72 -> #DIV/0! | F72: =SUM(F56:F71) -> 0 | H72: =SUM(H56:H71) -> 0 | I72: =SUM(I56:I71) -> 0 | J72: =SUM(J56:J71) -> 0 | K72: =SUM(K56:K71) -> 0 | L72: =SUM(L56:L71) -> 0 | N72: =SUM(N56:N71) -> 0 | O72: =SUM(O56:O71) -> 0 | P72: =SUM(P56:P71) -> 0 | T72: =SUM(F72:P72) -> 0 | U72: =SUM(U56:U71) -> 0 | V72: =SUM(V56:V71) -> 0 | W72: =SUM(W56:W71) -> 0 | X72: =SUM(X56:X71) -> 0 | Y72: =SUM(Y56:Y71) -> 0 | Z72: =SUM(Z56:Z71) -> 0 | AA72: =SUM(AA56:AA71) -> 0 | AB72: =SUM(AB56:AB71) -> 0 | ... AI72: =SUM(AI56:AI71) -> 0 | BW72: Total | BX72: =SUM(BX56:BX71) -> 0 | BZ72: =SUM(BZ56:BZ71) -> 0 | CA72: =SUM(CA56:CA71) -> 0 | CB72: =SUM(CB56:CB71) -> 0 | CC72: =SUM(CC56:CC71) -> 0 | CD72: =SUM(CD56:CD71) -> 0 | CF72: =SUM(CF56:CF71) -> 0 | CG72: =SUM(CG56:CG71) -> 0 | CH72: =SUM(CH56:CH71) -> 0 | CL72: =SUM(BX72:CH72) -> 0 | CM72: =SUM(CM56:CM71) -> 0 | CN72: =SUM(CN56:CN71) -> 0 | CO72: =SUM(CO56:CO71) -> 0 | CP72: =SUM(CP56:CP71) -> 0 | CQ72: =SUM(CQ56:CQ71) -> 0 | CR72: =SUM(CR56:CR71) -> 0 | CS72: =SUM(CS56:CS71) -> 0 | CT72: =SUM(CT56:CT71) -> 0 | ... DA72: =SUM(DA56:DA71) -> 0 | EJ72: TOTAL CALZADO | EK72: =EK56+EK57+EK58+EK59+EK60+EK61+EK62+EK63+EK64+EK67+EK68+EK70+EK71 -> 0 | EL72: =EL56+EL57+EL58+EL59+EL60+EL61+EL62+EL63+EL64+EL67+EL68+EL70+EL71 -> 0 | EM72: =EM56+EM57+EM58+EM59+EM60+EM61+EM62+EM63+EM64+EM67+EM68+EM70+EM71 -> 0 | EN72: =EN56+EN57+EN58+EN59+EN60+EN61+EN62+EN63+EN64+EN67+EN68+EN70+EN71 -> 0 | EO72: =EO56+EO57+EO58+EO59+EO60+EO61+EO62+EO63+EO64+EO67+EO68+EO70+EO71 -> 0 | EP72: =EP56+EP57+EP58+EP59+EP60+EP61+EP62+EP63+EP64+EP67+EP68+EP70+EP71 -> 0 | EQ72: =EQ56+EQ57+EQ58+EQ59+EQ60+EQ61+EQ62+EQ63+EQ64+EQ67+EQ68+EQ70+EQ71 -> 0 | ER72: =ER56+ER57+ER58+ER59+ER60+ER61+ER62+ER63+ER64+ER67+ER68+ER70+ER71 -> 0 | ... FN72: =FN56+FN57+FN58+FN59+FN60+FN61+FN62+FN63+FN64+FN67+FN68+FN70+FN71 -> 0 | FS72: TOTAL CALZADO | FU72: =FU56+FU57+FU58+FU59+FU60+FU61+FU62+FU63+FU64+FU67+FU68+FU70+FU71 -> 0 | FV72: =FV56+FV57+FV58+FV59+FV60+FV61+FV62+FV63+FV64+FV67+FV68+FV70+FV71 -> 0 | FW72: =FW56+FW57+FW58+FW59+FW60+FW61+FW62+FW63+FW64+FW67+FW68+FW70+FW71 -> 0 | FX72: =FX56+FX57+FX58+FX59+FX60+FX61+FX62+FX63+FX64+FX67+FX68+FX70+FX71 -> 0 | FY72: =FY56+FY57+FY58+FY59+FY60+FY61+FY62+FY63+FY64+FY67+FY68+FY70+FY71 -> 0 | FZ72: =FZ56+FZ57+FZ58+FZ59+FZ60+FZ61+FZ62+FZ63+FZ64+FZ67+FZ68+FZ70+FZ71 -> 0 | GA72: =GA56+GA57+GA58+GA59+GA60+GA61+GA62+GA63+GA64+GA67+GA68+GA70+GA71 -> 0 | GB72: =GB56+GB57+GB58+GB59+GB60+GB61+GB62+GB63+GB64+GB67+GB68+GB70+GB71 -> 0 | ... GZ72: =GZ56+GZ57+GZ58+GZ59+GZ60+GZ61+GZ62+GZ63+GZ64+GZ67+GZ68+GZ70+GZ71 -> 0
C73: Costo de Oportunidad | F73: =SUM(T56:T71) -> 0 | BX73: =SUM(CL56:CL71) -> 0 | EJ73: TOTAL ROPA | EK73: =EK65+EK66+EK69 -> 0 | EL73: =EL65+EL66+EL69 -> 0 | EM73: =EM65+EM66+EM69 -> 0 | EN73: =EN65+EN66+EN69 -> 0 | EO73: =EO65+EO66+EO69 -> 0 | EP73: =EP65+EP66+EP69 -> 0 | EQ73: =EQ65+EQ66+EQ69 -> 0 | ER73: =ER65+ER66+ER69 -> 0 | ... FN73: =FN65+FN66+FN69 -> 0 | FS73: TOTAL ROPA | FU73: =FU65+FU66+FU69 -> 0 | FV73: =FV65+FV66+FV69 -> 0 | FW73: =FW65+FW66+FW69 -> 0 | FX73: =FX65+FX66+FX69 -> 0 | FY73: =FY65+FY66+FY69 -> 0 | FZ73: =FZ65+FZ66+FZ69 -> 0 | GA73: =GA65+GA66+GA69 -> 0 | GB73: =GB65+GB66+GB69 -> 0 | ... GZ73: =GZ65+GZ66+GZ69 -> 0
F76: Causas de Negado | U76: Incidencias de Auditoria | BX76: Causas de Negado | CM76: Incidencias de Auditoria | EK76: $ negados
A77: Arco Norte | B77: Responsable De Catalogo | C77: Tallas por pasillo | D77: Tallas por modelo | E77: % de Cobertura de auditoria | F77: Frenteos | G77: Ubicación Revuelta | H77: Bodega Venta (Sin marcar) | I77: Bodega Tapanco | J77: Doble Ubicación | K77: Excedente | L77: Origen | M77: Cambios/Probadores | N77: Negados Sin Recuperar | O77: Exhibición | P77: Bodega Aclaración | Q77: Aduanas | R77: Golden o apartados | S77: Control de calidad | T77: Costo por pasillo | U77: Sin Exhibición | V77: Exhibición fuera de Política | W77: Modelos revuelto | X77: Modelos mal entallados | Y77: Modelos con error de ubicación | Z77: Curva con diferencia en frentes | AA77: Curva con diferencia en fondos | AB77: Curva con diferencia en altura | AC77: Curvas vencidas | AD77: Curvas que no coincide Price Soft vs Piso de Venta | AE77: Curvas faltantes | AF77: Cenefas faltantes | AG77: Cenefas de precio Promoción faltantes | AH77: Cartas disculpa / destallados faltantes | AI77: modelos que no cadran con planograma | AJ77: Resultado de Check List | AK77: Resultado de banderazo surtido | AM77: Tallas por pasillo | AN77: Tallas por modelo | AO77: % de Cobertura de auditoria | AP77: Frenteos | AQ77: Ubicación Revuelta | AR77: Bodega Venta (Sin marcar) | AS77: Bodega Tapanco | AT77: Doble Ubicación | AU77: Excedente | AV77: Origen | AW77: Cambios/Probadores | AX77: Negados Sin Recuperar | AY77: Exhibición | AZ77: Bodega Aclaración | BA77: Aduanas | BB77: Golden o apartados | BC77: Control de calidad | BD77: Costo por pasillo | BE77: Sin Exhibición | BF77: Exhibición fuera de Política | BG77: Modelos revuelto | BH77: Modelos mal entallados | BI77: Modelos con error de ubicación | BJ77: Curva con diferencia en frentes | BK77: Curva con diferencia en fondos | BL77: Curva con diferencia en altura | BM77: Curvas vencidas | BN77: Curvas que no coincide Price Soft vs Piso de Venta | BO77: Curvas faltantes | BP77: Cenefas faltantes | BQ77: Cenefas de precio Promoción faltantes | BR77: Cartas disculpa / destallados faltantes | BS77: Fechas de llegada faltantes | BT77: Resultado de Check List | BU77: Resultado de banderazo surtido | BV77: Arco Norte | BW77: Responsable de Catalogo | BX77: Frenteos | BY77: Ubicación Revuelta | BZ77: Bodega Venta (Sin marcar) | CA77: Bodega Tapanco | CB77: Doble Ubicación | CC77: Excedente | CD77: Origen | CE77: Cambios/Probadores | CF77: Negados Sin Recuperar | CG77: Exhibición | CH77: Bodega Aclaración | CI77: Aduanas | CJ77: Golden o apartados | CK77: Control de calidad | CL77: Costo por pasillo | CM77: Sin Exhibición | CN77: Exhibición fuera de Política | CO77: Modelos revuelto | CP77: Modelos mal entallados | CQ77: Modelos con error de ubicación | CR77: Curva con diferencia en frentes | CS77: Curva con diferencia en fondos | CT77: Curva con diferencia en altura | CU77: Curvas vencidas | CV77: Curvas que no coincide Price Soft vs Piso de Venta | CW77: Curvas faltantes | CX77: Cenefas faltantes | CY77: Cenefas de precio Promoción faltantes | CZ77: Cartas disculpa / destallados faltantes | DA77: Fechas de llegada faltantes | DB77: Resultado de Check List | DE77: Frenteos | DF77: Ubicación Revuelta | DG77: Bodega Venta (Sin marcar) | DH77: Bodega Tapanco | DI77: Doble Ubicación | DJ77: Excedente | DK77: Origen | DL77: Cambios/Probadores | DM77: Negados Sin Recuperar | DN77: Exhibición | DO77: Bodega Aclaración | DP77: Aduanas | DQ77: Golden o apartados | DR77: Control de calidad | DS77: Costo por pasillo | DT77: Sin Exhibición | DU77: Exhibición fuera de Política | DV77: Modelos revuelto | DW77: Modelos mal entallados | DX77: Modelos con error de ubicación | DY77: Curva con diferencia en frentes | DZ77: Curva con diferencia en fondos | EA77: Curva con diferencia en altura | EB77: Curvas vencidas | EC77: Curvas que no coincide Price Soft vs Piso de Venta | ED77: Curvas faltantes | EE77: Cenefas faltantes | EF77: Cenefas de precio Promoción faltantes | EG77: Cartas disculpa / destallados faltantes | EH77: Fechas de llegada faltantes | EK77: Frenteos | EL77: Ubicación Revuelta | EM77: Bodega Venta (Sin marcar) | EN77: Bodega Tapanco | EO77: Doble Ubicación | EP77: Excedente | EQ77: Origen | ER77: Cambios/Probadores | ES77: Negados Sin Recuperar | ET77: Exhibición | EU77: Bodega Aclaración | EV77: Aduanas | EW77: Golden o apartados | EX77: Control de calidad | EZ77: Frenteos | FA77: Ubicación Revuelta | FB77: Bodega Venta (Sin marcar) | FC77: Bodega Tapanco | FD77: Doble Ubicación | FE77: Excedente | FF77: Origen | FG77: Cambios/Probadores | FH77: Negados Sin Recuperar | FI77: Exhibición | FJ77: Bodega Aclaración | FK77: Aduanas | FL77: Golden o apartados | FM77: Control de calidad | FU77: Sin Exhibición | FV77: Exhibición fuera de Política | FW77: Modelos revuelto | FX77: Modelos mal entallados | FY77: Modelos con error de ubicación | FZ77: Curva con diferencia en frentes | GA77: Curva con diferencia en fondos | GB77: Curva con diferencia en altura | GC77: Curvas vencidas | GD77: Curvas que no coincide Price Soft vs Piso de Venta | GE77: Curvas faltantes | GF77: Cenefas faltantes | GG77: Cenefas de precio Promoción faltantes | GH77: Cartas disculpa / destallados faltantes | GI77: modelos que no cadran con planograma | GK77: Sin Exhibición | GL77: Exhibición fuera de Política | GM77: Modelos revuelto | GN77: Modelos mal entallados | GO77: Modelos con error de ubicación | GP77: Curva con diferencia en frentes | GQ77: Curva con diferencia en fondos | GR77: Curva con diferencia en altura | GS77: Curvas vencidas | GT77: Curvas que no coincide Price Soft vs Piso de Venta | GU77: Curvas faltantes | GV77: Cenefas faltantes | GW77: Cenefas de precio Promoción faltantes | GX77: Cartas disculpa / destallados faltantes | GY77: modelos que no cadran con planograma
AM78: =SUM(C78,C79,C80,C81,C82,C83,C84,C85,C86,C89,C90,C92,C93) -> 0 | AN78: =SUM(D78,D79,D80,D81,D82,D83,D84,D85,D86,D89,D90,D92,D93) -> 0 | AO78: =IF(AN78=0,"",AN78/AM78) | AP78: =SUM(F78,F79,F80,F81,F82,F83,F84,F85,F86,F89,F90,F92,F93) -> 0 | AQ78: =SUM(G78,G79,G80,G81,G82,G83,G84,G85,G86,G89,G90,G92,G93) -> 0 | AR78: =SUM(H78,H79,H80,H81,H82,H83,H84,H85,H86,H89,H90,H92,H93) -> 0 | AS78: =SUM(I78,I79,I80,I81,I82,I83,I84,I85,I86,I89,I90,I92,I93) -> 0 | AT78: =SUM(J78,J79,J80,J81,J82,J83,J84,J85,J86,J89,J90,J92,J93) -> 0 | AU78: =SUM(K78,K79,K80,K81,K82,K83,K84,K85,K86,K89,K90,K92,K93) -> 0 | AV78: =SUM(L78,L79,L80,L81,L82,L83,L84,L85,L86,L89,L90,L92,L93) -> 0 | AW78: =SUM(M78,M79,M80,M81,M82,M83,M84,M85,M86,M89,M90,M92,M93) -> 0 | ... BU78: =SUM(AK78,AK79,AK80,AK81,AK82,AK83,AK84,AK85,AK86,AK89,AK90,AK92,AK93) -> 0 | DD78: =(DD72/BZ84) -> #DIV/0! | DE78: =SUM(BX78,BX79,BX80,BX81,BX82,BX83,BX84,BX85,BX86,BX89,BX90,BX92,BX93) -> 0 | DF78: =SUM(BY78,BY79,BY80,BY81,BY82,BY83,BY84,BY85,BY86,BY89,BY90,BY92,BY93) -> 0 | DG78: =SUM(BZ78,BZ79,BZ80,BZ81,BZ82,BZ83,BZ84,BZ85,BZ86,BZ89,BZ90,BZ92,BZ93) -> 0 | DH78: =SUM(CA78,CA79,CA80,CA81,CA82,CA83,CA84,CA85,CA86,CA89,CA90,CA92,CA93) -> 0 | DI78: =SUM(CB78,CB79,CB80,CB81,CB82,CB83,CB84,CB85,CB86,CB89,CB90,CB92,CB93) -> 0 | DJ78: =SUM(CC78,CC79,CC80,CC81,CC82,CC83,CC84,CC85,CC86,CC89,CC90,CC92,CC93) -> 0 | DK78: =SUM(CD78,CD79,CD80,CD81,CD82,CD83,CD84,CD85,CD86,CD89,CD90,CD92,CD93) -> 0 | DL78: =SUM(CE78,CE79,CE80,CE81,CE82,CE83,CE84,CE85,CE86,CE89,CE90,CE92,CE93) -> 0 | ... EH78: =SUM(DA78,DA79,DA80,DA81,DA82,DA83,DA84,DA85,DA86,DA89,DA90,DA92,DA93) -> 0 | EI78: BOTAS | EJ78: 521 | EK78: =$EJ78*F78 -> 0 | EL78: =$EJ78*G78 -> 0 | EM78: =$EJ78*H78 -> 0 | EN78: =$EJ78*I78 -> 0 | EO78: =$EJ78*J78 -> 0 | EP78: =$EJ78*K78 -> 0 | EQ78: =$EJ78*L78 -> 0 | ER78: =$EJ78*M78 -> 0 | ... EX78: =$EJ78*S78 -> 0 | EY78: =SUM(EK78:EX78) -> 0 | EZ78: =BX78*$EJ78 -> 0 | FA78: =BY78*$EJ78 -> 0 | FB78: =BZ78*$EJ78 -> 0 | FC78: =CA78*$EJ78 -> 0 | FD78: =CB78*$EJ78 -> 0 | FE78: =CC78*$EJ78 -> 0 | FF78: =CD78*$EJ78 -> 0 | FG78: =CE78*$EJ78 -> 0 | ... FM78: =CK78*$EJ78 -> 0 | FN78: =SUM(EZ78:FM78) -> 0 | FO78: =SUM(EZ78:FJ78) -> 0 | FS78: BOTAS | FU78: =U78 -> 0 | FV78: =V78 -> 0 | FW78: =W78 -> 0 | FX78: =X78 -> 0 | FY78: =Y78 -> 0 | FZ78: =Z78 -> 0 | GA78: =AA78 -> 0 | GB78: =AB78 -> 0 | ... GH78: =AH78 -> 0 | GI78: 0 | GJ78: =SUM(FU78:GI78) -> 0 | GK78: =CM78 -> 0 | GL78: =CN78 -> 0 | GM78: =CO78 -> 0 | GN78: =CP78 -> 0 | GO78: =CQ78 -> 0 | GP78: =CR78 -> 0 | GQ78: =CS78 -> 0 | GR78: =CT78 -> 0 | ... GX78: =CZ78 -> 0 | GY78: 0 | GZ78: =SUM(GK78:GY78) -> 0 | HA78: =SUM(GK78:GY78) -> 0
AO79: =IF(AN79=0,"",AN79/AM79) | EI79: URBANO | EJ79: 540 | EK79: =$EJ79*F79 -> 0 | EL79: =$EJ79*G79 -> 0 | EM79: =$EJ79*H79 -> 0 | EN79: =$EJ79*I79 -> 0 | EO79: =$EJ79*J79 -> 0 | EP79: =$EJ79*K79 -> 0 | EQ79: =$EJ79*L79 -> 0 | ER79: =$EJ79*M79 -> 0 | ... EX79: =$EJ79*S79 -> 0 | EY79: =SUM(EK79:EX79) -> 0 | EZ79: =BX79*$EJ79 -> 0 | FA79: =BY79*$EJ79 -> 0 | FB79: =BZ79*$EJ79 -> 0 | FC79: =CA79*$EJ79 -> 0 | FD79: =CB79*$EJ79 -> 0 | FE79: =CC79*$EJ79 -> 0 | FF79: =CD79*$EJ79 -> 0 | FG79: =CE79*$EJ79 -> 0 | ... FM79: =CK79*$EJ79 -> 0 | FN79: =SUM(EZ79:FM79) -> 0 | FO79: =SUM(EZ79:FJ79) -> 0 | FS79: URBANO | FU79: =U79 -> 0 | FV79: =V79 -> 0 | FW79: =W79 -> 0 | FX79: =X79 -> 0 | FY79: =Y79 -> 0 | FZ79: =Z79 -> 0 | GA79: =AA79 -> 0 | GB79: =AB79 -> 0 | ... GH79: =AH79 -> 0 | GI79: 0 | GJ79: =SUM(FU79:GI79) -> 0 | GK79: =CM79 -> 0 | GL79: =CN79 -> 0 | GM79: =CO79 -> 0 | GN79: =CP79 -> 0 | GO79: =CQ79 -> 0 | GP79: =CR79 -> 0 | GQ79: =CS79 -> 0 | GR79: =CT79 -> 0 | ... GX79: =CZ79 -> 0 | GY79: 0 | GZ79: =SUM(GK79:GY79) -> 0 | HA79: =SUM(GK79:GY79) -> 0
AL80: % de tallas negadas | AM80: =SUM(C87,C88,C91) -> 0 | AN80: =SUM(D87,D88,D91) -> 0 | AO80: =IF(AN80=0,"",AN80/AM80) | AP80: =SUM(F87,F88,F91) -> 0 | AQ80: =SUM(G87,G88,G91) -> 0 | AR80: =SUM(H87,H88,H91) -> 0 | AS80: =SUM(I87,I88,I91) -> 0 | AT80: =SUM(J87,J88,J91) -> 0 | AU80: =SUM(K87,K88,K91) -> 0 | AV80: =SUM(L87,L88,L91) -> 0 | AW80: =SUM(M87,M88,M91) -> 0 | ... BS80: =SUM(AI87,AI88,AI91) -> 0 | BT80: =AVERAGE(AJ87,AJ88,AJ91) -> #DIV/0! | DC80: % de tallas recuperadas | DE80: =SUM(BX87,BX88,BX91) -> 0 | DF80: =SUM(BY87,BY88,BY91) -> 0 | DG80: =SUM(BZ87,BZ88,BZ91) -> 0 | DH80: =SUM(CA87,CA88,CA91) -> 0 | DI80: =SUM(CB87,CB88,CB91) -> 0 | DJ80: =SUM(CC87,CC88,CC91) -> 0 | DK80: =SUM(CD87,CD88,CD91) -> 0 | DL80: =SUM(CE87,CE88,CE91) -> 0 | ... EH80: =SUM(DA87,DA88,DA91) -> 0 | EI80: ESCOLAR | EJ80: 441.24 | EK80: =$EJ80*F80 -> 0 | EL80: =$EJ80*G80 -> 0 | EM80: =$EJ80*H80 -> 0 | EN80: =$EJ80*I80 -> 0 | EO80: =$EJ80*J80 -> 0 | EP80: =$EJ80*K80 -> 0 | EQ80: =$EJ80*L80 -> 0 | ER80: =$EJ80*M80 -> 0 | ... EX80: =$EJ80*S80 -> 0 | EY80: =SUM(EK80:EX80) -> 0 | EZ80: =BX80*$EJ80 -> 0 | FA80: =BY80*$EJ80 -> 0 | FB80: =BZ80*$EJ80 -> 0 | FC80: =CA80*$EJ80 -> 0 | FD80: =CB80*$EJ80 -> 0 | FE80: =CC80*$EJ80 -> 0 | FF80: =CD80*$EJ80 -> 0 | FG80: =CE80*$EJ80 -> 0 | ... FM80: =CK80*$EJ80 -> 0 | FN80: =SUM(EZ80:FM80) -> 0 | FO80: =SUM(EZ80:FJ80) -> 0 | FS80: ESCOLAR | FU80: =U80 -> 0 | FV80: =V80 -> 0 | FW80: =W80 -> 0 | FX80: =X80 -> 0 | FY80: =Y80 -> 0 | FZ80: =Z80 -> 0 | GA80: =AA80 -> 0 | GB80: =AB80 -> 0 | ... GH80: =AH80 -> 0 | GI80: 0 | GJ80: =SUM(FU80:GI80) -> 0 | GK80: =CM80 -> 0 | GL80: =CN80 -> 0 | GM80: =CO80 -> 0 | GN80: =CP80 -> 0 | GO80: =CQ80 -> 0 | GP80: =CR80 -> 0 | GQ80: =CS80 -> 0 | GR80: =CT80 -> 0 | ... GX80: =CZ80 -> 0 | GY80: 0 | GZ80: =SUM(GK80:GY80) -> 0 | HA80: =SUM(GK80:GY80) -> 0
EI81: SANDALIAS | EJ81: 294.47 | EK81: =$EJ81*F81 -> 0 | EL81: =$EJ81*G81 -> 0 | EM81: =$EJ81*H81 -> 0 | EN81: =$EJ81*I81 -> 0 | EO81: =$EJ81*J81 -> 0 | EP81: =$EJ81*K81 -> 0 | EQ81: =$EJ81*L81 -> 0 | ER81: =$EJ81*M81 -> 0 | ... EX81: =$EJ81*S81 -> 0 | EY81: =SUM(EK81:EX81) -> 0 | EZ81: =BX81*$EJ81 -> 0 | FA81: =BY81*$EJ81 -> 0 | FB81: =BZ81*$EJ81 -> 0 | FC81: =CA81*$EJ81 -> 0 | FD81: =CB81*$EJ81 -> 0 | FE81: =CC81*$EJ81 -> 0 | FF81: =CD81*$EJ81 -> 0 | FG81: =CE81*$EJ81 -> 0 | ... FM81: =CK81*$EJ81 -> 0 | FN81: =SUM(EZ81:FM81) -> 0 | FO81: =SUM(EZ81:FJ81) -> 0 | FS81: SANDALIAS | FU81: =U81 -> 0 | FV81: =V81 -> 0 | FW81: =W81 -> 0 | FX81: =X81 -> 0 | FY81: =Y81 -> 0 | FZ81: =Z81 -> 0 | GA81: =AA81 -> 0 | GB81: =AB81 -> 0 | ... GH81: =AH81 -> 0 | GI81: 0 | GJ81: =SUM(FU81:GI81) -> 0 | GK81: =CM81 -> 0 | GL81: =CN81 -> 0 | GM81: =CO81 -> 0 | GN81: =CP81 -> 0 | GO81: =CQ81 -> 0 | GP81: =CR81 -> 0 | GQ81: =CS81 -> 0 | GR81: =CT81 -> 0 | ... GX81: =CZ81 -> 0 | GY81: 0 | GZ81: =SUM(GK81:GY81) -> 0 | HA81: =SUM(GK81:GY81) -> 0
AL82: =T94/D94 -> #DIV/0! | DC82: =CL94/T94 -> #DIV/0! | EI82: CONFORT | EJ82: 422 | EK82: =$EJ82*F82 -> 0 | EL82: =$EJ82*G82 -> 0 | EM82: =$EJ82*H82 -> 0 | EN82: =$EJ82*I82 -> 0 | EO82: =$EJ82*J82 -> 0 | EP82: =$EJ82*K82 -> 0 | EQ82: =$EJ82*L82 -> 0 | ER82: =$EJ82*M82 -> 0 | ... EX82: =$EJ82*S82 -> 0 | EY82: =SUM(EK82:EX82) -> 0 | EZ82: =BX82*$EJ82 -> 0 | FA82: =BY82*$EJ82 -> 0 | FB82: =BZ82*$EJ82 -> 0 | FC82: =CA82*$EJ82 -> 0 | FD82: =CB82*$EJ82 -> 0 | FE82: =CC82*$EJ82 -> 0 | FF82: =CD82*$EJ82 -> 0 | FG82: =CE82*$EJ82 -> 0 | ... FM82: =CK82*$EJ82 -> 0 | FN82: =SUM(EZ82:FM82) -> 0 | FO82: =SUM(EZ82:FJ82) -> 0 | FS82: CONFORT | FU82: =U82 -> 0 | FV82: =V82 -> 0 | FW82: =W82 -> 0 | FX82: =X82 -> 0 | FY82: =Y82 -> 0 | FZ82: =Z82 -> 0 | GA82: =AA82 -> 0 | GB82: =AB82 -> 0 | ... GH82: =AH82 -> 0 | GI82: 0 | GJ82: =SUM(FU82:GI82) -> 0 | GK82: =CM82 -> 0 | GL82: =CN82 -> 0 | GM82: =CO82 -> 0 | GN82: =CP82 -> 0 | GO82: =CQ82 -> 0 | GP82: =CR82 -> 0 | GQ82: =CS82 -> 0 | GR82: =CT82 -> 0 | ... GX82: =CZ82 -> 0 | GY82: 0 | GZ82: =SUM(GK82:GY82) -> 0 | HA82: =SUM(GK82:GY82) -> 0
EI83: VESTIR CASUAL | EJ83: 416.19 | EK83: =$EJ83*F83 -> 0 | EL83: =$EJ83*G83 -> 0 | EM83: =$EJ83*H83 -> 0 | EN83: =$EJ83*I83 -> 0 | EO83: =$EJ83*J83 -> 0 | EP83: =$EJ83*K83 -> 0 | EQ83: =$EJ83*L83 -> 0 | ER83: =$EJ83*M83 -> 0 | ... EX83: =$EJ83*S83 -> 0 | EY83: =SUM(EK83:EX83) -> 0 | EZ83: =BX83*$EJ83 -> 0 | FA83: =BY83*$EJ83 -> 0 | FB83: =BZ83*$EJ83 -> 0 | FC83: =CA83*$EJ83 -> 0 | FD83: =CB83*$EJ83 -> 0 | FE83: =CC83*$EJ83 -> 0 | FF83: =CD83*$EJ83 -> 0 | FG83: =CE83*$EJ83 -> 0 | ... FM83: =CK83*$EJ83 -> 0 | FN83: =SUM(EZ83:FM83) -> 0 | FO83: =SUM(EZ83:FJ83) -> 0 | FS83: VESTIR CASUAL | FU83: =U83 -> 0 | FV83: =V83 -> 0 | FW83: =W83 -> 0 | FX83: =X83 -> 0 | FY83: =Y83 -> 0 | FZ83: =Z83 -> 0 | GA83: =AA83 -> 0 | GB83: =AB83 -> 0 | ... GH83: =AH83 -> 0 | GI83: 0 | GJ83: =SUM(FU83:GI83) -> 0 | GK83: =CM83 -> 0 | GL83: =CN83 -> 0 | GM83: =CO83 -> 0 | GN83: =CP83 -> 0 | GO83: =CQ83 -> 0 | GP83: =CR83 -> 0 | GQ83: =CS83 -> 0 | GR83: =CT83 -> 0 | ... GX83: =CZ83 -> 0 | GY83: 0 | GZ83: =SUM(GK83:GY83) -> 0 | HA83: =SUM(GK83:GY83) -> 0
AL84: Diferencia Negado VS Recuperado | EI84: INFANTILES | EJ84: 375 | EK84: =$EJ84*F84 -> 0 | EL84: =$EJ84*G84 -> 0 | EM84: =$EJ84*H84 -> 0 | EN84: =$EJ84*I84 -> 0 | EO84: =$EJ84*J84 -> 0 | EP84: =$EJ84*K84 -> 0 | EQ84: =$EJ84*L84 -> 0 | ER84: =$EJ84*M84 -> 0 | ... EX84: =$EJ84*S84 -> 0 | EY84: =SUM(EK84:EX84) -> 0 | EZ84: =BX84*$EJ84 -> 0 | FA84: =BY84*$EJ84 -> 0 | FB84: =BZ84*$EJ84 -> 0 | FC84: =CA84*$EJ84 -> 0 | FD84: =CB84*$EJ84 -> 0 | FE84: =CC84*$EJ84 -> 0 | FF84: =CD84*$EJ84 -> 0 | FG84: =CE84*$EJ84 -> 0 | ... FM84: =CK84*$EJ84 -> 0 | FN84: =SUM(EZ84:FM84) -> 0 | FO84: =SUM(EZ84:FJ84) -> 0 | FS84: INFANTILES | FU84: =U84 -> 0 | FV84: =V84 -> 0 | FW84: =W84 -> 0 | FX84: =X84 -> 0 | FY84: =Y84 -> 0 | FZ84: =Z84 -> 0 | GA84: =AA84 -> 0 | GB84: =AB84 -> 0 | ... GH84: =AH84 -> 0 | GI84: 0 | GJ84: =SUM(FU84:GI84) -> 0 | GK84: =CM84 -> 0 | GL84: =CN84 -> 0 | GM84: =CO84 -> 0 | GN84: =CP84 -> 0 | GO84: =CQ84 -> 0 | GP84: =CR84 -> 0 | GQ84: =CS84 -> 0 | GR84: =CT84 -> 0 | ... GX84: =CZ84 -> 0 | GY84: 0 | GZ84: =SUM(GK84:GY84) -> 0 | HA84: =SUM(GK84:GY84) -> 0
EI85: CABALLEROS | EJ85: 730 | EK85: =$EJ85*F85 -> 0 | EL85: =$EJ85*G85 -> 0 | EM85: =$EJ85*H85 -> 0 | EN85: =$EJ85*I85 -> 0 | EO85: =$EJ85*J85 -> 0 | EP85: =$EJ85*K85 -> 0 | EQ85: =$EJ85*L85 -> 0 | ER85: =$EJ85*M85 -> 0 | ... EX85: =$EJ85*S85 -> 0 | EY85: =SUM(EK85:EX85) -> 0 | EZ85: =BX85*$EJ85 -> 0 | FA85: =BY85*$EJ85 -> 0 | FB85: =BZ85*$EJ85 -> 0 | FC85: =CA85*$EJ85 -> 0 | FD85: =CB85*$EJ85 -> 0 | FE85: =CC85*$EJ85 -> 0 | FF85: =CD85*$EJ85 -> 0 | FG85: =CE85*$EJ85 -> 0 | ... FM85: =CK85*$EJ85 -> 0 | FN85: =SUM(EZ85:FM85) -> 0 | FO85: =SUM(EZ85:FJ85) -> 0 | FS85: CABALLEROS | FU85: =U85 -> 0 | FV85: =V85 -> 0 | FW85: =W85 -> 0 | FX85: =X85 -> 0 | FY85: =Y85 -> 0 | FZ85: =Z85 -> 0 | GA85: =AA85 -> 0 | GB85: =AB85 -> 0 | ... GH85: =AH85 -> 0 | GI85: 0 | GJ85: =SUM(FU85:GI85) -> 0 | GK85: =CM85 -> 0 | GL85: =CN85 -> 0 | GM85: =CO85 -> 0 | GN85: =CP85 -> 0 | GO85: =CQ85 -> 0 | GP85: =CR85 -> 0 | GQ85: =CS85 -> 0 | GR85: =CT85 -> 0 | ... GX85: =CZ85 -> 0 | GY85: 0 | GZ85: =SUM(GK85:GY85) -> 0 | HA85: =SUM(GK85:GY85) -> 0
AL86: =o940bw94 -> #NAME? | EI86: CHANCLERO | EJ86: 178 | EK86: =$EJ86*F86 -> 0 | EL86: =$EJ86*G86 -> 0 | EM86: =$EJ86*H86 -> 0 | EN86: =$EJ86*I86 -> 0 | EO86: =$EJ86*J86 -> 0 | EP86: =$EJ86*K86 -> 0 | EQ86: =$EJ86*L86 -> 0 | ER86: =$EJ86*M86 -> 0 | ... EX86: =$EJ86*S86 -> 0 | EY86: =SUM(EK86:EX86) -> 0 | EZ86: =BX86*$EJ86 -> 0 | FA86: =BY86*$EJ86 -> 0 | FB86: =BZ86*$EJ86 -> 0 | FC86: =CA86*$EJ86 -> 0 | FD86: =CB86*$EJ86 -> 0 | FE86: =CC86*$EJ86 -> 0 | FF86: =CD86*$EJ86 -> 0 | FG86: =CE86*$EJ86 -> 0 | ... FM86: =CK86*$EJ86 -> 0 | FN86: =SUM(EZ86:FM86) -> 0 | FO86: =SUM(EZ86:FJ86) -> 0 | FS86: CHANCLERO | FU86: =U86 -> 0 | FV86: =V86 -> 0 | FW86: =W86 -> 0 | FX86: =X86 -> 0 | FY86: =Y86 -> 0 | FZ86: =Z86 -> 0 | GA86: =AA86 -> 0 | GB86: =AB86 -> 0 | ... GH86: =AH86 -> 0 | GI86: 0 | GJ86: =SUM(FU86:GI86) -> 0 | GK86: =CM86 -> 0 | GL86: =CN86 -> 0 | GM86: =CO86 -> 0 | GN86: =CP86 -> 0 | GO86: =CQ86 -> 0 | GP86: =CR86 -> 0 | GQ86: =CS86 -> 0 | GR86: =CT86 -> 0 | ... GX86: =CZ86 -> 0 | GY86: 0 | GZ86: =SUM(GK86:GY86) -> 0 | HA86: =SUM(GK86:GY86) -> 0
EI87: ROPA DOBLADA | EJ87: 263 | EK87: =$EJ87*F87 -> 0 | EL87: =$EJ87*G87 -> 0 | EM87: =$EJ87*H87 -> 0 | EN87: =$EJ87*I87 -> 0 | EO87: =$EJ87*J87 -> 0 | EP87: =$EJ87*K87 -> 0 | EQ87: =$EJ87*L87 -> 0 | ER87: =$EJ87*M87 -> 0 | ... EX87: =$EJ87*S87 -> 0 | EY87: =SUM(EK87:EX87) -> 0 | EZ87: =BX87*$EJ87 -> 0 | FA87: =BY87*$EJ87 -> 0 | FB87: =BZ87*$EJ87 -> 0 | FC87: =CA87*$EJ87 -> 0 | FD87: =CB87*$EJ87 -> 0 | FE87: =CC87*$EJ87 -> 0 | FF87: =CD87*$EJ87 -> 0 | FG87: =CE87*$EJ87 -> 0 | ... FM87: =CK87*$EJ87 -> 0 | FN87: =SUM(EZ87:FM87) -> 0 | FO87: =SUM(EZ87:FJ87) -> 0 | FS87: ROPA DOBLADA | FU87: 0 | FV87: 0 | FW87: =W87 -> 0 | FX87: =X87 -> 0 | FY87: =Y87 -> 0 | FZ87: 0 | GA87: 0 | GB87: 0 | GC87: =AC87 -> 0 | GD87: =AD87 -> 0 | GE87: =AE87 -> 0 | GF87: =AF87 -> 0 | GG87: =AG87 -> 0 | GH87: 0 | GI87: =AI87 -> 0 | GJ87: =SUM(FU87:GI87) -> 0 | GK87: 0 | GL87: 0 | GM87: =CO87 -> 0 | GN87: =CP87 -> 0 | GO87: =CQ87 -> 0 | GP87: 0 | GQ87: 0 | GR87: 0 | GS87: =CU87 -> 0 | GT87: =CV87 -> 0 | GU87: =CW87 -> 0 | GV87: =CX87 -> 0 | GW87: =CY87 -> 0 | GX87: 0 | GY87: =DA87 -> 0 | GZ87: =SUM(GK87:GY87) -> 0 | HA87: =SUM(GK87:GY87) -> 0
AL88: % de Costo no recuperado | EI88: ROPA COLGADA | EJ88: 405 | EK88: =$EJ88*F88 -> 0 | EL88: =$EJ88*G88 -> 0 | EM88: =$EJ88*H88 -> 0 | EN88: =$EJ88*I88 -> 0 | EO88: =$EJ88*J88 -> 0 | EP88: =$EJ88*K88 -> 0 | EQ88: =$EJ88*L88 -> 0 | ER88: =$EJ88*M88 -> 0 | ... EX88: =$EJ88*S88 -> 0 | EY88: =SUM(EK88:EX88) -> 0 | EZ88: =BX88*$EJ88 -> 0 | FA88: =BY88*$EJ88 -> 0 | FB88: =BZ88*$EJ88 -> 0 | FC88: =CA88*$EJ88 -> 0 | FD88: =CB88*$EJ88 -> 0 | FE88: =CC88*$EJ88 -> 0 | FF88: =CD88*$EJ88 -> 0 | FG88: =CE88*$EJ88 -> 0 | ... FM88: =CK88*$EJ88 -> 0 | FN88: =SUM(EZ88:FM88) -> 0 | FO88: =SUM(EZ88:FJ88) -> 0 | FS88: ROPA COLGADA | FU88: 0 | FV88: 0 | FW88: =W88 -> 0 | FX88: =X88 -> 0 | FY88: =Y88 -> 0 | FZ88: 0 | GA88: 0 | GB88: 0 | GC88: =AC88 -> 0 | GD88: =AD88 -> 0 | GE88: =AE88 -> 0 | GF88: =AF88 -> 0 | GG88: =AG88 -> 0 | GH88: 0 | GI88: =AI88 -> 0 | GJ88: =SUM(FU88:GI88) -> 0 | GK88: 0 | GL88: 0 | GM88: =CO88 -> 0 | GN88: =CP88 -> 0 | GO88: =CQ88 -> 0 | GP88: 0 | GQ88: 0 | GR88: 0 | GS88: =CU88 -> 0 | GT88: =CV88 -> 0 | GU88: =CW88 -> 0 | GV88: =CX88 -> 0 | GW88: =CY88 -> 0 | GX88: =CZ88 -> 0 | GY88: =DA88 -> 0 | GZ88: =SUM(GK88:GY88) -> 0 | HA88: =SUM(GK88:GY88) -> 0
EI89: IMPORTADOS | EJ89: 1287 | EK89: =$EJ89*F89 -> 0 | EL89: =$EJ89*G89 -> 0 | EM89: =$EJ89*H89 -> 0 | EN89: =$EJ89*I89 -> 0 | EO89: =$EJ89*J89 -> 0 | EP89: =$EJ89*K89 -> 0 | EQ89: =$EJ89*L89 -> 0 | ER89: =$EJ89*M89 -> 0 | ... EX89: =$EJ89*S89 -> 0 | EY89: =SUM(EK89:EX89) -> 0 | EZ89: =BX89*$EJ89 -> 0 | FA89: =BY89*$EJ89 -> 0 | FB89: =BZ89*$EJ89 -> 0 | FC89: =CA89*$EJ89 -> 0 | FD89: =CB89*$EJ89 -> 0 | FE89: =CC89*$EJ89 -> 0 | FF89: =CD89*$EJ89 -> 0 | FG89: =CE89*$EJ89 -> 0 | ... FM89: =CK89*$EJ89 -> 0 | FN89: =SUM(EZ89:FM89) -> 0 | FO89: =SUM(EZ89:FJ89) -> 0 | FS89: IMPORTADOS | FU89: 0 | FV89: 0 | FW89: =W89 -> 0 | FX89: =X89 -> 0 | FY89: =Y89 -> 0 | FZ89: =Z89 -> 0 | GA89: =AA89 -> 0 | GB89: =AB89 -> 0 | GC89: =AC89 -> 0 | GD89: =AD89 -> 0 | ... GH89: =AH89 -> 0 | GI89: 0 | GJ89: =SUM(FU89:GI89) -> 0 | GK89: 0 | GL89: 0 | GM89: =CO89 -> 0 | GN89: =CP89 -> 0 | GO89: =CQ89 -> 0 | GP89: =CR89 -> 0 | GQ89: =CS89 -> 0 | GR89: =CT89 -> 0 | GS89: =CU89 -> 0 | GT89: =CV89 -> 0 | ... GX89: =CZ89 -> 0 | GY89: 0 | GZ89: =SUM(GK89:GY89) -> 0 | HA89: =SUM(GK89:GY89) -> 0
AL90: =(AL86/F95) -> #NAME? | EI90: BARRA DE BEBES | EJ90: 326.07 | EK90: =$EJ90*F90 -> 0 | EL90: =$EJ90*G90 -> 0 | EM90: =$EJ90*H90 -> 0 | EN90: =$EJ90*I90 -> 0 | EO90: =$EJ90*J90 -> 0 | EP90: =$EJ90*K90 -> 0 | EQ90: =$EJ90*L90 -> 0 | ER90: =$EJ90*M90 -> 0 | ... EX90: =$EJ90*S90 -> 0 | EY90: =SUM(EK90:EX90) -> 0 | EZ90: =BX90*$EJ90 -> 0 | FA90: =BY90*$EJ90 -> 0 | FB90: =BZ90*$EJ90 -> 0 | FC90: =CA90*$EJ90 -> 0 | FD90: =CB90*$EJ90 -> 0 | FE90: =CC90*$EJ90 -> 0 | FF90: =CD90*$EJ90 -> 0 | FG90: =CE90*$EJ90 -> 0 | ... FM90: =CK90*$EJ90 -> 0 | FN90: =SUM(EZ90:FM90) -> 0 | FO90: =SUM(EZ90:FJ90) -> 0 | FS90: BARRA DE BEBES | FU90: 0 | FV90: 0 | FW90: =W90 -> 0 | FX90: =X90 -> 0 | FY90: =Y90 -> 0 | FZ90: =Z90 -> 0 | GA90: =AA90 -> 0 | GB90: =AB90 -> 0 | GC90: =AC90 -> 0 | GD90: =AD90 -> 0 | ... GH90: =AH90 -> 0 | GI90: 0 | GJ90: =SUM(FU90:GI90) -> 0 | GK90: 0 | GL90: 0 | GM90: =CO90 -> 0 | GN90: =CP90 -> 0 | GO90: =CQ90 -> 0 | GP90: =CR90 -> 0 | GQ90: =CS90 -> 0 | GR90: =CT90 -> 0 | GS90: =CU90 -> 0 | GT90: =CV90 -> 0 | ... GX90: =CZ90 -> 0 | GY90: 0 | GZ90: =SUM(GK90:GY90) -> 0 | HA90: =SUM(GK90:GY90) -> 0
EI91: JEANS | EJ91: 357 | EK91: =$EJ91*F91 -> 0 | EL91: =$EJ91*G91 -> 0 | EM91: =$EJ91*H91 -> 0 | EN91: =$EJ91*I91 -> 0 | EO91: =$EJ91*J91 -> 0 | EP91: =$EJ91*K91 -> 0 | EQ91: =$EJ91*L91 -> 0 | ER91: =$EJ91*M91 -> 0 | ... EX91: =$EJ91*S91 -> 0 | EY91: =SUM(EK91:EX91) -> 0 | EZ91: =BX91*$EJ91 -> 0 | FA91: =BY91*$EJ91 -> 0 | FB91: =BZ91*$EJ91 -> 0 | FC91: =CA91*$EJ91 -> 0 | FD91: =CB91*$EJ91 -> 0 | FE91: =CC91*$EJ91 -> 0 | FF91: =CD91*$EJ91 -> 0 | FG91: =CE91*$EJ91 -> 0 | ... FM91: =CK91*$EJ91 -> 0 | FN91: =SUM(EZ91:FM91) -> 0 | FO91: =SUM(EZ91:FJ91) -> 0 | FS91: JEANS | FU91: 0 | FV91: 0 | FW91: =W91 -> 0 | FX91: =X91 -> 0 | FY91: =Y91 -> 0 | FZ91: 0 | GA91: 0 | GB91: 0 | GC91: =AC91 -> 0 | GD91: =AD91 -> 0 | GE91: =AE91 -> 0 | GF91: =AF91 -> 0 | GG91: =AG91 -> 0 | GH91: 0 | GI91: =AI91 -> 0 | GJ91: =SUM(FU91:GI91) -> 0 | GK91: 0 | GL91: 0 | GM91: =CO91 -> 0 | GN91: =CP91 -> 0 | GO91: =CQ91 -> 0 | GP91: 0 | GQ91: 0 | GR91: 0 | GS91: =CU91 -> 0 | GT91: =CV91 -> 0 | GU91: =CW91 -> 0 | GV91: =CX91 -> 0 | GW91: =CY91 -> 0 | GX91: 0 | GY91: =DA91 -> 0 | GZ91: =SUM(GK91:GY91) -> 0 | HA91: =SUM(GK91:GY91) -> 0
EI92: MOCHILAS | EJ92: 482 | EK92: =$EJ92*F92 -> 0 | EL92: =$EJ92*G92 -> 0 | EM92: =$EJ92*H92 -> 0 | EN92: =$EJ92*I92 -> 0 | EO92: =$EJ92*J92 -> 0 | EP92: =$EJ92*K92 -> 0 | EQ92: =$EJ92*L92 -> 0 | ER92: =$EJ92*M92 -> 0 | ... EX92: =$EJ92*S92 -> 0 | EY92: =SUM(EK92:EX92) -> 0 | EZ92: =BX92*$EJ92 -> 0 | FA92: =BY92*$EJ92 -> 0 | FB92: =BZ92*$EJ92 -> 0 | FC92: =CA92*$EJ92 -> 0 | FD92: =CB92*$EJ92 -> 0 | FE92: =CC92*$EJ92 -> 0 | FF92: =CD92*$EJ92 -> 0 | FG92: =CE92*$EJ92 -> 0 | ... FM92: =CK92*$EJ92 -> 0 | FN92: =SUM(EZ92:FM92) -> 0 | FO92: =SUM(EZ92:FJ92) -> 0 | FS92: MOCHILAS | FU92: =U92 -> 0 | FV92: =V92 -> 0 | FW92: =W92 -> 0 | FX92: =X92 -> 0 | FY92: =Y92 -> 0 | FZ92: =Z92 -> 0 | GA92: =AA92 -> 0 | GB92: =AB92 -> 0 | ... GI92: =AI92 -> 0 | GJ92: =SUM(FU92:GI92) -> 0 | GK92: =CM92 -> 0 | GL92: =CN92 -> 0 | GM92: =CO92 -> 0 | GN92: =CP92 -> 0 | GO92: =CQ92 -> 0 | GP92: =CR92 -> 0 | GQ92: =CS92 -> 0 | GR92: =CT92 -> 0 | ... GX92: =CZ92 -> 0 | GY92: 0 | GZ92: =SUM(GK92:GY92) -> 0 | HA92: =SUM(GK92:GY92) -> 0
EI93: HASTA | EJ93: 275.36 | EK93: =$EJ93*F93 -> 0 | EL93: =$EJ93*G93 -> 0 | EM93: =$EJ93*H93 -> 0 | EN93: =$EJ93*I93 -> 0 | EO93: =$EJ93*J93 -> 0 | EP93: =$EJ93*K93 -> 0 | EQ93: =$EJ93*L93 -> 0 | ER93: =$EJ93*M93 -> 0 | ... EX93: =$EJ93*S93 -> 0 | EY93: =SUM(EK93:EX93) -> 0 | EZ93: =BX93*$EJ93 -> 0 | FA93: =BY93*$EJ93 -> 0 | FB93: =BZ93*$EJ93 -> 0 | FC93: =CA93*$EJ93 -> 0 | FD93: =CB93*$EJ93 -> 0 | FE93: =CC93*$EJ93 -> 0 | FF93: =CD93*$EJ93 -> 0 | FG93: =CE93*$EJ93 -> 0 | ... FM93: =CK93*$EJ93 -> 0 | FN93: =SUM(EZ93:FM93) -> 0 | FO93: =SUM(EZ93:FJ93) -> 0 | FS93: HASTA | FU93: =U93 -> 0 | FV93: =V93 -> 0 | FW93: =W93 -> 0 | FX93: =X93 -> 0 | FY93: =Y93 -> 0 | FZ93: =Z93 -> 0 | GA93: =AA93 -> 0 | GB93: =AB93 -> 0 | ... GH93: =AH93 -> 0 | GI93: 0 | GJ93: =SUM(FU93:GI93) -> 0 | GK93: =CM93 -> 0 | GL93: =CN93 -> 0 | GM93: =CO93 -> 0 | GN93: =CP93 -> 0 | GO93: =CQ93 -> 0 | GP93: =CR93 -> 0 | GQ93: =CS93 -> 0 | GR93: =CT93 -> 0 | ... GX93: =CZ93 -> 0 | GY93: 0 | GZ93: =SUM(GK93:GY93) -> 0 | HA93: =SUM(GK93:GY93) -> 0
B94: Total | C94: =SUM(C78:C93) -> 0 | D94: =SUM(D78:D93) -> 0 | E94: =D94/C94 -> #DIV/0! | F94: =SUM(F78:F93) -> 0 | H94: =SUM(H78:H93) -> 0 | I94: =SUM(I78:I93) -> 0 | J94: =SUM(J78:J93) -> 0 | K94: =SUM(K78:K93) -> 0 | L94: =SUM(L78:L93) -> 0 | N94: =SUM(N78:N93) -> 0 | O94: =SUM(O78:O93) -> 0 | P94: =SUM(P78:P93) -> 0 | T94: =SUM(F94:P94) -> 0 | U94: =SUM(U78:U93) -> 0 | V94: =SUM(V78:V93) -> 0 | W94: =SUM(W78:W93) -> 0 | X94: =SUM(X78:X93) -> 0 | Y94: =SUM(Y78:Y93) -> 0 | Z94: =SUM(Z78:Z93) -> 0 | AA94: =SUM(AA78:AA93) -> 0 | AB94: =SUM(AB78:AB93) -> 0 | ... AI94: =SUM(AI78:AI93) -> 0 | BW94: Total | BX94: =SUM(BX78:BX93) -> 0 | BZ94: =SUM(BZ78:BZ93) -> 0 | CA94: =SUM(CA78:CA93) -> 0 | CB94: =SUM(CB78:CB93) -> 0 | CC94: =SUM(CC78:CC93) -> 0 | CD94: =SUM(CD78:CD93) -> 0 | CF94: =SUM(CF78:CF93) -> 0 | CG94: =SUM(CG78:CG93) -> 0 | CH94: =SUM(CH78:CH93) -> 0 | CL94: =SUM(BX94:CH94) -> 0 | CM94: =SUM(CM78:CM93) -> 0 | CN94: =SUM(CN78:CN93) -> 0 | CO94: =SUM(CO78:CO93) -> 0 | CP94: =SUM(CP78:CP93) -> 0 | CQ94: =SUM(CQ78:CQ93) -> 0 | CR94: =SUM(CR78:CR93) -> 0 | CS94: =SUM(CS78:CS93) -> 0 | CT94: =SUM(CT78:CT93) -> 0 | ... DA94: =SUM(DA78:DA93) -> 0 | EJ94: TOTAL CALZADO | EK94: =EK78+EK79+EK80+EK81+EK82+EK83+EK84+EK85+EK86+EK89+EK90+EK92+EK93 -> 0 | EL94: =EL78+EL79+EL80+EL81+EL82+EL83+EL84+EL85+EL86+EL89+EL90+EL92+EL93 -> 0 | EM94: =EM78+EM79+EM80+EM81+EM82+EM83+EM84+EM85+EM86+EM89+EM90+EM92+EM93 -> 0 | EN94: =EN78+EN79+EN80+EN81+EN82+EN83+EN84+EN85+EN86+EN89+EN90+EN92+EN93 -> 0 | EO94: =EO78+EO79+EO80+EO81+EO82+EO83+EO84+EO85+EO86+EO89+EO90+EO92+EO93 -> 0 | EP94: =EP78+EP79+EP80+EP81+EP82+EP83+EP84+EP85+EP86+EP89+EP90+EP92+EP93 -> 0 | EQ94: =EQ78+EQ79+EQ80+EQ81+EQ82+EQ83+EQ84+EQ85+EQ86+EQ89+EQ90+EQ92+EQ93 -> 0 | ER94: =ER78+ER79+ER80+ER81+ER82+ER83+ER84+ER85+ER86+ER89+ER90+ER92+ER93 -> 0 | ... FN94: =FN78+FN79+FN80+FN81+FN82+FN83+FN84+FN85+FN86+FN89+FN90+FN92+FN93 -> 0 | FS94: TOTAL CALZADO | FU94: =FU78+FU79+FU80+FU81+FU82+FU83+FU84+FU85+FU86+FU89+FU90+FU92+FU93 -> 0 | FV94: =FV78+FV79+FV80+FV81+FV82+FV83+FV84+FV85+FV86+FV89+FV90+FV92+FV93 -> 0 | FW94: =FW78+FW79+FW80+FW81+FW82+FW83+FW84+FW85+FW86+FW89+FW90+FW92+FW93 -> 0 | FX94: =FX78+FX79+FX80+FX81+FX82+FX83+FX84+FX85+FX86+FX89+FX90+FX92+FX93 -> 0 | FY94: =FY78+FY79+FY80+FY81+FY82+FY83+FY84+FY85+FY86+FY89+FY90+FY92+FY93 -> 0 | FZ94: =FZ78+FZ79+FZ80+FZ81+FZ82+FZ83+FZ84+FZ85+FZ86+FZ89+FZ90+FZ92+FZ93 -> 0 | GA94: =GA78+GA79+GA80+GA81+GA82+GA83+GA84+GA85+GA86+GA89+GA90+GA92+GA93 -> 0 | GB94: =GB78+GB79+GB80+GB81+GB82+GB83+GB84+GB85+GB86+GB89+GB90+GB92+GB93 -> 0 | ... GZ94: =GZ78+GZ79+GZ80+GZ81+GZ82+GZ83+GZ84+GZ85+GZ86+GZ89+GZ90+GZ92+GZ93 -> 0
C95: Costo de Oportunidad | F95: =SUM(T78:T93) -> 0 | BX95: =SUM(CL78:CL93) -> 0 | EJ95: TOTAL ROPA | EK95: =EK87+EK88+EK91 -> 0 | EL95: =EL87+EL88+EL91 -> 0 | EM95: =EM87+EM88+EM91 -> 0 | EN95: =EN87+EN88+EN91 -> 0 | EO95: =EO87+EO88+EO91 -> 0 | EP95: =EP87+EP88+EP91 -> 0 | EQ95: =EQ87+EQ88+EQ91 -> 0 | ER95: =ER87+ER88+ER91 -> 0 | ... FN95: =FN87+FN88+FN91 -> 0 | FS95: TOTAL ROPA | FU95: =FU87+FU88+FU91 -> 0 | FV95: =FV87+FV88+FV91 -> 0 | FW95: =FW87+FW88+FW91 -> 0 | FX95: =FX87+FX88+FX91 -> 0 | FY95: =FY87+FY88+FY91 -> 0 | FZ95: =FZ87+FZ88+FZ91 -> 0 | GA95: =GA87+GA88+GA91 -> 0 | GB95: =GB87+GB88+GB91 -> 0 | ... GZ95: =GZ87+GZ88+GZ91 -> 0
F98: Causas de Negado | U98: Incidencias de Auditoria | BX98: Causas de Negado | CM98: Incidencias de Auditoria | EK98: $ negados
A99: Centro Historico | B99: Responsable De Catalogo | C99: Tallas por pasillo | D99: Tallas por modelo | E99: % de Cobertura de auditoria | F99: Frenteos | G99: Ubicación Revuelta | H99: Bodega Venta (Sin marcar) | I99: Bodega Tapanco | J99: Doble Ubicación | K99: Excedente | L99: Origen | M99: Cambios/Probadores | N99: Negados Sin Recuperar | O99: Exhibición | P99: Bodega Aclaración | Q99: Aduanas | R99: Golden o apartados | S99: Control de calidad | T99: Costo por pasillo | U99: Sin Exhibición | V99: Exhibición fuera de Política | W99: Modelos revuelto | X99: Modelos mal entallados | Y99: Modelos con error de ubicación | Z99: Curva con diferencia en frentes | AA99: Curva con diferencia en fondos | AB99: Curva con diferencia en altura | AC99: Curvas vencidas | AD99: Curvas que no coincide Price Soft vs Piso de Venta | AE99: Curvas faltantes | AF99: Cenefas faltantes | AG99: Cenefas de precio Promoción faltantes | AH99: Cartas disculpa / destallados faltantes | AI99: Fechas de llegada faltantes | AJ99: Resultado de Check List | AK99: Resultado de banderazo surtido | AM99: Tallas por pasillo | AN99: Tallas por modelo | AO99: % de Cobertura de auditoria | AP99: Frenteos | AQ99: Ubicación Revuelta | AR99: Bodega Venta (Sin marcar) | AS99: Bodega Tapanco | AT99: Doble Ubicación | AU99: Excedente | AV99: Origen | AW99: Cambios/Probadores | AX99: Negados Sin Recuperar | AY99: Exhibición | AZ99: Bodega Aclaración | BA99: Aduanas | BB99: Golden o apartados | BC99: Control de calidad | BD99: Costo por pasillo | BE99: Sin Exhibición | BF99: Exhibición fuera de Política | BG99: Modelos revuelto | BH99: Modelos mal entallados | BI99: Modelos con error de ubicación | BJ99: Curva con diferencia en frentes | BK99: Curva con diferencia en fondos | BL99: Curva con diferencia en altura | BM99: Curvas vencidas | BN99: Curvas que no coincide Price Soft vs Piso de Venta | BO99: Curvas faltantes | BP99: Cenefas faltantes | BQ99: Cenefas de precio Promoción faltantes | BR99: Cartas disculpa / destallados faltantes | BS99: Fechas de llegada faltantes | BT99: Resultado de Check List | BU99: Resultado de banderazo surtido | BV99: Centro Historico | BW99: Responsable de Catalogo | BX99: Frenteos | BY99: Ubicación Revuelta | BZ99: Bodega Venta (Sin marcar) | CA99: Bodega Tapanco | CB99: Doble Ubicación | CC99: Excedente | CD99: Origen | CE99: Cambios/Probadores | CF99: Negados Sin Recuperar | CG99: Exhibición | CH99: Bodega Aclaración | CI99: Aduanas | CJ99: Golden o apartados | CK99: Control de calidad | CL99: Costo por pasillo | CM99: Sin Exhibición | CN99: Exhibición fuera de Política | CO99: Modelos revuelto | CP99: Modelos mal entallados | CQ99: Modelos con error de ubicación | CR99: Curva con diferencia en frentes | CS99: Curva con diferencia en fondos | CT99: Curva con diferencia en altura | CU99: Curvas vencidas | CV99: Curvas que no coincide Price Soft vs Piso de Venta | CW99: Curvas faltantes | CX99: Cenefas faltantes | CY99: Cenefas de precio Promoción faltantes | CZ99: Cartas disculpa / destallados faltantes | DA99: Fechas de llegada faltantes | DB99: Resultado de Check List | DE99: Frenteos | DF99: Ubicación Revuelta | DG99: Bodega Venta (Sin marcar) | DH99: Bodega Tapanco | DI99: Doble Ubicación | DJ99: Excedente | DK99: Origen | DL99: Cambios/Probadores | DM99: Negados Sin Recuperar | DN99: Exhibición | DO99: Bodega Aclaración | DP99: Aduanas | DQ99: Golden o apartados | DR99: Control de calidad | DS99: Costo por pasillo | DT99: Sin Exhibición | DU99: Exhibición fuera de Política | DV99: Modelos revuelto | DW99: Modelos mal entallados | DX99: Modelos con error de ubicación | DY99: Curva con diferencia en frentes | DZ99: Curva con diferencia en fondos | EA99: Curva con diferencia en altura | EB99: Curvas vencidas | EC99: Curvas que no coincide Price Soft vs Piso de Venta | ED99: Curvas faltantes | EE99: Cenefas faltantes | EF99: Cenefas de precio Promoción faltantes | EG99: Cartas disculpa / destallados faltantes | EH99: Fechas de llegada faltantes | EK99: Frenteos | EL99: Ubicación Revuelta | EM99: Bodega Venta (Sin marcar) | EN99: Bodega Tapanco | EO99: Doble Ubicación | EP99: Excedente | EQ99: Origen | ER99: Cambios/Probadores | ES99: Negados Sin Recuperar | ET99: Exhibición | EU99: Bodega Aclaración | EV99: Aduanas | EW99: Golden o apartados | EX99: Control de calidad | EZ99: Frenteos | FA99: Ubicación Revuelta | FB99: Bodega Venta (Sin marcar) | FC99: Bodega Tapanco | FD99: Doble Ubicación | FE99: Excedente | FF99: Origen | FG99: Cambios/Probadores | FH99: Negados Sin Recuperar | FI99: Exhibición | FJ99: Bodega Aclaración | FK99: Aduanas | FL99: Golden o apartados | FM99: Control de calidad | FU99: Sin Exhibición | FV99: Exhibición fuera de Política | FW99: Modelos revuelto | FX99: Modelos mal entallados | FY99: Modelos con error de ubicación | FZ99: Curva con diferencia en frentes | GA99: Curva con diferencia en fondos | GB99: Curva con diferencia en altura | GC99: Curvas vencidas | GD99: Curvas que no coincide Price Soft vs Piso de Venta | GE99: Curvas faltantes | GF99: Cenefas faltantes | GG99: Cenefas de precio Promoción faltantes | GH99: Cartas disculpa / destallados faltantes | GI99: modelos que no cadran con planograma | GK99: Sin Exhibición | GL99: Exhibición fuera de Política | GM99: Modelos revuelto | GN99: Modelos mal entallados | GO99: Modelos con error de ubicación | GP99: Curva con diferencia en frentes | GQ99: Curva con diferencia en fondos | GR99: Curva con diferencia en altura | GS99: Curvas vencidas | GT99: Curvas que no coincide Price Soft vs Piso de Venta | GU99: Curvas faltantes | GV99: Cenefas faltantes | GW99: Cenefas de precio Promoción faltantes | GX99: Cartas disculpa / destallados faltantes | GY99: modelos que no cadran con planograma
AM100: =SUM(C100,C101,C102,C103,C104,C105,C106,C107,C108,C111,C112,C114,C115) -> 0 | AN100: =SUM(D100,D101,D102,D103,D104,D105,D106,D107,D108,D111,D112,D114,D115) -> 0 | AO100: =IF(AN100=0,"",AN100/AM100) | AP100: =SUM(F100,F101,F102,F103,F104,F105,F106,F107,F108,F111,F112,F114,F115) -> 0 | AQ100: =SUM(G100,G101,G102,G103,G104,G105,G106,G107,G108,G111,G112,G114,G115) -> 0 | AR100: =SUM(H100,H101,H102,H103,H104,H105,H106,H107,H108,H111,H112,H114,H115) -> 0 | AS100: =SUM(I100,I101,I102,I103,I104,I105,I106,I107,I108,I111,I112,I114,I115) -> 0 | AT100: =SUM(J100,J101,J102,J103,J104,J105,J106,J107,J108,J111,J112,J114,J115) -> 0 | AU100: =SUM(K100,K101,K102,K103,K104,K105,K106,K107,K108,K111,K112,K114,K115) -> 0 | AV100: =SUM(L100,L101,L102,L103,L104,L105,L106,L107,L108,L111,L112,L114,L115) -> 0 | AW100: =SUM(M100,M101,M102,M103,M104,M105,M106,M107,M108,M111,M112,M114,M115) -> 0 | ... BU100: =SUM(AK100,AK101,AK102,AK103,AK104,AK105,AK106,AK107,AK108,AK111,AK112,AK114,AK115) -> 0 | DD100: =(DD94/BZ106) -> #DIV/0! | DE100: =SUM(BX100,BX101,BX102,BX103,BX104,BX105,BX106,BX107,BX108,BX111,BX112,BX114,BX115) -> 0 | DF100: =SUM(BY100,BY101,BY102,BY103,BY104,BY105,BY106,BY107,BY108,BY111,BY112,BY114,BY115) -> 0 | DG100: =SUM(BZ100,BZ101,BZ102,BZ103,BZ104,BZ105,BZ106,BZ107,BZ108,BZ111,BZ112,BZ114,BZ115) -> 0 | DH100: =SUM(CA100,CA101,CA102,CA103,CA104,CA105,CA106,CA107,CA108,CA111,CA112,CA114,CA115) -> 0 | DI100: =SUM(CB100,CB101,CB102,CB103,CB104,CB105,CB106,CB107,CB108,CB111,CB112,CB114,CB115) -> 0 | DJ100: =SUM(CC100,CC101,CC102,CC103,CC104,CC105,CC106,CC107,CC108,CC111,CC112,CC114,CC115) -> 0 | DK100: =SUM(CD100,CD101,CD102,CD103,CD104,CD105,CD106,CD107,CD108,CD111,CD112,CD114,CD115) -> 0 | DL100: =SUM(CE100,CE101,CE102,CE103,CE104,CE105,CE106,CE107,CE108,CE111,CE112,CE114,CE115) -> 0 | ... EH100: =SUM(DA100,DA101,DA102,DA103,DA104,DA105,DA106,DA107,DA108,DA111,DA112,DA114,DA115) -> 0 | EI100: BOTAS | EJ100: 521 | EK100: =$EJ100*F100 -> 0 | EL100: =$EJ100*G100 -> 0 | EM100: =$EJ100*H100 -> 0 | EN100: =$EJ100*I100 -> 0 | EO100: =$EJ100*J100 -> 0 | EP100: =$EJ100*K100 -> 0 | EQ100: =$EJ100*L100 -> 0 | ER100: =$EJ100*M100 -> 0 | ... EX100: =$EJ100*S100 -> 0 | EY100: =SUM(EK100:EX100) -> 0 | EZ100: =BX100*$EJ100 -> 0 | FA100: =BY100*$EJ100 -> 0 | FB100: =BZ100*$EJ100 -> 0 | FC100: =CA100*$EJ100 -> 0 | FD100: =CB100*$EJ100 -> 0 | FE100: =CC100*$EJ100 -> 0 | FF100: =CD100*$EJ100 -> 0 | FG100: =CE100*$EJ100 -> 0 | ... FM100: =CK100*$EJ100 -> 0 | FN100: =SUM(EZ100:FM100) -> 0 | FO100: =SUM(EZ100:FJ100) -> 0 | FS100: BOTAS | FU100: =U100 -> 0 | FV100: =V100 -> 0 | FW100: =W100 -> 0 | FX100: =X100 -> 0 | FY100: =Y100 -> 0 | FZ100: =Z100 -> 0 | GA100: =AA100 -> 0 | GB100: =AB100 -> 0 | ... GH100: =AH100 -> 0 | GI100: 0 | GJ100: =SUM(FU100:GI100) -> 0 | GK100: =CM100 -> 0 | GL100: =CN100 -> 0 | GM100: =CO100 -> 0 | GN100: =CP100 -> 0 | GO100: =CQ100 -> 0 | GP100: =CR100 -> 0 | GQ100: =CS100 -> 0 | GR100: =CT100 -> 0 | ... GX100: =CZ100 -> 0 | GY100: 0 | GZ100: =SUM(GK100:GY100) -> 0 | HA100: =SUM(GK100:GY100) -> 0
AO101: =IF(AN101=0,"",AN101/AM101) | EI101: URBANO | EJ101: 540 | EK101: =$EJ101*F101 -> 0 | EL101: =$EJ101*G101 -> 0 | EM101: =$EJ101*H101 -> 0 | EN101: =$EJ101*I101 -> 0 | EO101: =$EJ101*J101 -> 0 | EP101: =$EJ101*K101 -> 0 | EQ101: =$EJ101*L101 -> 0 | ER101: =$EJ101*M101 -> 0 | ... EX101: =$EJ101*S101 -> 0 | EY101: =SUM(EK101:EX101) -> 0 | EZ101: =BX101*$EJ101 -> 0 | FA101: =BY101*$EJ101 -> 0 | FB101: =BZ101*$EJ101 -> 0 | FC101: =CA101*$EJ101 -> 0 | FD101: =CB101*$EJ101 -> 0 | FE101: =CC101*$EJ101 -> 0 | FF101: =CD101*$EJ101 -> 0 | FG101: =CE101*$EJ101 -> 0 | ... FM101: =CK101*$EJ101 -> 0 | FN101: =SUM(EZ101:FM101) -> 0 | FO101: =SUM(EZ101:FJ101) -> 0 | FS101: URBANO | FU101: =U101 -> 0 | FV101: =V101 -> 0 | FW101: =W101 -> 0 | FX101: =X101 -> 0 | FY101: =Y101 -> 0 | FZ101: =Z101 -> 0 | GA101: =AA101 -> 0 | GB101: =AB101 -> 0 | ... GH101: =AH101 -> 0 | GI101: 0 | GJ101: =SUM(FU101:GI101) -> 0 | GK101: =CM101 -> 0 | GL101: =CN101 -> 0 | GM101: =CO101 -> 0 | GN101: =CP101 -> 0 | GO101: =CQ101 -> 0 | GP101: =CR101 -> 0 | GQ101: =CS101 -> 0 | GR101: =CT101 -> 0 | ... GX101: =CZ101 -> 0 | GY101: 0 | GZ101: =SUM(GK101:GY101) -> 0 | HA101: =SUM(GK101:GY101) -> 0
AL102: % de tallas negadas | AM102: =SUM(C109,C110,C113) -> 0 | AN102: =SUM(D109,D110,D113) -> 0 | AO102: =IF(AN102=0,"",AN102/AM102) | AP102: =SUM(F109,F110,F113) -> 0 | AQ102: =SUM(G109,G110,G113) -> 0 | AR102: =SUM(H109,H110,H113) -> 0 | AS102: =SUM(I109,I110,I113) -> 0 | AT102: =SUM(J109,J110,J113) -> 0 | AU102: =SUM(K109,K110,K113) -> 0 | AV102: =SUM(L109,L110,L113) -> 0 | AW102: =SUM(M109,M110,M113) -> 0 | ... BS102: =SUM(AI109,AI110,AI113) -> 0 | BT102: =AVERAGE(AJ109,AJ110,AJ113) -> #DIV/0! | DC102: % de tallas recuperadas | DE102: =SUM(BX109,BX110,BX113) -> 0 | DF102: =SUM(BY109,BY110,BY113) -> 0 | DG102: =SUM(BZ109,BZ110,BZ113) -> 0 | DH102: =SUM(CA109,CA110,CA113) -> 0 | DI102: =SUM(CB109,CB110,CB113) -> 0 | DJ102: =SUM(CC109,CC110,CC113) -> 0 | DK102: =SUM(CD109,CD110,CD113) -> 0 | DL102: =SUM(CE109,CE110,CE113) -> 0 | ... EH102: =SUM(DA109,DA110,DA113) -> 0 | EI102: ESCOLAR | EJ102: 441.24 | EK102: =$EJ102*F102 -> 0 | EL102: =$EJ102*G102 -> 0 | EM102: =$EJ102*H102 -> 0 | EN102: =$EJ102*I102 -> 0 | EO102: =$EJ102*J102 -> 0 | EP102: =$EJ102*K102 -> 0 | EQ102: =$EJ102*L102 -> 0 | ER102: =$EJ102*M102 -> 0 | ... EX102: =$EJ102*S102 -> 0 | EY102: =SUM(EK102:EX102) -> 0 | EZ102: =BX102*$EJ102 -> 0 | FA102: =BY102*$EJ102 -> 0 | FB102: =BZ102*$EJ102 -> 0 | FC102: =CA102*$EJ102 -> 0 | FD102: =CB102*$EJ102 -> 0 | FE102: =CC102*$EJ102 -> 0 | FF102: =CD102*$EJ102 -> 0 | FG102: =CE102*$EJ102 -> 0 | ... FM102: =CK102*$EJ102 -> 0 | FN102: =SUM(EZ102:FM102) -> 0 | FO102: =SUM(EZ102:FJ102) -> 0 | FS102: ESCOLAR | FU102: =U102 -> 0 | FV102: =V102 -> 0 | FW102: =W102 -> 0 | FX102: =X102 -> 0 | FY102: =Y102 -> 0 | FZ102: =Z102 -> 0 | GA102: =AA102 -> 0 | GB102: =AB102 -> 0 | ... GH102: =AH102 -> 0 | GI102: 0 | GJ102: =SUM(FU102:GI102) -> 0 | GK102: =CM102 -> 0 | GL102: =CN102 -> 0 | GM102: =CO102 -> 0 | GN102: =CP102 -> 0 | GO102: =CQ102 -> 0 | GP102: =CR102 -> 0 | GQ102: =CS102 -> 0 | GR102: =CT102 -> 0 | ... GX102: =CZ102 -> 0 | GY102: 0 | GZ102: =SUM(GK102:GY102) -> 0 | HA102: =SUM(GK102:GY102) -> 0
EI103: SANDALIAS | EJ103: 294.47 | EK103: =$EJ103*F103 -> 0 | EL103: =$EJ103*G103 -> 0 | EM103: =$EJ103*H103 -> 0 | EN103: =$EJ103*I103 -> 0 | EO103: =$EJ103*J103 -> 0 | EP103: =$EJ103*K103 -> 0 | EQ103: =$EJ103*L103 -> 0 | ER103: =$EJ103*M103 -> 0 | ... EX103: =$EJ103*S103 -> 0 | EY103: =SUM(EK103:EX103) -> 0 | EZ103: =BX103*$EJ103 -> 0 | FA103: =BY103*$EJ103 -> 0 | FB103: =BZ103*$EJ103 -> 0 | FC103: =CA103*$EJ103 -> 0 | FD103: =CB103*$EJ103 -> 0 | FE103: =CC103*$EJ103 -> 0 | FF103: =CD103*$EJ103 -> 0 | FG103: =CE103*$EJ103 -> 0 | ... FM103: =CK103*$EJ103 -> 0 | FN103: =SUM(EZ103:FM103) -> 0 | FO103: =SUM(EZ103:FJ103) -> 0 | FS103: SANDALIAS | FU103: =U103 -> 0 | FV103: =V103 -> 0 | FW103: =W103 -> 0 | FX103: =X103 -> 0 | FY103: =Y103 -> 0 | FZ103: =Z103 -> 0 | GA103: =AA103 -> 0 | GB103: =AB103 -> 0 | ... GH103: =AH103 -> 0 | GI103: 0 | GJ103: =SUM(FU103:GI103) -> 0 | GK103: =CM103 -> 0 | GL103: =CN103 -> 0 | GM103: =CO103 -> 0 | GN103: =CP103 -> 0 | GO103: =CQ103 -> 0 | GP103: =CR103 -> 0 | GQ103: =CS103 -> 0 | GR103: =CT103 -> 0 | ... GX103: =CZ103 -> 0 | GY103: 0 | GZ103: =SUM(GK103:GY103) -> 0 | HA103: =SUM(GK103:GY103) -> 0
AL104: =T116/D116 -> #DIV/0! | AO104: =16*306 -> 4896 | DC104: =CL116/T116 -> #DIV/0! | EI104: CONFORT | EJ104: 422 | EK104: =$EJ104*F104 -> 0 | EL104: =$EJ104*G104 -> 0 | EM104: =$EJ104*H104 -> 0 | EN104: =$EJ104*I104 -> 0 | EO104: =$EJ104*J104 -> 0 | EP104: =$EJ104*K104 -> 0 | EQ104: =$EJ104*L104 -> 0 | ER104: =$EJ104*M104 -> 0 | ... EX104: =$EJ104*S104 -> 0 | EY104: =SUM(EK104:EX104) -> 0 | EZ104: =BX104*$EJ104 -> 0 | FA104: =BY104*$EJ104 -> 0 | FB104: =BZ104*$EJ104 -> 0 | FC104: =CA104*$EJ104 -> 0 | FD104: =CB104*$EJ104 -> 0 | FE104: =CC104*$EJ104 -> 0 | FF104: =CD104*$EJ104 -> 0 | FG104: =CE104*$EJ104 -> 0 | ... FM104: =CK104*$EJ104 -> 0 | FN104: =SUM(EZ104:FM104) -> 0 | FO104: =SUM(EZ104:FJ104) -> 0 | FS104: CONFORT | FU104: =U104 -> 0 | FV104: =V104 -> 0 | FW104: =W104 -> 0 | FX104: =X104 -> 0 | FY104: =Y104 -> 0 | FZ104: =Z104 -> 0 | GA104: =AA104 -> 0 | GB104: =AB104 -> 0 | ... GH104: =AH104 -> 0 | GI104: 0 | GJ104: =SUM(FU104:GI104) -> 0 | GK104: =CM104 -> 0 | GL104: =CN104 -> 0 | GM104: =CO104 -> 0 | GN104: =CP104 -> 0 | GO104: =CQ104 -> 0 | GP104: =CR104 -> 0 | GQ104: =CS104 -> 0 | GR104: =CT104 -> 0 | ... GX104: =CZ104 -> 0 | GY104: 0 | GZ104: =SUM(GK104:GY104) -> 0 | HA104: =SUM(GK104:GY104) -> 0
EI105: VESTIR CASUAL | EJ105: 416.19 | EK105: =$EJ105*F105 -> 0 | EL105: =$EJ105*G105 -> 0 | EM105: =$EJ105*H105 -> 0 | EN105: =$EJ105*I105 -> 0 | EO105: =$EJ105*J105 -> 0 | EP105: =$EJ105*K105 -> 0 | EQ105: =$EJ105*L105 -> 0 | ER105: =$EJ105*M105 -> 0 | ... EX105: =$EJ105*S105 -> 0 | EY105: =SUM(EK105:EX105) -> 0 | EZ105: =BX105*$EJ105 -> 0 | FA105: =BY105*$EJ105 -> 0 | FB105: =BZ105*$EJ105 -> 0 | FC105: =CA105*$EJ105 -> 0 | FD105: =CB105*$EJ105 -> 0 | FE105: =CC105*$EJ105 -> 0 | FF105: =CD105*$EJ105 -> 0 | FG105: =CE105*$EJ105 -> 0 | ... FM105: =CK105*$EJ105 -> 0 | FN105: =SUM(EZ105:FM105) -> 0 | FO105: =SUM(EZ105:FJ105) -> 0 | FS105: VESTIR CASUAL | FU105: =U105 -> 0 | FV105: =V105 -> 0 | FW105: =W105 -> 0 | FX105: =X105 -> 0 | FY105: =Y105 -> 0 | FZ105: =Z105 -> 0 | GA105: =AA105 -> 0 | GB105: =AB105 -> 0 | ... GH105: =AH105 -> 0 | GI105: 0 | GJ105: =SUM(FU105:GI105) -> 0 | GK105: =CM105 -> 0 | GL105: =CN105 -> 0 | GM105: =CO105 -> 0 | GN105: =CP105 -> 0 | GO105: =CQ105 -> 0 | GP105: =CR105 -> 0 | GQ105: =CS105 -> 0 | GR105: =CT105 -> 0 | ... GX105: =CZ105 -> 0 | GY105: 0 | GZ105: =SUM(GK105:GY105) -> 0 | HA105: =SUM(GK105:GY105) -> 0
AL106: Diferencia Negado VS Recuperado | EI106: INFANTILES | EJ106: 375 | EK106: =$EJ106*F106 -> 0 | EL106: =$EJ106*G106 -> 0 | EM106: =$EJ106*H106 -> 0 | EN106: =$EJ106*I106 -> 0 | EO106: =$EJ106*J106 -> 0 | EP106: =$EJ106*K106 -> 0 | EQ106: =$EJ106*L106 -> 0 | ER106: =$EJ106*M106 -> 0 | ... EX106: =$EJ106*S106 -> 0 | EY106: =SUM(EK106:EX106) -> 0 | EZ106: =BX106*$EJ106 -> 0 | FA106: =BY106*$EJ106 -> 0 | FB106: =BZ106*$EJ106 -> 0 | FC106: =CA106*$EJ106 -> 0 | FD106: =CB106*$EJ106 -> 0 | FE106: =CC106*$EJ106 -> 0 | FF106: =CD106*$EJ106 -> 0 | FG106: =CE106*$EJ106 -> 0 | ... FM106: =CK106*$EJ106 -> 0 | FN106: =SUM(EZ106:FM106) -> 0 | FO106: =SUM(EZ106:FJ106) -> 0 | FS106: INFANTILES | FU106: =U106 -> 0 | FV106: =V106 -> 0 | FW106: =W106 -> 0 | FX106: =X106 -> 0 | FY106: =Y106 -> 0 | FZ106: =Z106 -> 0 | GA106: =AA106 -> 0 | GB106: =AB106 -> 0 | ... GH106: =AH106 -> 0 | GI106: 0 | GJ106: =SUM(FU106:GI106) -> 0 | GK106: =CM106 -> 0 | GL106: =CN106 -> 0 | GM106: =CO106 -> 0 | GN106: =CP106 -> 0 | GO106: =CQ106 -> 0 | GP106: =CR106 -> 0 | GQ106: =CS106 -> 0 | GR106: =CT106 -> 0 | ... GX106: =CZ106 -> 0 | GY106: 0 | GZ106: =SUM(GK106:GY106) -> 0 | HA106: =SUM(GK106:GY106) -> 0
EI107: CABALLEROS | EJ107: 730 | EK107: =$EJ107*F107 -> 0 | EL107: =$EJ107*G107 -> 0 | EM107: =$EJ107*H107 -> 0 | EN107: =$EJ107*I107 -> 0 | EO107: =$EJ107*J107 -> 0 | EP107: =$EJ107*K107 -> 0 | EQ107: =$EJ107*L107 -> 0 | ER107: =$EJ107*M107 -> 0 | ... EX107: =$EJ107*S107 -> 0 | EY107: =SUM(EK107:EX107) -> 0 | EZ107: =BX107*$EJ107 -> 0 | FA107: =BY107*$EJ107 -> 0 | FB107: =BZ107*$EJ107 -> 0 | FC107: =CA107*$EJ107 -> 0 | FD107: =CB107*$EJ107 -> 0 | FE107: =CC107*$EJ107 -> 0 | FF107: =CD107*$EJ107 -> 0 | FG107: =CE107*$EJ107 -> 0 | ... FM107: =CK107*$EJ107 -> 0 | FN107: =SUM(EZ107:FM107) -> 0 | FO107: =SUM(EZ107:FJ107) -> 0 | FS107: CABALLEROS | FU107: =U107 -> 0 | FV107: =V107 -> 0 | FW107: =W107 -> 0 | FX107: =X107 -> 0 | FY107: =Y107 -> 0 | FZ107: =Z107 -> 0 | GA107: =AA107 -> 0 | GB107: =AB107 -> 0 | ... GH107: =AH107 -> 0 | GI107: 0 | GJ107: =SUM(FU107:GI107) -> 0 | GK107: =CM107 -> 0 | GL107: =CN107 -> 0 | GM107: =CO107 -> 0 | GN107: =CP107 -> 0 | GO107: =CQ107 -> 0 | GP107: =CR107 -> 0 | GQ107: =CS107 -> 0 | GR107: =CT107 -> 0 | ... GX107: =CZ107 -> 0 | GY107: 0 | GZ107: =SUM(GK107:GY107) -> 0 | HA107: =SUM(GK107:GY107) -> 0
AL108: =o1160bw116 -> #NAME? | EI108: CHANCLERO | EJ108: 178 | EK108: =$EJ108*F108 -> 0 | EL108: =$EJ108*G108 -> 0 | EM108: =$EJ108*H108 -> 0 | EN108: =$EJ108*I108 -> 0 | EO108: =$EJ108*J108 -> 0 | EP108: =$EJ108*K108 -> 0 | EQ108: =$EJ108*L108 -> 0 | ER108: =$EJ108*M108 -> 0 | ... EX108: =$EJ108*S108 -> 0 | EY108: =SUM(EK108:EX108) -> 0 | EZ108: =BX108*$EJ108 -> 0 | FA108: =BY108*$EJ108 -> 0 | FB108: =BZ108*$EJ108 -> 0 | FC108: =CA108*$EJ108 -> 0 | FD108: =CB108*$EJ108 -> 0 | FE108: =CC108*$EJ108 -> 0 | FF108: =CD108*$EJ108 -> 0 | FG108: =CE108*$EJ108 -> 0 | ... FM108: =CK108*$EJ108 -> 0 | FN108: =SUM(EZ108:FM108) -> 0 | FO108: =SUM(EZ108:FJ108) -> 0 | FS108: CHANCLERO | FU108: =U108 -> 0 | FV108: =V108 -> 0 | FW108: =W108 -> 0 | FX108: =X108 -> 0 | FY108: =Y108 -> 0 | FZ108: =Z108 -> 0 | GA108: =AA108 -> 0 | GB108: =AB108 -> 0 | ... GH108: =AH108 -> 0 | GI108: 0 | GJ108: =SUM(FU108:GI108) -> 0 | GK108: =CM108 -> 0 | GL108: =CN108 -> 0 | GM108: =CO108 -> 0 | GN108: =CP108 -> 0 | GO108: =CQ108 -> 0 | GP108: =CR108 -> 0 | GQ108: =CS108 -> 0 | GR108: =CT108 -> 0 | ... GX108: =CZ108 -> 0 | GY108: 0 | GZ108: =SUM(GK108:GY108) -> 0 | HA108: =SUM(GK108:GY108) -> 0
EI109: ROPA DOBLADA | EJ109: 263 | EK109: =$EJ109*F109 -> 0 | EL109: =$EJ109*G109 -> 0 | EM109: =$EJ109*H109 -> 0 | EN109: =$EJ109*I109 -> 0 | EO109: =$EJ109*J109 -> 0 | EP109: =$EJ109*K109 -> 0 | EQ109: =$EJ109*L109 -> 0 | ER109: =$EJ109*M109 -> 0 | ... EX109: =$EJ109*S109 -> 0 | EY109: =SUM(EK109:EX109) -> 0 | EZ109: =BX109*$EJ109 -> 0 | FA109: =BY109*$EJ109 -> 0 | FB109: =BZ109*$EJ109 -> 0 | FC109: =CA109*$EJ109 -> 0 | FD109: =CB109*$EJ109 -> 0 | FE109: =CC109*$EJ109 -> 0 | FF109: =CD109*$EJ109 -> 0 | FG109: =CE109*$EJ109 -> 0 | ... FM109: =CK109*$EJ109 -> 0 | FN109: =SUM(EZ109:FM109) -> 0 | FO109: =SUM(EZ109:FJ109) -> 0 | FS109: ROPA DOBLADA | FU109: 0 | FV109: 0 | FW109: =W109 -> 0 | FX109: =X109 -> 0 | FY109: =Y109 -> 0 | FZ109: 0 | GA109: 0 | GB109: 0 | GC109: =AC109 -> 0 | GD109: =AD109 -> 0 | GE109: =AE109 -> 0 | GF109: =AF109 -> 0 | GG109: =AG109 -> 0 | GH109: 0 | GI109: =AI109 -> 0 | GJ109: =SUM(FU109:GI109) -> 0 | GK109: 0 | GL109: 0 | GM109: =CO109 -> 0 | GN109: =CP109 -> 0 | GO109: =CQ109 -> 0 | GP109: 0 | GQ109: 0 | GR109: 0 | GS109: =CU109 -> 0 | GT109: =CV109 -> 0 | GU109: =CW109 -> 0 | GV109: =CX109 -> 0 | GW109: =CY109 -> 0 | GX109: 0 | GY109: =DA109 -> 0 | GZ109: =SUM(GK109:GY109) -> 0 | HA109: =SUM(GK109:GY109) -> 0
AL110: % de Costo no recuperado | EI110: ROPA COLGADA | EJ110: 405 | EK110: =$EJ110*F110 -> 0 | EL110: =$EJ110*G110 -> 0 | EM110: =$EJ110*H110 -> 0 | EN110: =$EJ110*I110 -> 0 | EO110: =$EJ110*J110 -> 0 | EP110: =$EJ110*K110 -> 0 | EQ110: =$EJ110*L110 -> 0 | ER110: =$EJ110*M110 -> 0 | ... EX110: =$EJ110*S110 -> 0 | EY110: =SUM(EK110:EX110) -> 0 | EZ110: =BX110*$EJ110 -> 0 | FA110: =BY110*$EJ110 -> 0 | FB110: =BZ110*$EJ110 -> 0 | FC110: =CA110*$EJ110 -> 0 | FD110: =CB110*$EJ110 -> 0 | FE110: =CC110*$EJ110 -> 0 | FF110: =CD110*$EJ110 -> 0 | FG110: =CE110*$EJ110 -> 0 | ... FM110: =CK110*$EJ110 -> 0 | FN110: =SUM(EZ110:FM110) -> 0 | FO110: =SUM(EZ110:FJ110) -> 0 | FS110: ROPA COLGADA | FU110: 0 | FV110: 0 | FW110: =W110 -> 0 | FX110: =X110 -> 0 | FY110: =Y110 -> 0 | FZ110: 0 | GA110: 0 | GB110: 0 | GC110: =AC110 -> 0 | GD110: =AD110 -> 0 | GE110: =AE110 -> 0 | GF110: =AF110 -> 0 | GG110: =AG110 -> 0 | GH110: 0 | GI110: =AI110 -> 0 | GJ110: =SUM(FU110:GI110) -> 0 | GK110: 0 | GL110: 0 | GM110: =CO110 -> 0 | GN110: =CP110 -> 0 | GO110: =CQ110 -> 0 | GP110: 0 | GQ110: 0 | GR110: 0 | GS110: =CU110 -> 0 | GT110: =CV110 -> 0 | GU110: =CW110 -> 0 | GV110: =CX110 -> 0 | GW110: =CY110 -> 0 | GX110: =CZ110 -> 0 | GY110: =DA110 -> 0 | GZ110: =SUM(GK110:GY110) -> 0 | HA110: =SUM(GK110:GY110) -> 0
EI111: IMPORTADOS | EJ111: 1287 | EK111: =$EJ111*F111 -> 0 | EL111: =$EJ111*G111 -> 0 | EM111: =$EJ111*H111 -> 0 | EN111: =$EJ111*I111 -> 0 | EO111: =$EJ111*J111 -> 0 | EP111: =$EJ111*K111 -> 0 | EQ111: =$EJ111*L111 -> 0 | ER111: =$EJ111*M111 -> 0 | ... EX111: =$EJ111*S111 -> 0 | EY111: =SUM(EK111:EX111) -> 0 | EZ111: =BX111*$EJ111 -> 0 | FA111: =BY111*$EJ111 -> 0 | FB111: =BZ111*$EJ111 -> 0 | FC111: =CA111*$EJ111 -> 0 | FD111: =CB111*$EJ111 -> 0 | FE111: =CC111*$EJ111 -> 0 | FF111: =CD111*$EJ111 -> 0 | FG111: =CE111*$EJ111 -> 0 | ... FM111: =CK111*$EJ111 -> 0 | FN111: =SUM(EZ111:FM111) -> 0 | FO111: =SUM(EZ111:FJ111) -> 0 | FS111: IMPORTADOS | FU111: 0 | FV111: 0 | FW111: =W111 -> 0 | FX111: =X111 -> 0 | FY111: =Y111 -> 0 | FZ111: =Z111 -> 0 | GA111: =AA111 -> 0 | GB111: =AB111 -> 0 | GC111: =AC111 -> 0 | GD111: =AD111 -> 0 | ... GH111: =AH111 -> 0 | GI111: 0 | GJ111: =SUM(FU111:GI111) -> 0 | GK111: 0 | GL111: 0 | GM111: =CO111 -> 0 | GN111: =CP111 -> 0 | GO111: =CQ111 -> 0 | GP111: =CR111 -> 0 | GQ111: =CS111 -> 0 | GR111: =CT111 -> 0 | GS111: =CU111 -> 0 | GT111: =CV111 -> 0 | ... GX111: =CZ111 -> 0 | GY111: 0 | GZ111: =SUM(GK111:GY111) -> 0 | HA111: =SUM(GK111:GY111) -> 0
...

Sheet SEMANA
A2: Concentrado por Tienda de Dictamen de Auditoria de Dummy | BV2: Recuperación por tienda y rubro
H3: Semana: | J3: "Semana " | V3: Periodo de evaluación: | BZ3: Semana: | CB3: =J3 -> "Semana " | CN3: Periodo de evaluación: | CQ3: =Y3 -> 0
F5: Causas de Negado | U5: Incidencias de Auditoria | BX5: Causas de Negado | CM5: Incidencias de Auditoria
A6: Tiendas | B6: Calzado | C6: Tallas por pasillo | D6: Tallas por modelo | E6: % de Cobertura de auditoria | F6: Frenteos | G6: Ubicación Revuelta | H6: Bodega Venta (Sin marcar) | I6: Bodega Tapanco | J6: Doble Ubicación | K6: Excedente | L6: Origen | M6: Cambios/Probadores | N6: Negados Sin Recuperar | O6: Exhibición | P6: Bodega Aclaración | Q6: Aduanas | R6: Golden o apartados | S6: Control de calidad | T6: Costo por pasillo | U6: Sin Exhibición | V6: Exhibición fuera de Política | W6: Modelos revuelto | X6: Modelos mal entallados | Y6: Modelos con error de ubicación | Z6: Curva con diferencia en frentes | AA6: Curva con diferencia en fondos | AB6: Curva con diferencia en altura | AC6: Curvas vencidas | AD6: Curvas que no coincide Price Soft vs Piso de Venta | AE6: Curvas faltantes | AF6: Cenefas faltantes | AG6: Cenefas de precio Promoción faltantes | AH6: Cartas disculpa / destallados faltantes | AI6: Fechas de llegada faltantes | AJ6: Resultado de Check List | AK6: Resultado de banderazo surtido | BV6: Tiendas | BW6: Calzado | BX6: Frenteos | BY6: Ubicación Revuelta | BZ6: Bodega Venta (Sin marcar) | CA6: Bodega Tapanco | CB6: Doble Ubicación | CC6: Excedente | CD6: Origen | CE6: Cambios/Probadores | CF6: Negados Sin Recuperar | CG6: Exhibición | CH6: Bodega Aclaración | CI6: Aduanas | CJ6: Golden o apartados | CK6: Control de calidad | CL6: Costo por pasillo | CM6: Sin Exhibición | CN6: Exhibición fuera de Política | CO6: Modelos revuelto | CP6: Modelos mal entallados | CQ6: Modelos con error de ubicación | CR6: Curva con diferencia en frentes | CS6: Curva con diferencia en fondos | CT6: Curva con diferencia en altura | CU6: Curvas vencidas | CV6: Curvas que no coincide Price Soft vs Piso de Venta | CW6: Curvas faltantes | CX6: Cenefas faltantes | CY6: Cenefas de precio Promoción faltantes | CZ6: Cartas disculpa / destallados faltantes | DA6: Fechas de llegada faltantes | EK6: Frenteos | EL6: Ubicación Revuelta | EM6: Bodega Venta (Sin marcar) | EN6: Bodega Tapanco | EO6: Doble Ubicación | EP6: Excedente | EQ6: Origen | ER6: Cambios/Probadores | ES6: Negados Sin Recuperar | ET6: Exhibición | EU6: Bodega Aclaración | EV6: Aduanas | EW6: Golden o apartados | EX6: Control de calidad | EZ6: Frenteos | FA6: Ubicación Revuelta | FB6: Bodega Venta (Sin marcar) | FC6: Bodega Tapanco | FD6: Doble Ubicación | FE6: Excedente | FF6: Origen | FG6: Cambios/Probadores | FH6: Negados Sin Recuperar | FI6: Exhibición | FJ6: Bodega Aclaración | FK6: Aduanas | FL6: Golden o apartados | FM6: Control de calidad
A7: Aguascalientes | C7: =AM56 -> 0 | D7: =AN56 -> 0 | E7: =D7/C7 -> #DIV/0! | F7: =AP56 -> 0 | G7: =AQ56 -> 0 | H7: =AR56 -> 0 | I7: =AS56 -> 0 | J7: =AT56 -> 0 | K7: =AU56 -> 0 | L7: =AV56 -> 0 | M7: =AW56 -> 0 | ... AI7: =BS56 -> 0 | BV7: Aguascalientes | BX7: =DE56 -> 0 | BY7: =DF56 -> 0 | BZ7: =DG56 -> 0 | CA7: =DH56 -> 0 | CB7: =DI56 -> 0 | CC7: =DJ56 -> 0 | CD7: =DK56 -> 0 | CE7: =DL56 -> 0 | ... DA7: =EH56 -> 0 | EJ7: Aguascalientes | EK7: =EK72 -> 0 | EL7: =EL72 -> 0 | EM7: =EM72 -> 0 | EN7: =EN72 -> 0 | EO7: =EO72 -> 0 | EP7: =EP72 -> 0 | EQ7: =EQ72 -> 0 | ER7: =ER72 -> 0 | ... FN7: =FN72 -> 0
A8: Arco Norte | C8: =AM78 -> 0 | D8: =AN78 -> 0 | E8: =D8/C8 -> #DIV/0! | F8: =AP78 -> 0 | G8: =AQ78 -> 0 | H8: =AR78 -> 0 | I8: =AS78 -> 0 | J8: =AT78 -> 0 | K8: =AU78 -> 0 | L8: =AV78 -> 0 | M8: =AW78 -> 0 | ... AI8: =BS78 -> 0 | BV8: Arco Norte | BX8: =DE78 -> 0 | BY8: =DF78 -> 0 | BZ8: =DG78 -> 0 | CA8: =DH78 -> 0 | CB8: =DI78 -> 0 | CC8: =DJ78 -> 0 | CD8: =DK78 -> 0 | CE8: =DL78 -> 0 | ... DA8: =EH78 -> 0 | EJ8: Arco Norte | EK8: =EK94 -> 0 | EL8: =EL94 -> 0 | EM8: =EM94 -> 0 | EN8: =EN94 -> 0 | EO8: =EO94 -> 0 | EP8: =EP94 -> 0 | EQ8: =EQ94 -> 0 | ER8: =ER94 -> 0 | ... FN8: =FN94 -> 0
A9: Centro Historico | C9: =AM100 -> 0 | D9: =AN100 -> 0 | E9: =D9/C9 -> #DIV/0! | F9: =AP100 -> 0 | G9: =AQ100 -> 0 | H9: =AR100 -> 0 | I9: =AS100 -> 0 | J9: =AT100 -> 0 | K9: =AU100 -> 0 | L9: =AV100 -> 0 | M9: =AW100 -> 0 | ... AI9: =BS100 -> 0 | BV9: Centro Historico | BX9: =DE100 -> 0 | BY9: =DF100 -> 0 | BZ9: =DG100 -> 0 | CA9: =DH100 -> 0 | CB9: =DI100 -> 0 | CC9: =DJ100 -> 0 | CD9: =DK100 -> 0 | CE9: =DL100 -> 0 | ... DA9: =EH100 -> 0 | EJ9: Centro Historico | EK9: =EK116 -> 0 | EL9: =EL116 -> 0 | EM9: =EM116 -> 0 | EN9: =EN116 -> 0 | EO9: =EO116 -> 0 | EP9: =EP116 -> 0 | EQ9: =EQ116 -> 0 | ER9: =ER116 -> 0 | ... FN9: =FN116 -> 0
A10: Ecatepec | C10: =AM122 -> 0 | D10: =AN122 -> 0 | E10: =D10/C10 -> #DIV/0! | F10: =AP122 -> 0 | G10: =AQ122 -> 0 | H10: =AR122 -> 0 | I10: =AS122 -> 0 | J10: =AT122 -> 0 | K10: =AU122 -> 0 | L10: =AV122 -> 0 | M10: =AW122 -> 0 | ... AI10: =BS122 -> 0 | BV10: Ecatepec | BX10: =DE122 -> 0 | BY10: =DF122 -> 0 | BZ10: =DG122 -> 0 | CA10: =DH122 -> 0 | CB10: =DI122 -> 0 | CC10: =DJ122 -> 0 | CD10: =DK122 -> 0 | CE10: =DL122 -> 0 | ... DA10: =EH122 -> 0 | EJ10: Ecatepec | EK10: =EK138 -> 0 | EL10: =EL138 -> 0 | EM10: =EM138 -> 0 | EN10: =EN138 -> 0 | EO10: =EO138 -> 0 | EP10: =EP138 -> 0 | EQ10: =EQ138 -> 0 | ER10: =ER138 -> 0 | ... FN10: =FN138 -> 0
A11: Guadalajara | C11: =AM144 -> 0 | D11: =AN144 -> 0 | E11: =D11/C11 -> #DIV/0! | F11: =AP144 -> 0 | G11: =AQ144 -> 0 | H11: =AR144 -> 0 | I11: =AS144 -> 0 | J11: =AT144 -> 0 | K11: =AU144 -> 0 | L11: =AV144 -> 0 | M11: =AW144 -> 0 | ... AI11: =BS144 -> 0 | BV11: Guadalajara | BX11: =DE144 -> 0 | BY11: =DF144 -> 0 | BZ11: =DG144 -> 0 | CA11: =DH144 -> 0 | CB11: =DI144 -> 0 | CC11: =DJ144 -> 0 | CD11: =DK144 -> 0 | CE11: =DL144 -> 0 | ... DA11: =EH144 -> 0 | EJ11: Guadalajara | EK11: =EK160 -> 0 | EL11: =EL160 -> 0 | EM11: =EM160 -> 0 | EN11: =EN160 -> 0 | EO11: =EO160 -> 0 | EP11: =EP160 -> 0 | EQ11: =EQ160 -> 0 | ER11: =ER160 -> 0 | ... FN11: =FN160 -> 0
A12: Ixtapaluca | C12: =AM166 -> 0 | D12: =AN166 -> 0 | E12: =D12/C12 -> #DIV/0! | F12: =AP166 -> 0 | G12: =AQ166 -> 0 | H12: =AR166 -> 0 | I12: =AS166 -> 0 | J12: =AT166 -> 0 | K12: =AU166 -> 0 | L12: =AV166 -> 0 | M12: =AW166 -> 0 | ... AI12: =BS166 -> 0 | BV12: Ixtapaluca | BX12: =DE166 -> 0 | BY12: =DF166 -> 0 | BZ12: =DG166 -> 0 | CA12: =DH166 -> 0 | CB12: =DI166 -> 0 | CC12: =DJ166 -> 0 | CD12: =DK166 -> 0 | CE12: =DL166 -> 0 | ... DA12: =EH166 -> 0 | EJ12: Ixtapaluca | EK12: =EK182 -> 0 | EL12: =EL182 -> 0 | EM12: =EM182 -> 0 | EN12: =EN182 -> 0 | EO12: =EO182 -> 0 | EP12: =EP182 -> 0 | EQ12: =EQ182 -> 0 | ER12: =ER182 -> 0 | ... FN12: =FN182 -> 0
A13: Iztapalapa | C13: =AM188 -> 0 | D13: =AN188 -> 0 | E13: =D13/C13 -> #DIV/0! | F13: =AP188 -> 0 | G13: =AQ188 -> 0 | H13: =AR188 -> 0 | I13: =AS188 -> 0 | J13: =AT188 -> 0 | K13: =AU188 -> 0 | L13: =AV188 -> 0 | M13: =AW188 -> 0 | ... AI13: =BS188 -> 0 | BV13: Iztapalapa | BX13: =DE188 -> 0 | BY13: =DF188 -> 0 | BZ13: =DG188 -> 0 | CA13: =DH188 -> 0 | CB13: =DI188 -> 0 | CC13: =DJ188 -> 0 | CD13: =DK188 -> 0 | CE13: =DL188 -> 0 | ... DA13: =EH188 -> 0 | EJ13: Iztapalapa | EK13: =EK204 -> 0 | EL13: =EL204 -> 0 | EM13: =EM204 -> 0 | EN13: =EN204 -> 0 | EO13: =EO204 -> 0 | EP13: =EP204 -> 0 | EQ13: =EQ204 -> 0 | ER13: =ER204 -> 0 | ... FN13: =FN204 -> 0
A14: León | C14: =AM210 -> 0 | D14: =AN210 -> 0 | E14: =D14/C14 -> #DIV/0! | F14: =AP210 -> 0 | G14: =AQ210 -> 0 | H14: =AR210 -> 0 | I14: =AS210 -> 0 | J14: =AT210 -> 0 | K14: =AU210 -> 0 | L14: =AV210 -> 0 | M14: =AW210 -> 0 | ... AI14: =BS210 -> 0 | BV14: León | BX14: =DE210 -> 0 | BY14: =DF210 -> 0 | BZ14: =DG210 -> 0 | CA14: =DH210 -> 0 | CB14: =DI210 -> 0 | CC14: =DJ210 -> 0 | CD14: =DK210 -> 0 | CE14: =DL210 -> 0 | ... DA14: =EH210 -> 0 | EJ14: León | EK14: =EK226 -> 0 | EL14: =EL226 -> 0 | EM14: =EM226 -> 0 | EN14: =EN226 -> 0 | EO14: =EO226 -> 0 | EP14: =EP226 -> 0 | EQ14: =EQ226 -> 0 | ER14: =ER226 -> 0 | ... FN14: =FN226 -> 0
A15: Miravalle | C15: =AM232 -> 0 | D15: =AN232 -> 0 | E15: =D15/C15 -> #DIV/0! | F15: =AP232 -> 0 | G15: =AQ232 -> 0 | H15: =AR232 -> 0 | I15: =AS232 -> 0 | J15: =AT232 -> 0 | K15: =AU232 -> 0 | L15: =AV232 -> 0 | M15: =AW232 -> 0 | ... AI15: =BS232 -> 0 | BV15: Miravalle | BX15: =DE232 -> 0 | BY15: =DF232 -> 0 | BZ15: =DG232 -> 0 | CA15: =DH232 -> 0 | CB15: =DI232 -> 0 | CC15: =DJ232 -> 0 | CD15: =DK232 -> 0 | CE15: =DL232 -> 0 | ... DA15: =EH232 -> 0 | EJ15: Miravalle | EK15: =EK248 -> 0 | EL15: =EL248 -> 0 | EM15: =EM248 -> 0 | EN15: =EN248 -> 0 | EO15: =EO248 -> 0 | EP15: =EP248 -> 0 | EQ15: =EQ248 -> 0 | ER15: =ER248 -> 0 | ... FN15: =FN248 -> 0
A16: Naucalpan | C16: =AM254 -> 0 | D16: =AN254 -> 0 | E16: =D16/C16 -> #DIV/0! | F16: =AP254 -> 0 | G16: =AQ254 -> 0 | H16: =AR254 -> 0 | I16: =AS254 -> 0 | J16: =AT254 -> 0 | K16: =AU254 -> 0 | L16: =AV254 -> 0 | M16: =AW254 -> 0 | ... AI16: =BS254 -> 0 | BV16: Naucalpan | BX16: =DE254 -> 0 | BY16: =DF254 -> 0 | BZ16: =DG254 -> 0 | CA16: =DH254 -> 0 | CB16: =DI254 -> 0 | CC16: =DJ254 -> 0 | CD16: =DK254 -> 0 | CE16: =DL254 -> 0 | ... DA16: =EH254 -> 0 | EJ16: Naucalpan | EK16: =EK270 -> 0 | EL16: =EL270 -> 0 | EM16: =EM270 -> 0 | EN16: =EN270 -> 0 | EO16: =EO270 -> 0 | EP16: =EP270 -> 0 | EQ16: =EQ270 -> 0 | ER16: =ER270 -> 0 | ... FN16: =FN270 -> 0
A17: Olivar del Conde | C17: =AM276 -> 0 | D17: =AN276 -> 0 | E17: =D17/C17 -> #DIV/0! | F17: =AP276 -> 0 | G17: =AQ276 -> 0 | H17: =AR276 -> 0 | I17: =AS276 -> 0 | J17: =AT276 -> 0 | K17: =AU276 -> 0 | L17: =AV276 -> 0 | M17: =AW276 -> 0 | ... AI17: =BS276 -> 0 | BV17: Olivar del Conde | BX17: =DE276 -> 0 | BY17: =DF276 -> 0 | BZ17: =DG276 -> 0 | CA17: =DH276 -> 0 | CB17: =DI276 -> 0 | CC17: =DJ276 -> 0 | CD17: =DK276 -> 0 | CE17: =DL276 -> 0 | ... DA17: =EH276 -> 0 | EJ17: Olivar del Conde | EK17: =EK292 -> 0 | EL17: =EL292 -> 0 | EM17: =EM292 -> 0 | EN17: =EN292 -> 0 | EO17: =EO292 -> 0 | EP17: =EP292 -> 0 | EQ17: =EQ292 -> 0 | ER17: =ER292 -> 0 | ... FN17: =FN292 -> 0
A18: Puebla | C18: =AM298 -> 0 | D18: =AN298 -> 0 | E18: =D18/C18 -> #DIV/0! | F18: =AP298 -> 0 | G18: =AQ298 -> 0 | H18: =AR298 -> 0 | I18: =AS298 -> 0 | J18: =AT298 -> 0 | K18: =AU298 -> 0 | L18: =AV298 -> 0 | M18: =AW298 -> 0 | ... AI18: =BS298 -> 0 | BV18: Puebla | BX18: =DE298 -> 0 | BY18: =DF298 -> 0 | BZ18: =DG298 -> 0 | CA18: =DH298 -> 0 | CB18: =DI298 -> 0 | CC18: =DJ298 -> 0 | CD18: =DK298 -> 0 | CE18: =DL298 -> 0 | ... DA18: =EH298 -> 0 | EJ18: Puebla | EK18: =EK314 -> 0 | EL18: =EL314 -> 0 | EM18: =EM314 -> 0 | EN18: =EN314 -> 0 | EO18: =EO314 -> 0 | EP18: =EP314 -> 0 | EQ18: =EQ314 -> 0 | ER18: =ER314 -> 0 | ... FN18: =FN314 -> 0
A19: Queretaro | C19: =AM320 -> 0 | D19: =AN320 -> 0 | E19: =D19/C19 -> #DIV/0! | F19: =AP320 -> 0 | G19: =AQ320 -> 0 | H19: =AR320 -> 0 | I19: =AS320 -> 0 | J19: =AT320 -> 0 | K19: =AU320 -> 0 | L19: =AV320 -> 0 | M19: =AW320 -> 0 | ... AI19: =BS320 -> 0 | BV19: Queretaro | BX19: =DE320 -> 0 | BY19: =DF320 -> 0 | BZ19: =DG320 -> 0 | CA19: =DH320 -> 0 | CB19: =DI320 -> 0 | CC19: =DJ320 -> 0 | CD19: =DK320 -> 0 | CE19: =DL320 -> 0 | ... DA19: =EH320 -> 0 | EJ19: Queretaro | EK19: =EK336 -> 0 | EL19: =EL336 -> 0 | EM19: =EM336 -> 0 | EN19: =EN336 -> 0 | EO19: =EO336 -> 0 | EP19: =EP336 -> 0 | EQ19: =EQ336 -> 0 | ER19: =ER336 -> 0 | ... FN19: =FN336 -> 0
A20: Puebla Sur | C20: =AM408 -> 0 | D20: =AN408 -> 0 | E20: =D20/C20 -> #DIV/0! | F20: =AP408 -> 0 | G20: =AQ408 -> 0 | H20: =AR408 -> 0 | I20: =AS408 -> 0 | J20: =AT408 -> 0 | K20: =AU408 -> 0 | L20: =AV408 -> 0 | M20: =AW408 -> 0 | ... AI20: =BS408 -> 0 | BV20: Tijuna | BX20: =DE408 -> 0 | BY20: =DF408 -> 0 | BZ20: =DG408 -> 0 | CA20: =DH408 -> 0 | CB20: =DI408 -> 0 | CC20: =DJ408 -> 0 | CD20: =DK408 -> 0 | CE20: =DL408 -> 0 | ... DA20: =EH408 -> 0 | EJ20: Tijuna | EK20: =EK424 -> 0 | EL20: =EL424 -> 0 | EM20: =EM424 -> 0 | EN20: =EN424 -> 0 | EO20: =EO424 -> 0 | EP20: =EP424 -> 0 | EQ20: =EQ424 -> 0 | ER20: =ER424 -> 0 | ... FN20: =FN424 -> 0
A21: Toluca | C21: =AM342 -> 0 | D21: =AN342 -> 0 | E21: =D21/C21 -> #DIV/0! | F21: =AP342 -> 0 | G21: =AQ342 -> 0 | H21: =AR342 -> 0 | I21: =AS342 -> 0 | J21: =AT342 -> 0 | K21: =AU342 -> 0 | L21: =AV342 -> 0 | M21: =AW342 -> 0 | ... AI21: =BS342 -> 0 | BV21: Toluca | BX21: =DE342 -> 0 | BY21: =DF342 -> 0 | BZ21: =DG342 -> 0 | CA21: =DH342 -> 0 | CB21: =DI342 -> 0 | CC21: =DJ342 -> 0 | CD21: =DK342 -> 0 | CE21: =DL342 -> 0 | ... DA21: =EH342 -> 0 | EJ21: Toluca | EK21: =EK358 -> 0 | EL21: =EL358 -> 0 | EM21: =EM358 -> 0 | EN21: =EN358 -> 0 | EO21: =EO358 -> 0 | EP21: =EP358 -> 0 | EQ21: =EQ358 -> 0 | ER21: =ER358 -> 0 | ... FN21: =FN358 -> 0
A22: Vallejo | C22: =AM364 -> 0 | D22: =AN364 -> 0 | E22: =D22/C22 -> #DIV/0! | F22: =AP364 -> 0 | G22: =AQ364 -> 0 | H22: =AR364 -> 0 | I22: =AS364 -> 0 | J22: =AT364 -> 0 | K22: =AU364 -> 0 | L22: =AV364 -> 0 | M22: =AW364 -> 0 | ... AI22: =BS364 -> 0 | BV22: Vallejo | BX22: =DE364 -> 0 | BY22: =DF364 -> 0 | BZ22: =DG364 -> 0 | CA22: =DH364 -> 0 | CB22: =DI364 -> 0 | CC22: =DJ364 -> 0 | CD22: =DK364 -> 0 | CE22: =DL364 -> 0 | ... DA22: =EH364 -> 0 | EJ22: Vallejo | EK22: =EK380 -> 0 | EL22: =EL380 -> 0 | EM22: =EM380 -> 0 | EN22: =EN380 -> 0 | EO22: =EO380 -> 0 | EP22: =EP380 -> 0 | EQ22: =EQ380 -> 0 | ER22: =ER380 -> 0 | ... FN22: =FN380 -> 0
A23: Veracruz | C23: =AM386 -> 0 | D23: =AN386 -> 0 | E23: =D23/C23 -> #DIV/0! | F23: =AP386 -> 0 | G23: =AQ386 -> 0 | H23: =AR386 -> 0 | I23: =AS386 -> 0 | J23: =AT386 -> 0 | K23: =AU386 -> 0 | L23: =AV386 -> 0 | M23: =AW386 -> 0 | ... AI23: =BS386 -> 0 | BV23: Veracruz | BX23: =DE386 -> 0 | BY23: =DF386 -> 0 | BZ23: =DG386 -> 0 | CA23: =DH386 -> 0 | CB23: =DI386 -> 0 | CC23: =DJ386 -> 0 | CD23: =DK386 -> 0 | CE23: =DL386 -> 0 | ... DA23: =EH386 -> 0 | EJ23: Veracruz | EK23: =EK402 -> 0 | EL23: =EL402 -> 0 | EM23: =EM402 -> 0 | EN23: =EN402 -> 0 | EO23: =EO402 -> 0 | EP23: =EP402 -> 0 | EQ23: =EQ402 -> 0 | ER23: =ER402 -> 0 | ... FN23: =FN402 -> 0
B24: Total | C24: =SUM(C7:C23) -> 0 | D24: =SUM(D7:D23) -> 0 | E24: =D24/C24 -> #DIV/0! | F24: =SUM(F7:F23) -> 0 | H24: =SUM(H7:H23) -> 0 | I24: =SUM(I7:I23) -> 0 | J24: =SUM(J7:J23) -> 0 | K24: =SUM(K7:K23) -> 0 | L24: =SUM(L7:L23) -> 0 | N24: =SUM(N7:N23) -> 0 | O24: =SUM(O7:O23) -> 0 | P24: =SUM(P7:P23) -> 0 | T24: =SUM(F24:P24) -> 0 | U24: =SUM(U7:U23) -> 0 | V24: =SUM(V7:V23) -> 0 | W24: =SUM(W7:W23) -> 0 | X24: =SUM(X7:X23) -> 0 | Y24: =SUM(Y7:Y23) -> 0 | Z24: =SUM(Z7:Z23) -> 0 | AA24: =SUM(AA7:AA23) -> 0 | AB24: =SUM(AB7:AB23) -> 0 | ... AI24: =SUM(AI7:AI23) -> 0 | AJ24: =AVERAGE(AJ7:AJ22) -> #DIV/0! | AK24: =AVERAGE(AK7:AK22) -> #DIV/0! | BW24: Total | BX24: =SUM(BX7:BX23) -> 0 | BZ24: =SUM(BZ7:BZ23) -> 0 | CA24: =SUM(CA7:CA23) -> 0 | CB24: =SUM(CB7:CB23) -> 0 | CC24: =SUM(CC7:CC23) -> 0 | CD24: =SUM(CD7:CD23) -> 0 | CF24: =SUM(CF7:CF23) -> 0 | CG24: =SUM(CG7:CG23) -> 0 | CH24: =SUM(CH7:CH23) -> 0 | CL24: =SUM(BX24:CH24) -> 0 | CM24: =SUM(CM7:CM22) -> 0 | CN24: =SUM(CN7:CN22) -> 0 | CO24: =SUM(CO7:CO22) -> 0 | CP24: =SUM(CP7:CP22) -> 0 | CQ24: =SUM(CQ7:CQ22) -> 0 | CR24: =SUM(CR7:CR22) -> 0 | CS24: =SUM(CS7:CS22) -> 0 | CT24: =SUM(CT7:CT22) -> 0 | ... DA24: =SUM(DA7:DA22) -> 0
C25: Costo de Oportunidad | F25: =SUM(T7:T23) -> 0 | BX25: =SUM(CL7:CL22) -> 0
A27: Concentrado por Tienda de Dictamen de Auditoria de Dummy | BV27: Recuperación por tienda y rubro
F30: Causas de Negado | U30: Incidencias de Auditoria | BX30: Causas de Negado | CM30: Incidencias de Auditoria
A31: Tiendas | B31: Ropa | C31: Tallas por pasillo | D31: Tallas por modelo | E31: % de Cobertura de auditoria | F31: Frenteos | G31: Ubicación Revuelta | H31: Bodega Venta (Sin marcar) | I31: Bodega Tapanco | J31: Doble Ubicación | K31: Excedente | L31: Origen | M31: Cambios/Probadores | N31: Negados Sin Recuperar | O31: Exhibición | P31: Bodega Aclaración | Q31: Aduanas | R31: Golden o apartados | S31: Control de calidad | T31: Costo por pasillo | U31: Sin Exhibición | V31: Exhibición fuera de Política | W31: Modelos revuelto | X31: Modelos mal entallados | Y31: Modelos con error de ubicación | Z31: Curva con diferencia en frentes | AA31: Curva con diferencia en fondos | AB31: Curva con diferencia en altura | AC31: Curvas vencidas | AD31: Curvas que no coincide Price Soft vs Piso de Venta | AE31: Curvas faltantes | AF31: Cenefas faltantes | AG31: Cenefas de precio Promoción faltantes | AH31: Cartas disculpa / destallados faltantes | AI31: Fechas de llegada faltantes | BV31: Tiendas | BW31: Responsable de Catalogo | BX31: Frenteos | BY31: Ubicación Revuelta | BZ31: Bodega Venta (Sin marcar) | CA31: Bodega Tapanco | CB31: Doble Ubicación | CC31: Excedente | CD31: Origen | CE31: Cambios/Probadores | CF31: Negados Sin Recuperar | CG31: Exhibición | CH31: Bodega Aclaración | CI31: Aduanas | CJ31: Golden o apartados | CK31: Control de calidad | CL31: Costo por pasillo | CM31: Sin Exhibición | CN31: Exhibición fuera de Política | CO31: Modelos revuelto | CP31: Modelos mal entallados | CQ31: Modelos con error de ubicación | CR31: Curva con diferencia en frentes | CS31: Curva con diferencia en fondos | CT31: Curva con diferencia en altura | CU31: Curvas vencidas | CV31: Curvas que no coincide Price Soft vs Piso de Venta | CW31: Curvas faltantes | CX31: Cenefas faltantes | CY31: Cenefas de precio Promoción faltantes | CZ31: Cartas disculpa / destallados faltantes | DA31: Fechas de llegada faltantes | EK31: Frenteos | EL31: Ubicación Revuelta | EM31: Bodega Venta (Sin marcar) | EN31: Bodega Tapanco | EO31: Doble Ubicación | EP31: Excedente | EQ31: Origen | ER31: Cambios/Probadores | ES31: Negados Sin Recuperar | ET31: Exhibición | EU31: Bodega Aclaración | EV31: Aduanas | EW31: Golden o apartados | EX31: Control de calidad | EZ31: Frenteos | FA31: Ubicación Revuelta | FB31: Bodega Venta (Sin marcar) | FC31: Bodega Tapanco | FD31: Doble Ubicación | FE31: Excedente | FF31: Origen | FG31: Cambios/Probadores | FH31: Negados Sin Recuperar | FI31: Exhibición | FJ31: Bodega Aclaración | FK31: Aduanas | FL31: Golden o apartados | FM31: Control de calidad
A32: Aguascalientes | C32: =AM58 -> 0 | D32: =AN58 -> 0 | E32: =D32/C32 -> #DIV/0! | F32: =AP58 -> 0 | G32: =AQ58 -> 0 | H32: =AR58 -> 0 | I32: =AS58 -> 0 | J32: =AT58 -> 0 | K32: =AU58 -> 0 | L32: =AV58 -> 0 | M32: =AW58 -> 0 | ... AI32: =BS58 -> 0 | BV32: Aguascalientes | BX32: =DE58 -> 0 | BY32: =DF58 -> 0 | BZ32: =DG58 -> 0 | CA32: =DH58 -> 0 | CB32: =DI58 -> 0 | CC32: =DJ58 -> 0 | CD32: =DK58 -> 0 | CE32: =DL58 -> 0 | ... DA32: =EH58 -> 0 | EJ32: Aguascalientes | EK32: =EK73 -> 0 | EL32: =EL73 -> 0 | EM32: =EM73 -> 0 | EN32: =EN73 -> 0 | EO32: =EO73 -> 0 | EP32: =EP73 -> 0 | EQ32: =EQ73 -> 0 | ER32: =ER73 -> 0 | ... FN32: =FN73 -> 0
A33: Arco Norte | C33: =AM80 -> 0 | D33: =AN80 -> 0 | E33: =D33/C33 -> #DIV/0! | F33: =AP80 -> 0 | G33: =AQ80 -> 0 | H33: =AR80 -> 0 | I33: =AS80 -> 0 | J33: =AT80 -> 0 | K33: =AU80 -> 0 | L33: =AV80 -> 0 | M33: =AW80 -> 0 | ... AI33: =BS80 -> 0 | BV33: Arco Norte | BX33: =DE80 -> 0 | BY33: =DF80 -> 0 | BZ33: =DG80 -> 0 | CA33: =DH80 -> 0 | CB33: =DI80 -> 0 | CC33: =DJ80 -> 0 | CD33: =DK80 -> 0 | CE33: =DL80 -> 0 | ... DA33: =EH80 -> 0 | EJ33: Arco Norte | EK33: =EK95 -> 0 | EL33: =EL95 -> 0 | EM33: =EM95 -> 0 | EN33: =EN95 -> 0 | EO33: =EO95 -> 0 | EP33: =EP95 -> 0 | EQ33: =EQ95 -> 0 | ER33: =ER95 -> 0 | ... FN33: =FN95 -> 0
A34: Centro Historico | C34: =AM102 -> 0 | D34: =AN102 -> 0 | E34: =D34/C34 -> #DIV/0! | F34: =AP102 -> 0 | G34: =AQ102 -> 0 | H34: =AR102 -> 0 | I34: =AS102 -> 0 | J34: =AT102 -> 0 | K34: =AU102 -> 0 | L34: =AV102 -> 0 | M34: =AW102 -> 0 | ... AI34: =BS102 -> 0 | BV34: Centro Historico | BX34: =DE102 -> 0 | BY34: =DF102 -> 0 | BZ34: =DG102 -> 0 | CA34: =DH102 -> 0 | CB34: =DI102 -> 0 | CC34: =DJ102 -> 0 | CD34: =DK102 -> 0 | CE34: =DL102 -> 0 | ... DA34: =EH102 -> 0 | EJ34: Centro Historico | EK34: =EK117 -> 0 | EL34: =EL117 -> 0 | EM34: =EM117 -> 0 | EN34: =EN117 -> 0 | EO34: =EO117 -> 0 | EP34: =EP117 -> 0 | EQ34: =EQ117 -> 0 | ER34: =ER117 -> 0 | ... FN34: =FN117 -> 0
A35: Ecatepec | C35: =AM124 -> 0 | D35: =AN124 -> 0 | E35: =D35/C35 -> #DIV/0! | F35: =AP124 -> 0 | G35: =AQ124 -> 0 | H35: =AR124 -> 0 | I35: =AS124 -> 0 | J35: =AT124 -> 0 | K35: =AU124 -> 0 | L35: =AV124 -> 0 | M35: =AW124 -> 0 | ... AI35: =BS124 -> 0 | BV35: Ecatepec | BX35: =DE124 -> 0 | BY35: =DF124 -> 0 | BZ35: =DG124 -> 0 | CA35: =DH124 -> 0 | CB35: =DI124 -> 0 | CC35: =DJ124 -> 0 | CD35: =DK124 -> 0 | CE35: =DL124 -> 0 | ... DA35: =EH124 -> 0 | EJ35: Ecatepec | EK35: =EK139 -> 0 | EL35: =EL139 -> 0 | EM35: =EM139 -> 0 | EN35: =EN139 -> 0 | EO35: =EO139 -> 0 | EP35: =EP139 -> 0 | EQ35: =EQ139 -> 0 | ER35: =ER139 -> 0 | ... FN35: =FN139 -> 0
A36: Guadalajara | C36: =AM146 -> 0 | D36: =AN146 -> 0 | E36: =D36/C36 -> #DIV/0! | F36: =AP146 -> 0 | G36: =AQ146 -> 0 | H36: =AR146 -> 0 | I36: =AS146 -> 0 | J36: =AT146 -> 0 | K36: =AU146 -> 0 | L36: =AV146 -> 0 | M36: =AW146 -> 0 | ... AI36: =BS146 -> 0 | BV36: Guadalajara | BX36: =DE146 -> 0 | BY36: =DF146 -> 0 | BZ36: =DG146 -> 0 | CA36: =DH146 -> 0 | CB36: =DI146 -> 0 | CC36: =DJ146 -> 0 | CD36: =DK146 -> 0 | CE36: =DL146 -> 0 | ... DA36: =EH146 -> 0 | EJ36: Guadalajara | EK36: =EK161 -> 0 | EL36: =EL161 -> 0 | EM36: =EM161 -> 0 | EN36: =EN161 -> 0 | EO36: =EO161 -> 0 | EP36: =EP161 -> 0 | EQ36: =EQ161 -> 0 | ER36: =ER161 -> 0 | ... FN36: =FN161 -> 0
A37: Ixtapaluca | C37: =AM168 -> 0 | D37: =AN168 -> 0 | E37: =D37/C37 -> #DIV/0! | F37: =AP168 -> 0 | G37: =AQ168 -> 0 | H37: =AR168 -> 0 | I37: =AS168 -> 0 | J37: =AT168 -> 0 | K37: =AU168 -> 0 | L37: =AV168 -> 0 | M37: =AW168 -> 0 | ... AI37: =BS168 -> 0 | BV37: Ixtapaluca | BX37: =DE168 -> 0 | BY37: =DF168 -> 0 | BZ37: =DG168 -> 0 | CA37: =DH168 -> 0 | CB37: =DI168 -> 0 | CC37: =DJ168 -> 0 | CD37: =DK168 -> 0 | CE37: =DL168 -> 0 | ... DA37: =EH168 -> 0 | EJ37: Ixtapaluca | EK37: =EK183 -> 0 | EL37: =EL183 -> 0 | EM37: =EM183 -> 0 | EN37: =EN183 -> 0 | EO37: =EO183 -> 0 | EP37: =EP183 -> 0 | EQ37: =EQ183 -> 0 | ER37: =ER183 -> 0 | ... FN37: =FN183 -> 0
A38: Iztapalapa | C38: =AM190 -> 0 | D38: =AN190 -> 0 | E38: =D38/C38 -> #DIV/0! | F38: =AP190 -> 0 | G38: =AQ190 -> 0 | H38: =AR190 -> 0 | I38: =AS190 -> 0 | J38: =AT190 -> 0 | K38: =AU190 -> 0 | L38: =AV190 -> 0 | M38: =AW190 -> 0 | ... AI38: =BS190 -> 0 | BV38: Iztapalapa | BX38: =DE190 -> 0 | BY38: =DF190 -> 0 | BZ38: =DG190 -> 0 | CA38: =DH190 -> 0 | CB38: =DI190 -> 0 | CC38: =DJ190 -> 0 | CD38: =DK190 -> 0 | CE38: =DL190 -> 0 | ... DA38: =EH190 -> 0 | EJ38: Iztapalapa | EK38: =EK205 -> 0 | EL38: =EL205 -> 0 | EM38: =EM205 -> 0 | EN38: =EN205 -> 0 | EO38: =EO205 -> 0 | EP38: =EP205 -> 0 | EQ38: =EQ205 -> 0 | ER38: =ER205 -> 0 | ... FN38: =FN205 -> 0
A39: León | C39: =AM212 -> 0 | D39: =AN212 -> 0 | E39: =D39/C39 -> #DIV/0! | F39: =AP212 -> 0 | G39: =AQ212 -> 0 | H39: =AR212 -> 0 | I39: =AS212 -> 0 | J39: =AT212 -> 0 | K39: =AU212 -> 0 | L39: =AV212 -> 0 | M39: =AW212 -> 0 | ... AI39: =BS212 -> 0 | BV39: León | BX39: =DE212 -> 0 | BY39: =DF212 -> 0 | BZ39: =DG212 -> 0 | CA39: =DH212 -> 0 | CB39: =DI212 -> 0 | CC39: =DJ212 -> 0 | CD39: =DK212 -> 0 | CE39: =DL212 -> 0 | ... DA39: =EH212 -> 0 | EJ39: León | EK39: =EK227 -> 0 | EL39: =EL227 -> 0 | EM39: =EM227 -> 0 | EN39: =EN227 -> 0 | EO39: =EO227 -> 0 | EP39: =EP227 -> 0 | EQ39: =EQ227 -> 0 | ER39: =ER227 -> 0 | ... FN39: =FN227 -> 0
A40: Miravalle | C40: =AM234 -> 0 | D40: =AN234 -> 0 | E40: =D40/C40 -> #DIV/0! | F40: =AP234 -> 0 | G40: =AQ234 -> 0 | H40: =AR234 -> 0 | I40: =AS234 -> 0 | J40: =AT234 -> 0 | K40: =AU234 -> 0 | L40: =AV234 -> 0 | M40: =AW234 -> 0 | ... AI40: =BS234 -> 0 | BV40: Miravalle | BX40: =DE234 -> 0 | BY40: =DF234 -> 0 | BZ40: =DG234 -> 0 | CA40: =DH234 -> 0 | CB40: =DI234 -> 0 | CC40: =DJ234 -> 0 | CD40: =DK234 -> 0 | CE40: =DL234 -> 0 | ... DA40: =EH234 -> 0 | EJ40: Miravalle | EK40: =EK249 -> 0 | EL40: =EL249 -> 0 | EM40: =EM249 -> 0 | EN40: =EN249 -> 0 | EO40: =EO249 -> 0 | EP40: =EP249 -> 0 | EQ40: =EQ249 -> 0 | ER40: =ER249 -> 0 | ... FN40: =FN249 -> 0
A41: Naucalpan | C41: =AM256 -> 0 | D41: =AN256 -> 0 | E41: =D41/C41 -> #DIV/0! | F41: =AP256 -> 0 | G41: =AQ256 -> 0 | H41: =AR256 -> 0 | I41: =AS256 -> 0 | J41: =AT256 -> 0 | K41: =AU256 -> 0 | L41: =AV256 -> 0 | M41: =AW256 -> 0 | ... AI41: =BS256 -> 0 | BV41: Naucalpan | BX41: =DE256 -> 0 | BY41: =DF256 -> 0 | BZ41: =DG256 -> 0 | CA41: =DH256 -> 0 | CB41: =DI256 -> 0 | CC41: =DJ256 -> 0 | CD41: =DK256 -> 0 | CE41: =DL256 -> 0 | ... DA41: =EH256 -> 0 | EJ41: Naucalpan | EK41: =EK271 -> 0 | EL41: =EL271 -> 0 | EM41: =EM271 -> 0 | EN41: =EN271 -> 0 | EO41: =EO271 -> 0 | EP41: =EP271 -> 0 | EQ41: =EQ271 -> 0 | ER41: =ER271 -> 0 | ... FN41: =FN271 -> 0
A42: Olivar del Conde | C42: =AM278 -> 0 | D42: =AN278 -> 0 | E42: =D42/C42 -> #DIV/0! | F42: =AP278 -> 0 | G42: =AQ278 -> 0 | H42: =AR278 -> 0 | I42: =AS278 -> 0 | J42: =AT278 -> 0 | K42: =AU278 -> 0 | L42: =AV278 -> 0 | M42: =AW278 -> 0 | ... AI42: =BS278 -> 0 | BV42: Olivar del Conde | BX42: =DE278 -> 0 | BY42: =DF278 -> 0 | BZ42: =DG278 -> 0 | CA42: =DH278 -> 0 | CB42: =DI278 -> 0 | CC42: =DJ278 -> 0 | CD42: =DK278 -> 0 | CE42: =DL278 -> 0 | ... DA42: =EH278 -> 0 | EJ42: Olivar del Conde | EK42: =EK293 -> 0 | EL42: =EL293 -> 0 | EM42: =EM293 -> 0 | EN42: =EN293 -> 0 | EO42: =EO293 -> 0 | EP42: =EP293 -> 0 | EQ42: =EQ293 -> 0 | ER42: =ER293 -> 0 | ... FN42: =FN293 -> 0
A43: Puebla | C43: =AM300 -> 0 | D43: =AN300 -> 0 | E43: =D43/C43 -> #DIV/0! | F43: =AP300 -> 0 | G43: =AQ300 -> 0 | H43: =AR300 -> 0 | I43: =AS300 -> 0 | J43: =AT300 -> 0 | K43: =AU300 -> 0 | L43: =AV300 -> 0 | M43: =AW300 -> 0 | ... AI43: =BS300 -> 0 | BV43: Puebla | BX43: =DE300 -> 0 | BY43: =DF300 -> 0 | BZ43: =DG300 -> 0 | CA43: =DH300 -> 0 | CB43: =DI300 -> 0 | CC43: =DJ300 -> 0 | CD43: =DK300 -> 0 | CE43: =DL300 -> 0 | ... DA43: =EH300 -> 0 | EJ43: Puebla | EK43: =EK315 -> 0 | EL43: =EL315 -> 0 | EM43: =EM315 -> 0 | EN43: =EN315 -> 0 | EO43: =EO315 -> 0 | EP43: =EP315 -> 0 | EQ43: =EQ315 -> 0 | ER43: =ER315 -> 0 | ... FN43: =FN315 -> 0
A44: Queretaro | C44: =AM322 -> 0 | D44: =AN322 -> 0 | E44: =D44/C44 -> #DIV/0! | F44: =AP322 -> 0 | G44: =AQ322 -> 0 | H44: =AR322 -> 0 | I44: =AS322 -> 0 | J44: =AT322 -> 0 | K44: =AU322 -> 0 | L44: =AV322 -> 0 | M44: =AW322 -> 0 | ... AI44: =BS322 -> 0 | BV44: Queretaro | BX44: =DE322 -> 0 | BY44: =DF322 -> 0 | BZ44: =DG322 -> 0 | CA44: =DH322 -> 0 | CB44: =DI322 -> 0 | CC44: =DJ322 -> 0 | CD44: =DK322 -> 0 | CE44: =DL322 -> 0 | ... DA44: =EH322 -> 0 | EJ44: Queretaro | EK44: =EK337 -> 0 | EL44: =EL337 -> 0 | EM44: =EM337 -> 0 | EN44: =EN337 -> 0 | EO44: =EO337 -> 0 | EP44: =EP337 -> 0 | EQ44: =EQ337 -> 0 | ER44: =ER337 -> 0 | ... FN44: =FN337 -> 0
A45: Puebla Sur | C45: =AM410 -> 0 | D45: =AN410 -> 0 | E45: =D45/C45 -> #DIV/0! | F45: =AP410 -> 0 | G45: =AQ410 -> 0 | H45: =AR410 -> 0 | I45: =AS410 -> 0 | J45: =AT410 -> 0 | K45: =AU410 -> 0 | L45: =AV410 -> 0 | M45: =AW410 -> 0 | ... AI45: =BS410 -> 0 | BV45: Tijuna | BX45: =DE410 -> 0 | BY45: =DF410 -> 0 | BZ45: =DG410 -> 0 | CA45: =DH410 -> 0 | CB45: =DI410 -> 0 | CC45: =DJ410 -> 0 | CD45: =DK410 -> 0 | CE45: =DL410 -> 0 | ... DA45: =EH410 -> 0 | EJ45: Tijuna | EK45: =EK425 -> 0 | EL45: =EL425 -> 0 | EM45: =EM425 -> 0 | EN45: =EN425 -> 0 | EO45: =EO425 -> 0 | EP45: =EP425 -> 0 | EQ45: =EQ425 -> 0 | ER45: =ER425 -> 0 | ... FN45: =FN425 -> 0
A46: Toluca | C46: =AM344 -> 0 | D46: =AN344 -> 0 | E46: =D46/C46 -> #DIV/0! | F46: =AP344 -> 0 | G46: =AQ344 -> 0 | H46: =AR344 -> 0 | I46: =AS344 -> 0 | J46: =AT344 -> 0 | K46: =AU344 -> 0 | L46: =AV344 -> 0 | M46: =AW344 -> 0 | ... AI46: =BS344 -> 0 | BV46: Toluca | BX46: =DE344 -> 0 | BY46: =DF344 -> 0 | BZ46: =DG344 -> 0 | CA46: =DH344 -> 0 | CB46: =DI344 -> 0 | CC46: =DJ344 -> 0 | CD46: =DK344 -> 0 | CE46: =DL344 -> 0 | ... DA46: =EH344 -> 0 | EJ46: Toluca | EK46: =EK359 -> 0 | EL46: =EL359 -> 0 | EM46: =EM359 -> 0 | EN46: =EN359 -> 0 | EO46: =EO359 -> 0 | EP46: =EP359 -> 0 | EQ46: =EQ359 -> 0 | ER46: =ER359 -> 0 | ... FN46: =FN359 -> 0
A47: Vallejo | C47: =AM366 -> 0 | D47: =AN366 -> 0 | E47: =D47/C47 -> #DIV/0! | F47: =AP366 -> 0 | G47: =AQ366 -> 0 | H47: =AR366 -> 0 | I47: =AS366 -> 0 | J47: =AT366 -> 0 | K47: =AU366 -> 0 | L47: =AV366 -> 0 | M47: =AW366 -> 0 | ... AI47: =BS366 -> 0 | BV47: Vallejo | BX47: =DE366 -> 0 | BY47: =DF366 -> 0 | BZ47: =DG366 -> 0 | CA47: =DH366 -> 0 | CB47: =DI366 -> 0 | CC47: =DJ366 -> 0 | CD47: =DK366 -> 0 | CE47: =DL366 -> 0 | ... DA47: =EH366 -> 0 | EJ47: Vallejo | EK47: =EK381 -> 0 | EL47: =EL381 -> 0 | EM47: =EM381 -> 0 | EN47: =EN381 -> 0 | EO47: =EO381 -> 0 | EP47: =EP381 -> 0 | EQ47: =EQ381 -> 0 | ER47: =ER381 -> 0 | ... FN47: =FN381 -> 0
A48: Veracruz | C48: =AM388 -> 0 | D48: =AN388 -> 0 | E48: =D48/C48 -> #DIV/0! | F48: =AP388 -> 0 | G48: =AQ388 -> 0 | H48: =AR388 -> 0 | I48: =AS388 -> 0 | J48: =AT388 -> 0 | K48: =AU388 -> 0 | L48: =AV388 -> 0 | M48: =AW388 -> 0 | ... AI48: =BS388 -> 0 | BV48: Veracruz | BX48: =DE388 -> 0 | BY48: =DF388 -> 0 | BZ48: =DG388 -> 0 | CA48: =DH388 -> 0 | CB48: =DI388 -> 0 | CC48: =DJ388 -> 0 | CD48: =DK388 -> 0 | CE48: =DL388 -> 0 | ... DA48: =EH388 -> 0 | EJ48: Veracruz | EK48: =EK403 -> 0 | EL48: =EL403 -> 0 | EM48: =EM403 -> 0 | EN48: =EN403 -> 0 | EO48: =EO403 -> 0 | EP48: =EP403 -> 0 | EQ48: =EQ403 -> 0 | ER48: =ER403 -> 0 | ... FN48: =FN403 -> 0
B49: Total | C49: =SUM(C32:C48) -> 0 | D49: =SUM(D32:D48) -> 0 | E49: =D49/C49 -> #DIV/0! | F49: =SUM(F32:F48) -> 0 | H49: =SUM(H32:H48) -> 0 | I49: =SUM(I32:I48) -> 0 | J49: =SUM(J32:J48) -> 0 | K49: =SUM(K32:K48) -> 0 | L49: =SUM(L32:L48) -> 0 | N49: =SUM(N32:N48) -> 0 | O49: =SUM(O32:O48) -> 0 | P49: =SUM(P32:P48) -> 0 | T49: =SUM(F49:P49) -> 0 | U49: =SUM(U32:U48) -> 0 | V49: =SUM(V32:V48) -> 0 | W49: =SUM(W32:W48) -> 0 | X49: =SUM(X32:X48) -> 0 | Y49: =SUM(Y32:Y48) -> 0 | Z49: =SUM(Z32:Z48) -> 0 | AA49: =SUM(AA32:AA48) -> 0 | AB49: =SUM(AB32:AB48) -> 0 | ... AI49: =SUM(AI32:AI48) -> 0 | BW49: Total | BX49: =SUM(BX32:BX48) -> 0 | BZ49: =SUM(BZ32:BZ48) -> 0 | CA49: =SUM(CA32:CA48) -> 0 | CB49: =SUM(CB32:CB48) -> 0 | CC49: =SUM(CC32:CC48) -> 0 | CD49: =SUM(CD32:CD48) -> 0 | CF49: =SUM(CF32:CF48) -> 0 | CG49: =SUM(CG32:CG48) -> 0 | CH49: =SUM(CH32:CH48) -> 0 | CL49: =SUM(BX49:CH49) -> 0 | CM49: =SUM(CM32:CM47) -> 0 | CN49: =SUM(CN32:CN47) -> 0 | CO49: =SUM(CO32:CO47) -> 0 | CP49: =SUM(CP32:CP47) -> 0 | CQ49: =SUM(CQ32:CQ47) -> 0 | CR49: =SUM(CR32:CR47) -> 0 | CS49: =SUM(CS32:CS47) -> 0 | CT49: =SUM(CT32:CT47) -> 0 | ... DA49: =SUM(DA32:DA47) -> 0
BX50: =SUM(CL32:CL47) -> 0
A51: Concentrado de Dictamen de Auditoria de Dummy | BV51: Concentrado de Dictamen de Auditoria de Dummy
F54: Causas de Negado | U54: Incidencias de Auditoria | AJ54: =BT309 -> 0 | BX54: Causas de Negado | CM54: Incidencias de Auditoria | EK54: $ negados | FU54: Incidencias administrativas
A55: Aguascalientes | B55: Responsable De Catalogo | C55: Tallas por pasillo | D55: Tallas por modelo | E55: % de Cobertura de auditoria | F55: Frenteos | G55: Ubicación Revuelta | H55: Bodega Venta (Sin marcar) | I55: Bodega Tapanco | J55: Doble Ubicación | K55: Excedente | L55: Origen | M55: Cambios/Probadores | N55: Negados Sin Recuperar | O55: Exhibición | P55: Bodega Aclaración | Q55: Aduanas | R55: Golden o apartados | S55: Control de calidad | T55: Costo por pasillo | U55: Sin Exhibición | V55: Exhibición fuera de Política | W55: Modelos revuelto | X55: Modelos mal entallados | Y55: Modelos con error de ubicación | Z55: Curva con diferencia en frentes | AA55: Curva con diferencia en fondos | AB55: Curva con diferencia en altura | AC55: Curvas vencidas | AD55: Curvas que no coincide Price Soft vs Piso de Venta | AE55: Curvas faltantes | AF55: Cenefas faltantes | AG55: Cenefas de precio Promoción faltantes | AH55: Cartas disculpa / destallados faltantes | AI55: modelos que no cadran con planograma | AJ55: Resultado de Check List | AK55: Resultado de banderazo surtido | AM55: Tallas por pasillo | AN55: Tallas por modelo | AO55: % de Cobertura de auditoria | AP55: Frenteos | AQ55: Ubicación Revuelta | AR55: Bodega Venta (Sin marcar) | AS55: Bodega Tapanco | AT55: Doble Ubicación | AU55: Excedente | AV55: Origen | AW55: Cambios/Probadores | AX55: Negados Sin Recuperar | AY55: Exhibición | AZ55: Bodega Aclaración | BA55: Aduanas | BB55: Golden o apartados | BC55: Control de calidad | BD55: Costo por pasillo | BE55: Sin Exhibición | BF55: Exhibición fuera de Política | BG55: Modelos revuelto | BH55: Modelos mal entallados | BI55: Modelos con error de ubicación | BJ55: Curva con diferencia en frentes | BK55: Curva con diferencia en fondos | BL55: Curva con diferencia en altura | BM55: Curvas vencidas | BN55: Curvas que no coincide Price Soft vs Piso de Venta | BO55: Curvas faltantes | BP55: Cenefas faltantes | BQ55: Cenefas de precio Promoción faltantes | BR55: Cartas disculpa / destallados faltantes | BS55: Fechas de llegada faltantes | BT55: Resultado de Check List | BU55: Resultado de banderazo surtido | BV55: Aguascalientes | BW55: Responsable de Catalogo | BX55: Frenteos | BY55: Ubicación Revuelta | BZ55: Bodega Venta (Sin marcar) | CA55: Bodega Tapanco | CB55: Doble Ubicación | CC55: Excedente | CD55: Origen | CE55: Cambios/Probadores | CF55: Negados Sin Recuperar | CG55: Exhibición | CH55: Bodega Aclaración | CI55: Aduanas | CJ55: Golden o apartados | CK55: Control de calidad | CL55: Costo por pasillo | CM55: Sin Exhibición | CN55: Exhibición fuera de Política | CO55: Modelos revuelto | CP55: Modelos mal entallados | CQ55: Modelos con error de ubicación | CR55: Curva con diferencia en frentes | CS55: Curva con diferencia en fondos | CT55: Curva con diferencia en altura | CU55: Curvas vencidas | CV55: Curvas que no coincide Price Soft vs Piso de Venta | CW55: Curvas faltantes | CX55: Cenefas faltantes | CY55: Cenefas de precio Promoción faltantes | CZ55: Cartas disculpa / destallados faltantes | DA55: Fechas de llegada faltantes | DB55: Resultado de Check List | DE55: Frenteos | DF55: Ubicación Revuelta | DG55: Bodega Venta (Sin marcar) | DH55: Bodega Tapanco | DI55: Doble Ubicación | DJ55: Excedente | DK55: Origen | DL55: Cambios/Probadores | DM55: Negados Sin Recuperar | DN55: Exhibición | DO55: Bodega Aclaración | DP55: Aduanas | DQ55: Golden o apartados | DR55: Control de calidad | DS55: Costo por pasillo | DT55: Sin Exhibición | DU55: Exhibición fuera de Política | DV55: Modelos revuelto | DW55: Modelos mal entallados | DX55: Modelos con error de ubicación | DY55: Curva con diferencia en frentes | DZ55: Curva con diferencia en fondos | EA55: Curva con diferencia en altura | EB55: Curvas vencidas | EC55: Curvas que no coincide Price Soft vs Piso de Venta | ED55: Curvas faltantes | EE55: Cenefas faltantes | EF55: Cenefas de precio Promoción faltantes | EG55: Cartas disculpa / destallados faltantes | EH55: Fechas de llegada faltantes | EK55: Frenteos | EL55: Ubicación Revuelta | EM55: Bodega Venta (Sin marcar) | EN55: Bodega Tapanco | EO55: Doble Ubicación | EP55: Excedente | EQ55: Origen | ER55: Cambios/Probadores | ES55: Negados Sin Recuperar | ET55: Exhibición | EU55: Bodega Aclaración | EV55: Aduanas | EW55: Golden o apartados | EX55: Control de calidad | EZ55: Frenteos | FA55: Ubicación Revuelta | FB55: Bodega Venta (Sin marcar) | FC55: Bodega Tapanco | FD55: Doble Ubicación | FE55: Excedente | FF55: Origen | FG55: Cambios/Probadores | FH55: Negados Sin Recuperar | FI55: Exhibición | FJ55: Bodega Aclaración | FK55: Aduanas | FL55: Golden o apartados | FM55: Control de calidad | FU55: Sin Exhibición | FV55: Exhibición fuera de Política | FW55: Modelos revuelto | FX55: Modelos mal entallados | FY55: Modelos con error de ubicación | FZ55: Curva con diferencia en frentes | GA55: Curva con diferencia en fondos | GB55: Curva con diferencia en altura | GC55: Curvas vencidas | GD55: Curvas que no coincide Price Soft vs Piso de Venta | GE55: Curvas faltantes | GF55: Cenefas faltantes | GG55: Cenefas de precio Promoción faltantes | GH55: Cartas disculpa / destallados faltantes | GI55: modelos que no cadran con planograma | GK55: Sin Exhibición | GL55: Exhibición fuera de Política | GM55: Modelos revuelto | GN55: Modelos mal entallados | GO55: Modelos con error de ubicación | GP55: Curva con diferencia en frentes | GQ55: Curva con diferencia en fondos | GR55: Curva con diferencia en altura | GS55: Curvas vencidas | GT55: Curvas que no coincide Price Soft vs Piso de Venta | GU55: Curvas faltantes | GV55: Cenefas faltantes | GW55: Cenefas de precio Promoción faltantes | GX55: Cartas disculpa / destallados faltantes | GY55: modelos que no cadran con planograma
AM56: =SUM(C56,C57,C58,C59,C60,C61,C62,C63,C64,C67,C68,C70,C71) -> 0 | AN56: =SUM(D56,D57,D58,D59,D60,D61,D62,D63,D64,D67,D68,D70,D71) -> 0 | AO56: =IF(AN56=0,"",AN56/AM56) | AP56: =SUM(F56,F57,F58,F59,F60,F61,F62,F63,F64,F67,F68,F70,F71) -> 0 | AQ56: =SUM(G56,G57,G58,G59,G60,G61,G62,G63,G64,G67,G68,G70,G71) -> 0 | AR56: =SUM(H56,H57,H58,H59,H60,H61,H62,H63,H64,H67,H68,H70,H71) -> 0 | AS56: =SUM(I56,I57,I58,I59,I60,I61,I62,I63,I64,I67,I68,I70,I71) -> 0 | AT56: =SUM(J56,J57,J58,J59,J60,J61,J62,J63,J64,J67,J68,J70,J71) -> 0 | AU56: =SUM(K56,K57,K58,K59,K60,K61,K62,K63,K64,K67,K68,K70,K71) -> 0 | AV56: =SUM(L56,L57,L58,L59,L60,L61,L62,L63,L64,L67,L68,L70,L71) -> 0 | AW56: =SUM(M56,M57,M58,M59,M60,M61,M62,M63,M64,M67,M68,M70,M71) -> 0 | ... BU56: =SUM(AK56,AK57,AK58,AK59,AK60,AK61,AK62,AK63,AK64,AK67,AK68,AK70,AK71) -> 0 | DE56: =SUM(BX56,BX57,BX58,BX59,BX60,BX61,BX62,BX63,BX64,BX67,BX68,BX70,BX71) -> 0 | DF56: =SUM(BY56,BY57,BY58,BY59,BY60,BY61,BY62,BY63,BY64,BY67,BY68,BY70,BY71) -> 0 | DG56: =SUM(BZ56,BZ57,BZ58,BZ59,BZ60,BZ61,BZ62,BZ63,BZ64,BZ67,BZ68,BZ70,BZ71) -> 0 | DH56: =SUM(CA56,CA57,CA58,CA59,CA60,CA61,CA62,CA63,CA64,CA67,CA68,CA70,CA71) -> 0 | DI56: =SUM(CB56,CB57,CB58,CB59,CB60,CB61,CB62,CB63,CB64,CB67,CB68,CB70,CB71) -> 0 | DJ56: =SUM(CC56,CC57,CC58,CC59,CC60,CC61,CC62,CC63,CC64,CC67,CC68,CC70,CC71) -> 0 | DK56: =SUM(CD56,CD57,CD58,CD59,CD60,CD61,CD62,CD63,CD64,CD67,CD68,CD70,CD71) -> 0 | DL56: =SUM(CE56,CE57,CE58,CE59,CE60,CE61,CE62,CE63,CE64,CE67,CE68,CE70,CE71) -> 0 | ... EH56: =SUM(DA56,DA57,DA58,DA59,DA60,DA61,DA62,DA63,DA64,DA67,DA68,DA70,DA71) -> 0 | EI56: BOTAS | EJ56: 521 | EK56: =$EJ56*F56 -> 0 | EL56: =$EJ56*G56 -> 0 | EM56: =$EJ56*H56 -> 0 | EN56: =$EJ56*I56 -> 0 | EO56: =$EJ56*J56 -> 0 | EP56: =$EJ56*K56 -> 0 | EQ56: =$EJ56*L56 -> 0 | ER56: =$EJ56*M56 -> 0 | ES56: =EJ56*N56 -> 0 | ET56: =EJ56*O56 -> 0 | EU56: =$EJ56*P56 -> 0 | EV56: =$EJ56*Q56 -> 0 | EW56: =$EJ56*R56 -> 0 | EX56: =$EJ56*S56 -> 0 | EY56: =SUM(EK56:EX56) -> 0 | EZ56: =BX56*$EJ56 -> 0 | FA56: =BY56*$EJ56 -> 0 | FB56: =BZ56*$EJ56 -> 0 | FC56: =CA56*$EJ56 -> 0 | FD56: =CB56*$EJ56 -> 0 | FE56: =CC56*$EJ56 -> 0 | FF56: =CD56*$EJ56 -> 0 | FG56: =CE56*$EJ56 -> 0 | ... FM56: =CK56*$EJ56 -> 0 | FN56: =SUM(EZ56:FM56) -> 0 | FO56: =SUM(EZ56:FJ56) -> 0 | FS56: BOTAS | FU56: =U56 -> 0 | FV56: =V56 -> 0 | FW56: =W56 -> 0 | FX56: =X56 -> 0 | FY56: =Y56 -> 0 | FZ56: =Z56 -> 0 | GA56: =AA56 -> 0 | GB56: =AB56 -> 0 | ... GH56: =AH56 -> 0 | GI56: 0 | GJ56: =SUM(FU56:GI56) -> 0 | GK56: =CM56 -> 0 | GL56: =CN56 -> 0 | GM56: =CO56 -> 0 | GN56: =CP56 -> 0 | GO56: =CQ56 -> 0 | GP56: =CR56 -> 0 | GQ56: =CS56 -> 0 | GR56: =CT56 -> 0 | ... GX56: =CZ56 -> 0 | GY56: 0 | GZ56: =SUM(GK56:GY56) -> 0 | HA56: =SUM(GK56:GY56) -> 0
AO57: =IF(AN57=0,"",AN57/AM57) | EI57: URBANO | EJ57: 540 | EK57: =$EJ57*F57 -> 0 | EL57: =$EJ57*G57 -> 0 | EM57: =$EJ57*H57 -> 0 | EN57: =$EJ57*I57 -> 0 | EO57: =$EJ57*J57 -> 0 | EP57: =$EJ57*K57 -> 0 | EQ57: =$EJ57*L57 -> 0 | ER57: =$EJ57*M57 -> 0 | ES57: =EJ57*N57 -> 0 | ET57: =EJ57*O57 -> 0 | EU57: =$EJ57*P57 -> 0 | EV57: =$EJ57*Q57 -> 0 | EW57: =$EJ57*R57 -> 0 | EX57: =$EJ57*S57 -> 0 | EY57: =SUM(EK57:EX57) -> 0 | EZ57: =BX57*$EJ57 -> 0 | FA57: =BY57*$EJ57 -> 0 | FB57: =BZ57*$EJ57 -> 0 | FC57: =CA57*$EJ57 -> 0 | FD57: =CB57*$EJ57 -> 0 | FE57: =CC57*$EJ57 -> 0 | FF57: =CD57*$EJ57 -> 0 | FG57: =CE57*$EJ57 -> 0 | ... FM57: =CK57*$EJ57 -> 0 | FN57: =SUM(EZ57:FM57) -> 0 | FO57: =SUM(EZ57:FJ57) -> 0 | FS57: URBANO | FU57: =U57 -> 0 | FV57: =V57 -> 0 | FW57: =W57 -> 0 | FX57: =X57 -> 0 | FY57: =Y57 -> 0 | FZ57: =Z57 -> 0 | GA57: =AA57 -> 0 | GB57: =AB57 -> 0 | ... GH57: =AH57 -> 0 | GI57: 0 | GJ57: =SUM(FU57:GI57) -> 0 | GK57: =CM57 -> 0 | GL57: =CN57 -> 0 | GM57: =CO57 -> 0 | GN57: =CP57 -> 0 | GO57: =CQ57 -> 0 | GP57: =CR57 -> 0 | GQ57: =CS57 -> 0 | GR57: =CT57 -> 0 | ... GX57: =CZ57 -> 0 | GY57: 0 | GZ57: =SUM(GK57:GY57) -> 0 | HA57: =SUM(GK57:GY57) -> 0
AL58: % de tallas negadas | AM58: =SUM(C65,C66,C69) -> 0 | AN58: =SUM(D65,D66,D69) -> 0 | AO58: =IF(AN58=0,"",AN58/AM58) | AP58: =SUM(F65,F66,F69) -> 0 | AQ58: =SUM(G65,G66,G69) -> 0 | AR58: =SUM(H65,H66,H69) -> 0 | AS58: =SUM(I65,I66,I69) -> 0 | AT58: =SUM(J65,J66,J69) -> 0 | AU58: =SUM(K65,K66,K69) -> 0 | AV58: =SUM(L65,L66,L69) -> 0 | AW58: =SUM(M65,M66,M69) -> 0 | ... BS58: =SUM(AI65,AI66,AI69) -> 0 | BT58: =AVERAGE(AJ65,AJ66,AJ69) -> #DIV/0! | DC58: % de tallas recuperadas | DE58: =SUM(BX65,BX66,BX69) -> 0 | DF58: =SUM(BY65,BY66,BY69) -> 0 | DG58: =SUM(BZ65,BZ66,BZ69) -> 0 | DH58: =SUM(CA65,CA66,CA69) -> 0 | DI58: =SUM(CB65,CB66,CB69) -> 0 | DJ58: =SUM(CC65,CC66,CC69) -> 0 | DK58: =SUM(CD65,CD66,CD69) -> 0 | DL58: =SUM(CE65,CE66,CE69) -> 0 | ... EH58: =SUM(DA65,DA66,DA69) -> 0 | EI58: ESCOLAR | EJ58: 441.24 | EK58: =$EJ58*F58 -> 0 | EL58: =$EJ58*G58 -> 0 | EM58: =$EJ58*H58 -> 0 | EN58: =$EJ58*I58 -> 0 | EO58: =$EJ58*J58 -> 0 | EP58: =$EJ58*K58 -> 0 | EQ58: =$EJ58*L58 -> 0 | ER58: =$EJ58*M58 -> 0 | ES58: =EJ58*N58 -> 0 | ET58: =EJ58*O58 -> 0 | EU58: =$EJ58*P58 -> 0 | EV58: =$EJ58*Q58 -> 0 | EW58: =$EJ58*R58 -> 0 | EX58: =$EJ58*S58 -> 0 | EY58: =SUM(EK58:EX58) -> 0 | EZ58: =BX58*$EJ58 -> 0 | FA58: =BY58*$EJ58 -> 0 | FB58: =BZ58*$EJ58 -> 0 | FC58: =CA58*$EJ58 -> 0 | FD58: =CB58*$EJ58 -> 0 | FE58: =CC58*$EJ58 -> 0 | FF58: =CD58*$EJ58 -> 0 | FG58: =CE58*$EJ58 -> 0 | ... FM58: =CK58*$EJ58 -> 0 | FN58: =SUM(EZ58:FM58) -> 0 | FO58: =SUM(EZ58:FJ58) -> 0 | FS58: ESCOLAR | FU58: =U58 -> 0 | FV58: =V58 -> 0 | FW58: =W58 -> 0 | FX58: =X58 -> 0 | FY58: =Y58 -> 0 | FZ58: =Z58 -> 0 | GA58: =AA58 -> 0 | GB58: =AB58 -> 0 | ... GH58: =AH58 -> 0 | GI58: 0 | GJ58: =SUM(FU58:GI58) -> 0 | GK58: =CM58 -> 0 | GL58: =CN58 -> 0 | GM58: =CO58 -> 0 | GN58: =CP58 -> 0 | GO58: =CQ58 -> 0 | GP58: =CR58 -> 0 | GQ58: =CS58 -> 0 | GR58: =CT58 -> 0 | ... GX58: =CZ58 -> 0 | GY58: 0 | GZ58: =SUM(GK58:GY58) -> 0 | HA58: =SUM(GK58:GY58) -> 0
EI59: SANDALIAS | EJ59: 294.47 | EK59: =$EJ59*F59 -> 0 | EL59: =$EJ59*G59 -> 0 | EM59: =$EJ59*H59 -> 0 | EN59: =$EJ59*I59 -> 0 | EO59: =$EJ59*J59 -> 0 | EP59: =$EJ59*K59 -> 0 | EQ59: =$EJ59*L59 -> 0 | ER59: =$EJ59*M59 -> 0 | ES59: =EJ59*N59 -> 0 | ET59: =EJ59*O59 -> 0 | EU59: =$EJ59*P59 -> 0 | EV59: =$EJ59*Q59 -> 0 | EW59: =$EJ59*R59 -> 0 | EX59: =$EJ59*S59 -> 0 | EY59: =SUM(EK59:EX59) -> 0 | EZ59: =BX59*$EJ59 -> 0 | FA59: =BY59*$EJ59 -> 0 | FB59: =BZ59*$EJ59 -> 0 | FC59: =CA59*$EJ59 -> 0 | FD59: =CB59*$EJ59 -> 0 | FE59: =CC59*$EJ59 -> 0 | FF59: =CD59*$EJ59 -> 0 | FG59: =CE59*$EJ59 -> 0 | ... FM59: =CK59*$EJ59 -> 0 | FN59: =SUM(EZ59:FM59) -> 0 | FO59: =SUM(EZ59:FJ59) -> 0 | FS59: SANDALIAS | FU59: =U59 -> 0 | FV59: =V59 -> 0 | FW59: =W59 -> 0 | FX59: =X59 -> 0 | FY59: =Y59 -> 0 | FZ59: =Z59 -> 0 | GA59: =AA59 -> 0 | GB59: =AB59 -> 0 | ... GH59: =AH59 -> 0 | GI59: 0 | GJ59: =SUM(FU59:GI59) -> 0 | GK59: =CM59 -> 0 | GL59: =CN59 -> 0 | GM59: =CO59 -> 0 | GN59: =CP59 -> 0 | GO59: =CQ59 -> 0 | GP59: =CR59 -> 0 | GQ59: =CS59 -> 0 | GR59: =CT59 -> 0 | ... GX59: =CZ59 -> 0 | GY59: 0 | GZ59: =SUM(GK59:GY59) -> 0 | HA59: =SUM(GK59:GY59) -> 0
AL60: =T72/D72 -> #DIV/0! | DC60: =CL72/T72 -> #DIV/0! | EI60: CONFORT | EJ60: 422 | EK60: =$EJ60*F60 -> 0 | EL60: =$EJ60*G60 -> 0 | EM60: =$EJ60*H60 -> 0 | EN60: =$EJ60*I60 -> 0 | EO60: =$EJ60*J60 -> 0 | EP60: =$EJ60*K60 -> 0 | EQ60: =$EJ60*L60 -> 0 | ER60: =$EJ60*M60 -> 0 | ES60: =EJ60*N60 -> 0 | ET60: =EJ60*O60 -> 0 | EU60: =$EJ60*P60 -> 0 | EV60: =$EJ60*Q60 -> 0 | EW60: =$EJ60*R60 -> 0 | EX60: =$EJ60*S60 -> 0 | EY60: =SUM(EK60:EX60) -> 0 | EZ60: =BX60*$EJ60 -> 0 | FA60: =BY60*$EJ60 -> 0 | FB60: =BZ60*$EJ60 -> 0 | FC60: =CA60*$EJ60 -> 0 | FD60: =CB60*$EJ60 -> 0 | FE60: =CC60*$EJ60 -> 0 | FF60: =CD60*$EJ60 -> 0 | FG60: =CE60*$EJ60 -> 0 | ... FM60: =CK60*$EJ60 -> 0 | FN60: =SUM(EZ60:FM60) -> 0 | FO60: =SUM(EZ60:FJ60) -> 0 | FS60: CONFORT | FU60: =U60 -> 0 | FV60: =V60 -> 0 | FW60: =W60 -> 0 | FX60: =X60 -> 0 | FY60: =Y60 -> 0 | FZ60: =Z60 -> 0 | GA60: =AA60 -> 0 | GB60: =AB60 -> 0 | ... GH60: =AH60 -> 0 | GI60: 0 | GJ60: =SUM(FU60:GI60) -> 0 | GK60: =CM60 -> 0 | GL60: =CN60 -> 0 | GM60: =CO60 -> 0 | GN60: =CP60 -> 0 | GO60: =CQ60 -> 0 | GP60: =CR60 -> 0 | GQ60: =CS60 -> 0 | GR60: =CT60 -> 0 | ... GX60: =CZ60 -> 0 | GY60: 0 | GZ60: =SUM(GK60:GY60) -> 0 | HA60: =SUM(GK60:GY60) -> 0
EI61: VESTIR CASUAL | EJ61: 416.19 | EK61: =$EJ61*F61 -> 0 | EL61: =$EJ61*G61 -> 0 | EM61: =$EJ61*H61 -> 0 | EN61: =$EJ61*I61 -> 0 | EO61: =$EJ61*J61 -> 0 | EP61: =$EJ61*K61 -> 0 | EQ61: =$EJ61*L61 -> 0 | ER61: =$EJ61*M61 -> 0 | ES61: =EJ61*N61 -> 0 | ET61: =EJ61*O61 -> 0 | EU61: =$EJ61*P61 -> 0 | EV61: =$EJ61*Q61 -> 0 | EW61: =$EJ61*R61 -> 0 | EX61: =$EJ61*S61 -> 0 | EY61: =SUM(EK61:EX61) -> 0 | EZ61: =BX61*$EJ61 -> 0 | FA61: =BY61*$EJ61 -> 0 | FB61: =BZ61*$EJ61 -> 0 | FC61: =CA61*$EJ61 -> 0 | FD61: =CB61*$EJ61 -> 0 | FE61: =CC61*$EJ61 -> 0 | FF61: =CD61*$EJ61 -> 0 | FG61: =CE61*$EJ61 -> 0 | ... FM61: =CK61*$EJ61 -> 0 | FN61: =SUM(EZ61:FM61) -> 0 | FO61: =SUM(EZ61:FJ61) -> 0 | FS61: VESTIR CASUAL | FU61: =U61 -> 0 | FV61: =V61 -> 0 | FW61: =W61 -> 0 | FX61: =X61 -> 0 | FY61: =Y61 -> 0 | FZ61: =Z61 -> 0 | GA61: =AA61 -> 0 | GB61: =AB61 -> 0 | ... GH61: =AH61 -> 0 | GI61: 0 | GJ61: =SUM(FU61:GI61) -> 0 | GK61: =CM61 -> 0 | GL61: =CN61 -> 0 | GM61: =CO61 -> 0 | GN61: =CP61 -> 0 | GO61: =CQ61 -> 0 | GP61: =CR61 -> 0 | GQ61: =CS61 -> 0 | GR61: =CT61 -> 0 | ... GX61: =CZ61 -> 0 | GY61: 0 | GZ61: =SUM(GK61:GY61) -> 0 | HA61: =SUM(GK61:GY61) -> 0
AL62: Diferencia Negado VS Recuperado | EI62: INFANTILES | EJ62: 375 | EK62: =$EJ62*F62 -> 0 | EL62: =$EJ62*G62 -> 0 | EM62: =$EJ62*H62 -> 0 | EN62: =$EJ62*I62 -> 0 | EO62: =$EJ62*J62 -> 0 | EP62: =$EJ62*K62 -> 0 | EQ62: =$EJ62*L62 -> 0 | ER62: =$EJ62*M62 -> 0 | ES62: =EJ62*N62 -> 0 | ET62: =EJ62*O62 -> 0 | EU62: =$EJ62*P62 -> 0 | EV62: =$EJ62*Q62 -> 0 | EW62: =$EJ62*R62 -> 0 | EX62: =$EJ62*S62 -> 0 | EY62: =SUM(EK62:EX62) -> 0 | EZ62: =BX62*$EJ62 -> 0 | FA62: =BY62*$EJ62 -> 0 | FB62: =BZ62*$EJ62 -> 0 | FC62: =CA62*$EJ62 -> 0 | FD62: =CB62*$EJ62 -> 0 | FE62: =CC62*$EJ62 -> 0 | FF62: =CD62*$EJ62 -> 0 | FG62: =CE62*$EJ62 -> 0 | ... FM62: =CK62*$EJ62 -> 0 | FN62: =SUM(EZ62:FM62) -> 0 | FO62: =SUM(EZ62:FJ62) -> 0 | FS62: INFANTILES | FU62: =U62 -> 0 | FV62: =V62 -> 0 | FW62: =W62 -> 0 | FX62: =X62 -> 0 | FY62: =Y62 -> 0 | FZ62: =Z62 -> 0 | GA62: =AA62 -> 0 | GB62: =AB62 -> 0 | ... GH62: =AH62 -> 0 | GI62: 0 | GJ62: =SUM(FU62:GI62) -> 0 | GK62: =CM62 -> 0 | GL62: =CN62 -> 0 | GM62: =CO62 -> 0 | GN62: =CP62 -> 0 | GO62: =CQ62 -> 0 | GP62: =CR62 -> 0 | GQ62: =CS62 -> 0 | GR62: =CT62 -> 0 | ... GX62: =CZ62 -> 0 | GY62: 0 | GZ62: =SUM(GK62:GY62) -> 0 | HA62: =SUM(GK62:GY62) -> 0
EI63: CABALLEROS | EJ63: 730 | EK63: =$EJ63*F63 -> 0 | EL63: =$EJ63*G63 -> 0 | EM63: =$EJ63*H63 -> 0 | EN63: =$EJ63*I63 -> 0 | EO63: =$EJ63*J63 -> 0 | EP63: =$EJ63*K63 -> 0 | EQ63: =$EJ63*L63 -> 0 | ER63: =$EJ63*M63 -> 0 | ES63: =EJ63*N63 -> 0 | ET63: =EJ63*O63 -> 0 | EU63: =$EJ63*P63 -> 0 | EV63: =$EJ63*Q63 -> 0 | EW63: =$EJ63*R63 -> 0 | EX63: =$EJ63*S63 -> 0 | EY63: =SUM(EK63:EX63) -> 0 | EZ63: =BX63*$EJ63 -> 0 | FA63: =BY63*$EJ63 -> 0 | FB63: =BZ63*$EJ63 -> 0 | FC63: =CA63*$EJ63 -> 0 | FD63: =CB63*$EJ63 -> 0 | FE63: =CC63*$EJ63 -> 0 | FF63: =CD63*$EJ63 -> 0 | FG63: =CE63*$EJ63 -> 0 | ... FM63: =CK63*$EJ63 -> 0 | FN63: =SUM(EZ63:FM63) -> 0 | FO63: =SUM(EZ63:FJ63) -> 0 | FS63: CABALLEROS | FU63: =U63 -> 0 | FV63: =V63 -> 0 | FW63: =W63 -> 0 | FX63: =X63 -> 0 | FY63: =Y63 -> 0 | FZ63: =Z63 -> 0 | GA63: =AA63 -> 0 | GB63: =AB63 -> 0 | ... GH63: =AH63 -> 0 | GI63: 0 | GJ63: =SUM(FU63:GI63) -> 0 | GK63: =CM63 -> 0 | GL63: =CN63 -> 0 | GM63: =CO63 -> 0 | GN63: =CP63 -> 0 | GO63: =CQ63 -> 0 | GP63: =CR63 -> 0 | GQ63: =CS63 -> 0 | GR63: =CT63 -> 0 | ... GX63: =CZ63 -> 0 | GY63: 0 | GZ63: =SUM(GK63:GY63) -> 0 | HA63: =SUM(GK63:GY63) -> 0
AL64: =f730bn73 -> #NAME? | EI64: CHANCLERO | EJ64: 178 | EK64: =$EJ64*F64 -> 0 | EL64: =$EJ64*G64 -> 0 | EM64: =$EJ64*H64 -> 0 | EN64: =$EJ64*I64 -> 0 | EO64: =$EJ64*J64 -> 0 | EP64: =$EJ64*K64 -> 0 | EQ64: =$EJ64*L64 -> 0 | ER64: =$EJ64*M64 -> 0 | ES64: =EJ64*N64 -> 0 | ET64: =EJ64*O64 -> 0 | EU64: =$EJ64*P64 -> 0 | EV64: =$EJ64*Q64 -> 0 | EW64: =$EJ64*R64 -> 0 | EX64: =$EJ64*S64 -> 0 | EY64: =SUM(EK64:EX64) -> 0 | EZ64: =BX64*$EJ64 -> 0 | FA64: =BY64*$EJ64 -> 0 | FB64: =BZ64*$EJ64 -> 0 | FC64: =CA64*$EJ64 -> 0 | FD64: =CB64*$EJ64 -> 0 | FE64: =CC64*$EJ64 -> 0 | FF64: =CD64*$EJ64 -> 0 | FG64: =CE64*$EJ64 -> 0 | ... FM64: =CK64*$EJ64 -> 0 | FN64: =SUM(EZ64:FM64) -> 0 | FO64: =SUM(EZ64:FJ64) -> 0 | FS64: CHANCLERO | FU64: =U64 -> 0 | FV64: =V64 -> 0 | FW64: =W64 -> 0 | FX64: =X64 -> 0 | FY64: =Y64 -> 0 | FZ64: =Z64 -> 0 | GA64: =AA64 -> 0 | GB64: =AB64 -> 0 | ... GH64: =AH64 -> 0 | GI64: 0 | GJ64: =SUM(FU64:GI64) -> 0 | GK64: =CM64 -> 0 | GL64: =CN64 -> 0 | GM64: =CO64 -> 0 | GN64: =CP64 -> 0 | GO64: =CQ64 -> 0 | GP64: =CR64 -> 0 | GQ64: =CS64 -> 0 | GR64: =CT64 -> 0 | ... GX64: =CZ64 -> 0 | GY64: 0 | GZ64: =SUM(GK64:GY64) -> 0 | HA64: =SUM(GK64:GY64) -> 0
EI65: ROPA DOBLADA | EJ65: 263 | EK65: =$EJ65*F65 -> 0 | EL65: =$EJ65*G65 -> 0 | EM65: =$EJ65*H65 -> 0 | EN65: =$EJ65*I65 -> 0 | EO65: =$EJ65*J65 -> 0 | EP65: =$EJ65*K65 -> 0 | EQ65: =$EJ65*L65 -> 0 | ER65: =$EJ65*M65 -> 0 | ES65: =EJ65*N65 -> 0 | ET65: =EJ65*O65 -> 0 | EU65: =$EJ65*P65 -> 0 | EV65: =$EJ65*Q65 -> 0 | EW65: =$EJ65*R65 -> 0 | EX65: =$EJ65*S65 -> 0 | EY65: =SUM(EK65:EX65) -> 0 | EZ65: =BX65*$EJ65 -> 0 | FA65: =BY65*$EJ65 -> 0 | FB65: =BZ65*$EJ65 -> 0 | FC65: =CA65*$EJ65 -> 0 | FD65: =CB65*$EJ65 -> 0 | FE65: =CC65*$EJ65 -> 0 | FF65: =CD65*$EJ65 -> 0 | FG65: =CE65*$EJ65 -> 0 | ... FM65: =CK65*$EJ65 -> 0 | FN65: =SUM(EZ65:FM65) -> 0 | FO65: =SUM(EZ65:FJ65) -> 0 | FS65: ROPA DOBLADA | FU65: 0 | FV65: 0 | FW65: =W65 -> 0 | FX65: =X65 -> 0 | FY65: =Y65 -> 0 | FZ65: 0 | GA65: 0 | GB65: 0 | GC65: =AC65 -> 0 | GD65: =AD65 -> 0 | GE65: =AE65 -> 0 | GF65: =AF65 -> 0 | GG65: =AG65 -> 0 | GH65: 0 | GI65: =AI65 -> 0 | GJ65: =SUM(FU65:GI65) -> 0 | GK65: 0 | GL65: 0 | GM65: =CO65 -> 0 | GN65: =CP65 -> 0 | GO65: =CQ65 -> 0 | GP65: 0 | GQ65: 0 | GR65: 0 | GS65: =CU65 -> 0 | GT65: =CV65 -> 0 | GU65: =CW65 -> 0 | GV65: =CX65 -> 0 | GW65: =CY65 -> 0 | GX65: 0 | GY65: =DA65 -> 0 | GZ65: =SUM(GK65:GY65) -> 0 | HA65: =SUM(GK65:GY65) -> 0
AL66: % de Costo no recuperado | EI66: ROPA COLGADA | EJ66: 405 | EK66: =$EJ66*F66 -> 0 | EL66: =$EJ66*G66 -> 0 | EM66: =$EJ66*H66 -> 0 | EN66: =$EJ66*I66 -> 0 | EO66: =$EJ66*J66 -> 0 | EP66: =$EJ66*K66 -> 0 | EQ66: =$EJ66*L66 -> 0 | ER66: =$EJ66*M66 -> 0 | ES66: =EJ66*N66 -> 0 | ET66: =EJ66*O66 -> 0 | EU66: =$EJ66*P66 -> 0 | EV66: =$EJ66*Q66 -> 0 | EW66: =$EJ66*R66 -> 0 | EX66: =$EJ66*S66 -> 0 | EY66: =SUM(EK66:EX66) -> 0 | EZ66: =BX66*$EJ66 -> 0 | FA66: =BY66*$EJ66 -> 0 | FB66: =BZ66*$EJ66 -> 0 | FC66: =CA66*$EJ66 -> 0 | FD66: =CB66*$EJ66 -> 0 | FE66: =CC66*$EJ66 -> 0 | FF66: =CD66*$EJ66 -> 0 | FG66: =CE66*$EJ66 -> 0 | ... FM66: =CK66*$EJ66 -> 0 | FN66: =SUM(EZ66:FM66) -> 0 | FO66: =SUM(EZ66:FJ66) -> 0 | FS66: ROPA COLGADA | FU66: 0 | FV66: 0 | FW66: =W66 -> 0 | FX66: =X66 -> 0 | FY66: =Y66 -> 0 | FZ66: 0 | GA66: 0 | GB66: 0 | GC66: =AC66 -> 0 | GD66: =AD66 -> 0 | GE66: =AE66 -> 0 | GF66: =AF66 -> 0 | GG66: =AG66 -> 0 | GH66: 0 | GI66: =AI66 -> 0 | GJ66: =SUM(FU66:GI66) -> 0 | GK66: 0 | GL66: 0 | GM66: =CO66 -> 0 | GN66: =CP66 -> 0 | GO66: =CQ66 -> 0 | GP66: 0 | GQ66: 0 | GR66: 0 | GS66: =CU66 -> 0 | GT66: =CV66 -> 0 | GU66: =CW66 -> 0 | GV66: =CX66 -> 0 | GW66: =CY66 -> 0 | GX66: =CZ66 -> 0 | GY66: =DA66 -> 0 | GZ66: =SUM(GK66:GY66) -> 0 | HA66: =SUM(GK66:GY66) -> 0
EI67: IMPORTADOS | EJ67: 1287 | EK67: =$EJ67*F67 -> 0 | EL67: =$EJ67*G67 -> 0 | EM67: =$EJ67*H67 -> 0 | EN67: =$EJ67*I67 -> 0 | EO67: =$EJ67*J67 -> 0 | EP67: =$EJ67*K67 -> 0 | EQ67: =$EJ67*L67 -> 0 | ER67: =$EJ67*M67 -> 0 | ES67: =EJ67*N67 -> 0 | ET67: =EJ67*O67 -> 0 | EU67: =$EJ67*P67 -> 0 | EV67: =$EJ67*Q67 -> 0 | EW67: =$EJ67*R67 -> 0 | EX67: =$EJ67*S67 -> 0 | EY67: =SUM(EK67:EX67) -> 0 | EZ67: =BX67*$EJ67 -> 0 | FA67: =BY67*$EJ67 -> 0 | FB67: =BZ67*$EJ67 -> 0 | FC67: =CA67*$EJ67 -> 0 | FD67: =CB67*$EJ67 -> 0 | FE67: =CC67*$EJ67 -> 0 | FF67: =CD67*$EJ67 -> 0 | FG67: =CE67*$EJ67 -> 0 | ... FM67: =CK67*$EJ67 -> 0 | FN67: =SUM(EZ67:FM67) -> 0 | FO67: =SUM(EZ67:FJ67) -> 0 | FS67: IMPORTADOS | FU67: 0 | FV67: 0 | FW67: =W67 -> 0 | FX67: =X67 -> 0 | FY67: =Y67 -> 0 | FZ67: =Z67 -> 0 | GA67: =AA67 -> 0 | GB67: =AB67 -> 0 | GC67: =AC67 -> 0 | GD67: =AD67 -> 0 | ... GH67: =AH67 -> 0 | GI67: 0 | GJ67: =SUM(FU67:GI67) -> 0 | GK67: 0 | GL67: 0 | GM67: =CO67 -> 0 | GN67: =CP67 -> 0 | GO67: =CQ67 -> 0 | GP67: =CR67 -> 0 | GQ67: =CS67 -> 0 | GR67: =CT67 -> 0 | GS67: =CU67 -> 0 | GT67: =CV67 -> 0 | ... GX67: =CZ67 -> 0 | GY67: 0 | GZ67: =SUM(GK67:GY67) -> 0 | HA67: =SUM(GK67:GY67) -> 0
AL68: =(AL64/F73) -> #NAME? | EI68: BARRA DE BEBES | EJ68: 326.07 | EK68: =$EJ68*F68 -> 0 | EL68: =$EJ68*G68 -> 0 | EM68: =$EJ68*H68 -> 0 | EN68: =$EJ68*I68 -> 0 | EO68: =$EJ68*J68 -> 0 | EP68: =$EJ68*K68 -> 0 | EQ68: =$EJ68*L68 -> 0 | ER68: =$EJ68*M68 -> 0 | ES68: =EJ68*N68 -> 0 | ET68: =EJ68*O68 -> 0 | EU68: =$EJ68*P68 -> 0 | EV68: =$EJ68*Q68 -> 0 | EW68: =$EJ68*R68 -> 0 | EX68: =$EJ68*S68 -> 0 | EY68: =SUM(EK68:EX68) -> 0 | EZ68: =BX68*$EJ68 -> 0 | FA68: =BY68*$EJ68 -> 0 | FB68: =BZ68*$EJ68 -> 0 | FC68: =CA68*$EJ68 -> 0 | FD68: =CB68*$EJ68 -> 0 | FE68: =CC68*$EJ68 -> 0 | FF68: =CD68*$EJ68 -> 0 | FG68: =CE68*$EJ68 -> 0 | ... FM68: =CK68*$EJ68 -> 0 | FN68: =SUM(EZ68:FM68) -> 0 | FO68: =SUM(EZ68:FJ68) -> 0 | FS68: BARRA DE BEBES | FU68: 0 | FV68: 0 | FW68: =W68 -> 0 | FX68: =X68 -> 0 | FY68: =Y68 -> 0 | FZ68: =Z68 -> 0 | GA68: =AA68 -> 0 | GB68: =AB68 -> 0 | GC68: =AC68 -> 0 | GD68: =AD68 -> 0 | ... GH68: =AH68 -> 0 | GI68: 0 | GJ68: =SUM(FU68:GI68) -> 0 | GK68: 0 | GL68: 0 | GM68: =CO68 -> 0 | GN68: =CP68 -> 0 | GO68: =CQ68 -> 0 | GP68: =CR68 -> 0 | GQ68: =CS68 -> 0 | GR68: =CT68 -> 0 | GS68: =CU68 -> 0 | GT68: =CV68 -> 0 | ... GX68: =CZ68 -> 0 | GY68: 0 | GZ68: =SUM(GK68:GY68) -> 0 | HA68: =SUM(GK68:GY68) -> 0
EI69: JEANS | EJ69: 357 | EK69: =$EJ69*F69 -> 0 | EL69: =$EJ69*G69 -> 0 | EM69: =$EJ69*H69 -> 0 | EN69: =$EJ69*I69 -> 0 | EO69: =$EJ69*J69 -> 0 | EP69: =$EJ69*K69 -> 0 | EQ69: =$EJ69*L69 -> 0 | ER69: =$EJ69*M69 -> 0 | ES69: =EJ69*N69 -> 0 | ET69: =EJ69*O69 -> 0 | EU69: =$EJ69*P69 -> 0 | EV69: =$EJ69*Q69 -> 0 | EW69: =$EJ69*R69 -> 0 | EX69: =$EJ69*S69 -> 0 | EY69: =SUM(EK69:EX69) -> 0 | EZ69: =BX69*$EJ69 -> 0 | FA69: =BY69*$EJ69 -> 0 | FB69: =BZ69*$EJ69 -> 0 | FC69: =CA69*$EJ69 -> 0 | FD69: =CB69*$EJ69 -> 0 | FE69: =CC69*$EJ69 -> 0 | FF69: =CD69*$EJ69 -> 0 | FG69: =CE69*$EJ69 -> 0 | ... FM69: =CK69*$EJ69 -> 0 | FN69: =SUM(EZ69:FM69) -> 0 | FO69: =SUM(EZ69:FJ69) -> 0 | FS69: JEANS | FU69: 0 | FV69: 0 | FW69: =W69 -> 0 | FX69: =X69 -> 0 | FY69: =Y69 -> 0 | FZ69: 0 | GA69: 0 | GB69: 0 | GC69: =AC69 -> 0 | GD69: =AD69 -> 0 | GE69: =AE69 -> 0 | GF69: =AF69 -> 0 | GG69: =AG69 -> 0 | GH69: 0 | GI69: =AI69 -> 0 | GJ69: =SUM(FU69:GI69) -> 0 | GK69: 0 | GL69: 0 | GM69: =CO69 -> 0 | GN69: =CP69 -> 0 | GO69: =CQ69 -> 0 | GP69: 0 | GQ69: 0 | GR69: 0 | GS69: =CU69 -> 0 | GT69: =CV69 -> 0 | GU69: =CW69 -> 0 | GV69: =CX69 -> 0 | GW69: =CY69 -> 0 | GX69: 0 | GY69: =DA69 -> 0 | GZ69: =SUM(GK69:GY69) -> 0 | HA69: =SUM(GK69:GY69) -> 0
EI70: MOCHILAS | EJ70: 482 | EK70: =$EJ70*F70 -> 0 | EL70: =$EJ70*G70 -> 0 | EM70: =$EJ70*H70 -> 0 | EN70: =$EJ70*I70 -> 0 | EO70: =$EJ70*J70 -> 0 | EP70: =$EJ70*K70 -> 0 | EQ70: =$EJ70*L70 -> 0 | ER70: =$EJ70*M70 -> 0 | ES70: =EJ70*N70 -> 0 | ET70: =EJ70*O70 -> 0 | EU70: =$EJ70*P70 -> 0 | EV70: =$EJ70*Q70 -> 0 | EW70: =$EJ70*R70 -> 0 | EX70: =$EJ70*S70 -> 0 | EY70: =SUM(EK70:EX70) -> 0 | EZ70: =BX70*$EJ70 -> 0 | FA70: =BY70*$EJ70 -> 0 | FB70: =BZ70*$EJ70 -> 0 | FC70: =CA70*$EJ70 -> 0 | FD70: =CB70*$EJ70 -> 0 | FE70: =CC70*$EJ70 -> 0 | FF70: =CD70*$EJ70 -> 0 | FG70: =CE70*$EJ70 -> 0 | ... FM70: =CK70*$EJ70 -> 0 | FN70: =SUM(EZ70:FM70) -> 0 | FO70: =SUM(EZ70:FJ70) -> 0 | FS70: MOCHILAS | FU70: =U70 -> 0 | FV70: =V70 -> 0 | FW70: =W70 -> 0 | FX70: =X70 -> 0 | FY70: =Y70 -> 0 | FZ70: =Z70 -> 0 | GA70: =AA70 -> 0 | GB70: =AB70 -> 0 | ... GI70: =AI70 -> 0 | GJ70: =SUM(FU70:GI70) -> 0 | GK70: =CM70 -> 0 | GL70: =CN70 -> 0 | GM70: =CO70 -> 0 | GN70: =CP70 -> 0 | GO70: =CQ70 -> 0 | GP70: =CR70 -> 0 | GQ70: =CS70 -> 0 | GR70: =CT70 -> 0 | ... GX70: =CZ70 -> 0 | GY70: 0 | GZ70: =SUM(GK70:GY70) -> 0 | HA70: =SUM(GK70:GY70) -> 0
EI71: HASTA | EJ71: 275.36 | EK71: =$EJ71*F71 -> 0 | EL71: =$EJ71*G71 -> 0 | EM71: =$EJ71*H71 -> 0 | EN71: =$EJ71*I71 -> 0 | EO71: =$EJ71*J71 -> 0 | EP71: =$EJ71*K71 -> 0 | EQ71: =$EJ71*L71 -> 0 | ER71: =$EJ71*M71 -> 0 | ES71: =EJ71*N71 -> 0 | ET71: =EJ71*O71 -> 0 | EU71: =$EJ71*P71 -> 0 | EV71: =$EJ71*Q71 -> 0 | EW71: =$EJ71*R71 -> 0 | EX71: =$EJ71*S71 -> 0 | EY71: =SUM(EK71:EX71) -> 0 | EZ71: =BX71*$EJ71 -> 0 | FA71: =BY71*$EJ71 -> 0 | FB71: =BZ71*$EJ71 -> 0 | FC71: =CA71*$EJ71 -> 0 | FD71: =CB71*$EJ71 -> 0 | FE71: =CC71*$EJ71 -> 0 | FF71: =CD71*$EJ71 -> 0 | FG71: =CE71*$EJ71 -> 0 | ... FM71: =CK71*$EJ71 -> 0 | FN71: =SUM(EZ71:FM71) -> 0 | FO71: =SUM(EZ71:FJ71) -> 0 | FS71: HASTA | FU71: =U71 -> 0 | FV71: =V71 -> 0 | FW71: =W71 -> 0 | FX71: =X71 -> 0 | FY71: =Y71 -> 0 | FZ71: =Z71 -> 0 | GA71: =AA71 -> 0 | GB71: =AB71 -> 0 | ... GH71: =AH71 -> 0 | GI71: 0 | GJ71: =SUM(FU71:GI71) -> 0 | GK71: =CM71 -> 0 | GL71: =CN71 -> 0 | GM71: =CO71 -> 0 | GN71: =CP71 -> 0 | GO71: =CQ71 -> 0 | GP71: =CR71 -> 0 | GQ71: =CS71 -> 0 | GR71: =CT71 -> 0 | ... GX71: =CZ71 -> 0 | GY71: 0 | GZ71: =SUM(GK71:GY71) -> 0 | HA71: =SUM(GK71:GY71) -> 0
B72: Total | C72: =SUM(C56:C71) -> 0 | D72: =SUM(D56:D71) -> 0 | E72: =D72/C72 -> #DIV/0! | F72: =SUM(F56:F71) -> 0 | H72: =SUM(H56:H71) -> 0 | I72: =SUM(I56:I71) -> 0 | J72: =SUM(J56:J71) -> 0 | K72: =SUM(K56:K71) -> 0 | L72: =SUM(L56:L71) -> 0 | N72: =SUM(N56:N71) -> 0 | O72: =SUM(O56:O71) -> 0 | P72: =SUM(P56:P71) -> 0 | T72: =SUM(F72:P72) -> 0 | U72: =SUM(U56:U71) -> 0 | V72: =SUM(V56:V71) -> 0 | W72: =SUM(W56:W71) -> 0 | X72: =SUM(X56:X71) -> 0 | Y72: =SUM(Y56:Y71) -> 0 | Z72: =SUM(Z56:Z71) -> 0 | AA72: =SUM(AA56:AA71) -> 0 | AB72: =SUM(AB56:AB71) -> 0 | ... AI72: =SUM(AI56:AI71) -> 0 | BW72: Total | BX72: =SUM(BX56:BX71) -> 0 | BZ72: =SUM(BZ56:BZ71) -> 0 | CA72: =SUM(CA56:CA71) -> 0 | CB72: =SUM(CB56:CB71) -> 0 | CC72: =SUM(CC56:CC71) -> 0 | CD72: =SUM(CD56:CD71) -> 0 | CF72: =SUM(CF56:CF71) -> 0 | CG72: =SUM(CG56:CG71) -> 0 | CH72: =SUM(CH56:CH71) -> 0 | CL72: =SUM(BX72:CH72) -> 0 | CM72: =SUM(CM56:CM71) -> 0 | CN72: =SUM(CN56:CN71) -> 0 | CO72: =SUM(CO56:CO71) -> 0 | CP72: =SUM(CP56:CP71) -> 0 | CQ72: =SUM(CQ56:CQ71) -> 0 | CR72: =SUM(CR56:CR71) -> 0 | CS72: =SUM(CS56:CS71) -> 0 | CT72: =SUM(CT56:CT71) -> 0 | ... DA72: =SUM(DA56:DA71) -> 0 | EJ72: TOTAL CALZADO | EK72: =EK56+EK57+EK58+EK59+EK60+EK61+EK62+EK63+EK64+EK67+EK68+EK70+EK71 -> 0 | EL72: =EL56+EL57+EL58+EL59+EL60+EL61+EL62+EL63+EL64+EL67+EL68+EL70+EL71 -> 0 | EM72: =EM56+EM57+EM58+EM59+EM60+EM61+EM62+EM63+EM64+EM67+EM68+EM70+EM71 -> 0 | EN72: =EN56+EN57+EN58+EN59+EN60+EN61+EN62+EN63+EN64+EN67+EN68+EN70+EN71 -> 0 | EO72: =EO56+EO57+EO58+EO59+EO60+EO61+EO62+EO63+EO64+EO67+EO68+EO70+EO71 -> 0 | EP72: =EP56+EP57+EP58+EP59+EP60+EP61+EP62+EP63+EP64+EP67+EP68+EP70+EP71 -> 0 | EQ72: =EQ56+EQ57+EQ58+EQ59+EQ60+EQ61+EQ62+EQ63+EQ64+EQ67+EQ68+EQ70+EQ71 -> 0 | ER72: =ER56+ER57+ER58+ER59+ER60+ER61+ER62+ER63+ER64+ER67+ER68+ER70+ER71 -> 0 | ... FN72: =FN56+FN57+FN58+FN59+FN60+FN61+FN62+FN63+FN64+FN67+FN68+FN70+FN71 -> 0 | FS72: TOTAL CALZADO | FU72: =FU56+FU57+FU58+FU59+FU60+FU61+FU62+FU63+FU64+FU67+FU68+FU70+FU71 -> 0 | FV72: =FV56+FV57+FV58+FV59+FV60+FV61+FV62+FV63+FV64+FV67+FV68+FV70+FV71 -> 0 | FW72: =FW56+FW57+FW58+FW59+FW60+FW61+FW62+FW63+FW64+FW67+FW68+FW70+FW71 -> 0 | FX72: =FX56+FX57+FX58+FX59+FX60+FX61+FX62+FX63+FX64+FX67+FX68+FX70+FX71 -> 0 | FY72: =FY56+FY57+FY58+FY59+FY60+FY61+FY62+FY63+FY64+FY67+FY68+FY70+FY71 -> 0 | FZ72: =FZ56+FZ57+FZ58+FZ59+FZ60+FZ61+FZ62+FZ63+FZ64+FZ67+FZ68+FZ70+FZ71 -> 0 | GA72: =GA56+GA57+GA58+GA59+GA60+GA61+GA62+GA63+GA64+GA67+GA68+GA70+GA71 -> 0 | GB72: =GB56+GB57+GB58+GB59+GB60+GB61+GB62+GB63+GB64+GB67+GB68+GB70+GB71 -> 0 | ... GZ72: =GZ56+GZ57+GZ58+GZ59+GZ60+GZ61+GZ62+GZ63+GZ64+GZ67+GZ68+GZ70+GZ71 -> 0
C73: Costo de Oportunidad | F73: =SUM(T56:T71) -> 0 | BX73: =SUM(CL56:CL71) -> 0 | EJ73: TOTAL ROPA | EK73: =EK65+EK66+EK69 -> 0 | EL73: =EL65+EL66+EL69 -> 0 | EM73: =EM65+EM66+EM69 -> 0 | EN73: =EN65+EN66+EN69 -> 0 | EO73: =EO65+EO66+EO69 -> 0 | EP73: =EP65+EP66+EP69 -> 0 | EQ73: =EQ65+EQ66+EQ69 -> 0 | ER73: =ER65+ER66+ER69 -> 0 | ... FN73: =FN65+FN66+FN69 -> 0 | FS73: TOTAL ROPA | FU73: =FU65+FU66+FU69 -> 0 | FV73: =FV65+FV66+FV69 -> 0 | FW73: =FW65+FW66+FW69 -> 0 | FX73: =FX65+FX66+FX69 -> 0 | FY73: =FY65+FY66+FY69 -> 0 | FZ73: =FZ65+FZ66+FZ69 -> 0 | GA73: =GA65+GA66+GA69 -> 0 | GB73: =GB65+GB66+GB69 -> 0 | ... GZ73: =GZ65+GZ66+GZ69 -> 0
F76: Causas de Negado | U76: Incidencias de Auditoria | BX76: Causas de Negado | CM76: Incidencias de Auditoria | EK76: $ negados
A77: Arco Norte | B77: Responsable De Catalogo | C77: Tallas por pasillo | D77: Tallas por modelo | E77: % de Cobertura de auditoria | F77: Frenteos | G77: Ubicación Revuelta | H77: Bodega Venta (Sin marcar) | I77: Bodega Tapanco | J77: Doble Ubicación | K77: Excedente | L77: Origen | M77: Cambios/Probadores | N77: Negados Sin Recuperar | O77: Exhibición | P77: Bodega Aclaración | Q77: Aduanas | R77: Golden o apartados | S77: Control de calidad | T77: Costo por pasillo | U77: Sin Exhibición | V77: Exhibición fuera de Política | W77: Modelos revuelto | X77: Modelos mal entallados | Y77: Modelos con error de ubicación | Z77: Curva con diferencia en frentes | AA77: Curva con diferencia en fondos | AB77: Curva con diferencia en altura | AC77: Curvas vencidas | AD77: Curvas que no coincide Price Soft vs Piso de Venta | AE77: Curvas faltantes | AF77: Cenefas faltantes | AG77: Cenefas de precio Promoción faltantes | AH77: Cartas disculpa / destallados faltantes | AI77: modelos que no cadran con planograma | AJ77: Resultado de Check List | AK77: Resultado de banderazo surtido | AM77: Tallas por pasillo | AN77: Tallas por modelo | AO77: % de Cobertura de auditoria | AP77: Frenteos | AQ77: Ubicación Revuelta | AR77: Bodega Venta (Sin marcar) | AS77: Bodega Tapanco | AT77: Doble Ubicación | AU77: Excedente | AV77: Origen | AW77: Cambios/Probadores | AX77: Negados Sin Recuperar | AY77: Exhibición | AZ77: Bodega Aclaración | BA77: Aduanas | BB77: Golden o apartados | BC77: Control de calidad | BD77: Costo por pasillo | BE77: Sin Exhibición | BF77: Exhibición fuera de Política | BG77: Modelos revuelto | BH77: Modelos mal entallados | BI77: Modelos con error de ubicación | BJ77: Curva con diferencia en frentes | BK77: Curva con diferencia en fondos | BL77: Curva con diferencia en altura | BM77: Curvas vencidas | BN77: Curvas que no coincide Price Soft vs Piso de Venta | BO77: Curvas faltantes | BP77: Cenefas faltantes | BQ77: Cenefas de precio Promoción faltantes | BR77: Cartas disculpa / destallados faltantes | BS77: Fechas de llegada faltantes | BT77: Resultado de Check List | BU77: Resultado de banderazo surtido | BV77: Arco Norte | BW77: Responsable de Catalogo | BX77: Frenteos | BY77: Ubicación Revuelta | BZ77: Bodega Venta (Sin marcar) | CA77: Bodega Tapanco | CB77: Doble Ubicación | CC77: Excedente | CD77: Origen | CE77: Cambios/Probadores | CF77: Negados Sin Recuperar | CG77: Exhibición | CH77: Bodega Aclaración | CI77: Aduanas | CJ77: Golden o apartados | CK77: Control de calidad | CL77: Costo por pasillo | CM77: Sin Exhibición | CN77: Exhibición fuera de Política | CO77: Modelos revuelto | CP77: Modelos mal entallados | CQ77: Modelos con error de ubicación | CR77: Curva con diferencia en frentes | CS77: Curva con diferencia en fondos | CT77: Curva con diferencia en altura | CU77: Curvas vencidas | CV77: Curvas que no coincide Price Soft vs Piso de Venta | CW77: Curvas faltantes | CX77: Cenefas faltantes | CY77: Cenefas de precio Promoción faltantes | CZ77: Cartas disculpa / destallados faltantes | DA77: Fechas de llegada faltantes | DB77: Resultado de Check List | DE77: Frenteos | DF77: Ubicación Revuelta | DG77: Bodega Venta (Sin marcar) | DH77: Bodega Tapanco | DI77: Doble Ubicación | DJ77: Excedente | DK77: Origen | DL77: Cambios/Probadores | DM77: Negados Sin Recuperar | DN77: Exhibición | DO77: Bodega Aclaración | DP77: Aduanas | DQ77: Golden o apartados | DR77: Control de calidad | DS77: Costo por pasillo | DT77: Sin Exhibición | DU77: Exhibición fuera de Política | DV77: Modelos revuelto | DW77: Modelos mal entallados | DX77: Modelos con error de ubicación | DY77: Curva con diferencia en frentes | DZ77: Curva con diferencia en fondos | EA77: Curva con diferencia en altura | EB77: Curvas vencidas | EC77: Curvas que no coincide Price Soft vs Piso de Venta | ED77: Curvas faltantes | EE77: Cenefas faltantes | EF77: Cenefas de precio Promoción faltantes | EG77: Cartas disculpa / destallados faltantes | EH77: Fechas de llegada faltantes | EK77: Frenteos | EL77: Ubicación Revuelta | EM77: Bodega Venta (Sin marcar) | EN77: Bodega Tapanco | EO77: Doble Ubicación | EP77: Excedente | EQ77: Origen | ER77: Cambios/Probadores | ES77: Negados Sin Recuperar | ET77: Exhibición | EU77: Bodega Aclaración | EV77: Aduanas | EW77: Golden o apartados | EX77: Control de calidad | EZ77: Frenteos | FA77: Ubicación Revuelta | FB77: Bodega Venta (Sin marcar) | FC77: Bodega Tapanco | FD77: Doble Ubicación | FE77: Excedente | FF77: Origen | FG77: Cambios/Probadores | FH77: Negados Sin Recuperar | FI77: Exhibición | FJ77: Bodega Aclaración | FK77: Aduanas | FL77: Golden o apartados | FM77: Control de calidad | FU77: Sin Exhibición | FV77: Exhibición fuera de Política | FW77: Modelos revuelto | FX77: Modelos mal entallados | FY77: Modelos con error de ubicación | FZ77: Curva con diferencia en frentes | GA77: Curva con diferencia en fondos | GB77: Curva con diferencia en altura | GC77: Curvas vencidas | GD77: Curvas que no coincide Price Soft vs Piso de Venta | GE77: Curvas faltantes | GF77: Cenefas faltantes | GG77: Cenefas de precio Promoción faltantes | GH77: Cartas disculpa / destallados faltantes | GI77: modelos que no cadran con planograma | GK77: Sin Exhibición | GL77: Exhibición fuera de Política | GM77: Modelos revuelto | GN77: Modelos mal entallados | GO77: Modelos con error de ubicación | GP77: Curva con diferencia en frentes | GQ77: Curva con diferencia en fondos | GR77: Curva con diferencia en altura | GS77: Curvas vencidas | GT77: Curvas que no coincide Price Soft vs Piso de Venta | GU77: Curvas faltantes | GV77: Cenefas faltantes | GW77: Cenefas de precio Promoción faltantes | GX77: Cartas disculpa / destallados faltantes | GY77: modelos que no cadran con planograma
AM78: =SUM(C78,C79,C80,C81,C82,C83,C84,C85,C86,C89,C90,C92,C93) -> 0 | AN78: =SUM(D78,D79,D80,D81,D82,D83,D84,D85,D86,D89,D90,D92,D93) -> 0 | AO78: =IF(AN78=0,"",AN78/AM78) | AP78: =SUM(F78,F79,F80,F81,F82,F83,F84,F85,F86,F89,F90,F92,F93) -> 0 | AQ78: =SUM(G78,G79,G80,G81,G82,G83,G84,G85,G86,G89,G90,G92,G93) -> 0 | AR78: =SUM(H78,H79,H80,H81,H82,H83,H84,H85,H86,H89,H90,H92,H93) -> 0 | AS78: =SUM(I78,I79,I80,I81,I82,I83,I84,I85,I86,I89,I90,I92,I93) -> 0 | AT78: =SUM(J78,J79,J80,J81,J82,J83,J84,J85,J86,J89,J90,J92,J93) -> 0 | AU78: =SUM(K78,K79,K80,K81,K82,K83,K84,K85,K86,K89,K90,K92,K93) -> 0 | AV78: =SUM(L78,L79,L80,L81,L82,L83,L84,L85,L86,L89,L90,L92,L93) -> 0 | AW78: =SUM(M78,M79,M80,M81,M82,M83,M84,M85,M86,M89,M90,M92,M93) -> 0 | ... BU78: =SUM(AK78,AK79,AK80,AK81,AK82,AK83,AK84,AK85,AK86,AK89,AK90,AK92,AK93) -> 0 | DD78: =(DD72/BZ84) -> #DIV/0! | DE78: =SUM(BX78,BX79,BX80,BX81,BX82,BX83,BX84,BX85,BX86,BX89,BX90,BX92,BX93) -> 0 | DF78: =SUM(BY78,BY79,BY80,BY81,BY82,BY83,BY84,BY85,BY86,BY89,BY90,BY92,BY93) -> 0 | DG78: =SUM(BZ78,BZ79,BZ80,BZ81,BZ82,BZ83,BZ84,BZ85,BZ86,BZ89,BZ90,BZ92,BZ93) -> 0 | DH78: =SUM(CA78,CA79,CA80,CA81,CA82,CA83,CA84,CA85,CA86,CA89,CA90,CA92,CA93) -> 0 | DI78: =SUM(CB78,CB79,CB80,CB81,CB82,CB83,CB84,CB85,CB86,CB89,CB90,CB92,CB93) -> 0 | DJ78: =SUM(CC78,CC79,CC80,CC81,CC82,CC83,CC84,CC85,CC86,CC89,CC90,CC92,CC93) -> 0 | DK78: =SUM(CD78,CD79,CD80,CD81,CD82,CD83,CD84,CD85,CD86,CD89,CD90,CD92,CD93) -> 0 | DL78: =SUM(CE78,CE79,CE80,CE81,CE82,CE83,CE84,CE85,CE86,CE89,CE90,CE92,CE93) -> 0 | ... EH78: =SUM(DA78,DA79,DA80,DA81,DA82,DA83,DA84,DA85,DA86,DA89,DA90,DA92,DA93) -> 0 | EI78: BOTAS | EJ78: 521 | EK78: =$EJ78*F78 -> 0 | EL78: =$EJ78*G78 -> 0 | EM78: =$EJ78*H78 -> 0 | EN78: =$EJ78*I78 -> 0 | EO78: =$EJ78*J78 -> 0 | EP78: =$EJ78*K78 -> 0 | EQ78: =$EJ78*L78 -> 0 | ER78: =$EJ78*M78 -> 0 | ... EX78: =$EJ78*S78 -> 0 | EY78: =SUM(EK78:EX78) -> 0 | EZ78: =BX78*$EJ78 -> 0 | FA78: =BY78*$EJ78 -> 0 | FB78: =BZ78*$EJ78 -> 0 | FC78: =CA78*$EJ78 -> 0 | FD78: =CB78*$EJ78 -> 0 | FE78: =CC78*$EJ78 -> 0 | FF78: =CD78*$EJ78 -> 0 | FG78: =CE78*$EJ78 -> 0 | ... FM78: =CK78*$EJ78 -> 0 | FN78: =SUM(EZ78:FM78) -> 0 | FO78: =SUM(EZ78:FJ78) -> 0 | FS78: BOTAS | FU78: =U78 -> 0 | FV78: =V78 -> 0 | FW78: =W78 -> 0 | FX78: =X78 -> 0 | FY78: =Y78 -> 0 | FZ78: =Z78 -> 0 | GA78: =AA78 -> 0 | GB78: =AB78 -> 0 | ... GH78: =AH78 -> 0 | GI78: 0 | GJ78: =SUM(FU78:GI78) -> 0 | GK78: =CM78 -> 0 | GL78: =CN78 -> 0 | GM78: =CO78 -> 0 | GN78: =CP78 -> 0 | GO78: =CQ78 -> 0 | GP78: =CR78 -> 0 | GQ78: =CS78 -> 0 | GR78: =CT78 -> 0 | ... GX78: =CZ78 -> 0 | GY78: 0 | GZ78: =SUM(GK78:GY78) -> 0 | HA78: =SUM(GK78:GY78) -> 0
AO79: =IF(AN79=0,"",AN79/AM79) | EI79: URBANO | EJ79: 540 | EK79: =$EJ79*F79 -> 0 | EL79: =$EJ79*G79 -> 0 | EM79: =$EJ79*H79 -> 0 | EN79: =$EJ79*I79 -> 0 | EO79: =$EJ79*J79 -> 0 | EP79: =$EJ79*K79 -> 0 | EQ79: =$EJ79*L79 -> 0 | ER79: =$EJ79*M79 -> 0 | ... EX79: =$EJ79*S79 -> 0 | EY79: =SUM(EK79:EX79) -> 0 | EZ79: =BX79*$EJ79 -> 0 | FA79: =BY79*$EJ79 -> 0 | FB79: =BZ79*$EJ79 -> 0 | FC79: =CA79*$EJ79 -> 0 | FD79: =CB79*$EJ79 -> 0 | FE79: =CC79*$EJ79 -> 0 | FF79: =CD79*$EJ79 -> 0 | FG79: =CE79*$EJ79 -> 0 | ... FM79: =CK79*$EJ79 -> 0 | FN79: =SUM(EZ79:FM79) -> 0 | FO79: =SUM(EZ79:FJ79) -> 0 | FS79: URBANO | FU79: =U79 -> 0 | FV79: =V79 -> 0 | FW79: =W79 -> 0 | FX79: =X79 -> 0 | FY79: =Y79 -> 0 | FZ79: =Z79 -> 0 | GA79: =AA79 -> 0 | GB79: =AB79 -> 0 | ... GH79: =AH79 -> 0 | GI79: 0 | GJ79: =SUM(FU79:GI79) -> 0 | GK79: =CM79 -> 0 | GL79: =CN79 -> 0 | GM79: =CO79 -> 0 | GN79: =CP79 -> 0 | GO79: =CQ79 -> 0 | GP79: =CR79 -> 0 | GQ79: =CS79 -> 0 | GR79: =CT79 -> 0 | ... GX79: =CZ79 -> 0 | GY79: 0 | GZ79: =SUM(GK79:GY79) -> 0 | HA79: =SUM(GK79:GY79) -> 0
AL80: % de tallas negadas | AM80: =SUM(C87,C88,C91) -> 0 | AN80: =SUM(D87,D88,D91) -> 0 | AO80: =IF(AN80=0,"",AN80/AM80) | AP80: =SUM(F87,F88,F91) -> 0 | AQ80: =SUM(G87,G88,G91) -> 0 | AR80: =SUM(H87,H88,H91) -> 0 | AS80: =SUM(I87,I88,I91) -> 0 | AT80: =SUM(J87,J88,J91) -> 0 | AU80: =SUM(K87,K88,K91) -> 0 | AV80: =SUM(L87,L88,L91) -> 0 | AW80: =SUM(M87,M88,M91) -> 0 | ... BS80: =SUM(AI87,AI88,AI91) -> 0 | BT80: =AVERAGE(AJ87,AJ88,AJ91) -> #DIV/0! | DC80: % de tallas recuperadas | DE80: =SUM(BX87,BX88,BX91) -> 0 | DF80: =SUM(BY87,BY88,BY91) -> 0 | DG80: =SUM(BZ87,BZ88,BZ91) -> 0 | DH80: =SUM(CA87,CA88,CA91) -> 0 | DI80: =SUM(CB87,CB88,CB91) -> 0 | DJ80: =SUM(CC87,CC88,CC91) -> 0 | DK80: =SUM(CD87,CD88,CD91) -> 0 | DL80: =SUM(CE87,CE88,CE91) -> 0 | ... EH80: =SUM(DA87,DA88,DA91) -> 0 | EI80: ESCOLAR | EJ80: 441.24 | EK80: =$EJ80*F80 -> 0 | EL80: =$EJ80*G80 -> 0 | EM80: =$EJ80*H80 -> 0 | EN80: =$EJ80*I80 -> 0 | EO80: =$EJ80*J80 -> 0 | EP80: =$EJ80*K80 -> 0 | EQ80: =$EJ80*L80 -> 0 | ER80: =$EJ80*M80 -> 0 | ... EX80: =$EJ80*S80 -> 0 | EY80: =SUM(EK80:EX80) -> 0 | EZ80: =BX80*$EJ80 -> 0 | FA80: =BY80*$EJ80 -> 0 | FB80: =BZ80*$EJ80 -> 0 | FC80: =CA80*$EJ80 -> 0 | FD80: =CB80*$EJ80 -> 0 | FE80: =CC80*$EJ80 -> 0 | FF80: =CD80*$EJ80 -> 0 | FG80: =CE80*$EJ80 -> 0 | ... FM80: =CK80*$EJ80 -> 0 | FN80: =SUM(EZ80:FM80) -> 0 | FO80: =SUM(EZ80:FJ80) -> 0 | FS80: ESCOLAR | FU80: =U80 -> 0 | FV80: =V80 -> 0 | FW80: =W80 -> 0 | FX80: =X80 -> 0 | FY80: =Y80 -> 0 | FZ80: =Z80 -> 0 | GA80: =AA80 -> 0 | GB80: =AB80 -> 0 | ... GH80: =AH80 -> 0 | GI80: 0 | GJ80: =SUM(FU80:GI80) -> 0 | GK80: =CM80 -> 0 | GL80: =CN80 -> 0 | GM80: =CO80 -> 0 | GN80: =CP80 -> 0 | GO80: =CQ80 -> 0 | GP80: =CR80 -> 0 | GQ80: =CS80 -> 0 | GR80: =CT80 -> 0 | ... GX80: =CZ80 -> 0 | GY80: 0 | GZ80: =SUM(GK80:GY80) -> 0 | HA80: =SUM(GK80:GY80) -> 0
EI81: SANDALIAS | EJ81: 294.47 | EK81: =$EJ81*F81 -> 0 | EL81: =$EJ81*G81 -> 0 | EM81: =$EJ81*H81 -> 0 | EN81: =$EJ81*I81 -> 0 | EO81: =$EJ81*J81 -> 0 | EP81: =$EJ81*K81 -> 0 | EQ81: =$EJ81*L81 -> 0 | ER81: =$EJ81*M81 -> 0 | ... EX81: =$EJ81*S81 -> 0 | EY81: =SUM(EK81:EX81) -> 0 | EZ81: =BX81*$EJ81 -> 0 | FA81: =BY81*$EJ81 -> 0 | FB81: =BZ81*$EJ81 -> 0 | FC81: =CA81*$EJ81 -> 0 | FD81: =CB81*$EJ81 -> 0 | FE81: =CC81*$EJ81 -> 0 | FF81: =CD81*$EJ81 -> 0 | FG81: =CE81*$EJ81 -> 0 | ... FM81: =CK81*$EJ81 -> 0 | FN81: =SUM(EZ81:FM81) -> 0 | FO81: =SUM(EZ81:FJ81) -> 0 | FS81: SANDALIAS | FU81: =U81 -> 0 | FV81: =V81 -> 0 | FW81: =W81 -> 0 | FX81: =X81 -> 0 | FY81: =Y81 -> 0 | FZ81: =Z81 -> 0 | GA81: =AA81 -> 0 | GB81: =AB81 -> 0 | ... GH81: =AH81 -> 0 | GI81: 0 | GJ81: =SUM(FU81:GI81) -> 0 | GK81: =CM81 -> 0 | GL81: =CN81 -> 0 | GM81: =CO81 -> 0 | GN81: =CP81 -> 0 | GO81: =CQ81 -> 0 | GP81: =CR81 -> 0 | GQ81: =CS81 -> 0 | GR81: =CT81 -> 0 | ... GX81: =CZ81 -> 0 | GY81: 0 | GZ81: =SUM(GK81:GY81) -> 0 | HA81: =SUM(GK81:GY81) -> 0
AL82: =T94/D94 -> #DIV/0! | DC82: =CL94/T94 -> #DIV/0! | EI82: CONFORT | EJ82: 422 | EK82: =$EJ82*F82 -> 0 | EL82: =$EJ82*G82 -> 0 | EM82: =$EJ82*H82 -> 0 | EN82: =$EJ82*I82 -> 0 | EO82: =$EJ82*J82 -> 0 | EP82: =$EJ82*K82 -> 0 | EQ82: =$EJ82*L82 -> 0 | ER82: =$EJ82*M82 -> 0 | ... EX82: =$EJ82*S82 -> 0 | EY82: =SUM(EK82:EX82) -> 0 | EZ82: =BX82*$EJ82 -> 0 | FA82: =BY82*$EJ82 -> 0 | FB82: =BZ82*$EJ82 -> 0 | FC82: =CA82*$EJ82 -> 0 | FD82: =CB82*$EJ82 -> 0 | FE82: =CC82*$EJ82 -> 0 | FF82: =CD82*$EJ82 -> 0 | FG82: =CE82*$EJ82 -> 0 | ... FM82: =CK82*$EJ82 -> 0 | FN82: =SUM(EZ82:FM82) -> 0 | FO82: =SUM(EZ82:FJ82) -> 0 | FS82: CONFORT | FU82: =U82 -> 0 | FV82: =V82 -> 0 | FW82: =W82 -> 0 | FX82: =X82 -> 0 | FY82: =Y82 -> 0 | FZ82: =Z82 -> 0 | GA82: =AA82 -> 0 | GB82: =AB82 -> 0 | ... GH82: =AH82 -> 0 | GI82: 0 | GJ82: =SUM(FU82:GI82) -> 0 | GK82: =CM82 -> 0 | GL82: =CN82 -> 0 | GM82: =CO82 -> 0 | GN82: =CP82 -> 0 | GO82: =CQ82 -> 0 | GP82: =CR82 -> 0 | GQ82: =CS82 -> 0 | GR82: =CT82 -> 0 | ... GX82: =CZ82 -> 0 | GY82: 0 | GZ82: =SUM(GK82:GY82) -> 0 | HA82: =SUM(GK82:GY82) -> 0
EI83: VESTIR CASUAL | EJ83: 416.19 | EK83: =$EJ83*F83 -> 0 | EL83: =$EJ83*G83 -> 0 | EM83: =$EJ83*H83 -> 0 | EN83: =$EJ83*I83 -> 0 | EO83: =$EJ83*J83 -> 0 | EP83: =$EJ83*K83 -> 0 | EQ83: =$EJ83*L83 -> 0 | ER83: =$EJ83*M83 -> 0 | ... EX83: =$EJ83*S83 -> 0 | EY83: =SUM(EK83:EX83) -> 0 | EZ83: =BX83*$EJ83 -> 0 | FA83: =BY83*$EJ83 -> 0 | FB83: =BZ83*$EJ83 -> 0 | FC83: =CA83*$EJ83 -> 0 | FD83: =CB83*$EJ83 -> 0 | FE83: =CC83*$EJ83 -> 0 | FF83: =CD83*$EJ83 -> 0 | FG83: =CE83*$EJ83 -> 0 | ... FM83: =CK83*$EJ83 -> 0 | FN83: =SUM(EZ83:FM83) -> 0 | FO83: =SUM(EZ83:FJ83) -> 0 | FS83: VESTIR CASUAL | FU83: =U83 -> 0 | FV83: =V83 -> 0 | FW83: =W83 -> 0 | FX83: =X83 -> 0 | FY83: =Y83 -> 0 | FZ83: =Z83 -> 0 | GA83: =AA83 -> 0 | GB83: =AB83 -> 0 | ... GH83: =AH83 -> 0 | GI83: 0 | GJ83: =SUM(FU83:GI83) -> 0 | GK83: =CM83 -> 0 | GL83: =CN83 -> 0 | GM83: =CO83 -> 0 | GN83: =CP83 -> 0 | GO83: =CQ83 -> 0 | GP83: =CR83 -> 0 | GQ83: =CS83 -> 0 | GR83: =CT83 -> 0 | ... GX83: =CZ83 -> 0 | GY83: 0 | GZ83: =SUM(GK83:GY83) -> 0 | HA83: =SUM(GK83:GY83) -> 0
AL84: Diferencia Negado VS Recuperado | EI84: INFANTILES | EJ84: 375 | EK84: =$EJ84*F84 -> 0 | EL84: =$EJ84*G84 -> 0 | EM84: =$EJ84*H84 -> 0 | EN84: =$EJ84*I84 -> 0 | EO84: =$EJ84*J84 -> 0 | EP84: =$EJ84*K84 -> 0 | EQ84: =$EJ84*L84 -> 0 | ER84: =$EJ84*M84 -> 0 | ... EX84: =$EJ84*S84 -> 0 | EY84: =SUM(EK84:EX84) -> 0 | EZ84: =BX84*$EJ84 -> 0 | FA84: =BY84*$EJ84 -> 0 | FB84: =BZ84*$EJ84 -> 0 | FC84: =CA84*$EJ84 -> 0 | FD84: =CB84*$EJ84 -> 0 | FE84: =CC84*$EJ84 -> 0 | FF84: =CD84*$EJ84 -> 0 | FG84: =CE84*$EJ84 -> 0 | ... FM84: =CK84*$EJ84 -> 0 | FN84: =SUM(EZ84:FM84) -> 0 | FO84: =SUM(EZ84:FJ84) -> 0 | FS84: INFANTILES | FU84: =U84 -> 0 | FV84: =V84 -> 0 | FW84: =W84 -> 0 | FX84: =X84 -> 0 | FY84: =Y84 -> 0 | FZ84: =Z84 -> 0 | GA84: =AA84 -> 0 | GB84: =AB84 -> 0 | ... GH84: =AH84 -> 0 | GI84: 0 | GJ84: =SUM(FU84:GI84) -> 0 | GK84: =CM84 -> 0 | GL84: =CN84 -> 0 | GM84: =CO84 -> 0 | GN84: =CP84 -> 0 | GO84: =CQ84 -> 0 | GP84: =CR84 -> 0 | GQ84: =CS84 -> 0 | GR84: =CT84 -> 0 | ... GX84: =CZ84 -> 0 | GY84: 0 | GZ84: =SUM(GK84:GY84) -> 0 | HA84: =SUM(GK84:GY84) -> 0
EI85: CABALLEROS | EJ85: 730 | EK85: =$EJ85*F85 -> 0 | EL85: =$EJ85*G85 -> 0 | EM85: =$EJ85*H85 -> 0 | EN85: =$EJ85*I85 -> 0 | EO85: =$EJ85*J85 -> 0 | EP85: =$EJ85*K85 -> 0 | EQ85: =$EJ85*L85 -> 0 | ER85: =$EJ85*M85 -> 0 | ... EX85: =$EJ85*S85 -> 0 | EY85: =SUM(EK85:EX85) -> 0 | EZ85: =BX85*$EJ85 -> 0 | FA85: =BY85*$EJ85 -> 0 | FB85: =BZ85*$EJ85 -> 0 | FC85: =CA85*$EJ85 -> 0 | FD85: =CB85*$EJ85 -> 0 | FE85: =CC85*$EJ85 -> 0 | FF85: =CD85*$EJ85 -> 0 | FG85: =CE85*$EJ85 -> 0 | ... FM85: =CK85*$EJ85 -> 0 | FN85: =SUM(EZ85:FM85) -> 0 | FO85: =SUM(EZ85:FJ85) -> 0 | FS85: CABALLEROS | FU85: =U85 -> 0 | FV85: =V85 -> 0 | FW85: =W85 -> 0 | FX85: =X85 -> 0 | FY85: =Y85 -> 0 | FZ85: =Z85 -> 0 | GA85: =AA85 -> 0 | GB85: =AB85 -> 0 | ... GH85: =AH85 -> 0 | GI85: 0 | GJ85: =SUM(FU85:GI85) -> 0 | GK85: =CM85 -> 0 | GL85: =CN85 -> 0 | GM85: =CO85 -> 0 | GN85: =CP85 -> 0 | GO85: =CQ85 -> 0 | GP85: =CR85 -> 0 | GQ85: =CS85 -> 0 | GR85: =CT85 -> 0 | ... GX85: =CZ85 -> 0 | GY85: 0 | GZ85: =SUM(GK85:GY85) -> 0 | HA85: =SUM(GK85:GY85) -> 0
AL86: =o940bw94 -> #NAME? | EI86: CHANCLERO | EJ86: 178 | EK86: =$EJ86*F86 -> 0 | EL86: =$EJ86*G86 -> 0 | EM86: =$EJ86*H86 -> 0 | EN86: =$EJ86*I86 -> 0 | EO86: =$EJ86*J86 -> 0 | EP86: =$EJ86*K86 -> 0 | EQ86: =$EJ86*L86 -> 0 | ER86: =$EJ86*M86 -> 0 | ... EX86: =$EJ86*S86 -> 0 | EY86: =SUM(EK86:EX86) -> 0 | EZ86: =BX86*$EJ86 -> 0 | FA86: =BY86*$EJ86 -> 0 | FB86: =BZ86*$EJ86 -> 0 | FC86: =CA86*$EJ86 -> 0 | FD86: =CB86*$EJ86 -> 0 | FE86: =CC86*$EJ86 -> 0 | FF86: =CD86*$EJ86 -> 0 | FG86: =CE86*$EJ86 -> 0 | ... FM86: =CK86*$EJ86 -> 0 | FN86: =SUM(EZ86:FM86) -> 0 | FO86: =SUM(EZ86:FJ86) -> 0 | FS86: CHANCLERO | FU86: =U86 -> 0 | FV86: =V86 -> 0 | FW86: =W86 -> 0 | FX86: =X86 -> 0 | FY86: =Y86 -> 0 | FZ86: =Z86 -> 0 | GA86: =AA86 -> 0 | GB86: =AB86 -> 0 | ... GH86: =AH86 -> 0 | GI86: 0 | GJ86: =SUM(FU86:GI86) -> 0 | GK86: =CM86 -> 0 | GL86: =CN86 -> 0 | GM86: =CO86 -> 0 | GN86: =CP86 -> 0 | GO86: =CQ86 -> 0 | GP86: =CR86 -> 0 | GQ86: =CS86 -> 0 | GR86: =CT86 -> 0 | ... GX86: =CZ86 -> 0 | GY86: 0 | GZ86: =SUM(GK86:GY86) -> 0 | HA86: =SUM(GK86:GY86) -> 0
EI87: ROPA DOBLADA | EJ87: 263 | EK87: =$EJ87*F87 -> 0 | EL87: =$EJ87*G87 -> 0 | EM87: =$EJ87*H87 -> 0 | EN87: =$EJ87*I87 -> 0 | EO87: =$EJ87*J87 -> 0 | EP87: =$EJ87*K87 -> 0 | EQ87: =$EJ87*L87 -> 0 | ER87: =$EJ87*M87 -> 0 | ... EX87: =$EJ87*S87 -> 0 | EY87: =SUM(EK87:EX87) -> 0 | EZ87: =BX87*$EJ87 -> 0 | FA87: =BY87*$EJ87 -> 0 | FB87: =BZ87*$EJ87 -> 0 | FC87: =CA87*$EJ87 -> 0 | FD87: =CB87*$EJ87 -> 0 | FE87: =CC87*$EJ87 -> 0 | FF87: =CD87*$EJ87 -> 0 | FG87: =CE87*$EJ87 -> 0 | ... FM87: =CK87*$EJ87 -> 0 | FN87: =SUM(EZ87:FM87) -> 0 | FO87: =SUM(EZ87:FJ87) -> 0 | FS87: ROPA DOBLADA | FU87: 0 | FV87: 0 | FW87: =W87 -> 0 | FX87: =X87 -> 0 | FY87: =Y87 -> 0 | FZ87: 0 | GA87: 0 | GB87: 0 | GC87: =AC87 -> 0 | GD87: =AD87 -> 0 | GE87: =AE87 -> 0 | GF87: =AF87 -> 0 | GG87: =AG87 -> 0 | GH87: 0 | GI87: =AI87 -> 0 | GJ87: =SUM(FU87:GI87) -> 0 | GK87: 0 | GL87: 0 | GM87: =CO87 -> 0 | GN87: =CP87 -> 0 | GO87: =CQ87 -> 0 | GP87: 0 | GQ87: 0 | GR87: 0 | GS87: =CU87 -> 0 | GT87: =CV87 -> 0 | GU87: =CW87 -> 0 | GV87: =CX87 -> 0 | GW87: =CY87 -> 0 | GX87: 0 | GY87: =DA87 -> 0 | GZ87: =SUM(GK87:GY87) -> 0 | HA87: =SUM(GK87:GY87) -> 0
AL88: % de Costo no recuperado | EI88: ROPA COLGADA | EJ88: 405 | EK88: =$EJ88*F88 -> 0 | EL88: =$EJ88*G88 -> 0 | EM88: =$EJ88*H88 -> 0 | EN88: =$EJ88*I88 -> 0 | EO88: =$EJ88*J88 -> 0 | EP88: =$EJ88*K88 -> 0 | EQ88: =$EJ88*L88 -> 0 | ER88: =$EJ88*M88 -> 0 | ... EX88: =$EJ88*S88 -> 0 | EY88: =SUM(EK88:EX88) -> 0 | EZ88: =BX88*$EJ88 -> 0 | FA88: =BY88*$EJ88 -> 0 | FB88: =BZ88*$EJ88 -> 0 | FC88: =CA88*$EJ88 -> 0 | FD88: =CB88*$EJ88 -> 0 | FE88: =CC88*$EJ88 -> 0 | FF88: =CD88*$EJ88 -> 0 | FG88: =CE88*$EJ88 -> 0 | ... FM88: =CK88*$EJ88 -> 0 | FN88: =SUM(EZ88:FM88) -> 0 | FO88: =SUM(EZ88:FJ88) -> 0 | FS88: ROPA COLGADA | FU88: 0 | FV88: 0 | FW88: =W88 -> 0 | FX88: =X88 -> 0 | FY88: =Y88 -> 0 | FZ88: 0 | GA88: 0 | GB88: 0 | GC88: =AC88 -> 0 | GD88: =AD88 -> 0 | GE88: =AE88 -> 0 | GF88: =AF88 -> 0 | GG88: =AG88 -> 0 | GH88: 0 | GI88: =AI88 -> 0 | GJ88: =SUM(FU88:GI88) -> 0 | GK88: 0 | GL88: 0 | GM88: =CO88 -> 0 | GN88: =CP88 -> 0 | GO88: =CQ88 -> 0 | GP88: 0 | GQ88: 0 | GR88: 0 | GS88: =CU88 -> 0 | GT88: =CV88 -> 0 | GU88: =CW88 -> 0 | GV88: =CX88 -> 0 | GW88: =CY88 -> 0 | GX88: =CZ88 -> 0 | GY88: =DA88 -> 0 | GZ88: =SUM(GK88:GY88) -> 0 | HA88: =SUM(GK88:GY88) -> 0
EI89: IMPORTADOS | EJ89: 1287 | EK89: =$EJ89*F89 -> 0 | EL89: =$EJ89*G89 -> 0 | EM89: =$EJ89*H89 -> 0 | EN89: =$EJ89*I89 -> 0 | EO89: =$EJ89*J89 -> 0 | EP89: =$EJ89*K89 -> 0 | EQ89: =$EJ89*L89 -> 0 | ER89: =$EJ89*M89 -> 0 | ... EX89: =$EJ89*S89 -> 0 | EY89: =SUM(EK89:EX89) -> 0 | EZ89: =BX89*$EJ89 -> 0 | FA89: =BY89*$EJ89 -> 0 | FB89: =BZ89*$EJ89 -> 0 | FC89: =CA89*$EJ89 -> 0 | FD89: =CB89*$EJ89 -> 0 | FE89: =CC89*$EJ89 -> 0 | FF89: =CD89*$EJ89 -> 0 | FG89: =CE89*$EJ89 -> 0 | ... FM89: =CK89*$EJ89 -> 0 | FN89: =SUM(EZ89:FM89) -> 0 | FO89: =SUM(EZ89:FJ89) -> 0 | FS89: IMPORTADOS | FU89: 0 | FV89: 0 | FW89: =W89 -> 0 | FX89: =X89 -> 0 | FY89: =Y89 -> 0 | FZ89: =Z89 -> 0 | GA89: =AA89 -> 0 | GB89: =AB89 -> 0 | GC89: =AC89 -> 0 | GD89: =AD89 -> 0 | ... GH89: =AH89 -> 0 | GI89: 0 | GJ89: =SUM(FU89:GI89) -> 0 | GK89: 0 | GL89: 0 | GM89: =CO89 -> 0 | GN89: =CP89 -> 0 | GO89: =CQ89 -> 0 | GP89: =CR89 -> 0 | GQ89: =CS89 -> 0 | GR89: =CT89 -> 0 | GS89: =CU89 -> 0 | GT89: =CV89 -> 0 | ... GX89: =CZ89 -> 0 | GY89: 0 | GZ89: =SUM(GK89:GY89) -> 0 | HA89: =SUM(GK89:GY89) -> 0
AL90: =(AL86/F95) -> #NAME? | EI90: BARRA DE BEBES | EJ90: 326.07 | EK90: =$EJ90*F90 -> 0 | EL90: =$EJ90*G90 -> 0 | EM90: =$EJ90*H90 -> 0 | EN90: =$EJ90*I90 -> 0 | EO90: =$EJ90*J90 -> 0 | EP90: =$EJ90*K90 -> 0 | EQ90: =$EJ90*L90 -> 0 | ER90: =$EJ90*M90 -> 0 | ... EX90: =$EJ90*S90 -> 0 | EY90: =SUM(EK90:EX90) -> 0 | EZ90: =BX90*$EJ90 -> 0 | FA90: =BY90*$EJ90 -> 0 | FB90: =BZ90*$EJ90 -> 0 | FC90: =CA90*$EJ90 -> 0 | FD90: =CB90*$EJ90 -> 0 | FE90: =CC90*$EJ90 -> 0 | FF90: =CD90*$EJ90 -> 0 | FG90: =CE90*$EJ90 -> 0 | ... FM90: =CK90*$EJ90 -> 0 | FN90: =SUM(EZ90:FM90) -> 0 | FO90: =SUM(EZ90:FJ90) -> 0 | FS90: BARRA DE BEBES | FU90: 0 | FV90: 0 | FW90: =W90 -> 0 | FX90: =X90 -> 0 | FY90: =Y90 -> 0 | FZ90: =Z90 -> 0 | GA90: =AA90 -> 0 | GB90: =AB90 -> 0 | GC90: =AC90 -> 0 | GD90: =AD90 -> 0 | ... GH90: =AH90 -> 0 | GI90: 0 | GJ90: =SUM(FU90:GI90) -> 0 | GK90: 0 | GL90: 0 | GM90: =CO90 -> 0 | GN90: =CP90 -> 0 | GO90: =CQ90 -> 0 | GP90: =CR90 -> 0 | GQ90: =CS90 -> 0 | GR90: =CT90 -> 0 | GS90: =CU90 -> 0 | GT90: =CV90 -> 0 | ... GX90: =CZ90 -> 0 | GY90: 0 | GZ90: =SUM(GK90:GY90) -> 0 | HA90: =SUM(GK90:GY90) -> 0
EI91: JEANS | EJ91: 357 | EK91: =$EJ91*F91 -> 0 | EL91: =$EJ91*G91 -> 0 | EM91: =$EJ91*H91 -> 0 | EN91: =$EJ91*I91 -> 0 | EO91: =$EJ91*J91 -> 0 | EP91: =$EJ91*K91 -> 0 | EQ91: =$EJ91*L91 -> 0 | ER91: =$EJ91*M91 -> 0 | ... EX91: =$EJ91*S91 -> 0 | EY91: =SUM(EK91:EX91) -> 0 | EZ91: =BX91*$EJ91 -> 0 | FA91: =BY91*$EJ91 -> 0 | FB91: =BZ91*$EJ91 -> 0 | FC91: =CA91*$EJ91 -> 0 | FD91: =CB91*$EJ91 -> 0 | FE91: =CC91*$EJ91 -> 0 | FF91: =CD91*$EJ91 -> 0 | FG91: =CE91*$EJ91 -> 0 | ... FM91: =CK91*$EJ91 -> 0 | FN91: =SUM(EZ91:FM91) -> 0 | FO91: =SUM(EZ91:FJ91) -> 0 | FS91: JEANS | FU91: 0 | FV91: 0 | FW91: =W91 -> 0 | FX91: =X91 -> 0 | FY91: =Y91 -> 0 | FZ91: 0 | GA91: 0 | GB91: 0 | GC91: =AC91 -> 0 | GD91: =AD91 -> 0 | GE91: =AE91 -> 0 | GF91: =AF91 -> 0 | GG91: =AG91 -> 0 | GH91: 0 | GI91: =AI91 -> 0 | GJ91: =SUM(FU91:GI91) -> 0 | GK91: 0 | GL91: 0 | GM91: =CO91 -> 0 | GN91: =CP91 -> 0 | GO91: =CQ91 -> 0 | GP91: 0 | GQ91: 0 | GR91: 0 | GS91: =CU91 -> 0 | GT91: =CV91 -> 0 | GU91: =CW91 -> 0 | GV91: =CX91 -> 0 | GW91: =CY91 -> 0 | GX91: 0 | GY91: =DA91 -> 0 | GZ91: =SUM(GK91:GY91) -> 0 | HA91: =SUM(GK91:GY91) -> 0
EI92: MOCHILAS | EJ92: 482 | EK92: =$EJ92*F92 -> 0 | EL92: =$EJ92*G92 -> 0 | EM92: =$EJ92*H92 -> 0 | EN92: =$EJ92*I92 -> 0 | EO92: =$EJ92*J92 -> 0 | EP92: =$EJ92*K92 -> 0 | EQ92: =$EJ92*L92 -> 0 | ER92: =$EJ92*M92 -> 0 | ... EX92: =$EJ92*S92 -> 0 | EY92: =SUM(EK92:EX92) -> 0 | EZ92: =BX92*$EJ92 -> 0 | FA92: =BY92*$EJ92 -> 0 | FB92: =BZ92*$EJ92 -> 0 | FC92: =CA92*$EJ92 -> 0 | FD92: =CB92*$EJ92 -> 0 | FE92: =CC92*$EJ92 -> 0 | FF92: =CD92*$EJ92 -> 0 | FG92: =CE92*$EJ92 -> 0 | ... FM92: =CK92*$EJ92 -> 0 | FN92: =SUM(EZ92:FM92) -> 0 | FO92: =SUM(EZ92:FJ92) -> 0 | FS92: MOCHILAS | FU92: =U92 -> 0 | FV92: =V92 -> 0 | FW92: =W92 -> 0 | FX92: =X92 -> 0 | FY92: =Y92 -> 0 | FZ92: =Z92 -> 0 | GA92: =AA92 -> 0 | GB92: =AB92 -> 0 | ... GI92: =AI92 -> 0 | GJ92: =SUM(FU92:GI92) -> 0 | GK92: =CM92 -> 0 | GL92: =CN92 -> 0 | GM92: =CO92 -> 0 | GN92: =CP92 -> 0 | GO92: =CQ92 -> 0 | GP92: =CR92 -> 0 | GQ92: =CS92 -> 0 | GR92: =CT92 -> 0 | ... GX92: =CZ92 -> 0 | GY92: 0 | GZ92: =SUM(GK92:GY92) -> 0 | HA92: =SUM(GK92:GY92) -> 0
EI93: HASTA | EJ93: 275.36 | EK93: =$EJ93*F93 -> 0 | EL93: =$EJ93*G93 -> 0 | EM93: =$EJ93*H93 -> 0 | EN93: =$EJ93*I93 -> 0 | EO93: =$EJ93*J93 -> 0 | EP93: =$EJ93*K93 -> 0 | EQ93: =$EJ93*L93 -> 0 | ER93: =$EJ93*M93 -> 0 | ... EX93: =$EJ93*S93 -> 0 | EY93: =SUM(EK93:EX93) -> 0 | EZ93: =BX93*$EJ93 -> 0 | FA93: =BY93*$EJ93 -> 0 | FB93: =BZ93*$EJ93 -> 0 | FC93: =CA93*$EJ93 -> 0 | FD93: =CB93*$EJ93 -> 0 | FE93: =CC93*$EJ93 -> 0 | FF93: =CD93*$EJ93 -> 0 | FG93: =CE93*$EJ93 -> 0 | ... FM93: =CK93*$EJ93 -> 0 | FN93: =SUM(EZ93:FM93) -> 0 | FO93: =SUM(EZ93:FJ93) -> 0 | FS93: HASTA | FU93: =U93 -> 0 | FV93: =V93 -> 0 | FW93: =W93 -> 0 | FX93: =X93 -> 0 | FY93: =Y93 -> 0 | FZ93: =Z93 -> 0 | GA93: =AA93 -> 0 | GB93: =AB93 -> 0 | ... GH93: =AH93 -> 0 | GI93: 0 | GJ93: =SUM(FU93:GI93) -> 0 | GK93: =CM93 -> 0 | GL93: =CN93 -> 0 | GM93: =CO93 -> 0 | GN93: =CP93 -> 0 | GO93: =CQ93 -> 0 | GP93: =CR93 -> 0 | GQ93: =CS93 -> 0 | GR93: =CT93 -> 0 | ... GX93: =CZ93 -> 0 | GY93: 0 | GZ93: =SUM(GK93:GY93) -> 0 | HA93: =SUM(GK93:GY93) -> 0
